Workbook

Sheet 全期間集計_TOTAL
A3: 項目名 | B3: 全期間合計
A4: 登録人数 | B4: ='202512'!B4+'202601'!B4 -> 8237
A5: ログインユーザー数 | B5: ='202512'!B5+'202601'!B5 -> 5858
A6: SMS認証 | B6: ='202512'!B6+'202601'!B6 -> 8206
A7: 登録に対してSMS認証割合 | B7: =B6/B4 -> 0.99623649
A8: 入金不要ボーナス使用済ユーザー数 | B8: ='202512'!B8+'202601'!B8 -> 7765
A9: 登録に対してNDB使用割合 | B9: =B8/B4 -> 0.94269758
A10: FTDのみ入金者数 | B10: ='202512'!B10+'202601'!B10 -> 579
A11: 登録に対してFTDのみの割合 | B11: =B10/B4 -> 0.070292582
A12: 2nd入金のみユーザー数 | B12: ='202512'!B12+'202601'!B12 -> 111
A13: 登録に対して2nd使用割合 | B13: =B12/B4 -> 0.01347578
A14: 3nd入金のみユーザー数 | B14: ='202512'!B14+'202601'!B14 -> 74
A15: 登録に対して3nd使用割合 | B15: =B14/B4 -> 0.0089838533
A16: 4nd入金以降ユーザー数 | B16: ='202512'!B16+'202601'!B16 -> 207
A17: 登録に対して4nd使用割合 | B17: =B16/B4 -> 0.025130509
A18: 今月登録のFTD以降ユーザー数 | B18: ='202512'!B18+'202601'!B18 -> 1312
A19: 今月登録FTD以降ユーザー割合 | B19: =B18/B4 -> 0.15928129
A20: 今月登録のアクティブユーザー数 | B20: ='202512'!B20+'202601'!B20 -> 1366
A21: 前月登録のアクティブユーザー数 | B21: ='202512'!B21+'202601'!B21 -> 743
A22: 前々月登録のアクティブユーザー数 | B22: ='202512'!B22+'202601'!B22 -> #VALUE!
A23: 3か月以上アクティブプレイヤー数 | B23: ='202512'!B23+'202601'!B23 -> #VALUE!
A24: 総入金回数 | B24: ='202512'!B24+'202601'!B24 -> 12432
A25: 入金者数(デイリーユニーク) | B25: ='202512'!B25+'202601'!B25 -> 3776
A26: アクティブプレイ人数（ユニーク） | B26: ='202512'!B26+'202601'!B26 -> 2137
A27: 総入金額 / Total DP amt | B27: ='202512'!B27+'202601'!B27 -> 196091868
A28: 平均入金額(一回の入金額) / Ave amt per DP | B28: =B27/B24 -> 15773.155
A29: 平均入金額(ユニークユーザー) / Ave DP amt (Unique user) | B29: =B27/B26 -> 91760.35
A30: 総出金回数 | B30: ='202512'!B30+'202601'!B30 -> 2744
A31: 総出金人数 | B31: ='202512'!B31+'202601'!B31 -> 1971
A32: 総出金額 / Total WD amt | B32: ='202512'!B32+'202601'!B32 -> 142781785
A33: 入金額に対して出金割合 | B33: =B32/B27 -> 0.72813721
A34: T/O(リアルのみ) / Total real bet | B34: ='202512'!B34+'202601'!B34 -> 3153510256
A35: T/O率(リアルのみ) / Total real bet ratio | B35: ='202512'!B35+'202601'!B35 -> 32.519293
A36: T/O(ボーナス+リアルマネーの合計) / Total bet (Real+Bonus) | B36: ='202512'!B36+'202601'!B36 -> 3153510256
A37: 勝利金(リアルのみ) / Winning amt (Real) | B37: ='202512'!B37+'202601'!B37 -> 3047926570
A38: 勝利金(ボーナスのみ) / Winning amt (Bonus) | B38: ='202512'!B38+'202601'!B38 -> 1242834.8
A39: 勝利金(ボーナス+リアルマネーの合計) / Winning (Bonus+Real) | B39: ='202512'!B39+'202601'!B39 -> 3049169405
A40: リアルマネー残高 / Real Money Balance | B40: ='202512'!B40+'202601'!B40 -> 18591291
A41: ボーナス・マネー残高 / Bonus Money Balance | B41: ='202512'!B41+'202601'!B41 -> 2084881
A42: RTP | B42: =('202512'!B42+'202601'!B42)/2 -> 0.96709261
A43: T/O(ボーナスのみ) / Total bet (Bonus) | B43: ='202512'!B43+'202601'!B43 -> 0
A44: T/O率(ボーナスのみ) / Total bet ratio (Bonus) | B44: ='202512'!B44+'202601'!B44 -> 0
A45: GGR | B45: ='202512'!B45+'202601'!B45 -> 1.0434085e+08
A46: GGR(入金に対して割合) | B46: ='202512'!B46+'202601'!B46 -> 1.0648444
A47: GGRLTV | B47: ='202512'!B47+'202601'!B47 -> 95920.617
A48: 入出金差分 | B48: ='202512'!B48+'202601'!B48 -> 53310083
A49: 差分(入金に対して割合) | B49: ='202512'!B49+'202601'!B49 -> 0.54501325
A50: 差分LTV | B50: ='202512'!B50+'202601'!B50 -> 49074.76
A51: ヘブンズショットコスト/Heavensshot Cost | B51: ='202512'!B51+'202601'!B51 -> 5686000
A52: トーナメントコスト/Tournament Cost | B52: ='202512'!B52+'202601'!B52 -> 0
A53: 新規用期間イベントコスト/new user event Cost | B53: ='202512'!B53+'202601'!B53 -> 1331635
A54: 休眠用期間イベントコスト/old user event Cost | B54: ='202512'!B54+'202601'!B54 -> 0
... A65: 差分利益 | B65: ='202512'!B65+'202601'!B65 -> 39781490
A66: プロモーション開催期間 / Promotion duration
A67: 目的
A68: プロモーション開催期間 / Promotion duration
A69: 目的
A70: プロモーション開催期間 / Promotion duration
A71: 目的
A72: プロモーション開催期間 / Promotion duration
A73: 目的
A74: 【分析指標】
A75: ARPU(全登録ユーザー) | B75: =B58/B4 -> 455.05081
A76: ARPPU(課金ユーザー) | B76: =B64/B25 -> 13773.168
A77: FTDコンバージョン率 | B77: =B18/B4 -> 0.15928129
A78: 2nd継続率 | B78: =B12/B10 -> 0.19170984
A79: アクティブ率 | B79: =B26/B4 -> 0.25943912
A80: GGRマージン率 | B80: =B45/B27 -> 0.53210188
A81: NGRマージン率 | B81: =B64/B27 -> 0.26521999
A82: 平均入金回数/ユーザー | B82: =B24/B25 -> 3.2923729
A83: プロモーション開催期間 / Promotion duration
A84: 目的 / Purpose
A85: Affiliate
A86: AFF経由登録者数 / Registration under AFF | B86: ='202512'!B94+'202601'!B94 -> 2800
A87: AFF経由FTD数 / FTD under AFF | B87: ='202512'!B95+'202601'!B95 -> 716
A88: AFF数 | B88: ='202512'!B96+'202601'!B96 -> 103
A89: AFF経由入金額 / DP amt under AFF | B89: ='202512'!B97+'202601'!B97 -> 63084211
A90: AFF経由出金額 / WD amt under AFF | B90: ='202512'!B98+'202601'!B98 -> 42226223
A91: Ｔ／Ｏ | B91: ='202512'!B99+'202601'!B99 -> 238046182
A92: 勝利金 | B92: ='202512'!B100+'202601'!B100 -> 227680021
A93: AFF経由RTP / RTP under AFF | B93: ='202512'!B101+'202601'!B101 -> 0.95645315
A94: AFF経由GGR / GGR under AFF | B94: ='202512'!B102+'202601'!B102 -> 12897830
A95: 差分GGR | B95: ='202512'!B103+'202601'!B103 -> 18326319
A96: AFF経由ボーナス額 / Bonus Granted Amt under AFF | B96: ='202512'!B104+'202601'!B104 -> 0
A97: AFFデモコスト(プロバイダーフィー) | B97: ='202512'!B105+'202601'!B105 -> 1812495
... A105: 目的 / Purpose | B105: ='202512'!B113+'202601'!B113 -> 0
A106: パチンコ
A107: リアルマネーTO / Turnover(Real) | B107: ='202512'!B116+'202601'!B116 -> 64486398
A108: 勝利金(リアル) / Payout(Real) | B108: ='202512'!B117+'202601'!B117 -> 53414080
A109: リアルマネーユニークユーザー数 / Unique user (Real) | B109: ='202512'!B118+'202601'!B118 -> 2705
A110: リアルマネーユニークベット数 / Bet number (Real) | B110: ='202512'!B119+'202601'!B119 -> 13590
A111: ボーナスマネーT/O / Turnover(Bonus) | B111: ='202512'!B120+'202601'!B120 -> 0
A112: 勝利金(ボーナス) / Payout(Bonus) | B112: ='202512'!B121+'202601'!B121 -> 0
A113: ボーナスマネーユニークユーザー数 / Unique user (Bonus) | B113: ='202512'!B122+'202601'!B122 -> 0
A114: ボーナスマネーユニークベット数 / Bet number (Bonus) | B114: ='202512'!B123+'202601'!B123 -> 0
A115: 合計ユニークユーザー数 / Total unique user | B115: ='202512'!B124+'202601'!B124 -> 2705
A116: 合計T/O / Total turnover | B116: ='202512'!B125+'202601'!B125 -> 64486398
A117: 合計勝利金 / Total payout | B117: ='202512'!B126+'202601'!B126 -> 53414080
A118: RTP | B118: ='202512'!B127+'202601'!B127 -> 1.6631095
... A123: 目的 / Purpose | B123: ='202512'!B132+'202601'!B132 -> 0
...

Sheet ダッシュボード
A1: スロット天国 KPI ダッシュボード
A3: 【全体サマリー（全期間合計）】
A4: 総登録人数 | B4: ='202511'!B4+'202512'!B4+'202601'!B4 -> 8537
A5: 総FTD数 | B5: ='202511'!B10+'202512'!B10+'202601'!B10 -> 587
A6: 総入金額 | B6: ='202511'!B23+'202512'!B27+'202601'!B27 -> 196678014
A7: 総出金額 | B7: ='202511'!B28+'202512'!B32+'202601'!B32 -> 143310248
A8: 入出金差分 | B8: =B6-B7 -> 53367766
A9: 総GGR | B9: ='202511'!B41+'202512'!B45+'202601'!B45 -> 1.0440442e+08
A10: 総NGR | B10: ='202511'!B56+'202512'!B64+'202601'!B64 -> 47205265
A11: 平均RTP | B11: =AVERAGE('202511'!C38,'202512'!C42,'202601'!C42) -> 0.96343727
A13: 【月次KPI比較】
A14: 指標 | B14: 2025/11 | C14: 2025/12 | D14: 2026/01 | E14: 合計/平均
A15: 登録人数 | B15: ='202511'!B4 -> 300 | C15: ='202512'!B4 -> 2552 | D15: ='202601'!B4 -> 5685 | E15: =SUM(B15:D15) -> 8537
A16: SMS認証 | B16: ='202511'!B6 -> 166 | C16: ='202512'!B6 -> 2521 | D16: ='202601'!B6 -> 5685 | E16: =SUM(B16:D16) -> 8372
A17: FTD数 | B17: ='202511'!B10 -> 8 | C17: ='202512'!B10 -> 231 | D17: ='202601'!B10 -> 348 | E17: =SUM(B17:D17) -> 587
A18: 入金者数(ユニーク) | B18: ='202511'!B21 -> 32 | C18: ='202512'!B25 -> 2234 | D18: ='202601'!B25 -> 1542 | E18: =SUM(B18:D18) -> 3808
A19: アクティブプレイ人数 | B19: ='202511'!B22 -> 84 | C19: ='202512'!B26 -> 798 | D19: ='202601'!B26 -> 1339 | E19: =SUM(B19:D19) -> 2221
A20: 総入金額 | B20: ='202511'!B23 -> 586146 | C20: ='202512'!B27 -> 66633871 | D20: ='202601'!B27 -> 129457997 | E20: =SUM(B20:D20) -> 196678014
A21: 総出金額 | B21: ='202511'!B28 -> 528463 | C21: ='202512'!B32 -> 48341793 | D21: ='202601'!B32 -> 94439992 | E21: =SUM(B21:D21) -> 143310248
A22: 入出金差分 | B22: ='202511'!B23-'202511'!B28 -> 57683 | C22: ='202512'!B27-'202512'!B32 -> 18292078 | D22: ='202601'!B27-'202601'!B32 -> 35018005 | E22: =SUM(B22:D22) -> 53367766
A23: T/O(合計) | B23: ='202511'!B32 -> 5043994.2 | C23: ='202512'!B36 -> 1120432234 | D23: ='202601'!B36 -> 2033078021 | E23: =SUM(B23:D23) -> 3158554250
A24: 勝利金(合計) | B24: ='202511'!B35 -> 4980421.4 | C24: ='202512'!B39 -> 1084888258 | D24: ='202601'!B39 -> 1964281147 | E24: =SUM(B24:D24) -> 3054149826
A25: RTP | B25: ='202511'!C38 -> 0.95612659 | C25: ='202512'!C42 -> 0.96604376 | D25: ='202601'!C42 -> 0.96814145 | E25: =AVERAGE(B25:D25) -> 0.96343727
A26: GGR | B26: ='202511'!B41 -> 63572.8 | C26: ='202512'!B45 -> 35543976 | D26: ='202601'!B45 -> 68796875 | E26: =SUM(B26:D26) -> 1.0440442e+08
A27: NGR | B27: ='202511'!B56 -> -4802217.4 | C27: ='202512'!B64 -> 15958869 | D27: ='202601'!B64 -> 36048614 | E27: =SUM(B27:D27) -> 47205265
A30: 【ゲーム別GGR（2025/12）】
A31: ゲーム種別 | B31: GGR | C31: NGR | D31: 割合
A32: パチンコ | B32: ='202512'!B128 -> 4373745.1 | C32: ='202512'!B130 -> 4373745.1 | D32: =IFERROR(B32/SUM($B$32:$B$35),0) -> 0.1487952
A33: パチスロ | B33: ='202512'!B147 -> 3186351.8 | C33: ='202512'!B149 -> 3186351.8 | D33: =IFERROR(B33/SUM($B$32:$B$35),0) -> 0.10839997
A34: スロット | B34: ='202512'!B166 -> 17254981 | C34: ='202512'!B168 -> 17254981 | D34: =IFERROR(B34/SUM($B$32:$B$35),0) -> 0.58701601
A35: ライブ | B35: ='202512'!B185 -> 4579318.2 | C35: ='202512'!B187 -> 4579318.2 | D35: =IFERROR(B35/SUM($B$32:$B$35),0) -> 0.15578882
A36: 合計 | B36: =SUM(B32:B35) -> 29394396 | C36: =SUM(C32:C35) -> 29394396 | D36: 100%
A39: 【入出金手段別内訳（2025/12）】
A40: 入金手段 | B40: 金額 | C40: 件数 | D40: 割合
A41: 銀行（自動） | B41: ='202512'!B194 -> 15576600 | C41: ='202512'!C194 -> 164 | D41: =IFERROR(B41/SUM($B$41:$B$45),0) -> 0.233764
A42: 仮想通貨 | B42: ='202512'!B195 -> 7849442 | C42: ='202512'!C195 -> 312 | D42: =IFERROR(B42/SUM($B$41:$B$45),0) -> 0.11779958
A43: 銀行（手動） | B43: ='202512'!B196 -> 8729186 | C43: ='202512'!C196 -> 519 | D43: =IFERROR(B43/SUM($B$41:$B$45),0) -> 0.13100223
A44: EC(コンビニ) | B44: ='202512'!B197 -> 1121000 | C44: ='202512'!C197 -> 36 | D44: =IFERROR(B44/SUM($B$41:$B$45),0) -> 0.016823276
A45: PayPay | B45: ='202512'!B198 -> 33357643 | C45: ='202512'!C198 -> 2660 | D45: =IFERROR(B45/SUM($B$41:$B$45),0) -> 0.50061091
A46: 入金合計 | B46: =SUM(B41:B45) -> 66633871 | C46: =SUM(C41:C45) -> 3691 | D46: 100%
A50: 【全期間 入出金手段別内訳】
A52: 入金手段 | B52: 2025/11 | C52: 2025/12 | D52: 2026/01 | E52: 合計 | F52: 割合
A53: 銀行（自動） | B53: 21000 | C53: ='202512'!B194 -> 15576600 | D53: ='202601'!B194 -> 27866500 | E53: =SUM(B53:D53) -> 43464100 | F53: =IFERROR(E53/E58,0) -> 0.22102038
A54: 仮想通貨 | B54: 54634 | C54: ='202512'!B195 -> 7849442 | D54: ='202601'!B195 -> 8929491 | E54: =SUM(B54:D54) -> 16833567 | F54: =IFERROR(E54/E58,0) -> 0.085600791
A55: 銀行（手動） | B55: 80000 | C55: ='202512'!B196 -> 8729186 | D55: ='202601'!B196 -> 16432390 | E55: =SUM(B55:D55) -> 25241576 | F55: =IFERROR(E55/E58,0) -> 0.12835657
A56: EC(コンビニ) | B56: 10000 | C56: ='202512'!B197 -> 1121000 | D56: ='202601'!B197 -> 7622000 | E56: =SUM(B56:D56) -> 8753000 | F56: =IFERROR(E56/E58,0) -> 0.044510099
A57: PayPay | B57: 394500 | C57: ='202512'!B198 -> 33357643 | D57: ='202601'!B198 -> 68607616 | E57: =SUM(B57:D57) -> 102359759 | F57: =IFERROR(E57/E58,0) -> 0.52051216
A58: 入金合計 | B58: =SUM(B53:B57) -> 560134 | C58: =SUM(C53:C57) -> 66633871 | D58: =SUM(D53:D57) -> 129457997 | E58: =SUM(E53:E57) -> 196652002 | F58: 100%
A61: 出金手段 | B61: 2025/11 | C61: 2025/12 | D61: 2026/01 | E61: 合計 | F61: 割合
A62: 銀行（自動） | B62: 0 | C62: ='202512'!B202 -> 11122808 | D62: ='202601'!B202 -> 40559584 | E62: =SUM(B62:D62) -> 51682392 | F62: =IFERROR(E62/E66,0) -> 0.36065808
A63: 仮想通貨 | B63: 8000 | C63: ='202512'!B203 -> 10897654 | D63: ='202601'!B203 -> 28256801 | E63: =SUM(B63:D63) -> 39162455 | F63: =IFERROR(E63/E66,0) -> 0.27328951
A64: 銀行（手動） | B64: 100000 | C64: ='202512'!B204 -> 18865520 | D64: ='202601'!B204 -> 22693638 | E64: =SUM(B64:D64) -> 41659158 | F64: =IFERROR(E64/E66,0) -> 0.29071239
A65: PayPay | B65: 410463 | C65: ='202512'!B205 -> 7455811 | D65: ='202601'!B205 -> 2929969 | E65: =SUM(B65:D65) -> 10796243 | F65: =IFERROR(E65/E66,0) -> 0.075340016
A66: 出金合計 | B66: =SUM(B62:B65) -> 518463 | C66: =SUM(C62:C65) -> 48341793 | D66: =SUM(D62:D65) -> 94439992 | E66: =SUM(E62:E65) -> 143300248 | F66: 100%
A69: リスト経由 | B69: 2025/11 | C69: 2025/12 | D69: 2026/01 | E69: 合計
A70: リスト経由 | B70: ='202511'!B200 | C70: ='202512'!B208 -> 430 | D70: ='202601'!B207 | E70: =SUM(B70:D70) -> 430
A71: リスト経由入金ユーザー | B71: ='202511'!B201 | C71: ='202512'!B209 -> 119 | D71: ='202601'!B208 | E71: =SUM(B71:D71) -> 119

Sheet 202511
A1: 項目名 | B1: 月次合計 | C1: 日次平均 | D1: 11/27 | E1: 11/28 | F1: 11/29 | G1: 11/30
D2: 木 | E2: 金 | F2: 土 | G2: 日
A3: 全体KPI | B3: =SUM(D3:G3) -> 0
A4: 登録人数 | B4: =SUM(D4:G4) -> 300 | C4: =AVERAGE(D4:G4) -> 75 | D4: =171-10 -> 161 | E4: 50 | F4: 41 | G4: 48
A5: ログインユーザー数 | B5: =SUM(D5:G5) -> 193 | C5: =AVERAGE(D5:G5) -> 48.25 | D5: 92 | E5: 46 | F5: 31 | G5: 24
A6: SMS認証 | B6: =SUM(D6:G6) -> 166 | C6: =AVERAGE(D6:G6) -> 41.5 | D6: 89 | E6: 27 | F6: 32 | G6: 18
A7: 登録に対してSMS認証割合 | B7: =SUM(D7:G7) -> 2.2482828 | C7: =AVERAGE(D7:G7) -> 0.56207071 | D7: =IFERROR(D6/D4,0) -> 0.55279503 | E7: =IFERROR(E6/E4,0) -> 0.54 | F7: =IFERROR(F6/F4,0) -> 0.7804878 | G7: =IFERROR(G6/G4,0) -> 0.375
A8: 入金不要ボーナス使用済ユーザー数 | B8: =SUM(D8:G8) -> 0 | C8: =AVERAGE(D8:G8) -> 0 | D8: 0 | E8: 0 | F8: 0 | G8: 0
A9: 登録に対してNDB使用割合 | B9: =SUM(D9:G9) -> 0 | C9: =AVERAGE(D9:G9) -> 0 | D9: =D8/D4 -> 0 | E9: =E8/E4 -> 0 | F9: =F8/F4 -> 0 | G9: =G8/G4 -> 0
A10: FTD数 | B10: =SUM(D10:G10) -> 8 | C10: =AVERAGE(D10:G10) -> 2 | D10: 7 | E10: 1 | F10: 0 | G10: 0
A11: 登録に対して1st使用割合 | B11: =SUM(D11:G11) -> 0.063478261 | C11: =AVERAGE(D11:G11) -> 0.015869565 | D11: =D10/D4 -> 0.043478261 | E11: =E10/E4 -> 0.02 | F11: =F10/F4 -> 0 | G11: =G10/G4 -> 0
A12: 2nd入金以降ユーザー数 | B12: =SUM(D12:G12) -> 10 | C12: =AVERAGE(D12:G12) -> 2.5 | D12: 6 | E12: 1 | F12: 0 | G12: 3
A13: 登録に対して2nd使用割合 | B13: =SUM(D13:G13) -> 0.11976708 | C13: =AVERAGE(D13:G13) -> 0.02994177 | D13: =D12/D4 -> 0.037267081 | E13: =E12/E4 -> 0.02 | F13: =F12/F4 -> 0 | G13: =G12/G4 -> 0.0625
A14: 3nd入金以降ユーザー数 | B14: =SUM(D14:G14) -> 3 | C14: =AVERAGE(D14:G14) -> 0.75 | D14: 3 | E14: 0 | F14: 0 | G14: 0
A15: 登録に対して3nd使用割合 | B15: =SUM(D15:G15) -> 0.01863354 | C15: =AVERAGE(D15:G15) -> 0.0046583851 | D15: =D14/D4 -> 0.01863354 | E15: =E14/E4 -> 0 | F15: =F14/F4 -> 0 | G15: =G14/G4 -> 0
A16: 4nd入金以降ユーザー数 | B16: =SUM(D16:G16) -> 21 | C16: =AVERAGE(D16:G16) -> 5.25 | D16: 6 | E16: 4 | F16: 5 | G16: 6
A17: 登録に対して4nd使用割合 | B17: =SUM(D17:G17) -> 0.3642183 | C17: =AVERAGE(D17:G17) -> 0.091054575 | D17: =D16/D4 -> 0.037267081 | E17: =E16/E4 -> 0.08 | F17: =F16/F4 -> 0.12195122 | G17: =G16/G4 -> 0.125
A18: 今月登録のFTD以降ユーザー数 | B18: =SUM(D18:G18) -> 42 | C18: =AVERAGE(D18:G18) -> 10.5 | D18: =D10+D12+D14+D16 -> 22 | E18: =E10+E12+E14+E16 -> 6 | F18: =F10+F12+F14+F16 -> 5 | G18: =G10+G12+G14+G16 -> 9
A19: 今月登録FTD以降ユーザー割合 | B19: =SUM(D19:G19) -> 0.56609718 | C19: =AVERAGE(D19:G19) -> 0.1415243 | D19: =D18/D4 -> 0.13664596 | E19: =E18/E4 -> 0.12 | F19: =F18/F4 -> 0.12195122 | G19: =G18/G4 -> 0.1875
A20: 総入金回数 | B20: =SUM(D20:G20) -> 44 | C20: =AVERAGE(D20:G20) -> 11 | D20: 5 | E20: 13 | F20: 9 | G20: 17
A21: 入金者数(ユニーク) | B21: =SUM(D21:G21) -> 32 | C21: =AVERAGE(D21:G21) -> 8 | D21: 4 | E21: 9 | F21: 7 | G21: 12
A22: アクティブプレイ人数 | B22: 84 | C22: =AVERAGE(D22:G22) -> 10 | D22: 6 | E22: 9 | F22: 11 | G22: 14
A23: 総入金額 / Total DP amt | B23: =SUM(D23:G23) -> 586146 | C23: =AVERAGE(D23:G23) -> 146536.5 | D23: 96446 | E23: 224500 | F23: 90000 | G23: 175200
A24: 平均入金額(一回の入金額) / Ave amt per DP | B24: =SUM(D24:G24) -> 56864.313 | C24: =AVERAGE(D24:G24) -> 14216.078 | D24: =D23/D20 -> 19289.2 | E24: =E23/E20 -> 17269.231 | F24: =F23/F20 -> 10000 | G24: =G23/G20 -> 10305.882
A25: 平均入金額(ユニークユーザー) / Ave DP amt (Unique user) | B25: =SUM(D25:G25) -> 76513.087 | C25: =AVERAGE(D25:G25) -> 19128.272 | D25: =D23/D21 -> 24111.5 | E25: =E23/E21 -> 24944.444 | F25: =F23/F21 -> 12857.143 | G25: =G23/G21 -> 14600
A26: 総出金回数 | D26: 0 | E26: 0 | F26: 7 | G26: 7
A27: 総出金人数 | D27: 0 | E27: 0 | F27: 5 | G27: 6
A28: 総出金額 / Total WD amt | B28: =SUM(D28:G28) -> 528463 | C28: =AVERAGE(D28:G28) -> 132115.75 | D28: 0 | E28: 0 | F28: 240587 | G28: 287876
A29: 入金額に対して出金割合
A30: T/O(リアルのみ) / Total real bet | B30: =SUM(D30:G30) -> 5043994.2 | C30: =AVERAGE(D30:G30) -> 1260998.6 | D30: 449205 | E30: 1168610 | F30: 1223669.2 | G30: 2202510
A31: T/O率(リアルのみ) / Total real bet ratio | B31: =B30/B23 -> 8.6053546 | C31: =AVERAGE(D31:G31) -> 9.0076747 | D31: =D30/D23 -> 4.6575804 | E31: =E30/E23 -> 5.2053898 | F31: =F30/F23 -> 13.596324 | G31: =G30/G23 -> 12.571404
A32: T/O(ボーナス+リアルマネーの合計) / Total bet (Real+Bonus) | B32: =SUM(D32:G32) -> 5043994.2 | C32: =AVERAGE(D32:G32) -> 1260998.6 | D32: =D30 -> 449205 | E32: =E30 -> 1168610 | F32: =F30 -> 1223669.2 | G32: =G30 -> 2202510
A33: 勝利金(リアルのみ) / Winning amt (Real) | B33: =SUM(D33:G33) -> 4980421.4 | C33: =AVERAGE(D33:G33) -> 1245105.4 | D33: 374255.4 | E33: 1088771 | F33: 1273949 | G33: 2243446
A34: 勝利金(ボーナスのみ) / Winning amt (Bonus) | B34: =SUM(D34:G34) -> 0 | C34: =AVERAGE(D34:G34) -> 0 | D34: 0 | E34: 0 | F34: ¥0 | G34: 0
A35: 勝利金(ボーナス+リアルマネーの合計) / Winning (Bonus+Real) | B35: =SUM(D35:G35) -> 4980421.4 | C35: =AVERAGE(D35:G35) -> 1245105.4 | D35: =D33 -> 374255.4 | E35: =E33 -> 1088771 | F35: =F33 -> 1273949 | G35: =G33 -> 2243446
A36: リアルマネー残高 / Real Money Balance | B36: =SUM(D36:G36) -> 12692491 | C36: =AVERAGE(D36:G36) -> 3173122.8 | D36: 0 | E36: 4311521 | F36: 4243937 | G36: 4137033
A37: ボーナス・マネー残高 / Bonus Money Balance | B37: =SUM(D37:G37) -> 2199720 | C37: =AVERAGE(D37:G37) -> 549930 | D37: 0 | E37: 0 | F37: 1099879 | G37: 1099841
A38: RTP | B38: =SUM(D38:G38) -> 3.8245064 | C38: =AVERAGE(D38:G38) -> 0.95612659 | D38: =D35/D32 -> 0.83315057 | E38: =E35/E32 -> 0.93168037 | F38: =F35/F32 -> 1.0410894 | G38: =G35/G32 -> 1.0185861
A39: T/O(ボーナスのみ) / Total bet (Bonus) | B39: =SUM(D39:G39) -> 0 | C39: =AVERAGE(D39:G39) -> 0 | D39: 0 | E39: 0 | F39: ¥0 | G39: ¥1
A40: T/O率(ボーナスのみ) / Total bet ratio (Bonus) | B40: =SUM(D40:G40) -> 0 | C40: =AVERAGE(D40:G40) -> 0 | D40: 0 | E40: 0 | F40: 0.00% | G40: 0.00%
A41: GGR | B41: =SUM(D41:G41) -> 63572.8 | C41: =AVERAGE(D41:G41) -> 15893.2 | D41: =D32-D35 -> 74949.6 | E41: =E32-E35 -> 79839 | F41: =F32-F35 -> -50279.8 | G41: =G30-G33 -> -40936
A42: 差分GGR | B42: =SUM(D42:G42) -> 57683 | C42: =AVERAGE(D42:G42) -> 14420.75 | D42: =D23-D28 -> 96446 | E42: =E23-E28 -> 224500 | F42: =F23-F28 -> -150587 | G42: =G23-G28 -> -112676
A43: ヘブンズショットコスト/Heavensshot Cost | B43: =SUM(D43:G43) -> 0 | C43: =AVERAGE(D43:G43) -> 0 | D43: 0 | E43: 0 | F43: ¥0 | G43: ¥0
A44: トーナメントコスト/Tournament Cost | B44: =SUM(D44:G44) -> 0 | C44: =AVERAGE(D44:G44) -> 0 | D44: 0 | E44: 0 | F44: ¥0 | G44: ¥0
A45: 新規用期間イベントコスト/new user event Cost | B45: =SUM(D45:G45) -> 0 | C45: =AVERAGE(D45:G45) -> 0 | D45: 0 | E45: 0 | F45: ¥0 | G45: ¥0
A46: 休眠用期間イベントコスト/old user event Cost | B46: =SUM(D46:G46) -> 0 | C46: =AVERAGE(D46:G46) -> 0 | D46: 0 | E46: 0 | F46: ¥0 | G46: ¥0
A47: 既存用期間イベントコスト/Active user event Cost | B47: =SUM(D47:G47) -> 0 | C47: =AVERAGE(D47:G47) -> 0 | D47: 0 | E47: 0 | F47: ¥0 | G47: ¥0
A48: ドリームポットコスト/Jackpot Cost | B48: =SUM(D48:G48) -> 0 | C48: =AVERAGE(D48:G48) -> 0 | D48: 0 | E48: 0 | F48: ¥0 | G48: ¥0
A49: 入金不要コスト/ Cost | B49: =SUM(D49:G49) -> 0 | C49: =AVERAGE(D49:G49) -> 0 | D49: 0 | E49: 0 | F49: ¥0 | G49: ¥0
A50: AFFイベント コスト / AFF EventCost
A51: ペイメントコスト / Payment cost | B51: =1723439*1.3% -> 22404.707 | C51: =AVERAGE(D51:G51) -> 0 | D51: 0 | E51: 0 | F51: ¥0 | G51: ¥0
A52: プロバイダーフィー / Provider fee | B52: 134503.45 | C52: =AVERAGE(D52:G52) -> 0 | D52: 0 | E52: 0 | F52: ¥0 | G52: ¥0
A53: AFFコスト / Aff cost | B53: =SUM(D53:G53) -> 5407006 | C53: =AVERAGE(D53:G53) -> 1351751.5 | D53: =D86 -> 4957006 | E53: =E86 -> 0 | F53: =F86 -> 0 | G53: =G86 -> 450000
A54: otherコスト / Other cost | B54: =SUM(D54:G54) -> 0 | C54: =AVERAGE(D54:G54) -> 0 | D54: 0 | E54: 0 | F54: ¥0 | G54: ¥0
A55: 総コスト(ボーナスは付与額ベース) / Total cost (Granted bonus included) | B55: =SUM(D55:G55) -> 4957006 | C55: =AVERAGE(D55:G55) -> 2478503 | D55: =SUM(D43:D54) -> 4957006 | E55: =SUM(E43:E54) -> 0 | F55: ¥0 | G55: ¥0
A56: NGR | B56: =SUM(D56:G56) -> -4802217.4 | C56: =AVERAGE(D56:G56) -> -2401108.7 | D56: =D41-D55 -> -4882056.4 | E56: =E41-E55 -> 79839
A57: 差分NGR | B57: =SUM(D57:G57) -> -4636060 | C57: =AVERAGE(D57:G57) -> -2318030 | D57: =D42-D51-D52-D53-D54 -> -4860560 | E57: =E42-E51-E52-E53-E54 -> 224500 | F57: ¥0 | G57: ¥0
B58: =SUM(D58:G58) -> 0 | C58: =AVERAGE(D58:G58) -> #DIV/0!
A59: 【分析指標】 | B59: =SUM(D59:G59) -> 0 | C59: =AVERAGE(D59:G59) -> #DIV/0!
A60: ARPU(全登録ユーザー) | B60: =B56/B4 -> -16007.391 | C60: =C56/C4 -> -32014.783 | D60: =D56/D4 -> -30323.332 | E60: =E56/E4 -> 1596.78 | F60: =F56/F4 -> 0 | G60: =G56/G4 -> 0
A61: ARPPU(課金ユーザー) | B61: =B56/B21 -> -150069.29 | C61: =C56/C21 -> -300138.59 | D61: =D56/D21 -> -1220514.1 | E61: =E56/E21 -> 8871 | F61: =F56/F21 -> 0 | G61: =G56/G21 -> 0
A62: FTD以上転移率 | B62: =B18/B4 -> 0.14 | C62: =C18/C4 -> 0.14 | D62: =D18/D4 -> 0.13664596 | E62: =E18/E4 -> 0.12 | F62: =F18/F4 -> 0.12195122 | G62: =G18/G4 -> 0.1875
A63: 2nd継続率 | B63: =B12/B10 -> 1.25 | C63: =C12/C10 -> 1.25 | D63: =D12/D10 -> 0.85714286 | E63: =E12/E10 -> 1 | F63: =F12/F10 -> #DIV/0! | G63: =G12/G10 -> #DIV/0!
A64: アクティブ率 | B64: =B22/B4 -> 0.28 | C64: =C22/C4 -> 0.13333333 | D64: =D22/D4 -> 0.037267081 | E64: =E22/E4 -> 0.18 | F64: =F22/F4 -> 0.26829268 | G64: =G22/G4 -> 0.29166667
A65: GGRマージン率 | B65: =B41/B23 -> 0.10845898 | C65: =C41/C23 -> 0.10845898 | D65: =D41/D23 -> 0.77711465 | E65: =E41/E23 -> 0.35563029 | F65: =F41/F23 -> -0.55866444 | G65: =G41/G23 -> -0.23365297
A66: NGRマージン率 | B66: =B56/B23 -> -8.192869 | C66: =C56/C23 -> -16.385738 | D66: =D56/D23 -> -50.619584 | E66: =E56/E23 -> 0.35563029 | F66: =F56/F23 -> 0 | G66: =G56/G23 -> 0
A67: 平均入金回数/ユーザー | B67: =B20/B21 -> 1.375 | C67: =C20/C21 -> 1.375 | D67: =D20/D21 -> 1.25 | E67: =E20/E21 -> 1.4444444 | F67: =F20/F21 -> 1.2857143 | G67: =G20/G21 -> 1.4166667
B68: =SUM(D68:G68) -> 0 | C68: =AVERAGE(D68:G68) -> #DIV/0!
A69: プロモーション開催期間 / Promotion duration | B69: =SUM(D69:G69) -> 0 | C69: =AVERAGE(D69:G69) -> #DIV/0!
A70: 目的 / Purpose | B70: =SUM(D70:G70) -> 0 | C70: =AVERAGE(D70:G70) -> #DIV/0!
B71: =SUM(D71:G71) -> 0 | C71: =AVERAGE(D71:G71) -> #DIV/0!
A72: Affiliate | B72: =SUM(D72:G72) -> 0 | C72: =AVERAGE(D72:G72) -> #DIV/0!
A73: AFF経由登録者数 / Registration under AFF | B73: =SUM(D73:G73) -> 302 | C73: =AVERAGE(D73:G73) -> 75.5 | D73: 169 | E73: 44 | F73: 39 | G73: 50
A74: AFF経由FTD数 / FTD under AFF | B74: =SUM(D74:G74) -> 34 | C74: =AVERAGE(D74:G74) -> 8.5 | D74: 17 | E74: 4 | F74: 5 | G74: 8
A75: AFF数 | B75: =SUM(D75:G75) -> 8 | C75: =AVERAGE(D75:G75) -> 2 | D75: 6 | E75: 1 | F75: 0 | G75: 1
A76: AFF経由入金額 / DP amt under AFF | B76: =SUM(D76:G76) -> 0 | C76: =AVERAGE(D76:G76) -> #DIV/0!
A77: AFF経由出金額 / WD amt under AFF | B77: =SUM(D77:G77) -> 0 | C77: =AVERAGE(D77:G77) -> #DIV/0!
A78: AFF経由RTP / RTP under AFF | B78: =SUM(D78:G78) -> 0 | C78: =AVERAGE(D78:G78) -> #DIV/0!
A79: AFF経由GGR / GGR under AFF | B79: =SUM(D79:G79) -> 0 | C79: =AVERAGE(D79:G79) -> #DIV/0!
A80: 差分GGR | B80: =SUM(D80:G80) -> 0 | C80: =AVERAGE(D80:G80) -> #DIV/0!
A81: AFF経由ボーナス額 / Bonus Granted Amt under AFF | B81: =SUM(D81:G81) -> 0 | C81: =AVERAGE(D81:G81) -> #DIV/0!
A82: AFFデモコスト(プロバイダーフィー) | B82: =SUM(D82:G82) -> 71000 | C82: =AVERAGE(D82:G82) -> 35500 | D82: 65000 | G82: 6000
A83: AFF経由otherコスト(掲載費等) / Other cost under AFF | B83: =SUM(D83:G83) -> 5405266 | C83: =AVERAGE(D83:G83) -> 1351316.5 | D83: 4955266 | E83: 0 | F83: 0 | G83: 450000
A84: AFFレベニュー報酬合計 | B84: =SUM(D84:G84) -> 0 | C84: =AVERAGE(D84:G84) -> #DIV/0!
A85: AFF支払い報酬額 / Aff commission amt | B85: 1740 | C85: =AVERAGE(D85:G85) -> 1740 | D85: 1740
A86: AFF全コスト / Total cost under AFF | B86: =SUM(D86:G86) -> 5407006 | C86: =AVERAGE(D86:G86) -> 1351751.5 | D86: =SUM(D83:D85) -> 4957006 | E86: =SUM(E83:E85) -> 0 | F86: =SUM(F83:F85) -> 0 | G86: =SUM(G83:G85) -> 450000
A87: AFF経由NGR / NGR under AFF | B87: =SUM(D87:G87) -> 0 | C87: =AVERAGE(D87:G87) -> #DIV/0!
A88: AFF経由FTD率 | B88: =SUM(D88:G88) -> 0.47970594 | C88: =AVERAGE(D88:G88) -> 0.11992648 | D88: =D74/D73 -> 0.10059172 | E88: =E74/E73 -> 0.090909091 | F88: =F74/F73 -> 0.12820513 | G88: =G74/G73 -> 0.16
A89: AFF経由ARPU | B89: =SUM(D89:G89) -> 0 | C89: =AVERAGE(D89:G89) -> #DIV/0!
A90: 目的 / Purpose | B90: =SUM(D90:G90) -> 0 | C90: =AVERAGE(D90:G90) -> #DIV/0!
B91: =SUM(D91:G91) -> 0 | C91: =AVERAGE(D91:G91) -> #DIV/0!
A92: パチンコ | B92: =SUM(D92:G92) -> 0 | C92: =AVERAGE(D92:G92) -> #DIV/0!
A93: リアルマネーTO / Turnover(Real) | B93: =SUM(D93:G93) -> 565098.5 | C93: =AVERAGE(D93:G93) -> 141274.62 | D93: 395163 | E93: 5104.5 | F93: 34833 | G93: 129998
A94: 勝利金(リアル) / Payout(Real) | B94: =SUM(D94:G94) -> 542962.1 | C94: =AVERAGE(D94:G94) -> 135740.52 | D94: 264634.6 | E94: 48330 | F94: 24213.8 | G94: 205783.7
A95: リアルマネーユニークユーザー数 / Unique user (Real) | B95: =SUM(D95:G95) -> 18 | C95: =AVERAGE(D95:G95) -> 4.5 | D95: 8 | E95: 1 | F95: 2 | G95: 7
A96: リアルマネーユニークベット数 / Bet number (Real) | B96: =SUM(D96:G96) -> 53 | C96: =AVERAGE(D96:G96) -> 13.25 | D96: 3 | E96: 4 | F96: 15 | G96: 31
A97: ボーナスマネーT/O / Turnover(Bonus) | B97: =SUM(D97:G97) -> 0 | C97: =AVERAGE(D97:G97) -> 0 | D97: 0 | E97: 0 | F97: 0 | G97: 0
A98: 勝利金(ボーナス) / Payout(Bonus) | B98: =SUM(D98:G98) -> 0 | C98: =AVERAGE(D98:G98) -> 0 | D98: 0 | E98: 0 | F98: 0 | G98: 0
A99: ボーナスマネーユニークユーザー数 / Unique user (Bonus) | B99: =SUM(D99:G99) -> 0 | C99: =AVERAGE(D99:G99) -> 0 | D99: 0 | E99: 0 | F99: 0 | G99: 0
A100: ボーナスマネーユニークベット数 / Bet number (Bonus) | B100: =SUM(D100:G100) -> 0 | C100: =AVERAGE(D100:G100) -> 0 | D100: 0 | E100: 0 | F100: 0 | G100: 0
...

Sheet 202512
A1: 項目名 | B1: 月次合計 | C1: 日次平均 | D1: 12/1 | E1: 12/2 | F1: 12/3 | G1: 12/4 | H1: 12/5 | I1: 12/6 | J1: 12/7 | K1: 12/8 | L1: 12/9 | M1: 12/10 | N1: 12/11 | O1: 12/12 | P1: 12/13 | Q1: 12/14 | R1: 12/15 | S1: 12/16 | T1: 12/17 | U1: 12/18 | V1: 12/19 | W1: 12/20 | X1: 12/21 | Y1: 12/22 | Z1: 12/23 | AA1: 12/24 | AB1: 12/25 | AC1: 12/26 | AD1: 12/27 | AE1: 12/28 | AF1: 12/29 | AG1: 12/30 | AH1: 12/31
D2: 月 | E2: 火 | F2: 水 | G2: 木 | H2: 金 | I2: 土 | J2: 日 | K2: 月 | L2: 火 | M2: 水 | N2: 木 | O2: 金 | P2: 土 | Q2: 日 | R2: 月 | S2: 火 | T2: 水 | U2: 木 | V2: 金 | W2: 土 | X2: 日 | Y2: 月 | Z2: 火 | AA2: 水 | AB2: 木 | AC2: 金 | AD2: 土 | AE2: 日 | AF2: 月 | AG2: 火 | AH2: 水
A3: 全体KPI
A4: 登録人数 | B4: =SUM(D4:AH4) -> 2552 | C4: =AVERAGE(D4:AH4) -> 82.322581 | D4: 33 | E4: 37 | F4: 29 | G4: 56 | H4: =44-7 -> 37 | I4: =36-1 -> 35 | J4: =39-1 -> 38 | K4: =32-1 -> 31 | L4: =40-5 -> 35 | M4: =69-26 -> 43 | N4: =34-2 -> 32 | O4: =41-3 -> 38 | P4: 46 | Q4: 59 | R4: 72 | S4: =84-1 -> 83 | T4: =62-1 -> 61 | U4: 29 | V4: =31-1 -> 30 | W4: 36 | X4: 43 | Y4: 116 | Z4: 208 | AA4: 175 | AB4: 211 | AC4: 156 | AD4: 140 | AE4: 133 | AF4: 69 | AG4: 164 | AH4: 277
A5: ログインユーザー数 | B5: =SUM(D5:AH5) -> 2399 | C5: =AVERAGE(D5:AH5) -> 79.966667 | D5: 25 | E5: 9 | F5: 32 | G5: 36 | H5: 44 | I5: 34 | J5: 31 | K5: 31 | L5: 36 | M5: 38 | N5: 39 | O5: 40 | P5: 47 | R5: 46 | S5: 57 | T5: 67 | U5: 51 | V5: 61 | W5: 67 | X5: 48 | Y5: 54 | Z5: 81 | AA5: 118 | AB5: 115 | AC5: 148 | AD5: 147 | AE5: 202 | AF5: 219 | AG5: 188 | AH5: 288
A6: SMS認証 | B6: =SUM(D6:AH6) -> 2521 | C6: =AVERAGE(D6:AH6) -> 81.322581 | D6: 25 | E6: 21 | F6: 24 | G6: 54 | H6: 37 | I6: 35 | J6: 38 | K6: 31 | L6: 35 | M6: 43 | N6: 32 | O6: 38 | P6: 46 | Q6: 59 | R6: 72 | S6: 83 | T6: 61 | U6: 29 | V6: 30 | W6: 36 | X6: 43 | Y6: 116 | Z6: 208 | AA6: 175 | AB6: 211 | AC6: 156 | AD6: 140 | AE6: 133 | AF6: 69 | AG6: 164 | AH6: 277
A7: 登録に対してSMS認証割合 | B7: =C7 -> 0.97151662 | C7: =AVERAGE(D7:AH7) -> 0.97151662 | D7: =D6/D4 -> 0.75757576 | E7: =E6/E4 -> 0.56756757 | F7: =F6/F4 -> 0.82758621 | G7: =G6/G4 -> 0.96428571 | H7: =H6/H4 -> 1 | I7: =I6/I4 -> 1 | J7: =J6/J4 -> 1 | K7: =K6/K4 -> 1 | ... AH7: =AH6/AH4 -> 1
A8: 入金不要ボーナス使用済ユーザー数 | B8: =SUM(D8:AH8) -> 1554 | C8: =AVERAGE(Y8:AH8) -> 155.4 | D8: 0 | E8: 0 | F8: 0 | G8: 0 | H8: 0 | I8: 0 | J8: 0 | K8: 0 | L8: 0 | M8: 0 | N8: 0 | O8: 0 | P8: 0 | Q8: 0 | R8: 0 | S8: 0 | T8: 0 | U8: 0 | V8: 0 | W8: 0 | X8: 0 | Y8: 106 | Z8: 184 | AA8: 166 | AB8: 210 | AC8: 136 | AD8: 123 | AE8: 133 | AF8: 60 | AG8: 162 | AH8: 274
A9: 登録に対してNDB使用割合 | B9: =SUM(D9:AH9) -> 9.3391467 | C9: =AVERAGE(Y9:AH9) -> 0.93391467 | D9: =D8/D4 -> 0 | E9: =E8/E4 -> 0 | F9: 0 | G9: 0 | H9: 0 | I9: 0 | J9: 0 | K9: 0 | L9: 0 | M9: 0 | N9: 0 | O9: 0 | P9: 0 | Q9: 0 | R9: 0 | S9: 0 | T9: 0 | U9: 0 | V9: 0 | W9: 0 | X9: 0 | Y9: =Y8/Y4 -> 0.9137931 | Z9: =Z8/Z4 -> 0.88461538 | AA9: =AA8/AA4 -> 0.94857143 | AB9: =AB8/AB4 -> 0.99526066 | AC9: =AC8/AC4 -> 0.87179487 | AD9: =AD8/AD4 -> 0.87857143 | AE9: =AE8/AE4 -> 1 | AF9: =AF8/AF4 -> 0.86956522 | ... AH9: =AH8/AH4 -> 0.98916968
A10: FTDのみ入金者数 | B10: =SUM(D10:AH10) -> 231 | C10: =AVERAGE(D10:AH10) -> 7.4516129 | D10: 3 | E10: 3 | F10: 1 | G10: 3 | H10: 4 | I10: 1 | J10: 2 | K10: 1 | L10: 4 | M10: 4 | N10: 2 | O10: 4 | P10: 1 | Q10: 8 | R10: 9 | S10: 9 | T10: 5 | U10: 3 | V10: 1 | W10: 5 | X10: 8 | Y10: 6 | Z10: 13 | AA10: 9 | AB10: 8 | AC10: 16 | AD10: 15 | AE10: 6 | AF10: 5 | AG10: 12 | AH10: 60
A11: 登録に対してFTDのみの割合 | B11: =C11 -> 0.084250455 | C11: =AVERAGE(D11:AH11) -> 0.084250455 | D11: =D10/D4 -> 0.090909091 | E11: =E10/E4 -> 0.081081081 | F11: =F10/F4 -> 0.034482759 | G11: =G10/G4 -> 0.053571429 | H11: =H10/H4 -> 0.10810811 | I11: =I10/I4 -> 0.028571429 | J11: =J10/J4 -> 0.052631579 | K11: =K10/K4 -> 0.032258065 | ... AH11: =AH10/AH4 -> 0.2166065
A12: 2nd入金のみユーザー数 | B12: =SUM(D12:AH12) -> 66 | C12: =AVERAGE(D12:AH12) -> 2.1290323 | D12: 1 | E12: 3 | F12: 0 | G12: 2 | H12: 0 | I12: 0 | J12: 2 | K12: 0 | L12: 0 | M12: 2 | N12: 1 | O12: 2 | P12: 1 | Q12: 1 | R12: 2 | S12: 4 | T12: 2 | U12: 1 | V12: 2 | W12: 2 | X12: 1 | Y12: 2 | Z12: 4 | AA12: 3 | AB12: 4 | AC12: 3 | AD12: 8 | AE12: 2 | AF12: 2 | AG12: 3 | AH12: 6
A13: 登録に対して2nd使用割合 | B13: =C13 -> 0.028724262 | C13: =AVERAGE(D13:AH13) -> 0.028724262 | D13: =D12/D4 -> 0.03030303 | E13: =E12/E4 -> 0.081081081 | F13: =F12/F4 -> 0 | G13: =G12/G4 -> 0.035714286 | H13: =H12/H4 -> 0 | I13: =I12/I4 -> 0 | J13: =J12/J4 -> 0.052631579 | K13: =K12/K4 -> 0 | ... AH13: =AH12/AH4 -> 0.02166065
A14: 3nd入金のみユーザー数 | B14: =SUM(D14:AH14) -> 30 | C14: =AVERAGE(D14:AH14) -> 0.96774194 | D14: 0 | E14: 1 | F14: 1 | G14: 0 | H14: 0 | I14: 0 | J14: 3 | K14: 1 | L14: 0 | M14: 2 | N14: 1 | O14: 2 | P14: 0 | Q14: 0 | R14: 2 | S14: 1 | T14: 2 | U14: 1 | V14: 1 | W14: 0 | X14: 0 | Y14: 1 | Z14: 2 | AA14: 1 | AB14: 2 | AC14: 1 | AD14: 1 | AE14: 0 | AF14: 2 | AG14: 2 | AH14: 0
A15: 登録に対して3nd使用割合 | B15: =C15 -> 0.017151618 | C15: =AVERAGE(D15:AH15) -> 0.017151618 | D15: =D14/D4 -> 0 | E15: =E14/E4 -> 0.027027027 | F15: =F14/F4 -> 0.034482759 | G15: =G14/G4 -> 0 | H15: =H14/H4 -> 0 | I15: =I14/I4 -> 0 | J15: =J14/J4 -> 0.078947368 | K15: =K14/K4 -> 0.032258065 | ... AH15: =AH14/AH4 -> 0
A16: 4nd入金以降ユーザー数 | B16: =SUM(D16:AH16) -> 45 | C16: =AVERAGE(D16:AH16) -> 1.4516129 | D16: 4 | E16: 2 | F16: 3 | G16: 5 | H16: 2 | I16: 4 | J16: 0 | K16: 4 | L16: 2 | M16: 1 | N16: 1 | O16: 1 | P16: 0 | Q16: 1 | R16: 1 | S16: 1 | T16: 0 | U16: 3 | V16: 3 | W16: 0 | X16: 0 | Y16: 0 | Z16: 1 | AA16: 1 | AB16: 0 | AC16: 1 | AD16: 2 | AE16: 0 | AF16: 0 | AG16: 1 | AH16: 1
A17: 登録に対して4nd使用割合 | B17: =C17 -> 0.035180541 | C17: =AVERAGE(D17:AH17) -> 0.035180541 | D17: =D16/D4 -> 0.12121212 | E17: =E16/E4 -> 0.054054054 | F17: =F16/F4 -> 0.10344828 | G17: =G16/G4 -> 0.089285714 | H17: =H16/H4 -> 0.054054054 | I17: =I16/I4 -> 0.11428571 | J17: =J16/J4 -> 0 | K17: =K16/K4 -> 0.12903226 | ... AH17: =AH16/AH4 -> 0.0036101083
A18: 今月登録のFTD以降ユーザー数 | B18: =347+106+57+203 -> 713 | C18: =AVERAGE(D18:AH18) -> 12 | D18: =D10+D12+D14+D16 -> 8 | E18: =E10+E12+E14+E16 -> 9 | F18: =F10+F12+F14+F16 -> 5 | G18: =G10+G12+G14+G16 -> 10 | H18: =H10+H12+H14+H16 -> 6 | I18: =I10+I12+I14+I16 -> 5 | J18: =J10+J12+J14+J16 -> 7 | K18: =K10+K12+K14+K16 -> 6 | ... AH18: =AH10+AH12+AH14+AH16 -> 67
A19: 今月登録FTD以降ユーザー割合 | B19: =C19 -> 0.16530688 | C19: =AVERAGE(D19:AH19) -> 0.16530688 | D19: =D11+D13+D15+D17 -> 0.24242424 | E19: =E11+E13+E15+E17 -> 0.24324324 | F19: =F11+F13+F15+F17 -> 0.17241379 | G19: =G11+G13+G15+G17 -> 0.17857143 | H19: =H11+H13+H15+H17 -> 0.16216216 | I19: =I11+I13+I15+I17 -> 0.14285714 | J19: =J11+J13+J15+J17 -> 0.18421053 | K19: =K11+K13+K15+K17 -> 0.19354839 | ... AH19: =AH11+AH13+AH15+AH17 -> 0.24187726
A20: 今月登録のアクティブユーザー数 | B20: 768
A21: 前月登録のアクティブユーザー数 | B21: 76
A22: 前々月登録のアクティブユーザー数 | B22: -
A23: 3か月以上アクティブプレイヤー数 | B23: -
A24: 総入金回数 | B24: =SUM(D24:AH24) -> 3948 | C24: =AVERAGE(D24:AH24) -> 127.35484 | D24: 42 | E24: 27 | F24: 51 | G24: 38 | H24: 54 | I24: 40 | J24: 49 | K24: 71 | L24: 59 | M24: 107 | N24: 103 | O24: 71 | P24: 88 | Q24: 64 | R24: 116 | S24: 126 | T24: 148 | U24: 108 | V24: 155 | W24: 120 | X24: 119 | Y24: 123 | Z24: 184 | AA24: 170 | AB24: 231 | AC24: 247 | AD24: 194 | AE24: 190 | AF24: 231 | AG24: 267 | AH24: 355
A25: 入金者数(デイリーユニーク) | B25: =SUM(D25:AH25) -> 2234 | C25: =AVERAGE(D25:AH25) -> 72.064516 | D25: 22 | E25: 18 | F25: 21 | G25: 15 | H25: 38 | I25: 22 | J25: 29 | K25: 35 | L25: 29 | M25: 55 | N25: 44 | O25: 37 | P25: 43 | Q25: 38 | R25: 60 | S25: 74 | T25: 70 | U25: 59 | V25: 75 | W25: 66 | X25: 69 | Y25: 71 | Z25: 100 | AA25: 95 | AB25: 121 | AC25: 145 | AD25: 109 | AE25: 127 | AF25: 139 | AG25: 156 | AH25: 252
A26: アクティブプレイ人数（ユニーク） | B26: 798 | C26: =AVERAGE(D26:AH26) -> 142.41935 | D26: 23 | E26: 28 | F26: 27 | G26: 19 | H26: 44 | I26: 30 | J26: 34 | K26: 41 | L26: 38 | M26: 67 | N26: 53 | O26: 47 | P26: 52 | Q26: 50 | R26: 70 | S26: 88 | T26: 86 | U26: 82 | V26: 97 | W26: 93 | X26: 88 | Y26: 176 | Z26: 308 | AA26: 319 | AB26: 340 | AC26: 337 | AD26: 299 | AE26: 331 | AF26: 300 | AG26: 366 | AH26: 482
A27: 総入金額 / Total DP amt | B27: =B193 -> 66633871 | C27: =AVERAGE(D27:AH27) -> 3056096.6 | D27: 945497 | E27: 349000 | F27: 438901 | G27: 792010 | H27: 1645913 | I27: 815512 | J27: 1218881 | K27: 1997198 | L27: 1538477 | M27: 2979139 | N27: 2730300 | O27: 2009507 | P27: 2275078 | Q27: 2904624 | R27: 2293456 | S27: 3684438 | T27: 4433098 | U27: 2314931 | V27: 3564619 | W27: 2441598 | X27: 2884129 | Y27: 3942853 | Z27: 3778360 | AA27: 4704279 | AB27: 5142895 | AC27: 5790196 | AD27: 5145990 | AE27: 3577109 | AF27: 7101798 | AG27: 6150880 | AH27: 5148329
A28: 平均入金額(一回の入金額) / Ave amt per DP | B28: =SUM(D28:AH28) -> 756310.37 | C28: =AVERAGE(D28:AH28) -> 24397.109 | D28: =D27/D24 -> 22511.833 | E28: =E27/E24 -> 12925.926 | F28: =F27/F24 -> 8605.902 | G28: =G27/G24 -> 20842.368 | H28: =H27/H24 -> 30479.87 | I28: =I27/I24 -> 20387.8 | J28: =J27/J24 -> 24875.122 | K28: =K27/K24 -> 28129.549 | ... AH28: =AH27/AH24 -> 14502.335
A29: 平均入金額(ユニークユーザー) / Ave DP amt (Unique user) | B29: =SUM(D29:AH29) -> 1396968.9 | C29: =AVERAGE(D29:AH29) -> 45063.512 | D29: =D27/D25 -> 42977.136 | E29: =E27/E25 -> 19388.889 | F29: =F27/F25 -> 20900.048 | G29: =G27/G25 -> 52800.667 | H29: =H27/H25 -> 43313.5 | I29: =I27/I25 -> 37068.727 | J29: =J27/J25 -> 42030.379 | K29: =K27/K25 -> 57062.8 | ... AH29: =AH27/AH25 -> 20429.877
A30: 総出金回数 | B30: =SUM(D30:AH30) -> 878 | C30: =AVERAGE(D30:AH30) -> 28.322581 | D30: 2 | E30: 9 | F30: 13 | G30: 11 | H30: 9 | I30: 12 | J30: 12 | K30: 11 | L30: 11 | M30: 27 | N30: 10 | O30: 14 | P30: 10 | Q30: 13 | R30: 21 | S30: 25 | T30: 34 | U30: 20 | V30: 30 | W30: 26 | X30: 27 | Y30: 30 | Z30: 43 | AA30: 32 | AB30: 47 | AC30: 82 | AD30: 53 | AE30: 41 | AF30: 57 | AG30: 78 | AH30: 68
A31: 総出金人数 | B31: =SUM(D31:AH31) -> 624 | C31: =AVERAGE(D31:AH31) -> 20.129032 | D31: 2 | E31: 7 | F31: 9 | G31: 7 | H31: 7 | I31: 6 | J31: 8 | K31: 9 | L31: 10 | M31: 13 | N31: 6 | O31: 9 | P31: 7 | Q31: 9 | R31: 15 | S31: 21 | T31: 21 | U31: 17 | V31: 22 | W31: 18 | X31: 20 | Y31: 23 | Z31: 28 | AA31: 25 | AB31: 34 | AC31: 48 | AD31: 38 | AE31: 34 | AF31: 45 | AG31: 53 | AH31: 53
A32: 総出金額 / Total WD amt | B32: =B201 -> 48341793 | C32: =AVERAGE(D32:AH32) -> 1927316.2 | D32: 65000 | E32: 296440 | F32: 1582558 | G32: 587100 | H32: 749292 | I32: 1402604 | J32: 700720 | K32: 552268 | L32: 565000 | M32: 2047916 | N32: 366553 | O32: 2829504 | P32: 1341051 | Q32: 1298576 | R32: 1407954 | S32: 1571617 | T32: 3663422 | U32: 1496310 | V32: 1832892 | W32: 1646195 | X32: 1484922 | Y32: 1991337 | Z32: 3380070 | AA32: 2385924 | AB32: 2618849 | AC32: 5654825 | AD32: 4176571 | AE32: 1342656 | AF32: 3297388 | AG32: 3393454 | AH32: 4017833
A33: 入金額に対して出金割合 | B33: =B32/B27 -> 0.72548379 | C33: =AVERAGE(D33:AH33) -> 0.90739079 | D33: =D32/D27 -> 0.068746913 | E33: =E32/E27 -> 0.84939828 | F33: =F32/F27 -> 3.6057289 | G33: =G32/G27 -> 0.74127852 | H33: =H32/H27 -> 0.45524399 | I33: =I32/I27 -> 1.719906 | J33: =J32/J27 -> 0.57488795 | K33: =K32/K27 -> 0.27652141 | ... O33: =O32/O27 -> 1.4080588
A34: T/O(リアルのみ) / Total real bet | B34: =SUM(D34:AH34) -> 1120432234 | C34: =AVERAGE(D34:AH34) -> 36142975 | D34: 5578051.2 | E34: 8403858.4 | F34: 23485815 | G34: 5800641 | H34: 13513206 | I34: 24148455 | J34: 16245815 | K34: 19277349 | L34: 16551076 | M34: 19662416 | N34: 20406699 | O34: 18747084 | P34: 13816335 | Q34: 28136316 | R34: 30020431 | S34: 32487601 | T34: 37302702 | U34: 45408503 | V34: 24870691 | W34: 22885651 | X34: 19865158 | Y34: 17786382 | Z34: 39858513 | AA34: 62480982 | AB34: 56547424 | AC34: 74079231 | AD34: 133999844 | AE34: 75565191 | AF34: 106387768 | AG34: 59752300 | AH34: 47360745
A35: T/O率(リアルのみ) / Total real bet ratio | B35: =B34/B27 -> 16.814755 | C35: =AVERAGE(D35:AH35) -> 13.158128 | D35: =D34/D27 -> 5.8995969 | E35: =E34/E27 -> 24.079824 | F35: =F34/F27 -> 53.510507 | G35: =G34/G27 -> 7.3239492 | H35: =H34/H27 -> 8.2101581 | I35: =I34/I27 -> 29.611403 | J35: =J34/J27 -> 13.328467 | K35: =K34/K27 -> 9.6521972 | ... AH35: =AH34/AH27 -> 9.199246
A36: T/O(ボーナス+リアルマネーの合計) / Total bet (Real+Bonus) | B36: =SUM(D36:AH36) -> 1120432234 | C36: =AVERAGE(D36:AH36) -> 36142975 | D36: =D34+D43 -> 5578051.2 | E36: =E34+E43 -> 8403858.4 | F36: =F34+F43 -> 23485815 | G36: =G34+G43 -> 5800641 | H36: =H34+H43 -> 13513206 | I36: =I34+I43 -> 24148455 | J36: =J34+J43 -> 16245815 | K36: =K34+K43 -> 19277349 | ... AH36: =AH34+AH43 -> 47360745
A37: 勝利金(リアルのみ) / Winning amt (Real) | B37: =SUM(D37:AH37) -> 1084887870 | C37: =AVERAGE(D37:AH37) -> 34996383 | D37: 5481706.2 | E37: 8095355.2 | F37: 24638687 | G37: 5380834 | H37: 13195295 | I37: 25771772 | J37: 14032319 | K37: 18207736 | L37: 15465830 | M37: 18572438 | N37: 18794351 | O37: 18224289 | P37: 14533094 | Q37: 25981992 | R37: 28429302 | S37: 30830700 | T37: 36220914 | U37: 43531998 | V37: 23520845 | W37: 21347954 | X37: 18800550 | Y37: 17348497 | Z37: 38934810 | AA37: 61209012 | AB37: 58333300 | AC37: 74770471 | AD37: 129994814 | AE37: 73671644 | AF37: 98632911 | AG37: 56271890 | AH37: 46662560
A38: 勝利金(ボーナスのみ) / Winning amt (Bonus) | B38: =SUM(D38:AH38) -> 387.8 | C38: =AVERAGE(D38:AH38) -> 12.509677 | D38: 15710.6 | E38: 341 | F38: -1431 | G38: 0 | H38: 0 | I38: 16800.6 | J38: 16800.6 | K38: 0 | L38: 0 | M38: -15353 | N38: 0 | O38: 0 | P38: 0 | Q38: 0 | R38: 0 | S38: 100 | T38: 85 | U38: -18866 | V38: -18866 | W38: 1692 | X38: 0 | Y38: -40 | Z38: -40 | AA38: 10 | AB38: 0 | AC38: 40 | AD38: 0 | AE38: 0 | AF38: 0 | AG38: 3404 | AH38: 0
A39: 勝利金(ボーナス+リアルマネーの合計) / Winning (Bonus+Real) | B39: =SUM(D39:AH39) -> 1084888258 | C39: =AVERAGE(D39:AH39) -> 34996395 | D39: =D38+D37 -> 5497416.8 | E39: =E38+E37 -> 8095696.2 | F39: =F38+F37 -> 24637256 | G39: =G38+G37 -> 5380834 | H39: =H38+H37 -> 13195295 | I39: =I38+I37 -> 25788572 | J39: =J38+J37 -> 14049120 | K39: =K38+K37 -> 18207736 | ... AH39: =AH38+AH37 -> 46662560
A40: リアルマネー残高 / Real Money Balance | B40: =LOOKUP(9^9, C40:AH40) -> 7288550 | C40: =AVERAGE(D40:AH40) -> 6581734.5 | D40: 4795205 | E40: 5659793 | F40: 4437436 | G40: 4459250 | H40: 4987653 | I40: 6402196 | J40: 4828189 | K40: 5138001 | L40: 4748285 | M40: 5092791 | N40: 5705485 | P40: 6758249 | R40: 6099617 | S40: 6382281 | T40: 6065153 | U40: 5352440 | V40: 5795843 | W40: 4921791 | X40: 5291502 | Y40: 6726519 | Z40: 6594095 | AA40: 7791521 | AB40: 11989746 | AC40: 12933406 | AD40: 9799360 | AE40: 10510352 | AF40: 6988030 | AG40: 7327562 | AH40: 7288550
A41: ボーナス・マネー残高 / Bonus Money Balance | B41: =LOOKUP(9^9, C41:AH41) -> 1042612 | C41: =AVERAGE(D41:AH41) -> 1059221 | D41: 1099841 | E41: 1100214 | F41: 1100214 | G41: 1100214 | H41: 1100214 | I41: 1061759 | J41: 1061759 | K41: 1061759 | L41: 1061759 | M41: 1061659 | N41: 1061659 | P41: 1061659 | Q41: 1061659 | R41: 1061659 | S41: 1061559 | T41: 1061559 | U41: 1042693 | V41: 1042693 | W41: 1042693 | X41: 1042693 | Y41: 1042653 | Z41: 1042668 | AA41: 1042668 | AB41: 1042668 | AC41: 1042708 | AD41: 1042708 | AE41: 1042708 | AF41: 1042708 | AG41: 1042612 | AH41: 1042612
A42: RTP | B42: =C42 -> 0.96604376 | C42: =AVERAGE(D42:AH42) -> 0.96604376 | D42: =D39/D36 -> 0.98554433 | E42: =E39/E36 -> 0.96333087 | F42: =F39/F36 -> 1.0490271 | G42: =G39/G36 -> 0.92762748 | H42: =H39/H36 -> 0.97647405 | I42: =I39/I36 -> 1.0679181 | J42: =J39/J36 -> 0.86478392 | K42: =K39/K36 -> 0.94451452 | ... AH42: =AH39/AH36 -> 0.98525815
A43: T/O(ボーナスのみ) / Total bet (Bonus) | B43: =SUM(D43:AH43) -> 0 | C43: =AVERAGE(D43:AH43) -> 0 | D43: 0 | E43: 0 | F43: 0 | G43: 0 | H43: 0 | I43: 0 | J43: 0 | K43: 0 | L43: 0 | M43: 0 | N43: 0 | O43: 0 | P43: 0 | Q43: 0 | R43: 0 | S43: 0 | T43: 0 | U43: 0 | V43: 0 | W43: 0 | X43: 0 | Y43: 0 | Z43: 0 | AA43: 0 | AB43: 0 | AC43: 0 | AD43: 0 | AE43: 0 | AF43: 0 | AG43: 0 | AH43: 0
A44: T/O率(ボーナスのみ) / Total bet ratio (Bonus) | B44: =SUM(D44:AH44) -> 0 | C44: =AVERAGE(D44:AH44) -> 0 | D44: =D43/D27 -> 0 | E44: =E43/E27 -> 0 | F44: =F43/F27 -> 0 | G44: =G43/G27 -> 0 | H44: =H43/H27 -> 0 | I44: =I43/I27 -> 0 | J44: =J43/J27 -> 0 | K44: =K43/K27 -> 0 | ... AH44: =AH43/AH27 -> 0
A45: GGR | B45: =SUM(D45:AH45) -> 35543976 | C45: =AVERAGE(D45:AH45) -> 1146579.9 | D45: =D36-D39 -> 80634.45 | E45: =E36-E39 -> 308162.21 | F45: =F36-F39 -> -1151441 | G45: =G36-G39 -> 419807 | H45: =H36-H39 -> 317911 | I45: =I36-I39 -> -1640117.6 | J45: =J36-J39 -> 2196695.4 | K45: =K36-K39 -> 1069613 | ... AH45: =AH36-AH39 -> 698185
A46: GGR(入金に対して割合) | B46: =B45/B27 -> 0.53342205 | C46: =AVERAGE(D46:AH46) -> 0.27730951 | D46: =D45/D27 -> 0.085282608 | E46: =E45/E27 -> 0.88298628 | F46: =F45/F27 -> -2.6234641 | G46: =G45/G27 -> 0.53005265 | H46: =H45/H27 -> 0.19315176 | I46: =I45/I27 -> -2.0111508 | J46: =J45/J27 -> 1.802223 | K46: =K45/K27 -> 0.53555682 | ... AH46: =AH45/AH27 -> 0.13561391
A47: GGRLTV | B47: =B45/B26 -> 44541.323 | C47: =AVERAGE(D47:AH47) -> 10683.07 | D47: =D45/D26 -> 3505.8457 | E47: =E45/E26 -> 11005.793 | F47: =F45/F26 -> -42645.963 | G47: =G45/G26 -> 22095.105 | H47: =H45/H26 -> 7225.25 | I47: =I45/I26 -> -54670.588 | J47: =J45/J26 -> 64608.688 | K47: =K45/K26 -> 26088.122 | ... AH47: =AH45/AH26 -> 1448.5166
A48: 入出金差分 | B48: =B27-B32 -> 18292078 | C48: =AVERAGE(D48:AH48) -> 1128780.5 | D48: =D27-D32 -> 880497 | E48: =E27-E32 -> 52560 | F48: =F27-F32 -> -1143657 | G48: =G27-G32 -> 204910 | H48: =H27-H32 -> 896621 | I48: =I27-I32 -> -587092 | J48: =J27-J32 -> 518161 | K48: =K27-K32 -> 1444930 | ... AH48: =AH27-AH32 -> 1130496
A49: 差分(入金に対して割合) | B49: =B48/B27 -> 0.27451621 | C49: =AVERAGE(D49:AH49) -> 0.27362126 | D49: =D48/D27 -> 0.93125309 | E49: =E48/E27 -> 0.15060172 | F49: =F48/F27 -> -2.6057289 | G49: =G48/G27 -> 0.25872148 | H49: =H48/H27 -> 0.54475601 | I49: =I48/I27 -> -0.71990602 | J49: =J48/J27 -> 0.42511205 | K49: =K48/K27 -> 0.72347859 | ... AH49: =AH48/AH27 -> 0.21958503
A50: 差分LTV | B50: =B48/B26 -> 22922.404 | C50: =AVERAGE(D50:AH50) -> 10792.084 | D50: =D48/D26 -> 38282.478 | E50: =E48/E26 -> 1877.1429 | F50: =F48/F26 -> -42357.667 | G50: =G48/G26 -> 10784.737 | H50: =H48/H26 -> 20377.75 | I50: =I48/I26 -> -19569.733 | J50: =J48/J26 -> 15240.029 | K50: =K48/K26 -> 35242.195 | ... AH50: =AH48/AH26 -> 2345.4274
A51: ヘブンズショットコスト/Heavensshot Cost | B51: =SUM(D51:AH51) -> 3580000 | C51: =AVERAGE(D51:AH51) -> 115483.87 | D51: 0 | E51: 0 | F51: 0 | G51: 0 | H51: 0 | I51: 0 | J51: 0 | K51: 0 | L51: 0 | M51: 10000 | N51: 0 | O51: 0 | P51: 10000 | Q51: 10000 | R51: 50000 | S51: 80000 | T51: 60000 | U51: 30000 | V51: 30000 | W51: 30000 | X51: 250000 | Y51: 40000 | Z51: 280000 | AA51: 270000 | AB51: 440000 | AC51: 1170000 | AD51: 240000 | AE51: 50000 | AF51: 290000 | AG51: 100000 | AH51: 140000
A52: トーナメントコスト/Tournament Cost | B52: =SUM(D52:AH52) -> 0 | C52: =AVERAGE(D52:AH52) -> 0 | D52: 0 | E52: 0 | F52: 0 | G52: 0 | H52: 0 | I52: 0 | J52: 0 | K52: 0 | L52: 0 | M52: 0 | N52: 0 | O52: 0 | P52: 0 | Q52: 0 | R52: 0 | S52: 0 | T52: 0 | U52: 0 | V52: 0 | W52: 0 | X52: 0 | Y52: 0 | Z52: 0 | AA52: 0 | AB52: 0 | AC52: 0 | AD52: 0 | AE52: 0 | AF52: 0 | AG52: 0 | AH52: 0
A53: 新規用期間イベントコスト/new user event Cost | B53: =SUM(D53:AH53) -> 524000 | C53: =AVERAGE(D53:AH53) -> 16903.226 | D53: 0 | E53: 0 | F53: 0 | G53: 0 | H53: 0 | I53: 0 | J53: 0 | K53: 0 | L53: 0 | M53: 0 | N53: 0 | O53: 0 | P53: 0 | Q53: 0 | R53: 0 | S53: 0 | T53: 0 | U53: 0 | V53: 0 | W53: 0 | X53: 0 | Y53: 0 | Z53: 0 | AA53: 0 | AB53: 0 | AC53: 0 | AD53: 0 | AE53: 8000 | AF53: 20000 | AG53: 68000 | AH53: 428000
A54: 休眠用期間イベントコスト/old user event Cost | B54: =SUM(D54:AH54) -> 0 | C54: =AVERAGE(D54:AH54) -> 0 | D54: 0 | E54: 0 | F54: 0 | G54: 0 | H54: 0 | I54: 0 | J54: 0 | K54: 0 | L54: 0 | M54: 0 | N54: 0 | O54: 0 | P54: 0 | Q54: 0 | R54: 0 | S54: 0 | T54: 0 | U54: 0 | V54: 0 | W54: 0 | X54: 0 | Y54: 0 | Z54: 0 | AA54: 0 | AB54: 0 | AC54: 0 | AD54: 0 | AE54: 0 | AF54: 0 | AG54: 0 | AH54: 0
A55: 既存用期間イベントコスト/Active user event Cost | B55: =SUM(D55:AH55) -> 0 | C55: =AVERAGE(D55:AH55) -> 0 | D55: 0 | E55: 0 | F55: 0 | G55: 0 | H55: 0 | I55: 0 | J55: 0 | K55: 0 | L55: 0 | M55: 0 | N55: 0 | O55: 0 | P55: 0 | Q55: 0 | R55: 0 | S55: 0 | T55: 0 | U55: 0 | V55: 0 | W55: 0 | X55: 0 | Y55: 0 | Z55: 0 | AA55: 0 | AB55: 0 | AC55: 0 | AD55: 0 | AE55: 0 | AF55: 0 | AG55: 0 | AH55: 0
A56: ドリームポットコスト/Jackpot Cost | B56: =SUM(D56:AH56) -> 0 | C56: =AVERAGE(D56:AH56) -> 0 | D56: 0 | E56: 0 | F56: 0 | G56: 0 | H56: 0 | I56: 0 | J56: 0 | K56: 0 | L56: 0 | M56: 0 | N56: 0 | O56: 0 | P56: 0 | Q56: 0 | R56: 0 | S56: 0 | T56: 0 | U56: 0 | V56: 0 | W56: 0 | X56: 0 | Y56: 0 | Z56: 0 | AA56: 0 | AB56: 0 | AC56: 0 | AD56: 0 | AE56: 0 | AF56: 0 | AG56: 0 | AH56: 0
A57: 入金不要コスト/ Cost | B57: =SUM(D57:AH57) -> 4758000 | C57: =AVERAGE(D57:AH57) -> 153483.87 | D57: 0 | E57: 0 | F57: 0 | G57: 0 | H57: 0 | I57: 0 | J57: 0 | K57: 0 | L57: 0 | M57: 0 | N57: 0 | O57: 0 | P57: 0 | Q57: 0 | R57: 0 | S57: 0 | T57: 0 | U57: 0 | V57: 0 | W57: 0 | X57: 0 | Y57: 348000 | Z57: 561000 | AA57: 513000 | AB57: 633000 | AC57: 420000 | AD57: 378000 | AE57: 399000 | AF57: 183000 | AG57: 492000 | AH57: 831000
A58: AFFイベント コスト / AFF EventCost | B58: =SUM(D58:AH58) -> 3748253.5 | C58: =AVERAGE(D58:AH58) -> 120911.4 | D58: =D109 -> 888795.54 | E58: =E109 -> 0 | F58: =F109 -> 0 | G58: =G109 -> 0 | H58: =H109 -> 0 | I58: =I109 -> 0 | J58: =J109 -> 0 | K58: =K109 -> 0 | ... AH58: =AH109 -> 0
A59: ペイメントコスト / Payment cost | B59: =2468559*58.33% -> 1439910.5 | C59: =AVERAGE(D59:AH59) -> 0 | D59: 0 | E59: 0 | F59: 0 | G59: 0 | H59: 0 | I59: 0 | J59: 0 | K59: 0 | L59: 0 | M59: 0 | N59: 0 | O59: 0 | P59: 0 | Q59: 0 | R59: 0 | S59: 0 | T59: 0 | U59: 0 | V59: 0 | W59: 0 | X59: 0 | Y59: 0 | Z59: 0 | AA59: 0 | AB59: 0 | AC59: 0 | AD59: 0 | AE59: 0 | AF59: 0 | AG59: 0 | AH59: 0
A60: プロバイダーフィー / Provider fee | B60: 5534943.1 | C60: =AVERAGE(D60:AH60) -> 0 | D60: 0 | E60: 0 | F60: 0 | G60: 0 | H60: 0 | I60: 0 | J60: 0 | K60: 0 | L60: 0 | M60: 0 | N60: 0 | O60: 0 | P60: 0 | Q60: 0 | R60: 0 | S60: 0 | T60: 0 | U60: 0 | V60: 0 | W60: 0 | X60: 0 | Y60: 0 | Z60: 0 | AA60: 0 | AB60: 0 | AC60: 0 | AD60: 0 | AE60: 0 | AF60: 0 | AG60: 0 | AH60: 0
A61: AFFコスト / Aff cost | B61: =B109 -> 3748253.5 | C61: =AVERAGE(D61:AH61) -> 0 | D61: 0 | E61: 0 | F61: 0 | G61: 0 | H61: 0 | I61: 0 | J61: 0 | K61: 0 | L61: 0 | M61: 0 | N61: 0 | O61: 0 | P61: 0 | Q61: 0 | R61: 0 | S61: 0 | T61: 0 | U61: 0 | V61: 0 | W61: 0 | X61: 0 | Y61: 0 | Z61: 0 | AA61: 0 | AB61: 0 | AC61: 0 | AD61: 0 | AE61: 0 | AF61: 0 | AG61: 0 | AH61: 0
A62: otherコスト / Other cost | B62: =SUM(D62:AH62) -> 0 | C62: =AVERAGE(D62:AH62) -> 0 | D62: 0 | E62: 0 | F62: 0 | G62: 0 | H62: 0 | I62: 0 | J62: 0 | K62: 0 | L62: 0 | M62: 0 | N62: 0 | O62: 0 | P62: 0 | Q62: 0 | R62: 0 | S62: 0 | T62: 0 | U62: 0 | V62: 0 | W62: 0 | X62: 0 | Y62: 0 | Z62: 0 | AA62: 0 | AB62: 0 | AC62: 0 | AD62: 0 | AE62: 0 | AF62: 0 | AG62: 0 | AH62: 0
A63: 総コスト(ボーナスは付与額ベース) / Total cost (Granted bonus included) | B63: =SUM(B58:B62) -> 14471361 | C63: =AVERAGE(D63:AH63) -> 0 | D63: =D62+D61+D60+D59 -> 0 | E63: =E62+E61+E60+E59 -> 0 | F63: =F62+F61+F60+F59 -> 0 | G63: =G62+G61+G60+G59 -> 0 | H63: =H62+H61+H60+H59 -> 0 | I63: =I62+I61+I60+I59 -> 0 | J63: =J62+J61+J60+J59 -> 0 | K63: =K62+K61+K60+K59 -> 0 | ... AH63: =AH62+AH61+AH60+AH59 -> 0
A64: NGR | B64: =B45-(B51+B52+B53+B54+B55+B56+B57+B59+B60+B61+B62) -> 15958869 | C64: =AVERAGE(D64:AH64) -> 860708.9 | D64: =D45-(D51+D52+D53+D54+D55+D56+D57+D59+D60+D61+D62) -> 80634.45 | E64: =E45-(E51+E52+E53+E54+E55+E56+E57+E59+E60+E61+E62) -> 308162.21 | F64: =F45-(F51+F52+F53+F54+F55+F56+F57+F59+F60+F61+F62) -> -1151441 | G64: =G45-(G51+G52+G53+G54+G55+G56+G57+G59+G60+G61+G62) -> 419807 | H64: =H45-(H51+H52+H53+H54+H55+H56+H57+H59+H60+H61+H62) -> 317911 | I64: =I45-(I51+I52+I53+I54+I55+I56+I57+I59+I60+I61+I62) -> -1640117.6 | J64: =J45-(J51+J52+J53+J54+J55+J56+J57+J59+J60+J61+J62) -> 2196695.4 | K64: =K45-(K51+K52+K53+K54+K55+K56+K57+K59+K60+K61+K62) -> 1069613 | ... AH64: =AH45-(AH51+AH52+AH53+AH54+AH55+AH56+AH57+AH59+AH60+AH61+AH62) -> -700815
A65: 差分利益 | B65: =B48-B63 -> 3820717.4 | C65: =AVERAGE(D65:AH65) -> 1128780.5 | D65: =D48-D63 -> 880497 | E65: =E48-E63 -> 52560 | F65: =F48-F63 -> -1143657 | G65: =G48-G63 -> 204910 | H65: =H48-H63 -> 896621 | I65: =I48-I63 -> -587092 | J65: =J48-J63 -> 518161 | K65: =K48-K63 -> 1444930 | ... AH65: =AH48-AH63 -> 1130496
A66: プロモーション開催期間 / Promotion duration | L66: ヘブンズショット
A67: 目的 | L67: アクティブ
A68: プロモーション開催期間 / Promotion duration | Y68: 入金不要
A69: 目的 | Y69: 登録
A70: プロモーション開催期間 / Promotion duration | Y70: 1/2 100% キャッシュバック スロ天おめでとう
A71: 目的 | Y71: FTD
A72: プロモーション開催期間 / Promotion duration | AD72: ステップヘブンズショット
A73: 目的 | AD73: FTD/2nd/3rd
A74: テスト資金 | AD74: 出金体験-グランドオープン
AD75: FTD
AG76: 年末ジャンボ
AG77: FTD
AH78: ヘブンズ無料
AH79: プレイ
A80: 【分析指標】 | B80: =SUM(D80:AH80) -> 0
A81: ARPU(全登録ユーザー) | B81: =SUM(D81:AH81) -> 530986.76 | C81: =AVERAGE(D81:AH81) -> 17128.605 | D81: =D64/D4 -> 2443.4682 | E81: =E64/E4 -> 8328.7084 | F81: =F64/F4 -> -39704.862 | G81: =G64/G4 -> 7496.5536 | H81: =H64/H4 -> 8592.1892 | I81: =I64/I4 -> -46860.504 | J81: =J64/J4 -> 57807.774 | K81: =K64/K4 -> 34503.645 | ... AH81: =AH64/AH4 -> -2530.0181
A82: ARPPU(課金ユーザー) | B82: =SUM(D82:AH82) -> 404607.53 | C82: =AVERAGE(D82:AH82) -> 13051.856 | D82: =D64/D25 -> 3665.2023 | E82: =E64/E25 -> 17120.123 | F82: =F64/F25 -> -54830.524 | G82: =G64/G25 -> 27987.133 | H82: =H64/H25 -> 8366.0789 | I82: =I64/I25 -> -74550.802 | J82: =J64/J25 -> 75748.117 | K82: =K64/K25 -> 30560.371 | ... AH82: =AH64/AH25 -> -2781.0119
A83: FTDコンバージョン率 | B83: =C83 -> 0.16530688 | C83: =AVERAGE(D83:AH83) -> 0.16530688 | D83: =D18/D4 -> 0.24242424 | E83: =E18/E4 -> 0.24324324 | F83: =F18/F4 -> 0.17241379 | G83: =G18/G4 -> 0.17857143 | H83: =H18/H4 -> 0.16216216 | I83: =I18/I4 -> 0.14285714 | J83: =J18/J4 -> 0.18421053 | K83: =K18/K4 -> 0.19354839 | ... AH83: =AH18/AH4 -> 0.24187726
A84: 2nd継続率 | B84: =C84 -> 0.41382341 | C84: =AVERAGE(D84:AH84) -> 0.41382341 | D84: =D12/D10 -> 0.33333333 | E84: =E12/E10 -> 1 | F84: =F12/F10 -> 0 | G84: =G12/G10 -> 0.66666667 | H84: =H12/H10 -> 0 | I84: =I12/I10 -> 0 | J84: =J12/J10 -> 1 | K84: =K12/K10 -> 0 | ... AH84: =AH12/AH10 -> 0.1
A85: アクティブ率 | B85: =C85 -> 1.6184561 | C85: =AVERAGE(D85:AH85) -> 1.6184561 | D85: =D26/D4 -> 0.6969697 | E85: =E26/E4 -> 0.75675676 | F85: =F26/F4 -> 0.93103448 | G85: =G26/G4 -> 0.33928571 | H85: =H26/H4 -> 1.1891892 | I85: =I26/I4 -> 0.85714286 | J85: =J26/J4 -> 0.89473684 | K85: =K26/K4 -> 1.3225806 | ... AH85: =AH26/AH4 -> 1.7400722
A86: GGRマージン率 | B86: =C86 -> 0.27730951 | C86: =AVERAGE(D86:AH86) -> 0.27730951 | D86: =D45/D27 -> 0.085282608 | E86: =E45/E27 -> 0.88298628 | F86: =F45/F27 -> -2.6234641 | G86: =G45/G27 -> 0.53005265 | H86: =H45/H27 -> 0.19315176 | I86: =I45/I27 -> -2.0111508 | J86: =J45/J27 -> 1.802223 | K86: =K45/K27 -> 0.53555682 | ... AH86: =AH45/AH27 -> 0.13561391
A87: NGRマージン率 | B87: =C87 -> 0.21745242 | C87: =AVERAGE(D87:AH87) -> 0.21745242 | D87: =D64/D27 -> 0.085282608 | E87: =E64/E27 -> 0.88298628 | F87: =F64/F27 -> -2.6234641 | G87: =G64/G27 -> 0.53005265 | H87: =H64/H27 -> 0.19315176 | I87: =I64/I27 -> -2.0111508 | J87: =J64/J27 -> 1.802223 | K87: =K64/K27 -> 0.53555682 | ... AH87: =AH64/AH27 -> -0.13612475
A88: 平均入金回数/ユーザー | B88: =C88 -> 1.8555383 | C88: =AVERAGE(D88:AH88) -> 1.8555383 | D88: =D24/D25 -> 1.9090909 | E88: =E24/E25 -> 1.5 | F88: =F24/F25 -> 2.4285714 | G88: =G24/G25 -> 2.5333333 | H88: =H24/H25 -> 1.4210526 | I88: =I24/I25 -> 1.8181818 | J88: =J24/J25 -> 1.6896552 | K88: =K24/K25 -> 2.0285714 | ... AH88: =AH24/AH25 -> 1.4087302
B89: =SUM(D89:AH89) -> 0
A90: プロモーション開催期間 / Promotion duration | B90: =SUM(D90:AH90) -> 0
A91: 目的 / Purpose | B91: =SUM(D91:AH91) -> 0
B92: =SUM(D92:AH92) -> 0
A93: Affiliate | B93: =SUM(D93:AH93) -> 0
A94: AFF経由登録者数 / Registration under AFF | B94: 1457 | C94: =AVERAGE(D94:AH94) -> 59.032258 | D94: 30 | E94: 32 | F94: 24 | G94: 52 | H94: 29 | I94: 32 | J94: 36 | K94: 27 | L94: 34 | M94: 29 | N94: 30 | O94: 33 | P94: 7 | Q94: 50 | R94: 60 | S94: 60 | T94: 46 | U94: 18 | V94: 22 | W94: 32 | X94: 32 | Y94: 96 | Z94: 149 | AA94: 154 | AB94: 140 | AC94: 101 | AD94: 96 | AE94: 107 | AF94: 40 | AG94: 84 | AH94: 148
A95: AFF経由FTD数 / FTD under AFF | B95: 543 | C95: =AVERAGE(D95:AH95) -> 13.548387 | D95: 5 | E95: 5 | F95: 2 | G95: 7 | H95: 1 | I95: 5 | J95: 2 | K95: 4 | L95: 2 | M95: 2 | N95: 4 | O95: 4 | P95: 1 | Q95: 5 | R95: 16 | S95: 11 | T95: 8 | U95: 5 | V95: 5 | W95: 5 | X95: 6 | Y95: 31 | Z95: 54 | AA95: 72 | AB95: 41 | AC95: 41 | AD95: 15 | AE95: 29 | AF95: 3 | AG95: 3 | AH95: 26
A96: AFF数 | B96: 34 | C96: =AVERAGE(D96:AH96) -> 1.483871 | D96: 1 | E96: 1 | F96: 0 | G96: 1 | H96: 1 | I96: 0 | J96: 2 | K96: 0 | L96: 3 | M96: 0 | N96: 0 | O96: 0 | P96: 1 | Q96: 1 | R96: 0 | S96: 3 | T96: 1 | U96: 4 | V96: 1 | W96: 0 | X96: 1 | Y96: 0 | Z96: 6 | AA96: 6 | AB96: 4 | AC96: 3 | AD96: 1 | AE96: 0 | AF96: 1 | AG96: 2 | AH96: 2
A97: AFF経由入金額 / DP amt under AFF | B97: 55061952
A98: AFF経由出金額 / WD amt under AFF | B98: 36735633
A99: Ｔ／Ｏ | B99: 238046182
A100: 勝利金 | B100: 227680021
...

Sheet 202601
A1: 項目名 | B1: 月次合計 | C1: 日次平均 | D1: 46023 | E1: 46024 | F1: 46025 | G1: 46026 | H1: 46027 | I1: 46028 | J1: 46029 | K1: 46030 | L1: 46031 | M1: 46032 | N1: 46033 | O1: 46034 | P1: 46035 | Q1: 46036 | R1: 46037 | S1: 46038 | T1: 46039 | U1: 46040 | V1: 46041 | W1: 46042 | X1: 46043 | Y1: 46044 | Z1: 46045 | AA1: 46046 | AB1: 46047 | AC1: 46048 | AD1: 46049 | AE1: 46050 | AF1: 46051 | AG1: 46052 | AH1: 46053
D2: 木 | E2: 金 | F2: 土 | G2: 日 | H2: 月 | I2: 火 | J2: 水 | K2: 木 | L2: 金 | M2: 土 | N2: 日 | O2: 月 | P2: 火 | Q2: 水 | R2: 木 | S2: 金 | T2: 土 | U2: 日 | V2: 月 | W2: 火 | X2: 水 | Y2: 木 | Z2: 金 | AA2: 土 | AB2: 日 | AC2: 月 | AD2: 火 | AE2: 水 | AF2: 木 | AG2: 金 | AH2: 土
A3: 全体KPI | B3: =SUM(D3:AH3) -> 0
A4: 登録人数 | B4: =SUM(D4:AH4) -> 5685 | C4: =AVERAGE(D4:AH4) -> 203.03571 | D4: 195 | E4: 141 | F4: 206 | G4: 159 | H4: 159 | I4: 278 | J4: 263 | K4: 219 | L4: 69 | M4: 172 | N4: 100 | O4: 382 | P4: 242 | Q4: 125 | R4: 331 | S4: 103 | T4: 114 | U4: 123 | V4: 232 | W4: 185 | X4: 107 | Y4: 314 | Z4: 146 | AA4: 244 | AB4: 209 | AC4: 265 | AD4: 272 | AE4: 330
A5: ログインユーザー数 | B5: 3459 | C5: =AVERAGE(D5:AH5) -> 252.25926 | D5: 186 | E5: 142 | F5: 153 | G5: 146 | I5: 184 | J5: 244 | K5: 220 | L5: 312 | M5: 261 | N5: 274 | O5: 234 | P5: 277 | Q5: 257 | R5: 260 | S5: 294 | T5: 275 | U5: 237 | V5: 205 | W5: 252 | X5: 273 | Y5: 273 | Z5: 303 | AA5: 272 | AB5: 280 | AC5: 287 | AD5: 327 | AE5: 383
A6: SMS認証 | B6: =SUM(D6:AH6) -> 5685 | C6: =AVERAGE(D6:AH6) -> 203.03571 | D6: 195 | E6: 141 | F6: 206 | G6: 159 | H6: 159 | I6: 278 | J6: 263 | K6: 219 | L6: 69 | M6: 172 | N6: 100 | O6: 382 | P6: 242 | Q6: 125 | R6: 331 | S6: 103 | T6: 114 | U6: 123 | V6: 232 | W6: 185 | X6: 107 | Y6: 314 | Z6: 146 | AA6: 244 | AB6: 209 | AC6: 265 | AD6: 272 | AE6: 330
A7: 登録に対してSMS認証割合 | B7: =C7 -> 1 | C7: =AVERAGE(D7:AH7) -> 1 | D7: =D6/D4 -> 1 | E7: =E6/E4 -> 1 | F7: =F6/F4 -> 1 | G7: =G6/G4 -> 1 | H7: =H6/H4 -> 1 | I7: =I6/I4 -> 1 | J7: =J6/J4 -> 1 | K7: =K6/K4 -> 1 | ... AE7: =AE6/AE4 -> 1
A8: 入金不要ボーナス使用済ユーザー数 | B8: 6211 | C8: =AVERAGE(D8:AH8) -> 180.75 | D8: 207 | E8: 134 | F8: 229 | G8: 134 | H8: 164 | I8: 220 | J8: 233 | K8: 162 | L8: 93 | M8: 135 | N8: 185 | O8: 178 | P8: 249 | Q8: 210 | R8: 198 | S8: 170 | T8: 136 | U8: 185 | V8: 184 | W8: 158 | X8: 217 | Y8: 251 | Z8: 194 | AA8: 112
A9: 登録に対してNDB使用割合 | B9: =B8/B4 -> 1.0925242 | C9: =AVERAGE(D9:AH9) -> 0.3079836 | D9: =D8/D4 -> 1.0615385 | E9: =E8/E4 -> 0.95035461 | F9: =F8/F4 -> 1.1116505 | G9: =G8/G4 -> 0.8427673 | H9: =H8/H4 -> 1.0314465 | I9: =I8/I4 -> 0.79136691 | J9: =J8/J4 -> 0.88593156 | K9: =K8/K4 -> 0.73972603 | ... M9: =M8/M4 -> 0.78488372 | N9: 0 | O9: 0 | P9: 0 | Q9: 0 | R9: 0 | S9: 0 | T9: 0 | U9: 0 | V9: 0 | W9: 0 | X9: 0 | Y9: 0 | Z9: 0 | AA9: 0 | AB9: 0 | AC9: 0 | AD9: 0 | AE9: 0 | AF9: 0 | AG9: 0 | AH9: 0
A10: FTDのみ入金者数 | B10: 348 | C10: =AVERAGE(D10:AH10) -> 6.1428571 | D10: 6 | E10: 7 | F10: 10 | G10: 8 | H10: 8 | I10: 9 | J10: 12 | K10: 6 | L10: 3 | M10: 7 | N10: 3 | O10: 2 | P10: 7 | Q10: 6 | R10: 10 | S10: 2 | T10: 3 | U10: 5 | V10: 8 | W10: 3 | X10: 5 | Y10: 6 | Z10: 4 | AA10: 6 | AB10: 6 | AC10: 5 | AD10: 6 | AE10: 9
A11: 登録に対して1st使用割合 | B11: =C11 -> 0.032619627 | C11: =AVERAGE(D11:AH11) -> 0.032619627 | D11: =D10/D4 -> 0.030769231 | E11: =E10/E4 -> 0.04964539 | F11: =F10/F4 -> 0.048543689 | G11: =G10/G4 -> 0.050314465 | H11: =H10/H4 -> 0.050314465 | I11: =I10/I4 -> 0.032374101 | J11: =J10/J4 -> 0.045627376 | K11: =K10/K4 -> 0.02739726 | ... AE11: =AE10/AE4 -> 0.027272727
A12: 2ndのみ入金者数 | B12: 45 | C12: =AVERAGE(D12:AH12) -> 1.2857143 | D12: 3 | E12: 1 | F12: 0 | G12: 0 | H12: 1 | I12: 2 | J12: 4 | K12: 0 | L12: 1 | M12: 4 | N12: 0 | O12: 2 | P12: 3 | Q12: 1 | R12: 3 | S12: 0 | T12: 1 | U12: 3 | V12: 0 | W12: 1 | X12: 1 | Y12: 1 | Z12: 0 | AA12: 1 | AB12: 0 | AC12: 0 | AD12: 1 | AE12: 2
A13: 登録に対して2nd使用割合 | B13: =C13 -> 0.006733833 | C13: =AVERAGE(D13:AH13) -> 0.006733833 | D13: =D12/D4 -> 0.015384615 | E13: =E12/E4 -> 0.0070921986 | F13: =F12/F4 -> 0 | G13: =G12/G4 -> 0 | H13: =H12/H4 -> 0.0062893082 | I13: =I12/I4 -> 0.0071942446 | J13: =J12/J4 -> 0.015209125 | K13: =K12/K4 -> 0 | ... AE13: =AE12/AE4 -> 0.0060606061
A14: 3nd入金以降ユーザー数 | B14: 44 | C14: =AVERAGE(D14:AH14) -> 0.85714286 | D14: 1 | E14: 1 | F14: 0 | G14: 4 | H14: 1 | I14: 0 | J14: 1 | K14: 0 | L14: 1 | M14: 1 | N14: 0 | O14: 2 | P14: 2 | Q14: 0 | R14: 3 | S14: 0 | T14: 1 | U14: 0 | V14: 1 | W14: 3 | X14: 0 | Y14: 0 | Z14: 0 | AA14: 1 | AB14: 1 | AC14: 0 | AD14: 0 | AE14: 0
A15: 登録に対して3nd使用割合 | B15: =C15 -> 0.0045900351 | C15: =AVERAGE(D15:AH15) -> 0.0045900351 | D15: =D14/D4 -> 0.0051282051 | E15: =E14/E4 -> 0.0070921986 | F15: =F14/F4 -> 0 | G15: =G14/G4 -> 0.025157233 | H15: =H14/H4 -> 0.0062893082 | I15: =I14/I4 -> 0 | J15: =J14/J4 -> 0.0038022814 | K15: =K14/K4 -> 0 | ... AE15: =AE14/AE4 -> 0
A16: 4nd入金以降ユーザー数 | B16: 162 | C16: =AVERAGE(D16:AH16) -> 1.1428571 | D16: 1 | E16: 2 | F16: 3 | G16: 0 | H16: 4 | I16: 1 | J16: 1 | K16: 1 | L16: 1 | M16: 3 | N16: 1 | O16: 1 | P16: 0 | Q16: 0 | R16: 2 | S16: 1 | T16: 0 | U16: 2 | V16: 1 | W16: 1 | X16: 0 | Y16: 0 | Z16: 0 | AA16: 0 | AB16: 2 | AC16: 2 | AD16: 0 | AE16: 2
A17: 登録に対して4nd使用割合 | B17: =C17 -> 0.006444824 | C17: =AVERAGE(D17:AH17) -> 0.006444824 | D17: =D16/D4 -> 0.0051282051 | E17: =E16/E4 -> 0.014184397 | F17: =F16/F4 -> 0.014563107 | G17: =G16/G4 -> 0 | H17: =H16/H4 -> 0.025157233 | I17: =I16/I4 -> 0.0035971223 | J17: =J16/J4 -> 0.0038022814 | K17: =K16/K4 -> 0.00456621 | ... AE17: =AE16/AE4 -> 0.0060606061
A18: 今月登録のFTD以降ユーザー数 | B18: =B10+B12+B14+B16 -> 599 | C18: =AVERAGE(D18:AH18) -> 8.516129 | D18: =D10+D12+D14+D16 -> 11 | E18: =E10+E12+E14+E16 -> 11 | F18: =F10+F12+F14+F16 -> 13 | G18: =G10+G12+G14+G16 -> 12 | H18: =H10+H12+H14+H16 -> 14 | I18: =I10+I12+I14+I16 -> 12 | J18: =J10+J12+J14+J16 -> 18 | K18: =K10+K12+K14+K16 -> 7 | ... AH18: =AH10+AH12+AH14+AH16 -> 0
A19: 今月登録FTD以降ユーザー割合 | B19: =B18/B4 -> 0.105365 | C19: =AVERAGE(D19:AH19) -> 0.050388319 | D19: =D11+D13+D15+D17 -> 0.056410256 | E19: =E11+E13+E15+E17 -> 0.078014184 | F19: =F11+F13+F15+F17 -> 0.063106796 | G19: =G11+G13+G15+G17 -> 0.075471698 | H19: =H11+H13+H15+H17 -> 0.088050314 | I19: =I11+I13+I15+I17 -> 0.043165468 | J19: =J11+J13+J15+J17 -> 0.068441065 | K19: =K11+K13+K15+K17 -> 0.03196347 | ... AE19: =AE11+AE13+AE15+AE17 -> 0.039393939
A20: 今月登録のアクティブユーザー数 | B20: 598
A21: 前月登録のアクティブユーザー数 | B21: 667
A22: 前々月登録のアクティブユーザー数 | B22: 74
A23: 3か月以上アクティブプレイヤー数 | B23: -
A24: 総入金回数 | B24: =SUM(D24:AH24) -> 8484 | C24: =AVERAGE(D24:AH24) -> 303 | D24: 268 | E24: 232 | F24: 214 | G24: 213 | H24: 308 | I24: 297 | J24: 260 | K24: 248 | L24: 273 | M24: 314 | N24: 267 | O24: 239 | P24: 352 | Q24: 303 | R24: 377 | S24: 312 | T24: 304 | U24: 270 | V24: 260 | W24: 377 | X24: 353 | Y24: 317 | Z24: 379 | AA24: 356 | AB24: 301 | AC24: 336 | AD24: 385 | AE24: 369
A25: 入金者数(デイリーユニーク) | B25: =G193 -> 1542 | C25: =AVERAGE(D25:AH25) -> 161.71429 | D25: 163 | E25: 127 | F25: 123 | G25: 118 | H25: 169 | I25: 153 | J25: 145 | K25: 130 | L25: 158 | M25: 163 | N25: 144 | O25: 145 | P25: 192 | Q25: 165 | R25: 194 | S25: 154 | T25: 164 | U25: 144 | V25: 146 | W25: 188 | X25: 169 | Y25: 174 | Z25: 190 | AA25: 182 | AB25: 168 | AC25: 172 | AD25: 192 | AE25: 196
A26: アクティブプレイ人数（ユニーク） | B26: =B20+B21+B22 -> 1339 | C26: =AVERAGE(D26:AH26) -> 405.32143 | D26: 417 | E26: 329 | F26: 405 | G26: 289 | H26: 354 | I26: 430 | J26: 444 | K26: 341 | L26: 303 | M26: 328 | N26: 395 | O26: 384 | P26: 481 | Q26: 416 | R26: 440 | S26: 383 | T26: 356 | U26: 384 | V26: 380 | W26: 412 | X26: 433 | Y26: 472 | Z26: 444 | AA26: 430 | AB26: 435 | AC26: 436 | AD26: 379 | AE26: 649
A27: 総入金額 / Total DP amt | B27: =B193 -> 129457997 | C27: =AVERAGE(D27:AH27) -> 5450610.5 | D27: 3779495 | E27: 2819739 | F27: 4002694 | G27: 3549751 | H27: 8311890 | I27: 6672779 | J27: 5573653 | K27: 4397152 | L27: 5628868 | M27: 4873108 | N27: 4209074 | O27: 3158505 | P27: 5274526 | Q27: 4534376 | R27: 4808188 | S27: 4999483 | T27: 4904107 | U27: 3990809 | V27: 4775395 | W27: 7969699 | X27: 6639499 | Y27: 5533068 | Z27: 8525244 | AA27: 7725120 | AB27: 5495767 | AC27: 8398889 | AD27: 6958335 | AE27: 5107881
A28: 平均入金額(一回の入金額) / Ave amt per DP | B28: =B27/B24 -> 15259.076 | C28: =AVERAGE(D28:AH28) -> 17862.159 | D28: =D27/D24 -> 14102.593 | E28: =E27/E24 -> 12154.047 | F28: =F27/F24 -> 18704.178 | G28: =G27/G24 -> 16665.498 | H28: =H27/H24 -> 26986.656 | I28: =I27/I24 -> 22467.269 | J28: =J27/J24 -> 21437.127 | K28: =K27/K24 -> 17730.452 | ... AE28: =AE27/AE24 -> 13842.496
A29: 平均入金額(ユニークユーザー) / Ave DP amt (Unique user) | B29: =B27/B25 -> 83954.602 | C29: =AVERAGE(D29:AH29) -> 33456.208 | D29: =D27/D25 -> 23187.086 | E29: =E27/E25 -> 22202.669 | F29: =F27/F25 -> 32542.228 | G29: =G27/G25 -> 30082.636 | H29: =H27/H25 -> 49182.781 | I29: =I27/I25 -> 43612.935 | J29: =J27/J25 -> 38438.986 | K29: =K27/K25 -> 33824.246 | ... AE29: =AE27/AE25 -> 26060.617
A30: 総出金回数 | B30: =SUM(D30:AH30) -> 1866 | C30: =AVERAGE(D30:AH30) -> 66.642857 | D30: 60 | E30: 46 | F30: 46 | G30: 53 | H30: 61 | I30: 65 | J30: 65 | K30: 46 | L30: 72 | M30: 74 | N30: 66 | O30: 50 | P30: 77 | Q30: 64 | R30: 80 | S30: 65 | T30: 85 | U30: 60 | V30: 51 | W30: 71 | X30: 66 | Y30: 69 | Z30: 93 | AA30: 64 | AB30: 74 | AC30: 88 | AD30: 63 | AE30: 92
A31: 総出金人数 | B31: =SUM(D31:AH31) -> 1347 | C31: =AVERAGE(D31:AH31) -> 48.107143 | D31: 48 | E31: 37 | F31: 36 | G31: 39 | H31: 46 | I31: 50 | J31: 42 | K31: 38 | L31: 49 | M31: 45 | N31: 45 | O31: 32 | P31: 59 | Q31: 40 | R31: 54 | S31: 48 | T31: 63 | U31: 41 | V31: 42 | W31: 51 | X31: 51 | Y31: 51 | Z31: 65 | AA31: 53 | AB31: 53 | AC31: 54 | AD31: 51 | AE31: 64
A32: 総出金額 / Total WD amt | B32: =B201 -> 94439992 | C32: =AVERAGE(D32:AH32) -> 3790935.6 | D32: 4902347 | E32: 3140979 | F32: 3280662 | G32: 4139569 | H32: 5061884 | I32: 4386705 | J32: 3086327 | K32: 2622203 | L32: 3623909 | M32: 3932470 | N32: 2615492 | O32: 1666395 | P32: 2209362 | Q32: 2081030 | R32: 3760947 | S32: 4026312 | T32: 3616612 | U32: 4068257 | V32: 2399347 | W32: 5863942 | X32: 3457169 | Y32: 3782050 | Z32: 5897027 | AA32: 4192596 | AB32: 5000943 | AC32: 4417378 | AD32: 4437421 | AE32: 4476863
A33: 入金額に対して出金割合 | B33: =B32/B27 -> 0.72950296 | C33: =AVERAGE(D33:AH33) -> 0.72365114 | D33: =D32/D27 -> 1.2970905 | E33: =E32/E27 -> 1.1139254 | F33: =F32/F27 -> 0.81961349 | G33: =G32/G27 -> 1.1661576 | H33: =H32/H27 -> 0.60899314 | I33: =I32/I27 -> 0.65740301 | J33: =J32/J27 -> 0.55373505 | K33: =K32/K27 -> 0.59634122 | ... AE33: =AE32/AE27 -> 0.87646188
A34: T/O(リアルのみ) / Total real bet | B34: =SUM(D34:AH34) -> 2033078021 | C34: =AVERAGE(D34:AH34) -> 72609929 | D34: 32861849 | E34: 37522938 | F34: 39569424 | G34: 54633736 | H34: 83462989 | I34: 114523955 | J34: 74599086 | K34: 68738303 | L34: 92216045 | M34: 40097378 | N34: 41425426 | O34: 33135945 | P34: 48557101 | Q34: 50690501 | R34: 63006286 | S34: 54588985 | T34: 54588985 | U34: 55796742 | V34: 70455216 | W34: 77376217 | X34: 87361273 | Y34: 65510916 | Z34: 117139905 | AA34: 237392513 | AB34: 115886373 | AC34: 94592577 | AD34: 66624665 | AE34: 60722692
A35: T/O率(リアルのみ) / Total real bet ratio | B35: =B34/B27 -> 15.704538 | C35: =AVERAGE(D35:AH35) -> 13.060946 | D35: =D34/D27 -> 8.6947725 | E35: =E34/E27 -> 13.307238 | F35: =F34/F27 -> 9.885698 | G35: =G34/G27 -> 15.390864 | H35: =H34/H27 -> 10.041397 | I35: =I34/I27 -> 17.162857 | J35: =J34/J27 -> 13.384236 | K35: =K34/K27 -> 15.63246 | ... AE35: =AE34/AE27 -> 11.88804
A36: T/O(ボーナス+リアルマネーの合計) / Total bet (Real+Bonus) | B36: =SUM(D36:AH36) -> 2033078021 | C36: =AVERAGE(D36:AH36) -> 65583162 | D36: =D34+D43 -> 32861849 | E36: =E34+E43 -> 37522938 | F36: =F34+F43 -> 39569424 | G36: =G34+G43 -> 54633736 | H36: =H34+H43 -> 83462989 | I36: =I34+I43 -> 114523955 | J36: =J34+J43 -> 74599086 | K36: =K34+K43 -> 68738303 | ... AH36: =AH34+AH43 -> 0
A37: 勝利金(リアルのみ) / Winning amt (Real) | B37: =SUM(D37:AH37) -> 1963038700 | C37: =AVERAGE(D37:AH37) -> 70108525 | D37: 32544172 | E37: 38310106 | F37: 39654863 | G37: 53106312 | H37: 82129397 | I37: 109076275 | J37: 73676542 | K37: 67787726 | L37: 86142048 | M37: 37471669 | N37: 39668188 | O37: 32943581 | P37: 43904615 | Q37: 47756626 | R37: 62478472 | S37: 54068694 | T37: 54068694 | U37: 54690912 | V37: 71326737 | W37: 73085637 | X37: 82280548 | Y37: 64436580 | Z37: 115529524 | AA37: 229071865 | AB37: 111864253 | AC37: 87927095 | AD37: 60775768 | AE37: 57261801
A38: 勝利金(ボーナスのみ) / Winning amt (Bonus) | B38: =SUM(D38:AH38) -> 1242447 | C38: =AVERAGE(D38:AH38) -> 44373.107 | D38: 0 | E38: 0 | F38: 0 | G38: 0 | H38: 0 | I38: 0 | J38: 0 | K38: 0 | L38: 0 | M38: 0 | N38: 0 | O38: 0 | P38: 0 | Q38: 0 | R38: 0 | S38: 0 | T38: 0 | U38: 0 | V38: 0 | W38: 0 | X38: 0 | Y38: 0 | Z38: -710000 | AA38: 0 | AB38: 2264099 | AC38: -103884 | AD38: -103884 | AE38: -103884
A39: 勝利金(ボーナス+リアルマネーの合計) / Winning (Bonus+Real) | B39: =SUM(D39:AH39) -> 1964281147 | C39: =AVERAGE(D39:AH39) -> 63363908 | D39: =D38+D37 -> 32544172 | E39: =E38+E37 -> 38310106 | F39: =F38+F37 -> 39654863 | G39: =G38+G37 -> 53106312 | H39: =H38+H37 -> 82129397 | I39: =I38+I37 -> 109076275 | J39: =J38+J37 -> 73676542 | K39: =K38+K37 -> 67787726 | ... AH39: =AH38+AH37 -> 0
A40: リアルマネー残高 / Real Money Balance | B40: =LOOKUP(9^9, C40:AH40) -> 11302741 | C40: =AVERAGE(D40:AH40) -> 9910366.3 | D40: 7233571 | E40: 7031022 | F40: 8725910 | G40: 9091789 | I40: 6885686 | J40: 9728845 | K40: 10744435 | L40: 8072992 | M40: 6395376 | N40: 6859009 | O40: 8756590 | P40: 6758249 | Q40: 7380567 | R40: 8790396 | S40: 10061116 | T40: 9349866 | U40: 8016444 | V40: 11201575 | W40: 9703057 | X40: 8909687 | Y40: 9057567 | Z40: 17398408 | AA40: 13109741 | AB40: 18189199 | AC40: 14928730 | AD40: 13897321 | AE40: 11302741
A41: ボーナス・マネー残高 / Bonus Money Balance | B41: =LOOKUP(9^9, C41:AH41) -> 1042269 | C41: =AVERAGE(D41:AH41) -> 1053525.2 | D41: 1042612 | E41: 1042612 | F41: 1042612 | G41: 1042612 | I41: 1042607 | J41: 1042607 | K41: 1042607 | L41: 1042607 | M41: 1042607 | N41: 1042607 | O41: 1042607 | P41: 1061659 | Q41: 1042607 | R41: 1042447 | S41: 1042267 | T41: 1042267 | U41: 1042267 | V41: 1042269 | W41: 1042269 | X41: 1042269 | Y41: 1042269 | Z41: 1042269 | AA41: 1042269 | AB41: 1322548 | AC41: 1042269 | AD41: 1042269 | AE41: 1042269
A42: RTP | B42: =C42 -> 0.96814145 | C42: =AVERAGE(D42:AH42) -> 0.96814145 | D42: =D39/D36 -> 0.99033295 | E42: =E39/E36 -> 1.0209783 | F42: =F39/F36 -> 1.0021592 | G42: =G39/G36 -> 0.97204248 | H42: =H39/H36 -> 0.98402175 | I42: =I39/I36 -> 0.95243196 | J42: =J39/J36 -> 0.98763331 | K42: =K39/K36 -> 0.98617107 | ... AE42: =AE39/AE36 -> 0.94129419
A43: T/O(ボーナスのみ) / Total bet (Bonus) | B43: =SUM(D43:AH43) -> 0 | C43: =AVERAGE(D43:AH43) -> 0 | D43: 0 | E43: 0 | F43: 0 | G43: 0 | H43: 0 | I43: 0 | J43: 0 | K43: 0 | L43: 0 | M43: 0 | N43: 0 | O43: 0 | P43: 0 | Q43: 0 | R43: 0 | S43: 0 | T43: 0 | U43: 0 | V43: 0 | W43: 0 | X43: 0 | Y43: 0 | Z43: 0 | AA43: 0 | AB43: 0 | AC43: 0 | AD43: 0 | AE43: 0
A44: T/O率(ボーナスのみ) / Total bet ratio (Bonus) | B44: =SUM(D44:AH44) -> 0 | C44: =AVERAGE(D44:AH44) -> 0 | D44: =D43/D27 -> 0 | E44: =E43/E27 -> 0 | F44: =F43/F27 -> 0 | G44: =G43/G27 -> 0 | H44: =H43/H27 -> 0 | I44: =I43/I27 -> 0 | J44: =J43/J27 -> 0 | K44: =K43/K27 -> 0 | ... AE44: =AE43/AE27 -> 0
A45: GGR | B45: =SUM(D45:AH45) -> 68796875 | C45: =AVERAGE(D45:AH45) -> 2219254 | D45: =D36-D39 -> 317677 | E45: =E36-E39 -> -787168 | F45: =F36-F39 -> -85439 | G45: =G36-G39 -> 1527424 | H45: =H36-H39 -> 1333592.8 | I45: =I36-I39 -> 5447680 | J45: =J36-J39 -> 922544 | K45: =K36-K39 -> 950577 | ... AH45: =AH36-AH39 -> 0
A46: GGR(入金に対して) | B46: =B45/B27 -> 0.53142236 | C46: =AVERAGE(D46:AH46) -> 0.39780611 | D46: =D45/D27 -> 0.084052764 | E46: =E45/E27 -> -0.27916343 | F46: =F45/F27 -> -0.021345374 | G46: =G45/G27 -> 0.43029046 | H46: =H45/H27 -> 0.16044398 | I46: =I45/I27 -> 0.81640348 | J46: =J45/J27 -> 0.16551874 | K46: =K45/K27 -> 0.21618015 | ... AE46: =AE45/AE27 -> 0.69789703
A47: GGRLTV | B47: =B45/B26 -> 51379.294 | C47: =AVERAGE(D47:AH47) -> 6030.1508 | D47: =D45/D26 -> 761.81535 | E47: =E45/E26 -> -2392.6079 | F47: =F45/F26 -> -210.96049 | G47: =G45/G26 -> 5285.2042 | H47: =H45/H26 -> 3767.2112 | I47: =I45/I26 -> 12669.023 | J47: =J45/J26 -> 2077.8018 | K47: =K45/K26 -> 2787.6158 | ... AE47: =AE45/AE26 -> 5492.7196
A48: 入出金差分 | B48: =B27-B32 -> 35018005 | C48: =AVERAGE(D48:AH48) -> 1499061.2 | D48: =D27-D32 -> -1122852 | E48: =E27-E32 -> -321240 | F48: =F27-F32 -> 722032 | G48: =G27-G32 -> -589818 | H48: =H27-H32 -> 3250006 | I48: =I27-I32 -> 2286074 | J48: =J27-J32 -> 2487326 | K48: =K27-K32 -> 1774949 | ... AH48: =AH27-AH32 -> 0
A49: 差分(入金に対して) | B49: =B48/B27 -> 0.27049704 | C49: =AVERAGE(D49:AH49) -> 0.27634886 | D49: =D48/D27 -> -0.29709048 | E49: =E48/E27 -> -0.11392544 | F49: =F48/F27 -> 0.18038651 | G49: =G48/G27 -> -0.16615757 | H49: =H48/H27 -> 0.39100686 | I49: =I48/I27 -> 0.34259699 | J49: =J48/J27 -> 0.44626495 | K49: =K48/K27 -> 0.40365878 | ... AE49: =AE48/AE27 -> 0.12353812
A50: 差分LTV | B50: =B48/B26 -> 26152.356 | C50: =AVERAGE(D50:AH50) -> 4065.6751 | D50: =D48/D26 -> -2692.6906 | E50: =E48/E26 -> -976.41337 | F50: =F48/F26 -> 1782.7951 | G50: =G48/G26 -> -2040.8927 | H50: =H48/H26 -> 9180.8079 | I50: =I48/I26 -> 5316.4512 | J50: =J48/J26 -> 5602.0856 | K50: =K48/K26 -> 5205.129 | ... AE50: =AE48/AE26 -> 972.29276
A51: ヘブンズショットコスト/Heavensshot Cost | B51: =SUM(D51:AH51) -> 2106000 | C51: =AVERAGE(D51:AH51) -> 67935.484 | D51: 42000 | E51: 90000 | F51: 14000 | G51: 8000 | H51: 22000 | I51: 10000 | J51: 150000 | K51: 0 | L51: 50000 | M51: 540000 | N51: 80000 | O51: 100000 | P51: 130000 | Q51: 10000 | R51: 10000 | S51: 0 | T51: 10000 | U51: 10000 | V51: 0 | W51: 40000 | X51: 10000 | Y51: 10000 | Z51: 30000 | AA51: 210000 | AB51: 420000 | AC51: 0 | AD51: 60000 | AE51: 50000 | AF51: 0 | AG51: 0 | AH51: 0
A52: トーナメントコスト/Tournament Cost | B52: =SUM(D52:AH52) -> 0 | C52: =AVERAGE(D52:AH52) -> 0 | D52: 0 | E52: 0 | F52: 0 | G52: 0 | H52: 0 | I52: 0 | J52: 0 | K52: 0 | L52: 0 | M52: 0 | N52: 0 | O52: 0 | P52: 0 | Q52: 0 | R52: 0 | S52: 0 | T52: 0 | U52: 0 | V52: 0 | W52: 0 | X52: 0 | Y52: 0 | Z52: 0 | AA52: 0 | AB52: 0 | AC52: 0 | AD52: 0 | AE52: 0 | AF52: 0 | AG52: 0 | AH52: 0
A53: 新規用期間イベントコスト/new user event Cost | B53: =SUM(D53:AH53) -> 807635 | C53: =AVERAGE(D53:AH53) -> 26052.742 | D53: 16000 | E53: 8000 | F53: 21000 | G53: 12000 | H53: 336635 | I53: 12000 | J53: 12000 | K53: 8000 | L53: 8000 | M53: 16000 | N53: 28000 | O53: 48000 | P53: 28000 | Q53: 16000 | R53: 44000 | S53: 16000 | T53: 20000 | U53: 20000 | V53: 12000 | W53: 16000 | X53: 20000 | Y53: 20000 | Z53: 4000 | AA53: 12000 | AB53: 8000 | AC53: 10000 | AD53: 16000 | AE53: 20000 | AF53: 0 | AG53: 0 | AH53: 0
A54: 休眠用期間イベントコスト/old user event Cost | B54: =SUM(D54:AH54) -> 0 | C54: =AVERAGE(D54:AH54) -> 0 | D54: 0 | E54: 0 | F54: 0 | G54: 0 | H54: 0 | I54: 0 | J54: 0 | K54: 0 | L54: 0 | M54: 0 | N54: 0 | O54: 0 | P54: 0 | Q54: 0 | R54: 0 | S54: 0 | T54: 0 | U54: 0 | V54: 0 | W54: 0 | X54: 0 | Y54: 0 | Z54: 0 | AA54: 0 | AB54: 0 | AC54: 0 | AD54: 0 | AE54: 0 | AF54: 0 | AG54: 0 | AH54: 0
A55: 既存用期間イベントコスト/Active user event Cost | B55: =SUM(D55:AH55) -> 1500 | C55: =AVERAGE(D55:AH55) -> 48.387097 | D55: 0 | E55: 0 | F55: 0 | G55: 0 | H55: 0 | I55: 0 | J55: 0 | K55: 0 | L55: 0 | M55: 0 | N55: 0 | O55: 0 | P55: 1500 | Q55: 0 | R55: 0 | S55: 0 | T55: 0 | U55: 0 | V55: 0 | W55: 0 | X55: 0 | Y55: 0 | Z55: 0 | AA55: 0 | AB55: 0 | AC55: 0 | AD55: 0 | AE55: 0 | AF55: 0 | AG55: 0 | AH55: 0
A56: ドリームポットコスト/Jackpot Cost | B56: =SUM(D56:AH56) -> 13845003 | C56: =AVERAGE(D56:AH56) -> 446613 | D56: 0 | E56: 0 | F56: 0 | G56: 0 | H56: 0 | I56: 0 | J56: 0 | K56: 0 | L56: 0 | M56: 0 | N56: 0 | O56: 0 | P56: 0 | Q56: 0 | R56: 0 | S56: 0 | T56: 0 | U56: 0 | V56: 0 | W56: 0 | X56: 0 | Y56: 0 | Z56: =27690005.98/2 -> 13845003 | AA56: 0 | AB56: 0 | AC56: 0 | AD56: 0 | AE56: 0 | AF56: 0 | AG56: 0 | AH56: 0
A57: 入金不要コスト/ Cost | B57: =SUM(D57:AH57) -> 5478000 | C57: =AVERAGE(D57:AH57) -> 182600 | D57: 585000 | E57: 423000 | F57: 618000 | G57: 378000 | H57: 477000 | I57: 834000 | J57: 789000 | K57: 657000 | L57: 207000 | M57: 510000 | O57: 0 | P57: 0 | Q57: 0 | R57: 0 | S57: 0 | T57: 0 | U57: 0 | V57: 0 | W57: 0 | X57: 0 | Y57: 0 | Z57: 0 | AA57: 0 | AB57: 0 | AC57: 0 | AD57: 0 | AE57: 0 | AF57: 0 | AG57: 0 | AH57: 0
A58: AFFイベント コスト / AFF EventCost | B58: =SUM(D58:AH58) -> 0 | C58: =AVERAGE(D58:AH58) -> 0 | D58: 0 | E58: 0 | F58: 0 | G58: 0 | H58: 0 | I58: 0 | J58: 0 | K58: 0 | L58: 0 | M58: 0 | N58: 0 | O58: 0 | P58: 0 | Q58: 0 | R58: 0 | S58: 0 | T58: 0 | U58: 0 | V58: 0 | W58: 0 | X58: 0 | Y58: 0 | Z58: 0 | AA58: 0 | AB58: 0 | AC58: 0 | AD58: 0 | AE58: 0 | AF58: 0 | AG58: 0 | AH58: 0
A59: ペイメントコスト / Payment cost | B59: =SUM(D59:AH59) -> 0 | C59: =AVERAGE(D59:AH59) -> 0 | D59: 0 | E59: 0 | F59: 0 | G59: 0 | H59: 0 | I59: 0 | J59: 0 | K59: 0 | L59: 0 | M59: 0 | N59: 0 | O59: 0 | P59: 0 | Q59: 0 | R59: 0 | S59: 0 | T59: 0 | U59: 0 | V59: 0 | W59: 0 | X59: 0 | Y59: 0 | Z59: 0 | AA59: 0 | AB59: 0 | AC59: 0 | AD59: 0 | AE59: 0 | AF59: 0 | AG59: 0 | AH59: 0
A60: プロバイダーフィー / Provider fee | B60: =SUM(D60:AH60) -> 0 | C60: =AVERAGE(D60:AH60) -> 0 | D60: 0 | E60: 0 | F60: 0 | G60: 0 | H60: 0 | I60: 0 | J60: 0 | K60: 0 | L60: 0 | M60: 0 | N60: 0 | O60: 0 | P60: 0 | Q60: 0 | R60: 0 | S60: 0 | T60: 0 | U60: 0 | V60: 0 | W60: 0 | X60: 0 | Y60: 0 | Z60: 0 | AA60: 0 | AB60: 0 | AC60: 0 | AD60: 0 | AE60: 0 | AF60: 0 | AG60: 0 | AH60: 0
A61: AFFコスト / Aff cost | B61: =SUM(D61:AH61) -> 10510123 | C61: =AVERAGE(D61:AH61) -> 420404.92 | D61: =D109 -> 885388.93 | E61: =E109 -> 0 | F61: =F109 -> 0 | G61: =G109 -> 0 | H61: =H109 -> 0 | I61: =I109 -> 0 | J61: =J109 -> 0 | K61: =K109 -> 0 | ... AH61: =AH109
A62: otherコスト / Other cost | B62: =SUM(D62:AH62) -> 0 | C62: =AVERAGE(D62:AH62) -> 0 | D62: 0 | E62: 0 | F62: 0 | G62: 0 | H62: 0 | I62: 0 | J62: 0 | K62: 0 | L62: 0 | M62: 0 | N62: 0 | O62: 0 | P62: 0 | Q62: 0 | R62: 0 | S62: 0 | T62: 0 | U62: 0 | V62: 0 | W62: 0 | X62: 0 | Y62: 0 | Z62: 0 | AA62: 0 | AB62: 0 | AC62: 0 | AD62: 0 | AE62: 0 | AF62: 0 | AG62: 0 | AH62: 0
A63: 総コスト(ボーナスは付与額ベース) / Total cost (Granted bonus included) | B63: =B62+B61+B60+B58+B59 -> 10510123 | C63: =AVERAGE(D63:AH63) -> 339036.23 | D63: =D62+D61+D60+D59 -> 885388.93 | E63: =E62+E61+E60+E59 -> 0 | F63: =F62+F61+F60+F59 -> 0 | G63: =G62+G61+G60+G59 -> 0 | H63: =H62+H61+H60+H59 -> 0 | I63: =I62+I61+I60+I59 -> 0 | J63: =J62+J61+J60+J59 -> 0 | K63: =K62+K61+K60+K59 -> 0 | ... AH63: =AH62+AH61+AH60+AH59 -> 0
A64: NGR | B64: =SUM(D64:AH64) -> 36048614 | C64: =AVERAGE(D64:AH64) -> 1162858.5 | D64: =D45-(D51+D52+D53+D54+D55+D56+D57+D58+D60+D61+D62) -> -1210711.9 | E64: =E45-(E51+E52+E53+E54+E55+E56+E57+E58+E60+E61+E62) -> -1308168 | F64: =F45-(F51+F52+F53+F54+F55+F56+F57+F58+F60+F61+F62) -> -738439 | G64: =G45-(G51+G52+G53+G54+G55+G56+G57+G58+G60+G61+G62) -> 1129424 | H64: =H45-(H51+H52+H53+H54+H55+H56+H57+H58+H60+H61+H62) -> 497957.75 | I64: =I45-(I51+I52+I53+I54+I55+I56+I57+I58+I60+I61+I62) -> 4591680 | J64: =J45-(J51+J52+J53+J54+J55+J56+J57+J58+J60+J61+J62) -> -28456 | K64: =K45-(K51+K52+K53+K54+K55+K56+K57+K58+K60+K61+K62) -> 285577 | ... AH64: =AH45-(AH51+AH52+AH53+AH54+AH55+AH56+AH57+AH58+AH60+AH61+AH62) -> 0
A65: 入出金差分 | B65: =SUM(D65:AH65) -> 35960773 | C65: =AVERAGE(D65:AH65) -> 1160024.9 | D65: =D48-D63 -> -2008240.9 | E65: =E48-E63 -> -321240 | F65: =F48-F63 -> 722032 | G65: =G48-G63 -> -589818 | H65: =H48-H63 -> 3250006 | I65: =I48-I63 -> 2286074 | J65: =J48-J63 -> 2487326 | K65: =K48-K63 -> 1774949 | ... AH65: =AH48-AH63 -> 0
A66: プロモーション開催期間 / Promotion duration | K66: だっちゃんヘブンズショット
A67: 目的 | K67: FTD・アクティブ
A68: プロモーション開催期間 / Promotion duration | D68: ヘブンズショット
A69: 目的 | D69: アクティブ
A70: プロモーション開催期間 / Promotion duration | D70: 入金不要
A71: 目的 | D71: 登録
A72: プロモーション開催期間 / Promotion duration | D72: ステップヘブンズショット
A73: 目的 | D73: FTD/2nd/3rd
A74: プロモーション開催期間 / Promotion duration | Z74: カスタムヘブンズショット
A75: 目的 | Z75: アクティブ
A79: テスト資金 | Q79: 100000 | R79: 200000 | S79: 100000 | Z79: 100000
A80: 【分析指標】
A81: ARPU(全登録ユーザー) | B81: =SUM(D81:AH81) -> 211616.59 | C81: =AVERAGE(D81:AH81) -> 7557.7354 | D81: =D64/D4 -> -6208.7791 | E81: =E64/E4 -> -9277.7872 | F81: =F64/F4 -> -3584.6553 | G81: =G64/G4 -> 7103.2956 | H81: =H64/H4 -> 3131.8097 | I81: =I64/I4 -> 16516.835 | J81: =J64/J4 -> -108.19772 | K81: =K64/K4 -> 1304.0046 | ... AE81: =AE64/AE4 -> 10590.227
A82: ARPPU(課金ユーザー) | B82: =SUM(D82:AH82) -> 212959.75 | C82: =AVERAGE(D82:AH82) -> 7605.7053 | D82: =D64/D25 -> -7427.6806 | E82: =E64/E25 -> -10300.535 | F82: =F64/F25 -> -6003.5691 | G82: =G64/G25 -> 9571.3898 | H82: =H64/H25 -> 2946.4956 | I82: =I64/I25 -> 30010.98 | J82: =J64/J25 -> -196.24828 | K82: =K64/K25 -> 2196.7462 | ... AE82: =AE64/AE25 -> 17830.485
A83: FTDコンバージョン率 | B83: =C83 -> 0.050388319 | C83: =AVERAGE(D83:AH83) -> 0.050388319 | D83: =D18/D4 -> 0.056410256 | E83: =E18/E4 -> 0.078014184 | F83: =F18/F4 -> 0.063106796 | G83: =G18/G4 -> 0.075471698 | H83: =H18/H4 -> 0.088050314 | I83: =I18/I4 -> 0.043165468 | J83: =J18/J4 -> 0.068441065 | K83: =K18/K4 -> 0.03196347 | ... AE83: =AE18/AE4 -> 0.039393939
A84: 2nd継続率 | B84: =C84 -> 0.22543934 | C84: =AVERAGE(D84:AH84) -> 0.22543934 | D84: =D12/D10 -> 0.5 | E84: =E12/E10 -> 0.14285714 | F84: =F12/F10 -> 0 | G84: =G12/G10 -> 0 | H84: =H12/H10 -> 0.125 | I84: =I12/I10 -> 0.22222222 | J84: =J12/J10 -> 0.33333333 | K84: =K12/K10 -> 0 | ... AE84: =AE12/AE10 -> 0.22222222
A85: アクティブ率 | B85: =C85 -> 2.3014449 | C85: =AVERAGE(D85:AH85) -> 2.3014449 | D85: =D26/D4 -> 2.1384615 | E85: =E26/E4 -> 2.3333333 | F85: =F26/F4 -> 1.9660194 | G85: =G26/G4 -> 1.8176101 | H85: =H26/H4 -> 2.2264151 | I85: =I26/I4 -> 1.5467626 | J85: =J26/J4 -> 1.6882129 | K85: =K26/K4 -> 1.5570776 | ... AE85: =AE26/AE4 -> 1.9666667
A86: GGRマージン率 | B86: =C86 -> 0.39780611 | C86: =AVERAGE(D86:AH86) -> 0.39780611 | D86: =D45/D27 -> 0.084052764 | E86: =E45/E27 -> -0.27916343 | F86: =F45/F27 -> -0.021345374 | G86: =G45/G27 -> 0.43029046 | H86: =H45/H27 -> 0.16044398 | I86: =I45/I27 -> 0.81640348 | J86: =J45/J27 -> 0.16551874 | K86: =K45/K27 -> 0.21618015 | ... AE86: =AE45/AE27 -> 0.69789703
A87: NGRマージン率 | B87: =C87 -> 0.19986239 | C87: =AVERAGE(D87:AH87) -> 0.19986239 | D87: =D64/D27 -> -0.32033696 | E87: =E64/E27 -> -0.4639323 | F87: =F64/F27 -> -0.1844855 | G87: =G64/G27 -> 0.31816992 | H87: =H64/H27 -> 0.059909088 | I87: =I64/I27 -> 0.6881211 | J87: =J64/J27 -> -0.0051054488 | K87: =K64/K27 -> 0.064945901 | ... AE87: =AE64/AE27 -> 0.68419272
A88: 平均入金回数/ユーザー | B88: =C88 -> 1.867327 | C88: =AVERAGE(D88:AH88) -> 1.867327 | D88: =D24/D25 -> 1.6441718 | E88: =E24/E25 -> 1.8267717 | F88: =F24/F25 -> 1.7398374 | G88: =G24/G25 -> 1.8050847 | H88: =H24/H25 -> 1.8224852 | I88: =I24/I25 -> 1.9411765 | J88: =J24/J25 -> 1.7931034 | K88: =K24/K25 -> 1.9076923 | ... AE88: =AE24/AE25 -> 1.8826531
A90: プロモーション開催期間 / Promotion duration
A91: 目的 / Purpose
A93: Affiliate
A94: AFF経由登録者数 / Registration under AFF | B94: =SUM(D94:AH94) -> 1343 | C94: =AVERAGE(D94:AH94) -> 53.72 | D94: 50 | E94: 45 | F94: 51 | G94: 34 | H94: 30 | I94: 66 | J94: 37 | K94: 40 | L94: 38 | M94: 48 | N94: 62 | O94: 87 | P94: 79 | Q94: 59 | R94: 57 | S94: 45 | T94: 37 | U94: 60 | V94: 70 | W94: 29 | X94: 46 | Y94: 67 | Z94: 82 | AA94: 62 | AB94: 62
A95: AFF経由FTD数 / FTD under AFF | B95: =SUM(D95:AH95) -> 173 | C95: =AVERAGE(D95:AH95) -> 6.92 | D95: 5 | E95: 9 | F95: 6 | G95: 2 | H95: 5 | I95: 3 | J95: 7 | K95: 6 | L95: 3 | M95: 10 | N95: 6 | O95: 12 | P95: 11 | Q95: 13 | R95: 9 | S95: 8 | T95: 6 | U95: 5 | V95: 11 | W95: 7 | X95: 8 | Y95: 2 | Z95: 7 | AA95: 7 | AB95: 5
A96: AFF数 | B96: =SUM(D96:AH96) -> 69 | C96: =AVERAGE(D96:AH96) -> 2.76 | D96: 5 | E96: 4 | F96: 3 | G96: 1 | H96: 1 | I96: 3 | J96: 3 | K96: 1 | L96: 3 | M96: 5 | N96: 1 | O96: 2 | P96: 2 | Q96: 4 | R96: 2 | S96: 2 | T96: 2 | U96: 2 | V96: 2 | W96: 3 | X96: 2 | Y96: 3 | Z96: 7 | AA96: 5 | AB96: 1
A97: AFF経由入金額 / DP amt under AFF | B97: 8022259 | C97: =AVERAGE(D97:AH97) -> #DIV/0!
A98: AFF経由出金額 / WD amt under AFF | B98: 5490590 | C98: =AVERAGE(D98:AH98) -> #DIV/0!
A99: Ｔ／Ｏ
A100: 勝利金
A101: AFF経由RTP / RTP under AFF | B101: =SUM(D101:AH101) -> 0 | C101: =AVERAGE(D101:AH101) -> #DIV/0!
A102: AFF経由GGR / GGR under AFF | B102: 2531669 | C102: =AVERAGE(D102:AH102) -> #DIV/0!
A103: 差分GGR | B103: =SUM(D103:AH103) -> 0 | C103: =AVERAGE(D103:AH103) -> #DIV/0!
A104: AFF経由ボーナス額 / Bonus Granted Amt under AFF | B104: =SUM(D104:AH104) -> 0 | C104: =AVERAGE(D104:AH104) -> #DIV/0!
A105: AFFデモコスト(10％換算) | B105: =SUM(D105:AH105) -> 339666 | C105: =AVERAGE(D105:AH105) -> 13586.64 | D105: 0 | E105: 0 | F105: 0 | G105: 0 | H105: 0 | I105: 0 | J105: 0 | K105: 0 | L105: 30000 | M105: 35000 | N105: 0 | O105: 0 | P105: 0 | Q105: 0 | R105: 0 | S105: 30000 | T105: 0 | U105: 0 | V105: 33000 | W105: 0 | X105: 0 | Y105: 0 | Z105: 130000 | AA105: 0 | AB105: 81666
...

Sheet 202602
A1: 項目名 | B1: 月次合計 | C1: 日次平均 | D1: 46054 | E1: 46055 | F1: 46056 | G1: 46057 | H1: 46058 | I1: 46059 | J1: 46060 | K1: 46061 | L1: 46062 | M1: 46063 | N1: 46064 | O1: 46065 | P1: 46066 | Q1: 46067 | R1: 46068 | S1: 46069 | T1: 46070 | U1: 46071 | V1: 46072 | W1: 46073 | X1: 46074 | Y1: 46075 | Z1: 46076 | AA1: 46077 | AB1: 46078 | AC1: 46079 | AD1: 46080 | AE1: 46081
D2: 日 | E2: 月 | F2: 火 | G2: 水 | H2: 木 | I2: 金 | J2: 土 | K2: 日 | L2: 月 | M2: 火 | N2: 水 | O2: 木 | P2: 金 | Q2: 土 | R2: 日 | S2: 月 | T2: 火 | U2: 水 | V2: 木 | W2: 金 | X2: 土 | Y2: 日 | Z2: 月 | AA2: 火 | AB2: 水 | AC2: 木 | AD2: 金 | AE2: 土
A3: 全体KPI | B3: =SUM(D3:AH3) -> 0
A4: 登録人数 | B4: =SUM(D4:AH4) -> 0 | C4: =AVERAGE(D4:AH4) -> #DIV/0!
A5: ログインユーザー数 | C5: =AVERAGE(D5:AH5) -> #DIV/0!
A6: SMS認証 | B6: =SUM(D6:AH6) -> 0 | C6: =AVERAGE(D6:AH6) -> #DIV/0!
A7: 登録に対してSMS認証割合 | B7: =C7 -> #DIV/0! | C7: =AVERAGE(D7:AH7) -> #DIV/0! | D7: =D6/D4 -> #DIV/0!
A8: 入金不要ボーナス使用済ユーザー数 | B8: 4643 | C8: =AVERAGE(D8:AH8) -> #DIV/0!
A9: 登録に対してNDB使用割合 | B9: =SUM(D9:AH9) -> #DIV/0! | C9: =AVERAGE(D9:AH9) -> #DIV/0! | D9: =D8/D4 -> #DIV/0!
A10: FTDのみ入金者数 | B10: 233 | C10: =AVERAGE(D10:AH10) -> #DIV/0!
A11: 登録に対して1st使用割合 | B11: =C11 -> #DIV/0! | C11: =AVERAGE(D11:AH11) -> #DIV/0! | D11: =D10/D4 -> #DIV/0!
A12: 2ndのみ入金者数 | B12: 44 | C12: =AVERAGE(D12:AH12) -> #DIV/0!
A13: 登録に対して2nd使用割合 | B13: =C13 -> #DIV/0! | C13: =AVERAGE(D13:AH13) -> #DIV/0! | D13: =D12/D4 -> #DIV/0!
A14: 3nd入金以降ユーザー数 | B14: 36 | C14: =AVERAGE(D14:AH14) -> #DIV/0!
A15: 登録に対して3nd使用割合 | B15: =C15 -> #DIV/0! | C15: =AVERAGE(D15:AH15) -> #DIV/0! | D15: =D14/D4 -> #DIV/0!
A16: 4nd入金以降ユーザー数 | B16: 116 | C16: =AVERAGE(D16:AH16) -> #DIV/0!
A17: 登録に対して4nd使用割合 | B17: =C17 -> #DIV/0! | C17: =AVERAGE(D17:AH17) -> #DIV/0! | D17: =D16/D4 -> #DIV/0!
A18: 今月登録のFTD以降ユーザー数 | B18: =B10+B12+B14+B16 -> 429 | C18: =AVERAGE(D18:AH18) -> 0 | D18: =D10+D12+D14+D16 -> 0
A19: 今月登録FTD以降ユーザー割合 | B19: =B18/B4 -> #DIV/0! | C19: =AVERAGE(D19:AH19) -> #DIV/0! | D19: =D11+D13+D15+D17 -> #DIV/0!
A20: 今月登録のアクティブユーザー数
A21: 前月登録のアクティブユーザー数
A22: 前々月登録のアクティブユーザー数
A23: 3か月以上アクティブプレイヤー数 | B23: -
A24: 総入金回数 | B24: =SUM(D24:AH24) -> 0 | C24: =AVERAGE(D24:AH24) -> #DIV/0!
A25: 入金者数(デイリーユニーク) | B25: =G193 -> 0 | C25: =AVERAGE(D25:AH25) -> #DIV/0!
A26: アクティブプレイ人数（ユニーク） | B26: =B20+B21+B22 -> 0 | C26: =AVERAGE(D26:AH26) -> #DIV/0!
A27: 総入金額 / Total DP amt | B27: =B193 -> 0 | C27: =AVERAGE(D27:AH27) -> #DIV/0!
A28: 平均入金額(一回の入金額) / Ave amt per DP | B28: =C28 -> #DIV/0! | C28: =AVERAGE(D28:AH28) -> #DIV/0! | D28: =D27/D24 -> #DIV/0!
A29: 平均入金額(ユニークユーザー) / Ave DP amt (Unique user) | B29: =C29 -> #DIV/0! | C29: =AVERAGE(D29:AH29) -> #DIV/0! | D29: =D27/D25 -> #DIV/0!
A30: 総出金回数 | B30: =SUM(D30:AH30) -> 0 | C30: =AVERAGE(D30:AH30) -> #DIV/0!
A31: 総出金人数 | B31: =SUM(D31:AH31) -> 0 | C31: =AVERAGE(D31:AH31) -> #DIV/0!
A32: 総出金額 / Total WD amt | B32: =B201 -> 0 | C32: =AVERAGE(D32:AH32) -> #DIV/0!
A33: 入金額に対して出金割合 | B33: =B32/B27 -> #DIV/0! | C33: =AVERAGE(D33:AH33) -> #DIV/0! | D33: =D32/D27 -> #DIV/0!
A34: T/O(リアルのみ) / Total real bet | B34: =SUM(D34:AH34) -> 0 | C34: =AVERAGE(D34:AH34) -> #DIV/0!
A35: T/O率(リアルのみ) / Total real bet ratio | B35: =B34/B27 -> #DIV/0! | C35: =AVERAGE(D35:AH35) -> #DIV/0! | D35: =D34/D27 -> #DIV/0!
A36: T/O(ボーナス+リアルマネーの合計) / Total bet (Real+Bonus) | B36: =SUM(D36:AH36) -> 0 | C36: =AVERAGE(D36:AH36) -> 0 | D36: =D34+D43 -> 0
A37: 勝利金(リアルのみ) / Winning amt (Real) | B37: =SUM(D37:AH37) -> 0 | C37: =AVERAGE(D37:AH37) -> #DIV/0!
A38: 勝利金(ボーナスのみ) / Winning amt (Bonus) | B38: =SUM(D38:AH38) -> 0 | C38: =AVERAGE(D38:AH38) -> 0 | D38: 0
A39: 勝利金(ボーナス+リアルマネーの合計) / Winning (Bonus+Real) | B39: =SUM(D39:AH39) -> 0 | C39: =AVERAGE(D39:AH39) -> 0 | D39: =D38+D37 -> 0
A40: リアルマネー残高 / Real Money Balance | B40: =LOOKUP(9^9, C40:AH40) -> #N/A | C40: =AVERAGE(D40:AH40) -> #DIV/0!
A41: ボーナス・マネー残高 / Bonus Money Balance | B41: =LOOKUP(9^9, C41:AH41) -> #N/A | C41: =AVERAGE(D41:AH41) -> #DIV/0!
A42: RTP | B42: =C42 -> #DIV/0! | C42: =AVERAGE(D42:AH42) -> #DIV/0! | D42: =D39/D36 -> #DIV/0!
A43: T/O(ボーナスのみ) / Total bet (Bonus) | B43: =SUM(D43:AH43) -> 0 | C43: =AVERAGE(D43:AH43) -> 0 | D43: 0
A44: T/O率(ボーナスのみ) / Total bet ratio (Bonus) | B44: =SUM(D44:AH44) -> #DIV/0! | C44: =AVERAGE(D44:AH44) -> #DIV/0! | D44: =D43/D27 -> #DIV/0!
A45: GGR | B45: =SUM(D45:AH45) -> 0 | C45: =AVERAGE(D45:AH45) -> 0 | D45: =D36-D39 -> 0
A46: GGR(入金に対して) | B46: =B45/B27 -> #DIV/0! | C46: =AVERAGE(D46:AH46) -> #DIV/0! | D46: =D45/D27 -> #DIV/0!
A47: GGRLTV | B47: =B45/B26 -> #DIV/0! | C47: =AVERAGE(D47:AH47) -> #DIV/0! | D47: =D45/D26 -> #DIV/0!
A48: 入出金差分 | B48: =B27-B32 -> 0 | C48: =AVERAGE(D48:AH48) -> 0 | D48: =D27-D32 -> 0
A49: 差分(入金に対して) | B49: =B48/B27 -> #DIV/0! | C49: =AVERAGE(D49:AH49) -> #DIV/0! | D49: =D48/D27 -> #DIV/0!
A50: 差分LTV | B50: =B48/B26 -> #DIV/0! | C50: =AVERAGE(D50:AH50) -> #DIV/0! | D50: =D48/D26 -> #DIV/0!
A51: ヘブンズショットコスト/Heavensshot Cost | B51: =SUM(D51:AH51) -> 0 | C51: =AVERAGE(D51:AH51) -> #DIV/0!
A52: トーナメントコスト/Tournament Cost | B52: =SUM(D52:AH52) -> 0 | C52: =AVERAGE(D52:AH52) -> #DIV/0!
A53: 新規用期間イベントコスト/new user event Cost | B53: =SUM(D53:AH53) -> 0 | C53: =AVERAGE(D53:AH53) -> #DIV/0!
A54: 休眠用期間イベントコスト/old user event Cost | B54: =SUM(D54:AH54) -> 0 | C54: =AVERAGE(D54:AH54) -> #DIV/0!
A55: 既存用期間イベントコスト/Active user event Cost | B55: =SUM(D55:AH55) -> 0 | C55: =AVERAGE(D55:AH55) -> #DIV/0!
A56: ドリームポットコスト/Jackpot Cost | B56: =SUM(D56:AH56) -> 0 | C56: =AVERAGE(D56:AH56) -> #DIV/0!
A57: 入金不要コスト/ Cost | B57: =SUM(D57:AH57) -> 0 | C57: =AVERAGE(D57:AH57) -> #DIV/0!
A58: AFFイベント コスト / AFF EventCost | B58: =SUM(D58:AH58) -> 0 | C58: =AVERAGE(D58:AH58) -> #DIV/0!
A59: ペイメントコスト / Payment cost | B59: =SUM(D59:AH59) -> 0 | C59: =AVERAGE(D59:AH59) -> #DIV/0!
A60: プロバイダーフィー / Provider fee | B60: =SUM(D60:AH60) -> 0 | C60: =AVERAGE(D60:AH60) -> #DIV/0!
A61: AFFコスト / Aff cost | B61: =SUM(D61:AH61) -> 0 | C61: =AVERAGE(D61:AH61) -> 0 | D61: =D109 -> 0
A62: otherコスト / Other cost | B62: =SUM(D62:AH62) -> 0 | C62: =AVERAGE(D62:AH62) -> 0 | D62: 0
A63: 総コスト(ボーナスは付与額ベース) / Total cost (Granted bonus included) | B63: =B62+B61+B60+B58+B59 -> 0 | C63: =AVERAGE(D63:AH63) -> 0 | D63: =D62+D61+D60+D59 -> 0
A64: NGR | B64: =SUM(D64:AH64) -> 0 | C64: =AVERAGE(D64:AH64) -> 0 | D64: =D45-(D51+D52+D53+D54+D55+D56+D57+D58+D60+D61+D62) -> 0
A65: 入出金差分 | B65: =SUM(D65:AH65) -> 0 | C65: =AVERAGE(D65:AH65) -> 0 | D65: =D48-D63 -> 0
A66: プロモーション開催期間 / Promotion duration | D66: ヘブンズショット
A67: 目的 | D67: アクティブ
A68: プロモーション開催期間 / Promotion duration | D68: ステップヘブンズショット
A69: 目的 | D69: FTD/2nd/3rd
A70: プロモーション開催期間 / Promotion duration | D70: カスタムヘブンズショット
A71: 目的 | D71: アクティブ
A72: プロモーション開催期間 / Promotion duration | F72: 鬼は外福は内 | O72: バレンタイン
A73: 目的 | F73: アクティブ | O73: アクション
A74: プロモーション開催期間 / Promotion duration
A75: 目的
A79: テスト資金 | Q79: 100000 | R79: 200000 | S79: 100000 | Z79: 100000
A80: 【分析指標】
A81: ARPU(全登録ユーザー) | B81: =SUM(D81:AH81) -> #DIV/0! | C81: =AVERAGE(D81:AH81) -> #DIV/0! | D81: =D64/D4 -> #DIV/0! | E81: =E64/E4 -> #DIV/0! | F81: =F64/F4 -> #DIV/0! | G81: =G64/G4 -> #DIV/0! | H81: =H64/H4 -> #DIV/0! | I81: =I64/I4 -> #DIV/0! | J81: =J64/J4 -> #DIV/0! | K81: =K64/K4 -> #DIV/0! | ... Y81: =Y64/Y4 -> #DIV/0!
A82: ARPPU(課金ユーザー) | B82: =SUM(D82:AH82) -> #DIV/0! | C82: =AVERAGE(D82:AH82) -> #DIV/0! | D82: =D64/D25 -> #DIV/0! | E82: =E64/E25 -> #DIV/0! | F82: =F64/F25 -> #DIV/0! | G82: =G64/G25 -> #DIV/0! | H82: =H64/H25 -> #DIV/0! | I82: =I64/I25 -> #DIV/0! | J82: =J64/J25 -> #DIV/0! | K82: =K64/K25 -> #DIV/0! | ... Y82: =Y64/Y25 -> #DIV/0!
A83: FTDコンバージョン率 | B83: =C83 -> #DIV/0! | C83: =AVERAGE(D83:AH83) -> #DIV/0! | D83: =D18/D4 -> #DIV/0! | E83: =E18/E4 -> #DIV/0! | F83: =F18/F4 -> #DIV/0! | G83: =G18/G4 -> #DIV/0! | H83: =H18/H4 -> #DIV/0! | I83: =I18/I4 -> #DIV/0! | J83: =J18/J4 -> #DIV/0! | K83: =K18/K4 -> #DIV/0! | ... Y83: =Y18/Y4 -> #DIV/0!
A84: 2nd継続率 | B84: =C84 -> #DIV/0! | C84: =AVERAGE(D84:AH84) -> #DIV/0! | D84: =D12/D10 -> #DIV/0! | E84: =E12/E10 -> #DIV/0! | F84: =F12/F10 -> #DIV/0! | G84: =G12/G10 -> #DIV/0! | H84: =H12/H10 -> #DIV/0! | I84: =I12/I10 -> #DIV/0! | J84: =J12/J10 -> #DIV/0! | K84: =K12/K10 -> #DIV/0! | ... Y84: =Y12/Y10 -> #DIV/0!
A85: アクティブ率 | B85: =C85 -> #DIV/0! | C85: =AVERAGE(D85:AH85) -> #DIV/0! | D85: =D26/D4 -> #DIV/0! | E85: =E26/E4 -> #DIV/0! | F85: =F26/F4 -> #DIV/0! | G85: =G26/G4 -> #DIV/0! | H85: =H26/H4 -> #DIV/0! | I85: =I26/I4 -> #DIV/0! | J85: =J26/J4 -> #DIV/0! | K85: =K26/K4 -> #DIV/0! | ... Y85: =Y26/Y4 -> #DIV/0!
A86: GGRマージン率 | B86: =C86 -> #DIV/0! | C86: =AVERAGE(D86:AH86) -> #DIV/0! | D86: =D45/D27 -> #DIV/0! | E86: =E45/E27 -> #DIV/0! | F86: =F45/F27 -> #DIV/0! | G86: =G45/G27 -> #DIV/0! | H86: =H45/H27 -> #DIV/0! | I86: =I45/I27 -> #DIV/0! | J86: =J45/J27 -> #DIV/0! | K86: =K45/K27 -> #DIV/0! | ... Y86: =Y45/Y27 -> #DIV/0!
A87: NGRマージン率 | B87: =C87 -> #DIV/0! | C87: =AVERAGE(D87:AH87) -> #DIV/0! | D87: =D64/D27 -> #DIV/0! | E87: =E64/E27 -> #DIV/0! | F87: =F64/F27 -> #DIV/0! | G87: =G64/G27 -> #DIV/0! | H87: =H64/H27 -> #DIV/0! | I87: =I64/I27 -> #DIV/0! | J87: =J64/J27 -> #DIV/0! | K87: =K64/K27 -> #DIV/0! | ... Y87: =Y64/Y27 -> #DIV/0!
A88: 平均入金回数/ユーザー | B88: =C88 -> #DIV/0! | C88: =AVERAGE(D88:AH88) -> #DIV/0! | D88: =D24/D25 -> #DIV/0! | E88: =E24/E25 -> #DIV/0! | F88: =F24/F25 -> #DIV/0! | G88: =G24/G25 -> #DIV/0! | H88: =H24/H25 -> #DIV/0! | I88: =I24/I25 -> #DIV/0! | J88: =J24/J25 -> #DIV/0! | K88: =K24/K25 -> #DIV/0! | ... Y88: =Y24/Y25 -> #DIV/0!
A90: プロモーション開催期間 / Promotion duration
A91: 目的 / Purpose
A93: Affiliate
A94: AFF経由登録者数 / Registration under AFF | B94: =SUM(D94:AH94) -> 0 | C94: =AVERAGE(D94:AH94) -> #DIV/0!
A95: AFF経由FTD数 / FTD under AFF | B95: =SUM(D95:AH95) -> 0 | C95: =AVERAGE(D95:AH95) -> #DIV/0!
A96: AFF数 | B96: =SUM(D96:AH96) -> 0 | C96: =AVERAGE(D96:AH96) -> #DIV/0!
A97: AFF経由入金額 / DP amt under AFF | B97: 8022259 | C97: =AVERAGE(D97:AH97) -> #DIV/0!
A98: AFF経由出金額 / WD amt under AFF | B98: 5490590 | C98: =AVERAGE(D98:AH98) -> #DIV/0!
A99: Ｔ／Ｏ
A100: 勝利金
A101: AFF経由RTP / RTP under AFF | B101: =SUM(D101:AH101) -> 0 | C101: =AVERAGE(D101:AH101) -> #DIV/0!
A102: AFF経由GGR / GGR under AFF | B102: 2531669 | C102: =AVERAGE(D102:AH102) -> #DIV/0!
A103: 差分GGR | B103: =SUM(D103:AH103) -> 0 | C103: =AVERAGE(D103:AH103) -> #DIV/0!
A104: AFF経由ボーナス額 / Bonus Granted Amt under AFF | B104: =SUM(D104:AH104) -> 0 | C104: =AVERAGE(D104:AH104) -> #DIV/0!
A105: AFFデモコスト(10％換算) | B105: =SUM(D105:AH105) -> 100000 | C105: =AVERAGE(D105:AH105) -> 100000 | Z105: 100000
...

Sheet Whitelist
A1: Whitelist TG ID
A2: 7996872876 | B2: Tom
A3: -1003439327565 | B3: Sloten group chat | D3: -1003439327565 | E3: Sloten group chat

Sheet KPI_PDF_SENT_LOG_DAILY_SLOTEN
A1: Timestamp | B1: Sheet | C1: D-2 | D1: D-1 | E1: File ID | F1: File Name | G1: Recipients (valid) | H1: Status | I1: Invalid IDs skipped | J1: Fail details | K1: DebugTrace
A2: 46041.158 | B2: 202601 | C2: 46053 | D2: 1R4lCeHlxj4UeBFGJD21NtTPqswxU56Ke | E2: 2026-01-31 Daily KPI Report.pdf | F2: 1 | G2: OK
A3: 46041.172 | B3: 202601 | C3: 46040 | D3: 46041 | E3: 1XCrsxtmQu5jddBr9OF8ngeJG0vkgaK4J | F3: 2026-01-19 Daily KPI Report.pdf | G3: 1 | H3: OK
A4: 46041.221 | B4: 46040 | C4: 1IpRiRZ56nupYl7OEEsxzPsR2bvZnrJTt | D4: 2026-01-18 Daily KPI Report.pdf | E4: 1 | F4: OK
A5: 46041.222 | B5: 46040 | C5: 1gUpG7TH2DPdMZlqq1rIDyORZMdn1s1gf | D5: 2026-01-18 Daily KPI Report.pdf | E5: 1 | F5: OK
A6: 46041.525 | B6: 202601 | C6: 46040 | D6: 46039 | E6: 142X_XeMD7P1tXFRVELlXTvGh-5oTAmhE | F6: 2026-01-18 Daily KPI Report.pdf | G6: 1 | H6: OK
A7: 46041.199 | B7: 202601 | C7: 46039 | D7: 46040 | E7: 1wPOmcg35j-k9IugWWD6O6QchU5z68TaY | F7: 2026-01-18 Daily KPI Report.pdf | G7: 1 | H7: OK
A8: 46041.22 | B8: 202601 | C8: 46052 | D8: 46053 | E8: 1EhzSvHG5Aqvt6RfgY_JTpVrtw0W8mtAH | F8: 2026-01-31 Daily KPI Report.pdf | G8: 1 | H8: OK
A9: 46041.228 | B9: 202601 | C9: 46039 | D9: 46040 | E9: 1-vNTt1qtA5z4KUXh3BU1lH-gfiBLuqro | F9: 2026-01-18 Daily KPI Report.pdf | G9: 1 | H9: OK | K9: Registered users: row=4 via=key-exact hit="登録人数" || Registered FTD+ users: row=18 via=key-exact hit="今月登録のftd以降ユーザー数" || Registered FTD+ ratio: row=19 via=key-exact hit="今月登録ftd以降ユーザー割合" || Registered active users: row=20 via=key-exact hit="今月登録のアクティブユーザー数" || Previous-month registered active users: row=21 via=key-exact hit="前月登録のアクティブユーザー数" || Total deposit amount: row=27 via=key-exact hit="総入金額 / total dp amt" || Active players (Unique): row=26 via=key-exact hit="アクティブプレイ人数（ユニーク）" || Average deposit amount (Unique user): row=29 via=key-exact hit="平均入金額(ユニークユーザー) / ave dp amt (unique user)" || Total withdrawal amount: row=32 via=key-exact hit="総出金額 / total wd amt" || Turnover (Real + Bonus): row=36 via=key-exact hit="t/o(ボーナス+リアルマネーの合計) / total bet (real+bonus)" || RTP: row=42 via=key-exact hit="rtp" || GGR: row=45 via=key-exact hit="ggr" || Deposit–Withdrawal difference: row=48 via=key-exact hit="入出金差分"
A10: 46041.24 | B10: 202601 | C10: 46039 | D10: 46040 | E10: 1Pje_amYyg5hMKcetASAP8A849nON9m0t | F10: 2026-01-18 Daily KPI Report.pdf | G10: 1 | H10: OK | K10: Registered users: row=4 via=key-exact hit="登録人数" || Registered FTD+ users: row=18 via=key-exact hit="今月登録のftd以降ユーザー数" || Registered FTD+ ratio: row=19 via=key-exact hit="今月登録ftd以降ユーザー割合" || Registered active users: row=20 via=key-exact hit="今月登録のアクティブユーザー数" || Previous-month registered active users: row=21 via=key-exact hit="前月登録のアクティブユーザー数" || Total deposit amount: row=27 via=key-exact hit="総入金額 / total dp amt" || Active players (Unique): row=26 via=key-exact hit="アクティブプレイ人数（ユニーク）" || Average deposit amount (Unique user): row=29 via=key-exact hit="平均入金額(ユニークユーザー) / ave dp amt (unique user)" || Total withdrawal amount: row=32 via=key-exact hit="総出金額 / total wd amt" || Turnover (Real + Bonus): row=36 via=key-exact hit="t/o(ボーナス+リアルマネーの合計) / total bet (real+bonus)" || RTP: row=42 via=key-exact hit="rtp" || GGR: row=45 via=key-exact hit="ggr" || Deposit–Withdrawal difference: row=48 via=key-exact hit="入出金差分"
A11: 46041.241 | B11: 202601 | C11: 46039 | D11: 46040 | E11: 1N4eDELY4S24tbxz5vbiPwG3-OobIi8vR | F11: 2026-01-18 Daily KPI Report.pdf | G11: 2 | H11: OK | K11: Registered users: row=4 via=key-exact hit="登録人数" || Registered FTD+ users: row=18 via=key-exact hit="今月登録のftd以降ユーザー数" || Registered FTD+ ratio: row=19 via=key-exact hit="今月登録ftd以降ユーザー割合" || Registered active users: row=20 via=key-exact hit="今月登録のアクティブユーザー数" || Previous-month registered active users: row=21 via=key-exact hit="前月登録のアクティブユーザー数" || Total deposit amount: row=27 via=key-exact hit="総入金額 / total dp amt" || Active players (Unique): row=26 via=key-exact hit="アクティブプレイ人数（ユニーク）" || Average deposit amount (Unique user): row=29 via=key-exact hit="平均入金額(ユニークユーザー) / ave dp amt (unique user)" || Total withdrawal amount: row=32 via=key-exact hit="総出金額 / total wd amt" || Turnover (Real + Bonus): row=36 via=key-exact hit="t/o(ボーナス+リアルマネーの合計) / total bet (real+bonus)" || RTP: row=42 via=key-exact hit="rtp" || GGR: row=45 via=key-exact hit="ggr" || Deposit–Withdrawal difference: row=48 via=key-exact hit="入出金差分"
A12: 46041.357 | B12: 202601 | C12: 46039 | D12: 46040 | E12: 1lIGNW0GUB_xxI0N0fEm50mmZLRshO2F9 | F12: 2026-01-18 Daily KPI Report.pdf | G12: 2 | H12: OK | K12: Registered users: row=4 via=key-exact hit="登録人数" || Registered FTD+ users: row=18 via=key-exact hit="今月登録のftd以降ユーザー数" || Registered FTD+ ratio: row=19 via=key-exact hit="今月登録ftd以降ユーザー割合" || Registered active users: row=20 via=key-exact hit="今月登録のアクティブユーザー数" || Previous-month registered active users: row=21 via=key-exact hit="前月登録のアクティブユーザー数" || Total deposit amount: row=27 via=key-exact hit="総入金額 / total dp amt" || Active players (Unique): row=26 via=key-exact hit="アクティブプレイ人数（ユニーク）" || Average deposit amount (Unique user): row=29 via=key-exact hit="平均入金額(ユニークユーザー) / ave dp amt (unique user)" || Total withdrawal amount: row=32 via=key-exact hit="総出金額 / total wd amt" || Turnover (Real + Bonus): row=36 via=key-exact hit="t/o(ボーナス+リアルマネーの合計) / total bet (real+bonus)" || RTP: row=42 via=key-exact hit="rtp" || GGR: row=45 via=key-exact hit="ggr" || Deposit–Withdrawal difference: row=48 via=key-exact hit="入出金差分"
A13: 46042.357 | B13: 202601 | C13: 46040 | D13: 46041 | E13: 1u10zaSTQG43ADjjzBJ7Af53G74B0aW0G | F13: 2026-01-19 Daily KPI Report.pdf | G13: 2 | H13: OK | K13: Registered users: row=4 via=key-exact hit="登録人数" || Registered FTD+ users: row=18 via=key-exact hit="今月登録のftd以降ユーザー数" || Registered FTD+ ratio: row=19 via=key-exact hit="今月登録ftd以降ユーザー割合" || Registered active users: row=20 via=key-exact hit="今月登録のアクティブユーザー数" || Previous-month registered active users: row=21 via=key-exact hit="前月登録のアクティブユーザー数" || Total deposit amount: row=27 via=key-exact hit="総入金額 / total dp amt" || Active players (Unique): row=26 via=key-exact hit="アクティブプレイ人数（ユニーク）" || Average deposit amount (Unique user): row=29 via=key-exact hit="平均入金額(ユニークユーザー) / ave dp amt (unique user)" || Total withdrawal amount: row=32 via=key-exact hit="総出金額 / total wd amt" || Turnover (Real + Bonus): row=36 via=key-exact hit="t/o(ボーナス+リアルマネーの合計) / total bet (real+bonus)" || RTP: row=42 via=key-exact hit="rtp" || GGR: row=45 via=key-exact hit="ggr" || Deposit–Withdrawal difference: row=48 via=key-exact hit="入出金差分"
A14: 46043.357 | B14: 202601 | C14: 46041 | D14: 46042 | E14: 1hVrVYMFb0ozeXgj5zNgROyoJDe1i6ODM | F14: 2026-01-20 Daily KPI Report.pdf | G14: 2 | H14: OK | K14: Registered users: row=4 via=key-exact hit="登録人数" || Registered FTD+ users: row=18 via=key-exact hit="今月登録のftd以降ユーザー数" || Registered FTD+ ratio: row=19 via=key-exact hit="今月登録ftd以降ユーザー割合" || Registered active users: row=20 via=key-exact hit="今月登録のアクティブユーザー数" || Previous-month registered active users: row=21 via=key-exact hit="前月登録のアクティブユーザー数" || Total deposit amount: row=27 via=key-exact hit="総入金額 / total dp amt" || Active players (Unique): row=26 via=key-exact hit="アクティブプレイ人数（ユニーク）" || Average deposit amount (Unique user): row=29 via=key-exact hit="平均入金額(ユニークユーザー) / ave dp amt (unique user)" || Total withdrawal amount: row=32 via=key-exact hit="総出金額 / total wd amt" || Turnover (Real + Bonus): row=36 via=key-exact hit="t/o(ボーナス+リアルマネーの合計) / total bet (real+bonus)" || RTP: row=42 via=key-exact hit="rtp" || GGR: row=45 via=key-exact hit="ggr" || Deposit–Withdrawal difference: row=48 via=key-exact hit="入出金差分"
A15: 46044.357 | B15: 202601 | C15: 46042 | D15: 46043 | E15: 1x4zyqgRegE2v6UQvAbGsST-xF9YqTEvu | F15: 2026-01-21 Daily KPI Report.pdf | G15: 2 | H15: OK | K15: Registered users: row=4 via=key-exact hit="登録人数" || Registered FTD+ users: row=18 via=key-exact hit="今月登録のftd以降ユーザー数" || Registered FTD+ ratio: row=19 via=key-exact hit="今月登録ftd以降ユーザー割合" || Registered active users: row=20 via=key-exact hit="今月登録のアクティブユーザー数" || Previous-month registered active users: row=21 via=key-exact hit="前月登録のアクティブユーザー数" || Total deposit amount: row=27 via=key-exact hit="総入金額 / total dp amt" || Active players (Unique): row=26 via=key-exact hit="アクティブプレイ人数（ユニーク）" || Average deposit amount (Unique user): row=29 via=key-exact hit="平均入金額(ユニークユーザー) / ave dp amt (unique user)" || Total withdrawal amount: row=32 via=key-exact hit="総出金額 / total wd amt" || Turnover (Real + Bonus): row=36 via=key-exact hit="t/o(ボーナス+リアルマネーの合計) / total bet (real+bonus)" || RTP: row=42 via=key-exact hit="rtp" || GGR: row=45 via=key-exact hit="ggr" || Deposit–Withdrawal difference: row=48 via=key-exact hit="入出金差分"
A16: 46045.357 | B16: 202601 | C16: 46043 | D16: 46044 | E16: 1c1T3SCE53nyVtZ8xQc9xVtgfNFX-35IX | F16: 2026-01-22 Daily KPI Report.pdf | G16: 2 | H16: OK | K16: Registered users: row=4 via=key-exact hit="登録人数" || Registered FTD+ users: row=18 via=key-exact hit="今月登録のftd以降ユーザー数" || Registered FTD+ ratio: row=19 via=key-exact hit="今月登録ftd以降ユーザー割合" || Registered active users: row=20 via=key-exact hit="今月登録のアクティブユーザー数" || Previous-month registered active users: row=21 via=key-exact hit="前月登録のアクティブユーザー数" || Total deposit amount: row=27 via=key-exact hit="総入金額 / total dp amt" || Active players (Unique): row=26 via=key-exact hit="アクティブプレイ人数（ユニーク）" || Average deposit amount (Unique user): row=29 via=key-exact hit="平均入金額(ユニークユーザー) / ave dp amt (unique user)" || Total withdrawal amount: row=32 via=key-exact hit="総出金額 / total wd amt" || Turnover (Real + Bonus): row=36 via=key-exact hit="t/o(ボーナス+リアルマネーの合計) / total bet (real+bonus)" || RTP: row=42 via=key-exact hit="rtp" || GGR: row=45 via=key-exact hit="ggr" || Deposit–Withdrawal difference: row=48 via=key-exact hit="入出金差分"
A17: 46046.357 | B17: 202601 | C17: 46044 | D17: 46045 | E17: 1goxBeR12v1I5iZYZg78s_wY0DnmJ5cyV | F17: 2026-01-23 Daily KPI Report.pdf | G17: 2 | H17: OK | K17: Registered users: row=4 via=key-exact hit="登録人数" || Registered FTD+ users: row=18 via=key-exact hit="今月登録のftd以降ユーザー数" || Registered FTD+ ratio: row=19 via=key-exact hit="今月登録ftd以降ユーザー割合" || Registered active users: row=20 via=key-exact hit="今月登録のアクティブユーザー数" || Previous-month registered active users: row=21 via=key-exact hit="前月登録のアクティブユーザー数" || Total deposit amount: row=27 via=key-exact hit="総入金額 / total dp amt" || Active players (Unique): row=26 via=key-exact hit="アクティブプレイ人数（ユニーク）" || Average deposit amount (Unique user): row=29 via=key-exact hit="平均入金額(ユニークユーザー) / ave dp amt (unique user)" || Total withdrawal amount: row=32 via=key-exact hit="総出金額 / total wd amt" || Turnover (Real + Bonus): row=36 via=key-exact hit="t/o(ボーナス+リアルマネーの合計) / total bet (real+bonus)" || RTP: row=42 via=key-exact hit="rtp" || GGR: row=45 via=key-exact hit="ggr" || Deposit–Withdrawal difference: row=48 via=key-exact hit="入出金差分"
A18: 46047.357 | B18: 202601 | C18: 46045 | D18: 46046 | E18: 1DzpejcOery9ssV4rfuKFWg8__a_1oJHD | F18: 2026-01-24 Daily KPI Report.pdf | G18: 2 | H18: OK | K18: Registered users: row=4 via=key-exact hit="登録人数" || Registered FTD+ users: row=18 via=key-exact hit="今月登録のftd以降ユーザー数" || Registered FTD+ ratio: row=19 via=key-exact hit="今月登録ftd以降ユーザー割合" || Registered active users: row=20 via=key-exact hit="今月登録のアクティブユーザー数" || Previous-month registered active users: row=21 via=key-exact hit="前月登録のアクティブユーザー数" || Total deposit amount: row=27 via=key-exact hit="総入金額 / total dp amt" || Active players (Unique): row=26 via=key-exact hit="アクティブプレイ人数（ユニーク）" || Average deposit amount (Unique user): row=29 via=key-exact hit="平均入金額(ユニークユーザー) / ave dp amt (unique user)" || Total withdrawal amount: row=32 via=key-exact hit="総出金額 / total wd amt" || Turnover (Real + Bonus): row=36 via=key-exact hit="t/o(ボーナス+リアルマネーの合計) / total bet (real+bonus)" || RTP: row=42 via=key-exact hit="rtp" || GGR: row=45 via=key-exact hit="ggr" || Deposit–Withdrawal difference: row=48 via=key-exact hit="入出金差分"
A19: 46048.357 | B19: 202601 | C19: 46046 | D19: 46047 | E19: 1kabosH9lUonf5gNibVrXBbw__Xa6hTN6 | F19: 2026-01-25 Daily KPI Report.pdf | G19: 2 | H19: OK | K19: Registered users: row=4 via=key-exact hit="登録人数" || Registered FTD+ users: row=18 via=key-exact hit="今月登録のftd以降ユーザー数" || Registered FTD+ ratio: row=19 via=key-exact hit="今月登録ftd以降ユーザー割合" || Registered active users: row=20 via=key-exact hit="今月登録のアクティブユーザー数" || Previous-month registered active users: row=21 via=key-exact hit="前月登録のアクティブユーザー数" || Total deposit amount: row=27 via=key-exact hit="総入金額 / total dp amt" || Active players (Unique): row=26 via=key-exact hit="アクティブプレイ人数（ユニーク）" || Average deposit amount (Unique user): row=29 via=key-exact hit="平均入金額(ユニークユーザー) / ave dp amt (unique user)" || Total withdrawal amount: row=32 via=key-exact hit="総出金額 / total wd amt" || Turnover (Real + Bonus): row=36 via=key-exact hit="t/o(ボーナス+リアルマネーの合計) / total bet (real+bonus)" || RTP: row=42 via=key-exact hit="rtp" || GGR: row=45 via=key-exact hit="ggr" || Deposit–Withdrawal difference: row=48 via=key-exact hit="入出金差分"
A20: 46049.357 | B20: 202601 | C20: 46047 | D20: 46048 | E20: 18TOIidWQX1_xW-bUgB7hPKhzzEpAzH8P | F20: 2026-01-26 Daily KPI Report.pdf | G20: 2 | H20: OK | K20: Registered users: row=4 via=key-exact hit="登録人数" || Registered FTD+ users: row=18 via=key-exact hit="今月登録のftd以降ユーザー数" || Registered FTD+ ratio: row=19 via=key-exact hit="今月登録ftd以降ユーザー割合" || Registered active users: row=20 via=key-exact hit="今月登録のアクティブユーザー数" || Previous-month registered active users: row=21 via=key-exact hit="前月登録のアクティブユーザー数" || Total deposit amount: row=27 via=key-exact hit="総入金額 / total dp amt" || Active players (Unique): row=26 via=key-exact hit="アクティブプレイ人数（ユニーク）" || Average deposit amount (Unique user): row=29 via=key-exact hit="平均入金額(ユニークユーザー) / ave dp amt (unique user)" || Total withdrawal amount: row=32 via=key-exact hit="総出金額 / total wd amt" || Turnover (Real + Bonus): row=36 via=key-exact hit="t/o(ボーナス+リアルマネーの合計) / total bet (real+bonus)" || RTP: row=42 via=key-exact hit="rtp" || GGR: row=45 via=key-exact hit="ggr" || Deposit–Withdrawal difference: row=48 via=key-exact hit="入出金差分"
... A22: 46051.357 | B22: 202601 | C22: 46049 | D22: 46050 | E22: 1K_HlUmHYna2NPQXUoj3JL4Hy46gn0Jza | F22: 2026-01-28 Daily KPI Report.pdf | G22: 2 | H22: OK | K22: Registered users: row=4 via=key-exact hit="登録人数" || Registered FTD+ users: row=18 via=key-exact hit="今月登録のftd以降ユーザー数" || Registered FTD+ ratio: row=19 via=key-exact hit="今月登録ftd以降ユーザー割合" || Registered active users: row=20 via=key-exact hit="今月登録のアクティブユーザー数" || Previous-month registered active users: row=21 via=key-exact hit="前月登録のアクティブユーザー数" || Total deposit amount: row=27 via=key-exact hit="総入金額 / total dp amt" || Active players (Unique): row=26 via=key-exact hit="アクティブプレイ人数（ユニーク）" || Average deposit amount (Unique user): row=29 via=key-exact hit="平均入金額(ユニークユーザー) / ave dp amt (unique user)" || Total withdrawal amount: row=32 via=key-exact hit="総出金額 / total wd amt" || Turnover (Real + Bonus): row=36 via=key-exact hit="t/o(ボーナス+リアルマネーの合計) / total bet (real+bonus)" || RTP: row=42 via=key-exact hit="rtp" || GGR: row=45 via=key-exact hit="ggr" || Deposit–Withdrawal difference: row=48 via=key-exact hit="入出金差分"

Sheet KPI_PDF_SENT_LOG_MONTHLY_SLOTEN
A1: Timestamp | B1: Sheet | C1: TOTAL Label | D1: M-1 | E1: M | F1: File ID | G1: File Name | H1: Recipients (valid) | I1: Status | J1: Invalid IDs skipped | K1: Fail details | L1: DebugTrace
A2: 46041.204 | B2: 全期間集計_TOTAL | C2: TOTAL | D2: 202512 | E2: 202601 | F2: 1Xg3wpPtq0Hrj5iyt5jEdnsDVZBXN2G22 | G2: 202601 Monthly KPI Report.pdf | H2: 1 | I2: OK
A3: 46041.21 | B3: 全期間集計_TOTAL | C3: TOTAL | D3: 202512 | E3: 202601 | F3: 1LVa-xXA4tqJ4WNRSCbGVjMxvm5yZG7P- | G3: 202601 Monthly KPI Report.pdf | H3: 1 | I3: OK
A4: 46041.213 | B4: 全期間集計_TOTAL | C4: TOTAL | D4: 202512 | E4: 202601 | F4: 1DE7nOtlqgm-ZjPm7YA4WAfbSvdSbFqRI | G4: 202601 Monthly KPI Report.pdf | H4: 1 | I4: OK
A5: 46041.215 | B5: 全期間集計_TOTAL | C5: TOTAL | D5: 202512 | E5: 202601 | F5: 1Ucu_Ko_-faFpqv0ArVBi3p6zsgq1C6xr | G5: 202601 Monthly KPI Report.pdf | H5: 2 | I5: OK
A6: 46041.226 | B6: 全期間集計_TOTAL | C6: TOTAL | D6: 202512 | E6: 202601 | F6: 18UShrZgUAETVcnt02GXBrgj1l9c5Nndg | G6: 202601 Monthly KPI Report.pdf | H6: 1 | I6: OK
A7: 46041.23 | B7: 全期間集計_TOTAL | C7: TOTAL | D7: 202512 | E7: 202601 | F7: 1OS4iNFfkc0iBzyxoYN8dU6ewcQQUMFdX | G7: 202601 Monthly KPI Report.pdf | H7: 1 | I7: OK | L7: Registered users: row=4 via=key-exact hit="登録人数" || Registered FTD+ users: row=18 via=key-exact hit="今月登録のftd以降ユーザー数" || Registered FTD+ ratio: row=19 via=key-exact hit="今月登録ftd以降ユーザー割合" || Registered active users: row=20 via=key-exact hit="今月登録のアクティブユーザー数" || Previous-month registered active users: row=21 via=key-exact hit="前月登録のアクティブユーザー数" || Total deposit amount: row=27 via=key-exact hit="総入金額 / total dp amt" || Active players (Unique): row=26 via=alias-exact hit="アクティブプレイ人数" || Average deposit amount (Unique user): row=29 via=key-exact hit="平均入金額(ユニークユーザー) / ave dp amt (unique user)" || Total withdrawal amount: row=30 via=key-exact hit="総出金額 / total wd amt" || Turnover (Real + Bonus): row=34 via=key-exact hit="t/o(ボーナス+リアルマネーの合計) / total bet (real+bonus)" || RTP: row=40 via=key-exact hit="rtp" || GGR: row=43 via=key-exact hit="ggr" || Deposit–Withdrawal difference: row=186 via=partial hit="出金"
A8: 46041.235 | B8: 全期間集計_TOTAL | C8: TOTAL | D8: 202512 | E8: 202601 | F8: 1lfMXI16QYKspaLvAamyQf58fh20er33l | G8: 202601 Monthly KPI Report.pdf | H8: 1 | I8: OK | L8: DP(row=27) via=exact hit="総入金額 / total dp amt" || WD(row=30) via=exact hit="総出金額 / total wd amt" || Registered users: row=4 via=key-exact hit="登録人数" || Registered FTD+ users: row=18 via=key-exact hit="今月登録のftd以降ユーザー数" || Registered FTD+ ratio: row=19 via=key-exact hit="今月登録ftd以降ユーザー割合" || Registered active users: row=20 via=key-exact hit="今月登録のアクティブユーザー数" || Previous-month registered active users: row=21 via=key-exact hit="前月登録のアクティブユーザー数" || Total deposit amount: row=27 via=key-exact hit="総入金額 / total dp amt" || Active players (Unique): row=26 via=alias-exact hit="アクティブプレイ人数" || Average deposit amount (Unique user): row=29 via=key-exact hit="平均入金額(ユニークユーザー) / ave dp amt (unique user)" || Total withdrawal amount: row=30 via=key-exact hit="総出金額 / total wd amt" || Turnover (Real + Bonus): row=34 via=key-exact hit="t/o(ボーナス+リアルマネーの合計) / total bet (real+bonus)" || RTP: row=40 via=key-exact hit="rtp" || GGR: row=43 via=key-exact hit="ggr" || CALC DP-WD: total=34115246, m1=18292078, m=15765485
A9: 46041.24 | B9: 全期間集計_TOTAL | C9: TOTAL | D9: 202512 | E9: 202601 | F9: 1QOsbl-h_B-xkTfozcai7OKewh3IOvIa7 | G9: 202601 Monthly KPI Report.pdf | H9: 1 | I9: OK | L9: DP(row=27) via=exact hit="総入金額 / total dp amt" || WD(row=30) via=exact hit="総出金額 / total wd amt" || Registered users: row=4 via=key-exact hit="登録人数" || Registered FTD+ users: row=18 via=key-exact hit="今月登録のftd以降ユーザー数" || Registered FTD+ ratio: row=19 via=key-exact hit="今月登録ftd以降ユーザー割合" || Registered active users: row=20 via=key-exact hit="今月登録のアクティブユーザー数" || Previous-month registered active users: row=21 via=key-exact hit="前月登録のアクティブユーザー数" || Total deposit amount: row=27 via=key-exact hit="総入金額 / total dp amt" || Active players (Unique): row=26 via=alias-exact hit="アクティブプレイ人数" || Average deposit amount (Unique user): row=29 via=key-exact hit="平均入金額(ユニークユーザー) / ave dp amt (unique user)" || Total withdrawal amount: row=30 via=key-exact hit="総出金額 / total wd amt" || Turnover (Real + Bonus): row=34 via=key-exact hit="t/o(ボーナス+リアルマネーの合計) / total bet (real+bonus)" || RTP: row=40 via=key-exact hit="rtp" || GGR: row=43 via=key-exact hit="ggr" || CALC DP-WD: total=34115246, m1=18292078, m=15765485
A10: 46041.241 | B10: 全期間集計_TOTAL | C10: TOTAL | D10: 202512 | E10: 202601 | F10: 1Hi4wQlQOGUI1in2FIwGqQ8kz6daepKrn | G10: 202601 Monthly KPI Report.pdf | H10: 2 | I10: OK | L10: DP(row=27) via=exact hit="総入金額 / total dp amt" || WD(row=30) via=exact hit="総出金額 / total wd amt" || Registered users: row=4 via=key-exact hit="登録人数" || Registered FTD+ users: row=18 via=key-exact hit="今月登録のftd以降ユーザー数" || Registered FTD+ ratio: row=19 via=key-exact hit="今月登録ftd以降ユーザー割合" || Registered active users: row=20 via=key-exact hit="今月登録のアクティブユーザー数" || Previous-month registered active users: row=21 via=key-exact hit="前月登録のアクティブユーザー数" || Total deposit amount: row=27 via=key-exact hit="総入金額 / total dp amt" || Active players (Unique): row=26 via=alias-exact hit="アクティブプレイ人数" || Average deposit amount (Unique user): row=29 via=key-exact hit="平均入金額(ユニークユーザー) / ave dp amt (unique user)" || Total withdrawal amount: row=30 via=key-exact hit="総出金額 / total wd amt" || Turnover (Real + Bonus): row=34 via=key-exact hit="t/o(ボーナス+リアルマネーの合計) / total bet (real+bonus)" || RTP: row=40 via=key-exact hit="rtp" || GGR: row=43 via=key-exact hit="ggr" || CALC DP-WD: total=34115246, m1=18292078, m=15765485
A11: 46041.367 | B11: 全期間集計_TOTAL | C11: TOTAL | D11: 202512 | E11: 202601 | F11: 1A9NgtE7Xnsa-xcZcL-dCkNSMEGdIMMMG | G11: 202601 Monthly KPI Report.pdf | H11: 2 | I11: OK | L11: DP(row=27) via=exact hit="総入金額 / total dp amt" || WD(row=30) via=exact hit="総出金額 / total wd amt" || Registered users: row=4 via=key-exact hit="登録人数" || Registered FTD+ users: row=18 via=key-exact hit="今月登録のftd以降ユーザー数" || Registered FTD+ ratio: row=19 via=key-exact hit="今月登録ftd以降ユーザー割合" || Registered active users: row=20 via=key-exact hit="今月登録のアクティブユーザー数" || Previous-month registered active users: row=21 via=key-exact hit="前月登録のアクティブユーザー数" || Total deposit amount: row=27 via=key-exact hit="総入金額 / total dp amt" || Active players (Unique): row=26 via=alias-exact hit="アクティブプレイ人数" || Average deposit amount (Unique user): row=29 via=key-exact hit="平均入金額(ユニークユーザー) / ave dp amt (unique user)" || Total withdrawal amount: row=30 via=key-exact hit="総出金額 / total wd amt" || Turnover (Real + Bonus): row=34 via=key-exact hit="t/o(ボーナス+リアルマネーの合計) / total bet (real+bonus)" || RTP: row=40 via=key-exact hit="rtp" || GGR: row=43 via=key-exact hit="ggr" || CALC DP-WD: total=34115246, m1=18292078, m=15765485
