Workbook

Sheet プロバイダー
B1: プロバイダー
B2: KA Gaming 5%
B3: Evolution 10%
B4: PlayNGo 7%
B5: Nolimit City 6%
B6: Hacksaw 7%
B7: Relax Gaming 5%
B8: AvatarUX 7%
B9: QuickSpin 6%
B10: Red Tiger 6%
B11: OctoPlay 6.5%
B14: SC（5%）
... B27: JILI

Sheet ログイン情報
B1: サイト名 | C1: URL | D1: ID | E1: PASS | F1: 備考 | I1: 稼働状況 | J1: 出金口座
B2: EC
B3: Moneytree | C3: https://app.getmoneytree.com/app/trends/net-worth | D3: amusevip@gmail.com | E3: Amuse1234
B4: LDCloud | C4: https://www.ldcloud.net/web/mobile/login | D4: amusevip2@gmail.com | E4: Amuse1234 | F4: メールログイン | I4: 稼働中
B5: ペライチ(Contens Store) | C5: https://peraichiapp.com/users/login/ | D5: asamimizuno850@gmail.com | E5: Amuse1234 | F5: 清水 | G5: https://hljxe.hp.peraichi.com/ | I5: 停止中
B6: ペライチ(憲子の部屋) | C6: https://peraichiapp.com/users/login/ | D6: xianzineihai@gmail.com | E6: Amuse1234 | F6: 内海 | G6: https://h1x0y.hp.peraichi.com/ | I6: 停止中
B7: ペライチ(アフリエイトの虎) | C7: https://peraichiapp.com/users/login/ | D7: satoutsuyoshi1971@gmail.com | E7: Amuse1234 | F7: 佐藤 | G7: https://bh7nd.hp.peraichi.com/ | I7: 出金制限中
B8: ペライチ(OGAWA DESIGN) | C8: https://peraichiapp.com/users/login/ | D8: ogawakanako09@gmail.com | E8: Amuse1234 | F8: 小川 | G8: https://f4eqv.hp.peraichi.com/ | I8: 出金制限中
B9: ペライチ(テンプレの龍) | C9: https://peraichiapp.com/users/login/ | D9: masaakihaizaki306@gmail.com | E9: Amuse1234 | F9: 拝崎 | I9: 停止中
B10: ペライチ（ひとみのイラスト） | C10: https://peraichiapp.com/users/login/ | D10: hitomiaraki55@gmail.com | E10: Amuse1234 | F10: 荒木ひとみ | G10: https://7phz6.hp.peraichi.com | I10: 出金制限中
B11: Stores（Contens Corner） | C11: https://dashboard.stores.jp/report/?tab=remittance | D11: asamimizuno850@gmail.com | E11: @Amuse12341234 | F11: 清水 | G11: https://contentcorner.stores.jp/ | I11: 稼働中 | J11: 楽天エスティカ
B12: Stores(アフリエイトの虎) | C12: https://dashboard.stores.jp/report/?tab=remittance | D12: satoutsuyoshi1971@gmail.com | E12: @Amuse123456 | F12: 佐藤 | G12: https://aflitiger.stores.jp | H12: 規約違反
B13: Stores(憲子の部屋) | C13: https://dashboard.stores.jp/report/?tab=remittance | D13: xianzineihai@gmail.com | E13: @Amuse123456 | F13: 内海 | G13: https://norikonoheya.stores.jp | I13: 稼働中 | J13: SBI ストフラ
B14: メンバーペイ(憲子の部屋) | C14: https://app.memberpay.jp/dashboard | D14: xianzineihai@gmail.com | E14: Amuse1234 | F14: 内海 | G14: https://norikonoheya.memberpay.jp/ | H14: 規約違反
B15: Stores (OGAWA DESIGN) | C15: https://dashboard.stores.jp/report/?tab=remittance | D15: ogawakanako09@gmail.com | E15: @Amuse123456 | F15: 小川 | G15: https://ogawadesign.stores.jp | I15: 稼働中 | J15: 楽天メイワ
B16: Stores(ひとみのイラスト) | C16: https://dashboard.stores.app/ | D16: hitomiaraki55@gmail.com | E16: @Amuse123456 | F16: 荒木ひとみ | G16: https://hitomidesign.stores.jp | I16: 稼働中
B18: 捨てアドURL | C18: https://m.kuku.lu/ | D18: 859063391204 | E18: 6ad#VBXi0r&M
B24: テレグラム | C24: グループＩＤ | D24: -1002400440893
B25: プロモーション | C25: 6396 | D25: @Roomcheckkkbot プロモーション
B26: メンテナンス🖥 | C26: 2 | D26: @Roomcheckkkbot メンテ
B27: 審査・アカウント作成 | C27: 7 | D27: @Roomcheckkkbot 審査
B28: ボーナス付与 | C28: 4 | D28: @Roomcheckkkbot ボーナス
B29: AMUSE×CS | C29: 54 | D29: @Roomcheckkkbot CS
B30: PayPay | C30: 34327 | D30: @Roomcheckkkbot Paypay
B31: 入金-仮想通貨 | C31: 28 | D31: @Roomcheckkkbot 仮想通貨
B32: 入金 | C32: 21 | D32: @Roomcheckkkbot 銀行入金
B33: 出金 | C33: 23 | D33: @Roomcheckkkbot 銀行出金
B34: 返済 | C34: 33334 | D34: @Roomcheckkkbot 返済自動アラート
B35: EC入金 | C35: 26480 | D35: @Roomcheckkkbot EC入金
B36: A-team | C36: 31072
B37: 返済計画 | C37: 48

Sheet 営業データ
B1: リスト別データ
B3: =IFERROR(__xludf.DUMMYFUNCTION("IMPORTRANGE(""11QmPanSRxykbUTB_EqX7W510tAZnhZpBpW7QiSnxobM"", ""リスト別データ!B3:R8"") "),"TOTAL") -> TOTAL
C4: =IFERROR(__xludf.DUMMYFUNCTION("""COMPUTED_VALUE"""),"リスト件数") -> リスト件数 | D4: =IFERROR(__xludf.DUMMYFUNCTION("""COMPUTED_VALUE"""),"アカウント作成数") -> アカウント作成数 | E4: =IFERROR(__xludf.DUMMYFUNCTION("""COMPUTED_VALUE"""),"LINE登録数") -> LINE登録数 | F4: =IFERROR(__xludf.DUMMYFUNCTION("""COMPUTED_VALUE"""),"打電数") -> 打電数 | G4: =IFERROR(__xludf.DUMMYFUNCTION("""COMPUTED_VALUE"""),"着電数") -> 着電数 | H4: =IFERROR(__xludf.DUMMYFUNCTION("""COMPUTED_VALUE"""),"新規信用枠") -> 新規信用枠 | I4: =IFERROR(__xludf.DUMMYFUNCTION("""COMPUTED_VALUE"""),"着電率") -> 着電率 | J4: =IFERROR(__xludf.DUMMYFUNCTION("""COMPUTED_VALUE"""),"LINE登録率") -> LINE登録率 | K4: =IFERROR(__xludf.DUMMYFUNCTION("""COMPUTED_VALUE"""),"アカウント作成率") -> アカウント作成率 | L4: =IFERROR(__xludf.DUMMYFUNCTION("""COMPUTED_VALUE"""),"客単価") -> 客単価
B5: =IFERROR(__xludf.DUMMYFUNCTION("""COMPUTED_VALUE"""),"リストC") -> リストC | C5: =IFERROR(__xludf.DUMMYFUNCTION("""COMPUTED_VALUE"""),50000.0) -> 50000 | D5: =IFERROR(__xludf.DUMMYFUNCTION("""COMPUTED_VALUE"""),87.5) -> 87.5 | E5: =IFERROR(__xludf.DUMMYFUNCTION("""COMPUTED_VALUE"""),123.0) -> 123 | F5: =IFERROR(__xludf.DUMMYFUNCTION("""COMPUTED_VALUE"""),105235.0) -> 105235 | G5: =IFERROR(__xludf.DUMMYFUNCTION("""COMPUTED_VALUE"""),6786.0) -> 6786 | H5: =IFERROR(__xludf.DUMMYFUNCTION("""COMPUTED_VALUE"""),2660185.0) -> 2660185 | I5: =IFERROR(__xludf.DUMMYFUNCTION("""COMPUTED_VALUE"""),0.13572) -> 0.13572 | J5: =IFERROR(__xludf.DUMMYFUNCTION("""COMPUTED_VALUE"""),0.00246) -> 0.00246 | K5: =IFERROR(__xludf.DUMMYFUNCTION("""COMPUTED_VALUE"""),0.00175) -> 0.00175 | L5: =IFERROR(__xludf.DUMMYFUNCTION("""COMPUTED_VALUE"""),30402.114285714284) -> 30402.114
B6: =IFERROR(__xludf.DUMMYFUNCTION("""COMPUTED_VALUE"""),"リストBE") -> リストBE | C6: =IFERROR(__xludf.DUMMYFUNCTION("""COMPUTED_VALUE"""),5000.0) -> 5000 | D6: =IFERROR(__xludf.DUMMYFUNCTION("""COMPUTED_VALUE"""),12.0) -> 12 | E6: =IFERROR(__xludf.DUMMYFUNCTION("""COMPUTED_VALUE"""),20.0) -> 20 | F6: =IFERROR(__xludf.DUMMYFUNCTION("""COMPUTED_VALUE"""),8284.0) -> 8284 | G6: =IFERROR(__xludf.DUMMYFUNCTION("""COMPUTED_VALUE"""),874.0) -> 874 | H6: =IFERROR(__xludf.DUMMYFUNCTION("""COMPUTED_VALUE"""),665000.0) -> 665000 | I6: =IFERROR(__xludf.DUMMYFUNCTION("""COMPUTED_VALUE"""),0.1748) -> 0.1748 | J6: =IFERROR(__xludf.DUMMYFUNCTION("""COMPUTED_VALUE"""),0.004) -> 0.004 | K6: =IFERROR(__xludf.DUMMYFUNCTION("""COMPUTED_VALUE"""),0.0024) -> 0.0024 | L6: =IFERROR(__xludf.DUMMYFUNCTION("""COMPUTED_VALUE"""),55416.666666666664) -> 55416.667
B7: =IFERROR(__xludf.DUMMYFUNCTION("""COMPUTED_VALUE"""),"リストS") -> リストS | C7: =IFERROR(__xludf.DUMMYFUNCTION("""COMPUTED_VALUE"""),78000.0) -> 78000 | D7: =IFERROR(__xludf.DUMMYFUNCTION("""COMPUTED_VALUE"""),641.5) -> 641.5 | E7: =IFERROR(__xludf.DUMMYFUNCTION("""COMPUTED_VALUE"""),1007.0) -> 1007 | F7: =IFERROR(__xludf.DUMMYFUNCTION("""COMPUTED_VALUE"""),385557.0) -> 385557 | G7: =IFERROR(__xludf.DUMMYFUNCTION("""COMPUTED_VALUE"""),22312.0) -> 22312 | H7: =IFERROR(__xludf.DUMMYFUNCTION("""COMPUTED_VALUE"""),4.0818115E7) -> 40818115 | I7: =IFERROR(__xludf.DUMMYFUNCTION("""COMPUTED_VALUE"""),0.28605128205128205) -> 0.28605128 | J7: =IFERROR(__xludf.DUMMYFUNCTION("""COMPUTED_VALUE"""),0.01291025641025641) -> 0.012910256 | K7: =IFERROR(__xludf.DUMMYFUNCTION("""COMPUTED_VALUE"""),0.008224358974358975) -> 0.008224359 | L7: =IFERROR(__xludf.DUMMYFUNCTION("""COMPUTED_VALUE"""),63629.17381137958) -> 63629.174
B8: =IFERROR(__xludf.DUMMYFUNCTION("""COMPUTED_VALUE"""),"リストE") -> リストE | C8: =IFERROR(__xludf.DUMMYFUNCTION("""COMPUTED_VALUE"""),80000.0) -> 80000 | D8: =IFERROR(__xludf.DUMMYFUNCTION("""COMPUTED_VALUE"""),1002.5) -> 1002.5 | E8: =IFERROR(__xludf.DUMMYFUNCTION("""COMPUTED_VALUE"""),1405.0) -> 1405 | F8: =IFERROR(__xludf.DUMMYFUNCTION("""COMPUTED_VALUE"""),384273.0) -> 384273 | G8: =IFERROR(__xludf.DUMMYFUNCTION("""COMPUTED_VALUE"""),28534.0) -> 28534 | H8: =IFERROR(__xludf.DUMMYFUNCTION("""COMPUTED_VALUE"""),8.3670082E7) -> 83670082 | I8: =IFERROR(__xludf.DUMMYFUNCTION("""COMPUTED_VALUE"""),0.356675) -> 0.356675 | J8: =IFERROR(__xludf.DUMMYFUNCTION("""COMPUTED_VALUE"""),0.0175625) -> 0.0175625 | K8: =IFERROR(__xludf.DUMMYFUNCTION("""COMPUTED_VALUE"""),0.01253125) -> 0.01253125 | L8: =IFERROR(__xludf.DUMMYFUNCTION("""COMPUTED_VALUE"""),83461.42842892768) -> 83461.428
B10: =IFERROR(__xludf.DUMMYFUNCTION("IMPORTRANGE(""11QmPanSRxykbUTB_EqX7W510tAZnhZpBpW7QiSnxobM"", ""リスト別データ!B11:BF29"") "),"11月") -> 11月 | F10: =IFERROR(__xludf.DUMMYFUNCTION("""COMPUTED_VALUE"""),"10月") -> 10月 | J10: =IFERROR(__xludf.DUMMYFUNCTION("""COMPUTED_VALUE"""),"9月") -> 9月 | N10: =IFERROR(__xludf.DUMMYFUNCTION("""COMPUTED_VALUE"""),"8月") -> 8月 | R10: =IFERROR(__xludf.DUMMYFUNCTION("""COMPUTED_VALUE"""),"7月") -> 7月 | V10: =IFERROR(__xludf.DUMMYFUNCTION("""COMPUTED_VALUE"""),"6月") -> 6月 | Z10: =IFERROR(__xludf.DUMMYFUNCTION("""COMPUTED_VALUE"""),"5月") -> 5月 | AD10: =IFERROR(__xludf.DUMMYFUNCTION("""COMPUTED_VALUE"""),"4月") -> 4月 | AH10: =IFERROR(__xludf.DUMMYFUNCTION("""COMPUTED_VALUE"""),"3月") -> 3月 | AL10: =IFERROR(__xludf.DUMMYFUNCTION("""COMPUTED_VALUE"""),"2月") -> 2月 | AP10: =IFERROR(__xludf.DUMMYFUNCTION("""COMPUTED_VALUE"""),"1月") -> 1月 | AT10: =IFERROR(__xludf.DUMMYFUNCTION("""COMPUTED_VALUE"""),"12月") -> 12月 | AX10: =IFERROR(__xludf.DUMMYFUNCTION("""COMPUTED_VALUE"""),"11月") -> 11月 | BB10: =IFERROR(__xludf.DUMMYFUNCTION("""COMPUTED_VALUE"""),"10月") -> 10月 | BF10: =IFERROR(__xludf.DUMMYFUNCTION("""COMPUTED_VALUE"""),"9月") -> 9月
C11: =IFERROR(__xludf.DUMMYFUNCTION("""COMPUTED_VALUE"""),"リスト件数") -> リスト件数 | D11: =IFERROR(__xludf.DUMMYFUNCTION("""COMPUTED_VALUE"""),"アカウント作成数") -> アカウント作成数 | E11: =IFERROR(__xludf.DUMMYFUNCTION("""COMPUTED_VALUE"""),"LINE登録数") -> LINE登録数 | G11: =IFERROR(__xludf.DUMMYFUNCTION("""COMPUTED_VALUE"""),"リスト件数") -> リスト件数 | H11: =IFERROR(__xludf.DUMMYFUNCTION("""COMPUTED_VALUE"""),"アカウント作成数") -> アカウント作成数 | I11: =IFERROR(__xludf.DUMMYFUNCTION("""COMPUTED_VALUE"""),"LINE登録数") -> LINE登録数 | K11: =IFERROR(__xludf.DUMMYFUNCTION("""COMPUTED_VALUE"""),"リスト件数") -> リスト件数 | L11: =IFERROR(__xludf.DUMMYFUNCTION("""COMPUTED_VALUE"""),"アカウント作成数") -> アカウント作成数 | M11: =IFERROR(__xludf.DUMMYFUNCTION("""COMPUTED_VALUE"""),"LINE登録数") -> LINE登録数 | O11: =IFERROR(__xludf.DUMMYFUNCTION("""COMPUTED_VALUE"""),"リスト件数") -> リスト件数 | P11: =IFERROR(__xludf.DUMMYFUNCTION("""COMPUTED_VALUE"""),"アカウント作成数") -> アカウント作成数 | Q11: =IFERROR(__xludf.DUMMYFUNCTION("""COMPUTED_VALUE"""),"LINE登録数") -> LINE登録数 | S11: =IFERROR(__xludf.DUMMYFUNCTION("""COMPUTED_VALUE"""),"リスト件数") -> リスト件数 | T11: =IFERROR(__xludf.DUMMYFUNCTION("""COMPUTED_VALUE"""),"アカウント作成数") -> アカウント作成数 | U11: =IFERROR(__xludf.DUMMYFUNCTION("""COMPUTED_VALUE"""),"LINE登録数") -> LINE登録数 | W11: =IFERROR(__xludf.DUMMYFUNCTION("""COMPUTED_VALUE"""),"リスト件数") -> リスト件数 | X11: =IFERROR(__xludf.DUMMYFUNCTION("""COMPUTED_VALUE"""),"アカウント作成数") -> アカウント作成数 | Y11: =IFERROR(__xludf.DUMMYFUNCTION("""COMPUTED_VALUE"""),"LINE登録数") -> LINE登録数 | AA11: =IFERROR(__xludf.DUMMYFUNCTION("""COMPUTED_VALUE"""),"リスト件数") -> リスト件数 | AB11: =IFERROR(__xludf.DUMMYFUNCTION("""COMPUTED_VALUE"""),"アカウント作成数") -> アカウント作成数 | AC11: =IFERROR(__xludf.DUMMYFUNCTION("""COMPUTED_VALUE"""),"LINE登録数") -> LINE登録数 | AE11: =IFERROR(__xludf.DUMMYFUNCTION("""COMPUTED_VALUE"""),"リスト件数") -> リスト件数 | AF11: =IFERROR(__xludf.DUMMYFUNCTION("""COMPUTED_VALUE"""),"アカウント作成数") -> アカウント作成数 | AG11: =IFERROR(__xludf.DUMMYFUNCTION("""COMPUTED_VALUE"""),"LINE登録数") -> LINE登録数 | AI11: =IFERROR(__xludf.DUMMYFUNCTION("""COMPUTED_VALUE"""),"リスト件数") -> リスト件数 | AJ11: =IFERROR(__xludf.DUMMYFUNCTION("""COMPUTED_VALUE"""),"アカウント作成数") -> アカウント作成数 | AK11: =IFERROR(__xludf.DUMMYFUNCTION("""COMPUTED_VALUE"""),"LINE登録数") -> LINE登録数 | AM11: =IFERROR(__xludf.DUMMYFUNCTION("""COMPUTED_VALUE"""),"リスト件数") -> リスト件数 | AN11: =IFERROR(__xludf.DUMMYFUNCTION("""COMPUTED_VALUE"""),"アカウント作成数") -> アカウント作成数 | AO11: =IFERROR(__xludf.DUMMYFUNCTION("""COMPUTED_VALUE"""),"LINE登録数") -> LINE登録数 | AQ11: =IFERROR(__xludf.DUMMYFUNCTION("""COMPUTED_VALUE"""),"リスト件数") -> リスト件数 | AR11: =IFERROR(__xludf.DUMMYFUNCTION("""COMPUTED_VALUE"""),"アカウント作成数") -> アカウント作成数 | AS11: =IFERROR(__xludf.DUMMYFUNCTION("""COMPUTED_VALUE"""),"LINE登録数") -> LINE登録数 | AT11: =IFERROR(__xludf.DUMMYFUNCTION("""COMPUTED_VALUE"""),"月トータル") -> 月トータル | AU11: =IFERROR(__xludf.DUMMYFUNCTION("""COMPUTED_VALUE"""),"リスト件数") -> リスト件数 | AV11: =IFERROR(__xludf.DUMMYFUNCTION("""COMPUTED_VALUE"""),"アカウント作成数") -> アカウント作成数 | AW11: =IFERROR(__xludf.DUMMYFUNCTION("""COMPUTED_VALUE"""),"LINE登録数") -> LINE登録数 | AX11: =IFERROR(__xludf.DUMMYFUNCTION("""COMPUTED_VALUE"""),"月トータル") -> 月トータル | AY11: =IFERROR(__xludf.DUMMYFUNCTION("""COMPUTED_VALUE"""),"リスト件数") -> リスト件数 | AZ11: =IFERROR(__xludf.DUMMYFUNCTION("""COMPUTED_VALUE"""),"アカウント作成数") -> アカウント作成数 | BA11: =IFERROR(__xludf.DUMMYFUNCTION("""COMPUTED_VALUE"""),"LINE登録数") -> LINE登録数 | BB11: =IFERROR(__xludf.DUMMYFUNCTION("""COMPUTED_VALUE"""),"月トータル") -> 月トータル | BC11: =IFERROR(__xludf.DUMMYFUNCTION("""COMPUTED_VALUE"""),"リスト件数") -> リスト件数 | BD11: =IFERROR(__xludf.DUMMYFUNCTION("""COMPUTED_VALUE"""),"アカウント作成数") -> アカウント作成数 | BE11: =IFERROR(__xludf.DUMMYFUNCTION("""COMPUTED_VALUE"""),"LINE登録数") -> LINE登録数 | BF11: =IFERROR(__xludf.DUMMYFUNCTION("""COMPUTED_VALUE"""),"月トータル") -> 月トータル
B12: =IFERROR(__xludf.DUMMYFUNCTION("""COMPUTED_VALUE"""),"リストC") -> リストC | C12: =IFERROR(__xludf.DUMMYFUNCTION("""COMPUTED_VALUE"""),7000.0) -> 7000 | D12: =IFERROR(__xludf.DUMMYFUNCTION("""COMPUTED_VALUE"""),7.0) -> 7 | E12: =IFERROR(__xludf.DUMMYFUNCTION("""COMPUTED_VALUE"""),12.0) -> 12 | F12: =IFERROR(__xludf.DUMMYFUNCTION("""COMPUTED_VALUE"""),"リストC") -> リストC | G12: =IFERROR(__xludf.DUMMYFUNCTION("""COMPUTED_VALUE"""),8000.0) -> 8000 | H12: =IFERROR(__xludf.DUMMYFUNCTION("""COMPUTED_VALUE"""),5.0) -> 5 | I12: =IFERROR(__xludf.DUMMYFUNCTION("""COMPUTED_VALUE"""),6.0) -> 6 | J12: =IFERROR(__xludf.DUMMYFUNCTION("""COMPUTED_VALUE"""),"リストC") -> リストC | K12: =IFERROR(__xludf.DUMMYFUNCTION("""COMPUTED_VALUE"""),8000.0) -> 8000 | L12: =IFERROR(__xludf.DUMMYFUNCTION("""COMPUTED_VALUE"""),13.0) -> 13 | M12: =IFERROR(__xludf.DUMMYFUNCTION("""COMPUTED_VALUE"""),14.0) -> 14 | N12: =IFERROR(__xludf.DUMMYFUNCTION("""COMPUTED_VALUE"""),"リストC") -> リストC | O12: =IFERROR(__xludf.DUMMYFUNCTION("""COMPUTED_VALUE"""),8000.0) -> 8000 | P12: =IFERROR(__xludf.DUMMYFUNCTION("""COMPUTED_VALUE"""),2.0) -> 2 | Q12: =IFERROR(__xludf.DUMMYFUNCTION("""COMPUTED_VALUE"""),12.0) -> 12 | R12: =IFERROR(__xludf.DUMMYFUNCTION("""COMPUTED_VALUE"""),"リストC") -> リストC | S12: =IFERROR(__xludf.DUMMYFUNCTION("""COMPUTED_VALUE"""),5000.0) -> 5000 | T12: =IFERROR(__xludf.DUMMYFUNCTION("""COMPUTED_VALUE"""),13.0) -> 13 | U12: =IFERROR(__xludf.DUMMYFUNCTION("""COMPUTED_VALUE"""),15.0) -> 15 | V12: =IFERROR(__xludf.DUMMYFUNCTION("""COMPUTED_VALUE"""),"リストC") -> リストC | W12: =IFERROR(__xludf.DUMMYFUNCTION("""COMPUTED_VALUE"""),4000.0) -> 4000 | X12: =IFERROR(__xludf.DUMMYFUNCTION("""COMPUTED_VALUE"""),0.0) -> 0 | Y12: =IFERROR(__xludf.DUMMYFUNCTION("""COMPUTED_VALUE"""),0.0) -> 0 | Z12: =IFERROR(__xludf.DUMMYFUNCTION("""COMPUTED_VALUE"""),"リストC") -> リストC | AA12: =IFERROR(__xludf.DUMMYFUNCTION("""COMPUTED_VALUE"""),5000.0) -> 5000 | AB12: =IFERROR(__xludf.DUMMYFUNCTION("""COMPUTED_VALUE"""),32.5) -> 32.5 | AC12: =IFERROR(__xludf.DUMMYFUNCTION("""COMPUTED_VALUE"""),43.0) -> 43 | AD12: =IFERROR(__xludf.DUMMYFUNCTION("""COMPUTED_VALUE"""),"リストC") -> リストC | AE12: =IFERROR(__xludf.DUMMYFUNCTION("""COMPUTED_VALUE"""),4000.0) -> 4000 | AF12: =IFERROR(__xludf.DUMMYFUNCTION("""COMPUTED_VALUE"""),15.0) -> 15 | AG12: =IFERROR(__xludf.DUMMYFUNCTION("""COMPUTED_VALUE"""),21.0) -> 21 | AH12: =IFERROR(__xludf.DUMMYFUNCTION("""COMPUTED_VALUE"""),"リストC") -> リストC | AI12: =IFERROR(__xludf.DUMMYFUNCTION("""COMPUTED_VALUE"""),1000.0) -> 1000 | AJ12: =IFERROR(__xludf.DUMMYFUNCTION("""COMPUTED_VALUE"""),0.0) -> 0 | AK12: =IFERROR(__xludf.DUMMYFUNCTION("""COMPUTED_VALUE"""),0.0) -> 0 | AL12: =IFERROR(__xludf.DUMMYFUNCTION("""COMPUTED_VALUE"""),"リストC") -> リストC | AM12: =IFERROR(__xludf.DUMMYFUNCTION("""COMPUTED_VALUE"""),0.0) -> 0 | AN12: =IFERROR(__xludf.DUMMYFUNCTION("""COMPUTED_VALUE"""),0.0) -> 0 | AO12: =IFERROR(__xludf.DUMMYFUNCTION("""COMPUTED_VALUE"""),0.0) -> 0 | AP12: =IFERROR(__xludf.DUMMYFUNCTION("""COMPUTED_VALUE"""),"リストC") -> リストC | AQ12: =IFERROR(__xludf.DUMMYFUNCTION("""COMPUTED_VALUE"""),0.0) -> 0 | AR12: =IFERROR(__xludf.DUMMYFUNCTION("""COMPUTED_VALUE"""),0.0) -> 0 | AS12: =IFERROR(__xludf.DUMMYFUNCTION("""COMPUTED_VALUE"""),0.0) -> 0 | AT12: =IFERROR(__xludf.DUMMYFUNCTION("""COMPUTED_VALUE"""),"リストC") -> リストC | AU12: =IFERROR(__xludf.DUMMYFUNCTION("""COMPUTED_VALUE"""),0.0) -> 0 | AV12: =IFERROR(__xludf.DUMMYFUNCTION("""COMPUTED_VALUE"""),0.0) -> 0 | AW12: =IFERROR(__xludf.DUMMYFUNCTION("""COMPUTED_VALUE"""),0.0) -> 0 | AX12: =IFERROR(__xludf.DUMMYFUNCTION("""COMPUTED_VALUE"""),"リストC") -> リストC | AY12: =IFERROR(__xludf.DUMMYFUNCTION("""COMPUTED_VALUE"""),0.0) -> 0 | AZ12: =IFERROR(__xludf.DUMMYFUNCTION("""COMPUTED_VALUE"""),0.0) -> 0 | BA12: =IFERROR(__xludf.DUMMYFUNCTION("""COMPUTED_VALUE"""),0.0) -> 0 | BB12: =IFERROR(__xludf.DUMMYFUNCTION("""COMPUTED_VALUE"""),"リストC") -> リストC | BC12: =IFERROR(__xludf.DUMMYFUNCTION("""COMPUTED_VALUE"""),0.0) -> 0 | BD12: =IFERROR(__xludf.DUMMYFUNCTION("""COMPUTED_VALUE"""),0.0) -> 0 | BE12: =IFERROR(__xludf.DUMMYFUNCTION("""COMPUTED_VALUE"""),0.0) -> 0 | BF12: =IFERROR(__xludf.DUMMYFUNCTION("""COMPUTED_VALUE"""),"リストC") -> リストC
B13: =IFERROR(__xludf.DUMMYFUNCTION("""COMPUTED_VALUE"""),"リストBE") -> リストBE | C13: =IFERROR(__xludf.DUMMYFUNCTION("""COMPUTED_VALUE"""),0.0) -> 0 | D13: =IFERROR(__xludf.DUMMYFUNCTION("""COMPUTED_VALUE"""),0.0) -> 0 | E13: =IFERROR(__xludf.DUMMYFUNCTION("""COMPUTED_VALUE"""),1.0) -> 1 | F13: =IFERROR(__xludf.DUMMYFUNCTION("""COMPUTED_VALUE"""),"リストBE") -> リストBE | G13: =IFERROR(__xludf.DUMMYFUNCTION("""COMPUTED_VALUE"""),0.0) -> 0 | H13: =IFERROR(__xludf.DUMMYFUNCTION("""COMPUTED_VALUE"""),0.0) -> 0 | I13: =IFERROR(__xludf.DUMMYFUNCTION("""COMPUTED_VALUE"""),0.0) -> 0 | J13: =IFERROR(__xludf.DUMMYFUNCTION("""COMPUTED_VALUE"""),"リストBE") -> リストBE | K13: =IFERROR(__xludf.DUMMYFUNCTION("""COMPUTED_VALUE"""),0.0) -> 0 | L13: =IFERROR(__xludf.DUMMYFUNCTION("""COMPUTED_VALUE"""),0.0) -> 0 | M13: =IFERROR(__xludf.DUMMYFUNCTION("""COMPUTED_VALUE"""),0.0) -> 0 | N13: =IFERROR(__xludf.DUMMYFUNCTION("""COMPUTED_VALUE"""),"リストBE") -> リストBE | O13: =IFERROR(__xludf.DUMMYFUNCTION("""COMPUTED_VALUE"""),0.0) -> 0 | P13: =IFERROR(__xludf.DUMMYFUNCTION("""COMPUTED_VALUE"""),0.0) -> 0 | Q13: =IFERROR(__xludf.DUMMYFUNCTION("""COMPUTED_VALUE"""),0.0) -> 0 | R13: =IFERROR(__xludf.DUMMYFUNCTION("""COMPUTED_VALUE"""),"リストBE") -> リストBE | S13: =IFERROR(__xludf.DUMMYFUNCTION("""COMPUTED_VALUE"""),0.0) -> 0 | T13: =IFERROR(__xludf.DUMMYFUNCTION("""COMPUTED_VALUE"""),0.0) -> 0 | U13: =IFERROR(__xludf.DUMMYFUNCTION("""COMPUTED_VALUE"""),0.0) -> 0 | V13: =IFERROR(__xludf.DUMMYFUNCTION("""COMPUTED_VALUE"""),"リストBE") -> リストBE | W13: =IFERROR(__xludf.DUMMYFUNCTION("""COMPUTED_VALUE"""),0.0) -> 0 | X13: =IFERROR(__xludf.DUMMYFUNCTION("""COMPUTED_VALUE"""),0.0) -> 0 | Y13: =IFERROR(__xludf.DUMMYFUNCTION("""COMPUTED_VALUE"""),0.0) -> 0 | Z13: =IFERROR(__xludf.DUMMYFUNCTION("""COMPUTED_VALUE"""),"リストBE") -> リストBE | AA13: =IFERROR(__xludf.DUMMYFUNCTION("""COMPUTED_VALUE"""),0.0) -> 0 | AB13: =IFERROR(__xludf.DUMMYFUNCTION("""COMPUTED_VALUE"""),0.0) -> 0 | AC13: =IFERROR(__xludf.DUMMYFUNCTION("""COMPUTED_VALUE"""),0.0) -> 0 | AD13: =IFERROR(__xludf.DUMMYFUNCTION("""COMPUTED_VALUE"""),"リストBE") -> リストBE | AE13: =IFERROR(__xludf.DUMMYFUNCTION("""COMPUTED_VALUE"""),0.0) -> 0 | AF13: =IFERROR(__xludf.DUMMYFUNCTION("""COMPUTED_VALUE"""),7.0) -> 7 | AG13: =IFERROR(__xludf.DUMMYFUNCTION("""COMPUTED_VALUE"""),7.0) -> 7 | AH13: =IFERROR(__xludf.DUMMYFUNCTION("""COMPUTED_VALUE"""),"リストBE") -> リストBE | AI13: =IFERROR(__xludf.DUMMYFUNCTION("""COMPUTED_VALUE"""),0.0) -> 0 | AJ13: =IFERROR(__xludf.DUMMYFUNCTION("""COMPUTED_VALUE"""),0.0) -> 0 | AK13: =IFERROR(__xludf.DUMMYFUNCTION("""COMPUTED_VALUE"""),0.0) -> 0 | AL13: =IFERROR(__xludf.DUMMYFUNCTION("""COMPUTED_VALUE"""),"リストBE") -> リストBE | AM13: =IFERROR(__xludf.DUMMYFUNCTION("""COMPUTED_VALUE"""),2000.0) -> 2000 | AN13: =IFERROR(__xludf.DUMMYFUNCTION("""COMPUTED_VALUE"""),5.0) -> 5 | AO13: =IFERROR(__xludf.DUMMYFUNCTION("""COMPUTED_VALUE"""),12.0) -> 12 | AP13: =IFERROR(__xludf.DUMMYFUNCTION("""COMPUTED_VALUE"""),"リストBE") -> リストBE | AQ13: =IFERROR(__xludf.DUMMYFUNCTION("""COMPUTED_VALUE"""),3000.0) -> 3000 | AR13: =IFERROR(__xludf.DUMMYFUNCTION("""COMPUTED_VALUE"""),0.0) -> 0 | AS13: =IFERROR(__xludf.DUMMYFUNCTION("""COMPUTED_VALUE"""),0.0) -> 0 | AT13: =IFERROR(__xludf.DUMMYFUNCTION("""COMPUTED_VALUE"""),"リストBE") -> リストBE | AU13: =IFERROR(__xludf.DUMMYFUNCTION("""COMPUTED_VALUE"""),0.0) -> 0 | AV13: =IFERROR(__xludf.DUMMYFUNCTION("""COMPUTED_VALUE"""),0.0) -> 0 | AW13: =IFERROR(__xludf.DUMMYFUNCTION("""COMPUTED_VALUE"""),0.0) -> 0 | AX13: =IFERROR(__xludf.DUMMYFUNCTION("""COMPUTED_VALUE"""),"リストBE") -> リストBE | AY13: =IFERROR(__xludf.DUMMYFUNCTION("""COMPUTED_VALUE"""),0.0) -> 0 | AZ13: =IFERROR(__xludf.DUMMYFUNCTION("""COMPUTED_VALUE"""),0.0) -> 0 | BA13: =IFERROR(__xludf.DUMMYFUNCTION("""COMPUTED_VALUE"""),0.0) -> 0 | BB13: =IFERROR(__xludf.DUMMYFUNCTION("""COMPUTED_VALUE"""),"リストBE") -> リストBE | BC13: =IFERROR(__xludf.DUMMYFUNCTION("""COMPUTED_VALUE"""),0.0) -> 0 | BD13: =IFERROR(__xludf.DUMMYFUNCTION("""COMPUTED_VALUE"""),0.0) -> 0 | BE13: =IFERROR(__xludf.DUMMYFUNCTION("""COMPUTED_VALUE"""),0.0) -> 0 | BF13: =IFERROR(__xludf.DUMMYFUNCTION("""COMPUTED_VALUE"""),"リストBE") -> リストBE
B14: =IFERROR(__xludf.DUMMYFUNCTION("""COMPUTED_VALUE"""),"リストS") -> リストS | C14: =IFERROR(__xludf.DUMMYFUNCTION("""COMPUTED_VALUE"""),4000.0) -> 4000 | D14: =IFERROR(__xludf.DUMMYFUNCTION("""COMPUTED_VALUE"""),8.0) -> 8 | E14: =IFERROR(__xludf.DUMMYFUNCTION("""COMPUTED_VALUE"""),9.0) -> 9 | F14: =IFERROR(__xludf.DUMMYFUNCTION("""COMPUTED_VALUE"""),"リストS") -> リストS | G14: =IFERROR(__xludf.DUMMYFUNCTION("""COMPUTED_VALUE"""),4000.0) -> 4000 | H14: =IFERROR(__xludf.DUMMYFUNCTION("""COMPUTED_VALUE"""),6.0) -> 6 | I14: =IFERROR(__xludf.DUMMYFUNCTION("""COMPUTED_VALUE"""),10.0) -> 10 | J14: =IFERROR(__xludf.DUMMYFUNCTION("""COMPUTED_VALUE"""),"リストS") -> リストS | K14: =IFERROR(__xludf.DUMMYFUNCTION("""COMPUTED_VALUE"""),4000.0) -> 4000 | L14: =IFERROR(__xludf.DUMMYFUNCTION("""COMPUTED_VALUE"""),28.0) -> 28 | M14: =IFERROR(__xludf.DUMMYFUNCTION("""COMPUTED_VALUE"""),39.0) -> 39 | N14: =IFERROR(__xludf.DUMMYFUNCTION("""COMPUTED_VALUE"""),"リストS") -> リストS | O14: =IFERROR(__xludf.DUMMYFUNCTION("""COMPUTED_VALUE"""),4000.0) -> 4000 | P14: =IFERROR(__xludf.DUMMYFUNCTION("""COMPUTED_VALUE"""),0.0) -> 0 | Q14: =IFERROR(__xludf.DUMMYFUNCTION("""COMPUTED_VALUE"""),7.0) -> 7 | R14: =IFERROR(__xludf.DUMMYFUNCTION("""COMPUTED_VALUE"""),"リストS") -> リストS | S14: =IFERROR(__xludf.DUMMYFUNCTION("""COMPUTED_VALUE"""),2500.0) -> 2500 | T14: =IFERROR(__xludf.DUMMYFUNCTION("""COMPUTED_VALUE"""),9.0) -> 9 | U14: =IFERROR(__xludf.DUMMYFUNCTION("""COMPUTED_VALUE"""),11.0) -> 11 | V14: =IFERROR(__xludf.DUMMYFUNCTION("""COMPUTED_VALUE"""),"リストS") -> リストS | W14: =IFERROR(__xludf.DUMMYFUNCTION("""COMPUTED_VALUE"""),3000.0) -> 3000 | X14: =IFERROR(__xludf.DUMMYFUNCTION("""COMPUTED_VALUE"""),84.0) -> 84 | Y14: =IFERROR(__xludf.DUMMYFUNCTION("""COMPUTED_VALUE"""),92.0) -> 92 | Z14: =IFERROR(__xludf.DUMMYFUNCTION("""COMPUTED_VALUE"""),"リストS") -> リストS | AA14: =IFERROR(__xludf.DUMMYFUNCTION("""COMPUTED_VALUE"""),2500.0) -> 2500 | AB14: =IFERROR(__xludf.DUMMYFUNCTION("""COMPUTED_VALUE"""),38.5) -> 38.5 | AC14: =IFERROR(__xludf.DUMMYFUNCTION("""COMPUTED_VALUE"""),49.0) -> 49 | AD14: =IFERROR(__xludf.DUMMYFUNCTION("""COMPUTED_VALUE"""),"リストS") -> リストS | AE14: =IFERROR(__xludf.DUMMYFUNCTION("""COMPUTED_VALUE"""),3000.0) -> 3000 | AF14: =IFERROR(__xludf.DUMMYFUNCTION("""COMPUTED_VALUE"""),81.0) -> 81 | AG14: =IFERROR(__xludf.DUMMYFUNCTION("""COMPUTED_VALUE"""),110.0) -> 110 | AH14: =IFERROR(__xludf.DUMMYFUNCTION("""COMPUTED_VALUE"""),"リストS") -> リストS | AI14: =IFERROR(__xludf.DUMMYFUNCTION("""COMPUTED_VALUE"""),2000.0) -> 2000 | AJ14: =IFERROR(__xludf.DUMMYFUNCTION("""COMPUTED_VALUE"""),104.0) -> 104 | AK14: =IFERROR(__xludf.DUMMYFUNCTION("""COMPUTED_VALUE"""),132.0) -> 132 | AL14: =IFERROR(__xludf.DUMMYFUNCTION("""COMPUTED_VALUE"""),"リストS") -> リストS | AM14: =IFERROR(__xludf.DUMMYFUNCTION("""COMPUTED_VALUE"""),2000.0) -> 2000 | AN14: =IFERROR(__xludf.DUMMYFUNCTION("""COMPUTED_VALUE"""),72.0) -> 72 | AO14: =IFERROR(__xludf.DUMMYFUNCTION("""COMPUTED_VALUE"""),142.0) -> 142 | AP14: =IFERROR(__xludf.DUMMYFUNCTION("""COMPUTED_VALUE"""),"リストS") -> リストS | AQ14: =IFERROR(__xludf.DUMMYFUNCTION("""COMPUTED_VALUE"""),1000.0) -> 1000 | AR14: =IFERROR(__xludf.DUMMYFUNCTION("""COMPUTED_VALUE"""),57.0) -> 57 | AS14: =IFERROR(__xludf.DUMMYFUNCTION("""COMPUTED_VALUE"""),104.0) -> 104 | AT14: =IFERROR(__xludf.DUMMYFUNCTION("""COMPUTED_VALUE"""),"リストS") -> リストS | AU14: =IFERROR(__xludf.DUMMYFUNCTION("""COMPUTED_VALUE"""),4000.0) -> 4000 | AV14: =IFERROR(__xludf.DUMMYFUNCTION("""COMPUTED_VALUE"""),22.0) -> 22 | AW14: =IFERROR(__xludf.DUMMYFUNCTION("""COMPUTED_VALUE"""),48.0) -> 48 | AX14: =IFERROR(__xludf.DUMMYFUNCTION("""COMPUTED_VALUE"""),"リストS") -> リストS | AY14: =IFERROR(__xludf.DUMMYFUNCTION("""COMPUTED_VALUE"""),27000.0) -> 27000 | AZ14: =IFERROR(__xludf.DUMMYFUNCTION("""COMPUTED_VALUE"""),59.0) -> 59 | BA14: =IFERROR(__xludf.DUMMYFUNCTION("""COMPUTED_VALUE"""),91.0) -> 91 | BB14: =IFERROR(__xludf.DUMMYFUNCTION("""COMPUTED_VALUE"""),"リストS") -> リストS | BC14: =IFERROR(__xludf.DUMMYFUNCTION("""COMPUTED_VALUE"""),7000.0) -> 7000 | BD14: =IFERROR(__xludf.DUMMYFUNCTION("""COMPUTED_VALUE"""),73.0) -> 73 | BE14: =IFERROR(__xludf.DUMMYFUNCTION("""COMPUTED_VALUE"""),163.0) -> 163 | BF14: =IFERROR(__xludf.DUMMYFUNCTION("""COMPUTED_VALUE"""),"リストS") -> リストS
B15: =IFERROR(__xludf.DUMMYFUNCTION("""COMPUTED_VALUE"""),"リストE") -> リストE | C15: =IFERROR(__xludf.DUMMYFUNCTION("""COMPUTED_VALUE"""),11000.0) -> 11000 | D15: =IFERROR(__xludf.DUMMYFUNCTION("""COMPUTED_VALUE"""),7.0) -> 7 | E15: =IFERROR(__xludf.DUMMYFUNCTION("""COMPUTED_VALUE"""),10.0) -> 10 | F15: =IFERROR(__xludf.DUMMYFUNCTION("""COMPUTED_VALUE"""),"リストE") -> リストE | G15: =IFERROR(__xludf.DUMMYFUNCTION("""COMPUTED_VALUE"""),4000.0) -> 4000 | H15: =IFERROR(__xludf.DUMMYFUNCTION("""COMPUTED_VALUE"""),5.0) -> 5 | I15: =IFERROR(__xludf.DUMMYFUNCTION("""COMPUTED_VALUE"""),7.0) -> 7 | J15: =IFERROR(__xludf.DUMMYFUNCTION("""COMPUTED_VALUE"""),"リストE") -> リストE | K15: =IFERROR(__xludf.DUMMYFUNCTION("""COMPUTED_VALUE"""),4000.0) -> 4000 | L15: =IFERROR(__xludf.DUMMYFUNCTION("""COMPUTED_VALUE"""),40.0) -> 40 | M15: =IFERROR(__xludf.DUMMYFUNCTION("""COMPUTED_VALUE"""),36.0) -> 36 | N15: =IFERROR(__xludf.DUMMYFUNCTION("""COMPUTED_VALUE"""),"リストE") -> リストE | O15: =IFERROR(__xludf.DUMMYFUNCTION("""COMPUTED_VALUE"""),4000.0) -> 4000 | P15: =IFERROR(__xludf.DUMMYFUNCTION("""COMPUTED_VALUE"""),7.0) -> 7 | Q15: =IFERROR(__xludf.DUMMYFUNCTION("""COMPUTED_VALUE"""),13.0) -> 13 | R15: =IFERROR(__xludf.DUMMYFUNCTION("""COMPUTED_VALUE"""),"リストE") -> リストE | S15: =IFERROR(__xludf.DUMMYFUNCTION("""COMPUTED_VALUE"""),2500.0) -> 2500 | T15: =IFERROR(__xludf.DUMMYFUNCTION("""COMPUTED_VALUE"""),26.0) -> 26 | U15: =IFERROR(__xludf.DUMMYFUNCTION("""COMPUTED_VALUE"""),25.0) -> 25 | V15: =IFERROR(__xludf.DUMMYFUNCTION("""COMPUTED_VALUE"""),"リストE") -> リストE | W15: =IFERROR(__xludf.DUMMYFUNCTION("""COMPUTED_VALUE"""),3000.0) -> 3000 | X15: =IFERROR(__xludf.DUMMYFUNCTION("""COMPUTED_VALUE"""),101.0) -> 101 | Y15: =IFERROR(__xludf.DUMMYFUNCTION("""COMPUTED_VALUE"""),119.0) -> 119 | Z15: =IFERROR(__xludf.DUMMYFUNCTION("""COMPUTED_VALUE"""),"リストE") -> リストE | AA15: =IFERROR(__xludf.DUMMYFUNCTION("""COMPUTED_VALUE"""),2500.0) -> 2500 | AB15: =IFERROR(__xludf.DUMMYFUNCTION("""COMPUTED_VALUE"""),55.5) -> 55.5 | AC15: =IFERROR(__xludf.DUMMYFUNCTION("""COMPUTED_VALUE"""),52.0) -> 52 | AD15: =IFERROR(__xludf.DUMMYFUNCTION("""COMPUTED_VALUE"""),"リストE") -> リストE | AE15: =IFERROR(__xludf.DUMMYFUNCTION("""COMPUTED_VALUE"""),3000.0) -> 3000 | AF15: =IFERROR(__xludf.DUMMYFUNCTION("""COMPUTED_VALUE"""),97.0) -> 97 | AG15: =IFERROR(__xludf.DUMMYFUNCTION("""COMPUTED_VALUE"""),129.0) -> 129 | AH15: =IFERROR(__xludf.DUMMYFUNCTION("""COMPUTED_VALUE"""),"リストE") -> リストE | AI15: =IFERROR(__xludf.DUMMYFUNCTION("""COMPUTED_VALUE"""),4000.0) -> 4000 | AJ15: =IFERROR(__xludf.DUMMYFUNCTION("""COMPUTED_VALUE"""),44.0) -> 44 | AK15: =IFERROR(__xludf.DUMMYFUNCTION("""COMPUTED_VALUE"""),66.0) -> 66 | AL15: =IFERROR(__xludf.DUMMYFUNCTION("""COMPUTED_VALUE"""),"リストE") -> リストE | AM15: =IFERROR(__xludf.DUMMYFUNCTION("""COMPUTED_VALUE"""),3000.0) -> 3000 | AN15: =IFERROR(__xludf.DUMMYFUNCTION("""COMPUTED_VALUE"""),14.0) -> 14 | AO15: =IFERROR(__xludf.DUMMYFUNCTION("""COMPUTED_VALUE"""),38.0) -> 38 | AP15: =IFERROR(__xludf.DUMMYFUNCTION("""COMPUTED_VALUE"""),"リストE") -> リストE | AQ15: =IFERROR(__xludf.DUMMYFUNCTION("""COMPUTED_VALUE"""),1000.0) -> 1000 | AR15: =IFERROR(__xludf.DUMMYFUNCTION("""COMPUTED_VALUE"""),75.0) -> 75 | AS15: =IFERROR(__xludf.DUMMYFUNCTION("""COMPUTED_VALUE"""),97.0) -> 97 | AT15: =IFERROR(__xludf.DUMMYFUNCTION("""COMPUTED_VALUE"""),"リストE") -> リストE | AU15: =IFERROR(__xludf.DUMMYFUNCTION("""COMPUTED_VALUE"""),2000.0) -> 2000 | AV15: =IFERROR(__xludf.DUMMYFUNCTION("""COMPUTED_VALUE"""),88.0) -> 88 | AW15: =IFERROR(__xludf.DUMMYFUNCTION("""COMPUTED_VALUE"""),123.0) -> 123 | AX15: =IFERROR(__xludf.DUMMYFUNCTION("""COMPUTED_VALUE"""),"リストE") -> リストE | AY15: =IFERROR(__xludf.DUMMYFUNCTION("""COMPUTED_VALUE"""),9000.0) -> 9000 | AZ15: =IFERROR(__xludf.DUMMYFUNCTION("""COMPUTED_VALUE"""),88.0) -> 88 | BA15: =IFERROR(__xludf.DUMMYFUNCTION("""COMPUTED_VALUE"""),145.0) -> 145 | BB15: =IFERROR(__xludf.DUMMYFUNCTION("""COMPUTED_VALUE"""),"リストE") -> リストE | BC15: =IFERROR(__xludf.DUMMYFUNCTION("""COMPUTED_VALUE"""),5000.0) -> 5000 | BD15: =IFERROR(__xludf.DUMMYFUNCTION("""COMPUTED_VALUE"""),82.0) -> 82 | BE15: =IFERROR(__xludf.DUMMYFUNCTION("""COMPUTED_VALUE"""),147.0) -> 147 | BF15: =IFERROR(__xludf.DUMMYFUNCTION("""COMPUTED_VALUE"""),"リストE") -> リストE
B16: =IFERROR(__xludf.DUMMYFUNCTION("""COMPUTED_VALUE"""),"TOTAL") -> TOTAL | C16: =IFERROR(__xludf.DUMMYFUNCTION("""COMPUTED_VALUE"""),22000.0) -> 22000 | D16: =IFERROR(__xludf.DUMMYFUNCTION("""COMPUTED_VALUE"""),22.0) -> 22 | E16: =IFERROR(__xludf.DUMMYFUNCTION("""COMPUTED_VALUE"""),32.0) -> 32 | F16: =IFERROR(__xludf.DUMMYFUNCTION("""COMPUTED_VALUE"""),"TOTAL") -> TOTAL | G16: =IFERROR(__xludf.DUMMYFUNCTION("""COMPUTED_VALUE"""),16000.0) -> 16000 | H16: =IFERROR(__xludf.DUMMYFUNCTION("""COMPUTED_VALUE"""),16.0) -> 16 | I16: =IFERROR(__xludf.DUMMYFUNCTION("""COMPUTED_VALUE"""),23.0) -> 23 | J16: =IFERROR(__xludf.DUMMYFUNCTION("""COMPUTED_VALUE"""),"TOTAL") -> TOTAL | K16: =IFERROR(__xludf.DUMMYFUNCTION("""COMPUTED_VALUE"""),16000.0) -> 16000 | L16: =IFERROR(__xludf.DUMMYFUNCTION("""COMPUTED_VALUE"""),81.0) -> 81 | M16: =IFERROR(__xludf.DUMMYFUNCTION("""COMPUTED_VALUE"""),89.0) -> 89 | N16: =IFERROR(__xludf.DUMMYFUNCTION("""COMPUTED_VALUE"""),"TOTAL") -> TOTAL | O16: =IFERROR(__xludf.DUMMYFUNCTION("""COMPUTED_VALUE"""),16000.0) -> 16000 | P16: =IFERROR(__xludf.DUMMYFUNCTION("""COMPUTED_VALUE"""),9.0) -> 9 | Q16: =IFERROR(__xludf.DUMMYFUNCTION("""COMPUTED_VALUE"""),32.0) -> 32 | R16: =IFERROR(__xludf.DUMMYFUNCTION("""COMPUTED_VALUE"""),"TOTAL") -> TOTAL | S16: =IFERROR(__xludf.DUMMYFUNCTION("""COMPUTED_VALUE"""),10000.0) -> 10000 | T16: =IFERROR(__xludf.DUMMYFUNCTION("""COMPUTED_VALUE"""),48.0) -> 48 | U16: =IFERROR(__xludf.DUMMYFUNCTION("""COMPUTED_VALUE"""),51.0) -> 51 | V16: =IFERROR(__xludf.DUMMYFUNCTION("""COMPUTED_VALUE"""),"TOTAL") -> TOTAL | W16: =IFERROR(__xludf.DUMMYFUNCTION("""COMPUTED_VALUE"""),10000.0) -> 10000 | X16: =IFERROR(__xludf.DUMMYFUNCTION("""COMPUTED_VALUE"""),185.0) -> 185 | Y16: =IFERROR(__xludf.DUMMYFUNCTION("""COMPUTED_VALUE"""),211.0) -> 211 | Z16: =IFERROR(__xludf.DUMMYFUNCTION("""COMPUTED_VALUE"""),"TOTAL") -> TOTAL | AA16: =IFERROR(__xludf.DUMMYFUNCTION("""COMPUTED_VALUE"""),10000.0) -> 10000 | AB16: =IFERROR(__xludf.DUMMYFUNCTION("""COMPUTED_VALUE"""),126.5) -> 126.5 | AC16: =IFERROR(__xludf.DUMMYFUNCTION("""COMPUTED_VALUE"""),144.0) -> 144 | AD16: =IFERROR(__xludf.DUMMYFUNCTION("""COMPUTED_VALUE"""),"TOTAL") -> TOTAL | AE16: =IFERROR(__xludf.DUMMYFUNCTION("""COMPUTED_VALUE"""),10000.0) -> 10000 | AF16: =IFERROR(__xludf.DUMMYFUNCTION("""COMPUTED_VALUE"""),200.0) -> 200 | AG16: =IFERROR(__xludf.DUMMYFUNCTION("""COMPUTED_VALUE"""),267.0) -> 267 | AH16: =IFERROR(__xludf.DUMMYFUNCTION("""COMPUTED_VALUE"""),"TOTAL") -> TOTAL | AI16: =IFERROR(__xludf.DUMMYFUNCTION("""COMPUTED_VALUE"""),7000.0) -> 7000 | AJ16: =IFERROR(__xludf.DUMMYFUNCTION("""COMPUTED_VALUE"""),148.0) -> 148 | AK16: =IFERROR(__xludf.DUMMYFUNCTION("""COMPUTED_VALUE"""),198.0) -> 198 | AL16: =IFERROR(__xludf.DUMMYFUNCTION("""COMPUTED_VALUE"""),"TOTAL") -> TOTAL | AM16: =IFERROR(__xludf.DUMMYFUNCTION("""COMPUTED_VALUE"""),7000.0) -> 7000 | AN16: =IFERROR(__xludf.DUMMYFUNCTION("""COMPUTED_VALUE"""),91.0) -> 91 | AO16: =IFERROR(__xludf.DUMMYFUNCTION("""COMPUTED_VALUE"""),192.0) -> 192 | AP16: =IFERROR(__xludf.DUMMYFUNCTION("""COMPUTED_VALUE"""),"TOTAL") -> TOTAL | AQ16: =IFERROR(__xludf.DUMMYFUNCTION("""COMPUTED_VALUE"""),5000.0) -> 5000 | AR16: =IFERROR(__xludf.DUMMYFUNCTION("""COMPUTED_VALUE"""),132.0) -> 132 | AS16: =IFERROR(__xludf.DUMMYFUNCTION("""COMPUTED_VALUE"""),201.0) -> 201 | AT16: =IFERROR(__xludf.DUMMYFUNCTION("""COMPUTED_VALUE"""),"TOTAL") -> TOTAL | AU16: =IFERROR(__xludf.DUMMYFUNCTION("""COMPUTED_VALUE"""),6000.0) -> 6000 | AV16: =IFERROR(__xludf.DUMMYFUNCTION("""COMPUTED_VALUE"""),110.0) -> 110 | AW16: =IFERROR(__xludf.DUMMYFUNCTION("""COMPUTED_VALUE"""),171.0) -> 171 | AX16: =IFERROR(__xludf.DUMMYFUNCTION("""COMPUTED_VALUE"""),"TOTAL") -> TOTAL | AY16: =IFERROR(__xludf.DUMMYFUNCTION("""COMPUTED_VALUE"""),36000.0) -> 36000 | AZ16: =IFERROR(__xludf.DUMMYFUNCTION("""COMPUTED_VALUE"""),147.0) -> 147 | BA16: =IFERROR(__xludf.DUMMYFUNCTION("""COMPUTED_VALUE"""),236.0) -> 236 | BB16: =IFERROR(__xludf.DUMMYFUNCTION("""COMPUTED_VALUE"""),"TOTAL") -> TOTAL | BC16: =IFERROR(__xludf.DUMMYFUNCTION("""COMPUTED_VALUE"""),12000.0) -> 12000 | BD16: =IFERROR(__xludf.DUMMYFUNCTION("""COMPUTED_VALUE"""),155.0) -> 155 | BE16: =IFERROR(__xludf.DUMMYFUNCTION("""COMPUTED_VALUE"""),310.0) -> 310 | BF16: =IFERROR(__xludf.DUMMYFUNCTION("""COMPUTED_VALUE"""),"TOTAL") -> TOTAL
C17: =IFERROR(__xludf.DUMMYFUNCTION("""COMPUTED_VALUE"""),"打電数") -> 打電数 | D17: =IFERROR(__xludf.DUMMYFUNCTION("""COMPUTED_VALUE"""),"着電数") -> 着電数 | E17: =IFERROR(__xludf.DUMMYFUNCTION("""COMPUTED_VALUE"""),"新規信用枠") -> 新規信用枠 | G17: =IFERROR(__xludf.DUMMYFUNCTION("""COMPUTED_VALUE"""),"打電数") -> 打電数 | H17: =IFERROR(__xludf.DUMMYFUNCTION("""COMPUTED_VALUE"""),"着電数") -> 着電数 | I17: =IFERROR(__xludf.DUMMYFUNCTION("""COMPUTED_VALUE"""),"SMS送信数") -> SMS送信数 | K17: =IFERROR(__xludf.DUMMYFUNCTION("""COMPUTED_VALUE"""),"打電数") -> 打電数 | L17: =IFERROR(__xludf.DUMMYFUNCTION("""COMPUTED_VALUE"""),"着電数") -> 着電数 | M17: =IFERROR(__xludf.DUMMYFUNCTION("""COMPUTED_VALUE"""),"新規信用枠") -> 新規信用枠 | O17: =IFERROR(__xludf.DUMMYFUNCTION("""COMPUTED_VALUE"""),"打電数") -> 打電数 | P17: =IFERROR(__xludf.DUMMYFUNCTION("""COMPUTED_VALUE"""),"着電数") -> 着電数 | Q17: =IFERROR(__xludf.DUMMYFUNCTION("""COMPUTED_VALUE"""),"新規信用枠") -> 新規信用枠 | S17: =IFERROR(__xludf.DUMMYFUNCTION("""COMPUTED_VALUE"""),"打電数") -> 打電数 | T17: =IFERROR(__xludf.DUMMYFUNCTION("""COMPUTED_VALUE"""),"着電数") -> 着電数 | U17: =IFERROR(__xludf.DUMMYFUNCTION("""COMPUTED_VALUE"""),"新規信用枠") -> 新規信用枠 | W17: =IFERROR(__xludf.DUMMYFUNCTION("""COMPUTED_VALUE"""),"打電数") -> 打電数 | X17: =IFERROR(__xludf.DUMMYFUNCTION("""COMPUTED_VALUE"""),"着電数") -> 着電数 | Y17: =IFERROR(__xludf.DUMMYFUNCTION("""COMPUTED_VALUE"""),"新規信用枠") -> 新規信用枠 | AA17: =IFERROR(__xludf.DUMMYFUNCTION("""COMPUTED_VALUE"""),"打電数") -> 打電数 | AB17: =IFERROR(__xludf.DUMMYFUNCTION("""COMPUTED_VALUE"""),"着電数") -> 着電数 | AC17: =IFERROR(__xludf.DUMMYFUNCTION("""COMPUTED_VALUE"""),"新規信用枠") -> 新規信用枠 | AE17: =IFERROR(__xludf.DUMMYFUNCTION("""COMPUTED_VALUE"""),"打電数") -> 打電数 | AF17: =IFERROR(__xludf.DUMMYFUNCTION("""COMPUTED_VALUE"""),"着電数") -> 着電数 | AG17: =IFERROR(__xludf.DUMMYFUNCTION("""COMPUTED_VALUE"""),"新規信用枠") -> 新規信用枠 | AI17: =IFERROR(__xludf.DUMMYFUNCTION("""COMPUTED_VALUE"""),"打電数") -> 打電数 | AJ17: =IFERROR(__xludf.DUMMYFUNCTION("""COMPUTED_VALUE"""),"着電数") -> 着電数 | AK17: =IFERROR(__xludf.DUMMYFUNCTION("""COMPUTED_VALUE"""),"新規信用枠") -> 新規信用枠 | AM17: =IFERROR(__xludf.DUMMYFUNCTION("""COMPUTED_VALUE"""),"打電数") -> 打電数 | AN17: =IFERROR(__xludf.DUMMYFUNCTION("""COMPUTED_VALUE"""),"着電数") -> 着電数 | AO17: =IFERROR(__xludf.DUMMYFUNCTION("""COMPUTED_VALUE"""),"新規信用枠") -> 新規信用枠 | AQ17: =IFERROR(__xludf.DUMMYFUNCTION("""COMPUTED_VALUE"""),"打電数") -> 打電数 | AR17: =IFERROR(__xludf.DUMMYFUNCTION("""COMPUTED_VALUE"""),"着電数") -> 着電数 | AS17: =IFERROR(__xludf.DUMMYFUNCTION("""COMPUTED_VALUE"""),"新規信用枠") -> 新規信用枠 | AU17: =IFERROR(__xludf.DUMMYFUNCTION("""COMPUTED_VALUE"""),"打電数") -> 打電数 | AV17: =IFERROR(__xludf.DUMMYFUNCTION("""COMPUTED_VALUE"""),"着電数") -> 着電数 | AW17: =IFERROR(__xludf.DUMMYFUNCTION("""COMPUTED_VALUE"""),"新規信用枠") -> 新規信用枠 | AY17: =IFERROR(__xludf.DUMMYFUNCTION("""COMPUTED_VALUE"""),"打電数") -> 打電数 | AZ17: =IFERROR(__xludf.DUMMYFUNCTION("""COMPUTED_VALUE"""),"着電数") -> 着電数 | BA17: =IFERROR(__xludf.DUMMYFUNCTION("""COMPUTED_VALUE"""),"新規信用枠") -> 新規信用枠 | BC17: =IFERROR(__xludf.DUMMYFUNCTION("""COMPUTED_VALUE"""),"打電数") -> 打電数 | BD17: =IFERROR(__xludf.DUMMYFUNCTION("""COMPUTED_VALUE"""),"着電数") -> 着電数 | BE17: =IFERROR(__xludf.DUMMYFUNCTION("""COMPUTED_VALUE"""),"新規信用枠") -> 新規信用枠
B18: =IFERROR(__xludf.DUMMYFUNCTION("""COMPUTED_VALUE"""),"リストC") -> リストC | C18: =IFERROR(__xludf.DUMMYFUNCTION("""COMPUTED_VALUE"""),1977.0) -> 1977 | D18: =IFERROR(__xludf.DUMMYFUNCTION("""COMPUTED_VALUE"""),228.0) -> 228 | E18: =IFERROR(__xludf.DUMMYFUNCTION("""COMPUTED_VALUE"""),0.0) -> 0 | F18: =IFERROR(__xludf.DUMMYFUNCTION("""COMPUTED_VALUE"""),"リストC") -> リストC | G18: =IFERROR(__xludf.DUMMYFUNCTION("""COMPUTED_VALUE"""),4822.0) -> 4822 | H18: =IFERROR(__xludf.DUMMYFUNCTION("""COMPUTED_VALUE"""),793.0) -> 793 | I18: =IFERROR(__xludf.DUMMYFUNCTION("""COMPUTED_VALUE"""),185.0) -> 185 | J18: =IFERROR(__xludf.DUMMYFUNCTION("""COMPUTED_VALUE"""),"リストC") -> リストC | K18: =IFERROR(__xludf.DUMMYFUNCTION("""COMPUTED_VALUE"""),2741.0) -> 2741 | L18: =IFERROR(__xludf.DUMMYFUNCTION("""COMPUTED_VALUE"""),351.0) -> 351 | M18: =IFERROR(__xludf.DUMMYFUNCTION("""COMPUTED_VALUE"""),580000.0) -> 580000 | N18: =IFERROR(__xludf.DUMMYFUNCTION("""COMPUTED_VALUE"""),"リストC") -> リストC | O18: =IFERROR(__xludf.DUMMYFUNCTION("""COMPUTED_VALUE"""),0.0) -> 0 | P18: =IFERROR(__xludf.DUMMYFUNCTION("""COMPUTED_VALUE"""),1100.0) -> 1100 | Q18: =IFERROR(__xludf.DUMMYFUNCTION("""COMPUTED_VALUE"""),30000.0) -> 30000 | R18: =IFERROR(__xludf.DUMMYFUNCTION("""COMPUTED_VALUE"""),"リストC") -> リストC | S18: =IFERROR(__xludf.DUMMYFUNCTION("""COMPUTED_VALUE"""),17785.0) -> 17785 | T18: =IFERROR(__xludf.DUMMYFUNCTION("""COMPUTED_VALUE"""),1428.0) -> 1428 | U18: =IFERROR(__xludf.DUMMYFUNCTION("""COMPUTED_VALUE"""),0.0) -> 0 | V18: =IFERROR(__xludf.DUMMYFUNCTION("""COMPUTED_VALUE"""),"リストC") -> リストC | W18: =IFERROR(__xludf.DUMMYFUNCTION("""COMPUTED_VALUE"""),0.0) -> 0 | X18: =IFERROR(__xludf.DUMMYFUNCTION("""COMPUTED_VALUE"""),0.0) -> 0 | Y18: =IFERROR(__xludf.DUMMYFUNCTION("""COMPUTED_VALUE"""),0.0) -> 0 | Z18: =IFERROR(__xludf.DUMMYFUNCTION("""COMPUTED_VALUE"""),"リストC") -> リストC | AA18: =IFERROR(__xludf.DUMMYFUNCTION("""COMPUTED_VALUE"""),69766.0) -> 69766 | AB18: =IFERROR(__xludf.DUMMYFUNCTION("""COMPUTED_VALUE"""),2591.0) -> 2591 | AC18: =IFERROR(__xludf.DUMMYFUNCTION("""COMPUTED_VALUE"""),1320000.0) -> 1320000 | AD18: =IFERROR(__xludf.DUMMYFUNCTION("""COMPUTED_VALUE"""),"リストC") -> リストC | AE18: =IFERROR(__xludf.DUMMYFUNCTION("""COMPUTED_VALUE"""),8144.0) -> 8144 | AF18: =IFERROR(__xludf.DUMMYFUNCTION("""COMPUTED_VALUE"""),295.0) -> 295 | AG18: =IFERROR(__xludf.DUMMYFUNCTION("""COMPUTED_VALUE"""),730000.0) -> 730000 | AH18: =IFERROR(__xludf.DUMMYFUNCTION("""COMPUTED_VALUE"""),"リストC") -> リストC | AI18: =IFERROR(__xludf.DUMMYFUNCTION("""COMPUTED_VALUE"""),0.0) -> 0 | AJ18: =IFERROR(__xludf.DUMMYFUNCTION("""COMPUTED_VALUE"""),0.0) -> 0 | AK18: =IFERROR(__xludf.DUMMYFUNCTION("""COMPUTED_VALUE"""),0.0) -> 0 | AL18: =IFERROR(__xludf.DUMMYFUNCTION("""COMPUTED_VALUE"""),"リストC") -> リストC | AM18: =IFERROR(__xludf.DUMMYFUNCTION("""COMPUTED_VALUE"""),0.0) -> 0 | AN18: =IFERROR(__xludf.DUMMYFUNCTION("""COMPUTED_VALUE"""),0.0) -> 0 | AO18: =IFERROR(__xludf.DUMMYFUNCTION("""COMPUTED_VALUE"""),0.0) -> 0 | AP18: =IFERROR(__xludf.DUMMYFUNCTION("""COMPUTED_VALUE"""),"リストC") -> リストC | AQ18: =IFERROR(__xludf.DUMMYFUNCTION("""COMPUTED_VALUE"""),0.0) -> 0 | AR18: =IFERROR(__xludf.DUMMYFUNCTION("""COMPUTED_VALUE"""),0.0) -> 0 | AS18: =IFERROR(__xludf.DUMMYFUNCTION("""COMPUTED_VALUE"""),0.0) -> 0 | AT18: =IFERROR(__xludf.DUMMYFUNCTION("""COMPUTED_VALUE"""),"リストC") -> リストC | AU18: =IFERROR(__xludf.DUMMYFUNCTION("""COMPUTED_VALUE"""),0.0) -> 0 | AV18: =IFERROR(__xludf.DUMMYFUNCTION("""COMPUTED_VALUE"""),0.0) -> 0 | AW18: =IFERROR(__xludf.DUMMYFUNCTION("""COMPUTED_VALUE"""),0.0) -> 0 | AX18: =IFERROR(__xludf.DUMMYFUNCTION("""COMPUTED_VALUE"""),"リストC") -> リストC | AY18: =IFERROR(__xludf.DUMMYFUNCTION("""COMPUTED_VALUE"""),0.0) -> 0 | AZ18: =IFERROR(__xludf.DUMMYFUNCTION("""COMPUTED_VALUE"""),0.0) -> 0 | BA18: =IFERROR(__xludf.DUMMYFUNCTION("""COMPUTED_VALUE"""),0.0) -> 0 | BB18: =IFERROR(__xludf.DUMMYFUNCTION("""COMPUTED_VALUE"""),"リストC") -> リストC | BC18: =IFERROR(__xludf.DUMMYFUNCTION("""COMPUTED_VALUE"""),0.0) -> 0 | BD18: =IFERROR(__xludf.DUMMYFUNCTION("""COMPUTED_VALUE"""),0.0) -> 0 | BE18: =IFERROR(__xludf.DUMMYFUNCTION("""COMPUTED_VALUE"""),0.0) -> 0 | BF18: =IFERROR(__xludf.DUMMYFUNCTION("""COMPUTED_VALUE"""),"リストC") -> リストC
B19: =IFERROR(__xludf.DUMMYFUNCTION("""COMPUTED_VALUE"""),"リストBE") -> リストBE | C19: =IFERROR(__xludf.DUMMYFUNCTION("""COMPUTED_VALUE"""),1415.0) -> 1415 | D19: =IFERROR(__xludf.DUMMYFUNCTION("""COMPUTED_VALUE"""),171.0) -> 171 | E19: =IFERROR(__xludf.DUMMYFUNCTION("""COMPUTED_VALUE"""),0.0) -> 0 | F19: =IFERROR(__xludf.DUMMYFUNCTION("""COMPUTED_VALUE"""),"リストBE") -> リストBE | G19: =IFERROR(__xludf.DUMMYFUNCTION("""COMPUTED_VALUE"""),0.0) -> 0 | H19: =IFERROR(__xludf.DUMMYFUNCTION("""COMPUTED_VALUE"""),0.0) -> 0 | I19: =IFERROR(__xludf.DUMMYFUNCTION("""COMPUTED_VALUE"""),0.0) -> 0 | J19: =IFERROR(__xludf.DUMMYFUNCTION("""COMPUTED_VALUE"""),"リストBE") -> リストBE | K19: =IFERROR(__xludf.DUMMYFUNCTION("""COMPUTED_VALUE"""),0.0) -> 0 | L19: =IFERROR(__xludf.DUMMYFUNCTION("""COMPUTED_VALUE"""),0.0) -> 0 | M19: =IFERROR(__xludf.DUMMYFUNCTION("""COMPUTED_VALUE"""),0.0) -> 0 | N19: =IFERROR(__xludf.DUMMYFUNCTION("""COMPUTED_VALUE"""),"リストBE") -> リストBE | O19: =IFERROR(__xludf.DUMMYFUNCTION("""COMPUTED_VALUE"""),0.0) -> 0 | P19: =IFERROR(__xludf.DUMMYFUNCTION("""COMPUTED_VALUE"""),0.0) -> 0 | Q19: =IFERROR(__xludf.DUMMYFUNCTION("""COMPUTED_VALUE"""),0.0) -> 0 | R19: =IFERROR(__xludf.DUMMYFUNCTION("""COMPUTED_VALUE"""),"リストBE") -> リストBE | S19: =IFERROR(__xludf.DUMMYFUNCTION("""COMPUTED_VALUE"""),0.0) -> 0 | T19: =IFERROR(__xludf.DUMMYFUNCTION("""COMPUTED_VALUE"""),0.0) -> 0 | U19: =IFERROR(__xludf.DUMMYFUNCTION("""COMPUTED_VALUE"""),0.0) -> 0 | V19: =IFERROR(__xludf.DUMMYFUNCTION("""COMPUTED_VALUE"""),"リストBE") -> リストBE | W19: =IFERROR(__xludf.DUMMYFUNCTION("""COMPUTED_VALUE"""),0.0) -> 0 | X19: =IFERROR(__xludf.DUMMYFUNCTION("""COMPUTED_VALUE"""),0.0) -> 0 | Y19: =IFERROR(__xludf.DUMMYFUNCTION("""COMPUTED_VALUE"""),0.0) -> 0 | Z19: =IFERROR(__xludf.DUMMYFUNCTION("""COMPUTED_VALUE"""),"リストBE") -> リストBE | AA19: =IFERROR(__xludf.DUMMYFUNCTION("""COMPUTED_VALUE"""),0.0) -> 0 | AB19: =IFERROR(__xludf.DUMMYFUNCTION("""COMPUTED_VALUE"""),0.0) -> 0 | AC19: =IFERROR(__xludf.DUMMYFUNCTION("""COMPUTED_VALUE"""),0.0) -> 0 | AD19: =IFERROR(__xludf.DUMMYFUNCTION("""COMPUTED_VALUE"""),"リストBE") -> リストBE | AE19: =IFERROR(__xludf.DUMMYFUNCTION("""COMPUTED_VALUE"""),4388.0) -> 4388 | AF19: =IFERROR(__xludf.DUMMYFUNCTION("""COMPUTED_VALUE"""),368.0) -> 368 | AG19: =IFERROR(__xludf.DUMMYFUNCTION("""COMPUTED_VALUE"""),405000.0) -> 405000 | AH19: =IFERROR(__xludf.DUMMYFUNCTION("""COMPUTED_VALUE"""),"リストBE") -> リストBE | AI19: =IFERROR(__xludf.DUMMYFUNCTION("""COMPUTED_VALUE"""),0.0) -> 0 | AJ19: =IFERROR(__xludf.DUMMYFUNCTION("""COMPUTED_VALUE"""),0.0) -> 0 | AK19: =IFERROR(__xludf.DUMMYFUNCTION("""COMPUTED_VALUE"""),0.0) -> 0 | AL19: =IFERROR(__xludf.DUMMYFUNCTION("""COMPUTED_VALUE"""),"リストBE") -> リストBE | AM19: =IFERROR(__xludf.DUMMYFUNCTION("""COMPUTED_VALUE"""),2481.0) -> 2481 | AN19: =IFERROR(__xludf.DUMMYFUNCTION("""COMPUTED_VALUE"""),335.0) -> 335 | AO19: =IFERROR(__xludf.DUMMYFUNCTION("""COMPUTED_VALUE"""),260000.0) -> 260000 | AP19: =IFERROR(__xludf.DUMMYFUNCTION("""COMPUTED_VALUE"""),"リストBE") -> リストBE | AQ19: =IFERROR(__xludf.DUMMYFUNCTION("""COMPUTED_VALUE"""),0.0) -> 0 | AR19: =IFERROR(__xludf.DUMMYFUNCTION("""COMPUTED_VALUE"""),0.0) -> 0 | AS19: =IFERROR(__xludf.DUMMYFUNCTION("""COMPUTED_VALUE"""),0.0) -> 0 | AT19: =IFERROR(__xludf.DUMMYFUNCTION("""COMPUTED_VALUE"""),"リストBE") -> リストBE | AU19: =IFERROR(__xludf.DUMMYFUNCTION("""COMPUTED_VALUE"""),0.0) -> 0 | AV19: =IFERROR(__xludf.DUMMYFUNCTION("""COMPUTED_VALUE"""),0.0) -> 0 | AW19: =IFERROR(__xludf.DUMMYFUNCTION("""COMPUTED_VALUE"""),0.0) -> 0 | AX19: =IFERROR(__xludf.DUMMYFUNCTION("""COMPUTED_VALUE"""),"リストBE") -> リストBE | AY19: =IFERROR(__xludf.DUMMYFUNCTION("""COMPUTED_VALUE"""),0.0) -> 0 | AZ19: =IFERROR(__xludf.DUMMYFUNCTION("""COMPUTED_VALUE"""),0.0) -> 0 | BA19: =IFERROR(__xludf.DUMMYFUNCTION("""COMPUTED_VALUE"""),0.0) -> 0 | BB19: =IFERROR(__xludf.DUMMYFUNCTION("""COMPUTED_VALUE"""),"リストBE") -> リストBE | BC19: =IFERROR(__xludf.DUMMYFUNCTION("""COMPUTED_VALUE"""),0.0) -> 0 | BD19: =IFERROR(__xludf.DUMMYFUNCTION("""COMPUTED_VALUE"""),0.0) -> 0 | BE19: =IFERROR(__xludf.DUMMYFUNCTION("""COMPUTED_VALUE"""),0.0) -> 0 | BF19: =IFERROR(__xludf.DUMMYFUNCTION("""COMPUTED_VALUE"""),"リストBE") -> リストBE
B20: =IFERROR(__xludf.DUMMYFUNCTION("""COMPUTED_VALUE"""),"リストS") -> リストS | C20: =IFERROR(__xludf.DUMMYFUNCTION("""COMPUTED_VALUE"""),3511.0) -> 3511 | D20: =IFERROR(__xludf.DUMMYFUNCTION("""COMPUTED_VALUE"""),380.0) -> 380 | E20: =IFERROR(__xludf.DUMMYFUNCTION("""COMPUTED_VALUE"""),0.0) -> 0 | F20: =IFERROR(__xludf.DUMMYFUNCTION("""COMPUTED_VALUE"""),"リストS") -> リストS | G20: =IFERROR(__xludf.DUMMYFUNCTION("""COMPUTED_VALUE"""),2740.0) -> 2740 | H20: =IFERROR(__xludf.DUMMYFUNCTION("""COMPUTED_VALUE"""),435.0) -> 435 | I20: =IFERROR(__xludf.DUMMYFUNCTION("""COMPUTED_VALUE"""),115.0) -> 115 | J20: =IFERROR(__xludf.DUMMYFUNCTION("""COMPUTED_VALUE"""),"リストS") -> リストS | K20: =IFERROR(__xludf.DUMMYFUNCTION("""COMPUTED_VALUE"""),3584.0) -> 3584 | L20: =IFERROR(__xludf.DUMMYFUNCTION("""COMPUTED_VALUE"""),723.0) -> 723 | M20: =IFERROR(__xludf.DUMMYFUNCTION("""COMPUTED_VALUE"""),2320000.0) -> 2320000 | N20: =IFERROR(__xludf.DUMMYFUNCTION("""COMPUTED_VALUE"""),"リストS") -> リストS | O20: =IFERROR(__xludf.DUMMYFUNCTION("""COMPUTED_VALUE"""),3585.0) -> 3585 | P20: =IFERROR(__xludf.DUMMYFUNCTION("""COMPUTED_VALUE"""),766.0) -> 766 | Q20: =IFERROR(__xludf.DUMMYFUNCTION("""COMPUTED_VALUE"""),0.0) -> 0 | R20: =IFERROR(__xludf.DUMMYFUNCTION("""COMPUTED_VALUE"""),"リストS") -> リストS | S20: =IFERROR(__xludf.DUMMYFUNCTION("""COMPUTED_VALUE"""),37758.0) -> 37758 | T20: =IFERROR(__xludf.DUMMYFUNCTION("""COMPUTED_VALUE"""),877.0) -> 877 | U20: =IFERROR(__xludf.DUMMYFUNCTION("""COMPUTED_VALUE"""),3140000.0) -> 3140000 | V20: =IFERROR(__xludf.DUMMYFUNCTION("""COMPUTED_VALUE"""),"リストS") -> リストS | W20: =IFERROR(__xludf.DUMMYFUNCTION("""COMPUTED_VALUE"""),82653.0) -> 82653 | X20: =IFERROR(__xludf.DUMMYFUNCTION("""COMPUTED_VALUE"""),3008.0) -> 3008 | Y20: =IFERROR(__xludf.DUMMYFUNCTION("""COMPUTED_VALUE"""),3140000.0) -> 3140000 | Z20: =IFERROR(__xludf.DUMMYFUNCTION("""COMPUTED_VALUE"""),"リストS") -> リストS | AA20: =IFERROR(__xludf.DUMMYFUNCTION("""COMPUTED_VALUE"""),63061.0) -> 63061 | AB20: =IFERROR(__xludf.DUMMYFUNCTION("""COMPUTED_VALUE"""),1730.0) -> 1730 | AC20: =IFERROR(__xludf.DUMMYFUNCTION("""COMPUTED_VALUE"""),1590000.0) -> 1590000 | AD20: =IFERROR(__xludf.DUMMYFUNCTION("""COMPUTED_VALUE"""),"リストS") -> リストS | AE20: =IFERROR(__xludf.DUMMYFUNCTION("""COMPUTED_VALUE"""),43496.0) -> 43496 | AF20: =IFERROR(__xludf.DUMMYFUNCTION("""COMPUTED_VALUE"""),1943.0) -> 1943 | AG20: =IFERROR(__xludf.DUMMYFUNCTION("""COMPUTED_VALUE"""),4585000.0) -> 4585000 | AH20: =IFERROR(__xludf.DUMMYFUNCTION("""COMPUTED_VALUE"""),"リストS") -> リストS | AI20: =IFERROR(__xludf.DUMMYFUNCTION("""COMPUTED_VALUE"""),45131.0) -> 45131 | AJ20: =IFERROR(__xludf.DUMMYFUNCTION("""COMPUTED_VALUE"""),2580.0) -> 2580 | AK20: =IFERROR(__xludf.DUMMYFUNCTION("""COMPUTED_VALUE"""),7043000.0) -> 7043000 | AL20: =IFERROR(__xludf.DUMMYFUNCTION("""COMPUTED_VALUE"""),"リストS") -> リストS | AM20: =IFERROR(__xludf.DUMMYFUNCTION("""COMPUTED_VALUE"""),30725.0) -> 30725 | AN20: =IFERROR(__xludf.DUMMYFUNCTION("""COMPUTED_VALUE"""),2894.0) -> 2894 | AO20: =IFERROR(__xludf.DUMMYFUNCTION("""COMPUTED_VALUE"""),5670000.0) -> 5670000 | AP20: =IFERROR(__xludf.DUMMYFUNCTION("""COMPUTED_VALUE"""),"リストS") -> リストS | AQ20: =IFERROR(__xludf.DUMMYFUNCTION("""COMPUTED_VALUE"""),14550.0) -> 14550 | AR20: =IFERROR(__xludf.DUMMYFUNCTION("""COMPUTED_VALUE"""),1687.0) -> 1687 | AS20: =IFERROR(__xludf.DUMMYFUNCTION("""COMPUTED_VALUE"""),3810000.0) -> 3810000 | AT20: =IFERROR(__xludf.DUMMYFUNCTION("""COMPUTED_VALUE"""),"リストS") -> リストS | AU20: =IFERROR(__xludf.DUMMYFUNCTION("""COMPUTED_VALUE"""),13305.0) -> 13305 | AV20: =IFERROR(__xludf.DUMMYFUNCTION("""COMPUTED_VALUE"""),1365.0) -> 1365 | AW20: =IFERROR(__xludf.DUMMYFUNCTION("""COMPUTED_VALUE"""),1340000.0) -> 1340000 | AX20: =IFERROR(__xludf.DUMMYFUNCTION("""COMPUTED_VALUE"""),"リストS") -> リストS | AY20: =IFERROR(__xludf.DUMMYFUNCTION("""COMPUTED_VALUE"""),20729.0) -> 20729 | AZ20: =IFERROR(__xludf.DUMMYFUNCTION("""COMPUTED_VALUE"""),1962.0) -> 1962 | BA20: =IFERROR(__xludf.DUMMYFUNCTION("""COMPUTED_VALUE"""),4090000.0) -> 4090000 | BB20: =IFERROR(__xludf.DUMMYFUNCTION("""COMPUTED_VALUE"""),"リストS") -> リストS | BC20: =IFERROR(__xludf.DUMMYFUNCTION("""COMPUTED_VALUE"""),20729.0) -> 20729 | BD20: =IFERROR(__xludf.DUMMYFUNCTION("""COMPUTED_VALUE"""),1962.0) -> 1962 | BE20: =IFERROR(__xludf.DUMMYFUNCTION("""COMPUTED_VALUE"""),4090000.0) -> 4090000 | BF20: =IFERROR(__xludf.DUMMYFUNCTION("""COMPUTED_VALUE"""),"リストS") -> リストS
B21: =IFERROR(__xludf.DUMMYFUNCTION("""COMPUTED_VALUE"""),"リストE") -> リストE | C21: =IFERROR(__xludf.DUMMYFUNCTION("""COMPUTED_VALUE"""),2803.0) -> 2803 | D21: =IFERROR(__xludf.DUMMYFUNCTION("""COMPUTED_VALUE"""),337.0) -> 337 | E21: =IFERROR(__xludf.DUMMYFUNCTION("""COMPUTED_VALUE"""),0.0) -> 0 | F21: =IFERROR(__xludf.DUMMYFUNCTION("""COMPUTED_VALUE"""),"リストE") -> リストE | G21: =IFERROR(__xludf.DUMMYFUNCTION("""COMPUTED_VALUE"""),1966.0) -> 1966 | H21: =IFERROR(__xludf.DUMMYFUNCTION("""COMPUTED_VALUE"""),300.0) -> 300 | I21: =IFERROR(__xludf.DUMMYFUNCTION("""COMPUTED_VALUE"""),82.0) -> 82 | J21: =IFERROR(__xludf.DUMMYFUNCTION("""COMPUTED_VALUE"""),"リストE") -> リストE | K21: =IFERROR(__xludf.DUMMYFUNCTION("""COMPUTED_VALUE"""),2477.0) -> 2477 | L21: =IFERROR(__xludf.DUMMYFUNCTION("""COMPUTED_VALUE"""),374.0) -> 374 | M21: =IFERROR(__xludf.DUMMYFUNCTION("""COMPUTED_VALUE"""),2630000.0) -> 2630000 | N21: =IFERROR(__xludf.DUMMYFUNCTION("""COMPUTED_VALUE"""),"リストE") -> リストE | O21: =IFERROR(__xludf.DUMMYFUNCTION("""COMPUTED_VALUE"""),6244.0) -> 6244 | P21: =IFERROR(__xludf.DUMMYFUNCTION("""COMPUTED_VALUE"""),821.0) -> 821 | Q21: =IFERROR(__xludf.DUMMYFUNCTION("""COMPUTED_VALUE"""),320000.0) -> 320000 | R21: =IFERROR(__xludf.DUMMYFUNCTION("""COMPUTED_VALUE"""),"リストE") -> リストE | S21: =IFERROR(__xludf.DUMMYFUNCTION("""COMPUTED_VALUE"""),44468.0) -> 44468 | T21: =IFERROR(__xludf.DUMMYFUNCTION("""COMPUTED_VALUE"""),1495.0) -> 1495 | U21: =IFERROR(__xludf.DUMMYFUNCTION("""COMPUTED_VALUE"""),3980000.0) -> 3980000 | V21: =IFERROR(__xludf.DUMMYFUNCTION("""COMPUTED_VALUE"""),"リストE") -> リストE | W21: =IFERROR(__xludf.DUMMYFUNCTION("""COMPUTED_VALUE"""),107566.0) -> 107566 | X21: =IFERROR(__xludf.DUMMYFUNCTION("""COMPUTED_VALUE"""),4794.0) -> 4794 | Y21: =IFERROR(__xludf.DUMMYFUNCTION("""COMPUTED_VALUE"""),3980000.0) -> 3980000 | Z21: =IFERROR(__xludf.DUMMYFUNCTION("""COMPUTED_VALUE"""),"リストE") -> リストE | AA21: =IFERROR(__xludf.DUMMYFUNCTION("""COMPUTED_VALUE"""),37759.0) -> 37759 | AB21: =IFERROR(__xludf.DUMMYFUNCTION("""COMPUTED_VALUE"""),1792.0) -> 1792 | AC21: =IFERROR(__xludf.DUMMYFUNCTION("""COMPUTED_VALUE"""),2150000.0) -> 2150000 | AD21: =IFERROR(__xludf.DUMMYFUNCTION("""COMPUTED_VALUE"""),"リストE") -> リストE | AE21: =IFERROR(__xludf.DUMMYFUNCTION("""COMPUTED_VALUE"""),39753.0) -> 39753 | AF21: =IFERROR(__xludf.DUMMYFUNCTION("""COMPUTED_VALUE"""),1882.0) -> 1882 | AG21: =IFERROR(__xludf.DUMMYFUNCTION("""COMPUTED_VALUE"""),6030000.0) -> 6030000 | AH21: =IFERROR(__xludf.DUMMYFUNCTION("""COMPUTED_VALUE"""),"リストE") -> リストE | AI21: =IFERROR(__xludf.DUMMYFUNCTION("""COMPUTED_VALUE"""),18692.0) -> 18692 | AJ21: =IFERROR(__xludf.DUMMYFUNCTION("""COMPUTED_VALUE"""),1460.0) -> 1460 | AK21: =IFERROR(__xludf.DUMMYFUNCTION("""COMPUTED_VALUE"""),2860000.0) -> 2860000 | AL21: =IFERROR(__xludf.DUMMYFUNCTION("""COMPUTED_VALUE"""),"リストE") -> リストE | AM21: =IFERROR(__xludf.DUMMYFUNCTION("""COMPUTED_VALUE"""),13043.0) -> 13043 | AN21: =IFERROR(__xludf.DUMMYFUNCTION("""COMPUTED_VALUE"""),1508.0) -> 1508 | AO21: =IFERROR(__xludf.DUMMYFUNCTION("""COMPUTED_VALUE"""),1200000.0) -> 1200000 | AP21: =IFERROR(__xludf.DUMMYFUNCTION("""COMPUTED_VALUE"""),"リストE") -> リストE | AQ21: =IFERROR(__xludf.DUMMYFUNCTION("""COMPUTED_VALUE"""),14878.0) -> 14878 | AR21: =IFERROR(__xludf.DUMMYFUNCTION("""COMPUTED_VALUE"""),1805.0) -> 1805 | AS21: =IFERROR(__xludf.DUMMYFUNCTION("""COMPUTED_VALUE"""),6150000.0) -> 6150000 | AT21: =IFERROR(__xludf.DUMMYFUNCTION("""COMPUTED_VALUE"""),"リストE") -> リストE | AU21: =IFERROR(__xludf.DUMMYFUNCTION("""COMPUTED_VALUE"""),23381.0) -> 23381 | AV21: =IFERROR(__xludf.DUMMYFUNCTION("""COMPUTED_VALUE"""),2663.0) -> 2663 | AW21: =IFERROR(__xludf.DUMMYFUNCTION("""COMPUTED_VALUE"""),7070000.0) -> 7070000 | AX21: =IFERROR(__xludf.DUMMYFUNCTION("""COMPUTED_VALUE"""),"リストE") -> リストE | AY21: =IFERROR(__xludf.DUMMYFUNCTION("""COMPUTED_VALUE"""),20220.0) -> 20220 | AZ21: =IFERROR(__xludf.DUMMYFUNCTION("""COMPUTED_VALUE"""),2883.0) -> 2883 | BA21: =IFERROR(__xludf.DUMMYFUNCTION("""COMPUTED_VALUE"""),7540000.0) -> 7540000 | BB21: =IFERROR(__xludf.DUMMYFUNCTION("""COMPUTED_VALUE"""),"リストE") -> リストE | BC21: =IFERROR(__xludf.DUMMYFUNCTION("""COMPUTED_VALUE"""),20220.0) -> 20220 | BD21: =IFERROR(__xludf.DUMMYFUNCTION("""COMPUTED_VALUE"""),2883.0) -> 2883 | BE21: =IFERROR(__xludf.DUMMYFUNCTION("""COMPUTED_VALUE"""),7540000.0) -> 7540000 | BF21: =IFERROR(__xludf.DUMMYFUNCTION("""COMPUTED_VALUE"""),"リストE") -> リストE
B22: =IFERROR(__xludf.DUMMYFUNCTION("""COMPUTED_VALUE"""),"TOTAL") -> TOTAL | C22: =IFERROR(__xludf.DUMMYFUNCTION("""COMPUTED_VALUE"""),9706.0) -> 9706 | D22: =IFERROR(__xludf.DUMMYFUNCTION("""COMPUTED_VALUE"""),1116.0) -> 1116 | E22: =IFERROR(__xludf.DUMMYFUNCTION("""COMPUTED_VALUE"""),0.0) -> 0 | F22: =IFERROR(__xludf.DUMMYFUNCTION("""COMPUTED_VALUE"""),"TOTAL") -> TOTAL | G22: =IFERROR(__xludf.DUMMYFUNCTION("""COMPUTED_VALUE"""),9528.0) -> 9528 | H22: =IFERROR(__xludf.DUMMYFUNCTION("""COMPUTED_VALUE"""),1528.0) -> 1528 | I22: =IFERROR(__xludf.DUMMYFUNCTION("""COMPUTED_VALUE"""),382.0) -> 382 | J22: =IFERROR(__xludf.DUMMYFUNCTION("""COMPUTED_VALUE"""),"TOTAL") -> TOTAL | K22: =IFERROR(__xludf.DUMMYFUNCTION("""COMPUTED_VALUE"""),8802.0) -> 8802 | L22: =IFERROR(__xludf.DUMMYFUNCTION("""COMPUTED_VALUE"""),1448.0) -> 1448 | M22: =IFERROR(__xludf.DUMMYFUNCTION("""COMPUTED_VALUE"""),5530000.0) -> 5530000 | N22: =IFERROR(__xludf.DUMMYFUNCTION("""COMPUTED_VALUE"""),"TOTAL") -> TOTAL | O22: =IFERROR(__xludf.DUMMYFUNCTION("""COMPUTED_VALUE"""),9829.0) -> 9829 | P22: =IFERROR(__xludf.DUMMYFUNCTION("""COMPUTED_VALUE"""),2687.0) -> 2687 | Q22: =IFERROR(__xludf.DUMMYFUNCTION("""COMPUTED_VALUE"""),350000.0) -> 350000 | R22: =IFERROR(__xludf.DUMMYFUNCTION("""COMPUTED_VALUE"""),"TOTAL") -> TOTAL | S22: =IFERROR(__xludf.DUMMYFUNCTION("""COMPUTED_VALUE"""),100011.0) -> 100011 | T22: =IFERROR(__xludf.DUMMYFUNCTION("""COMPUTED_VALUE"""),3800.0) -> 3800 | U22: =IFERROR(__xludf.DUMMYFUNCTION("""COMPUTED_VALUE"""),7120000.0) -> 7120000 | V22: =IFERROR(__xludf.DUMMYFUNCTION("""COMPUTED_VALUE"""),"TOTAL") -> TOTAL | W22: =IFERROR(__xludf.DUMMYFUNCTION("""COMPUTED_VALUE"""),190219.0) -> 190219 | X22: =IFERROR(__xludf.DUMMYFUNCTION("""COMPUTED_VALUE"""),7802.0) -> 7802 | Y22: =IFERROR(__xludf.DUMMYFUNCTION("""COMPUTED_VALUE"""),7120000.0) -> 7120000 | Z22: =IFERROR(__xludf.DUMMYFUNCTION("""COMPUTED_VALUE"""),"TOTAL") -> TOTAL | AA22: =IFERROR(__xludf.DUMMYFUNCTION("""COMPUTED_VALUE"""),170586.0) -> 170586 | AB22: =IFERROR(__xludf.DUMMYFUNCTION("""COMPUTED_VALUE"""),6113.0) -> 6113 | AC22: =IFERROR(__xludf.DUMMYFUNCTION("""COMPUTED_VALUE"""),5060000.0) -> 5060000 | AD22: =IFERROR(__xludf.DUMMYFUNCTION("""COMPUTED_VALUE"""),"TOTAL") -> TOTAL | AE22: =IFERROR(__xludf.DUMMYFUNCTION("""COMPUTED_VALUE"""),95781.0) -> 95781 | AF22: =IFERROR(__xludf.DUMMYFUNCTION("""COMPUTED_VALUE"""),4488.0) -> 4488 | AG22: =IFERROR(__xludf.DUMMYFUNCTION("""COMPUTED_VALUE"""),1.175E7) -> 11750000 | AH22: =IFERROR(__xludf.DUMMYFUNCTION("""COMPUTED_VALUE"""),"TOTAL") -> TOTAL | AI22: =IFERROR(__xludf.DUMMYFUNCTION("""COMPUTED_VALUE"""),63823.0) -> 63823 | AJ22: =IFERROR(__xludf.DUMMYFUNCTION("""COMPUTED_VALUE"""),4040.0) -> 4040 | AK22: =IFERROR(__xludf.DUMMYFUNCTION("""COMPUTED_VALUE"""),9903000.0) -> 9903000 | AL22: =IFERROR(__xludf.DUMMYFUNCTION("""COMPUTED_VALUE"""),"TOTAL") -> TOTAL | AM22: =IFERROR(__xludf.DUMMYFUNCTION("""COMPUTED_VALUE"""),46249.0) -> 46249 | AN22: =IFERROR(__xludf.DUMMYFUNCTION("""COMPUTED_VALUE"""),4737.0) -> 4737 | AO22: =IFERROR(__xludf.DUMMYFUNCTION("""COMPUTED_VALUE"""),7130000.0) -> 7130000 | AP22: =IFERROR(__xludf.DUMMYFUNCTION("""COMPUTED_VALUE"""),"TOTAL") -> TOTAL | AQ22: =IFERROR(__xludf.DUMMYFUNCTION("""COMPUTED_VALUE"""),29428.0) -> 29428 | AR22: =IFERROR(__xludf.DUMMYFUNCTION("""COMPUTED_VALUE"""),3492.0) -> 3492 | AS22: =IFERROR(__xludf.DUMMYFUNCTION("""COMPUTED_VALUE"""),9960000.0) -> 9960000 | AT22: =IFERROR(__xludf.DUMMYFUNCTION("""COMPUTED_VALUE"""),"TOTAL") -> TOTAL | AU22: =IFERROR(__xludf.DUMMYFUNCTION("""COMPUTED_VALUE"""),36686.0) -> 36686 | AV22: =IFERROR(__xludf.DUMMYFUNCTION("""COMPUTED_VALUE"""),4028.0) -> 4028 | AW22: =IFERROR(__xludf.DUMMYFUNCTION("""COMPUTED_VALUE"""),8410000.0) -> 8410000 | AX22: =IFERROR(__xludf.DUMMYFUNCTION("""COMPUTED_VALUE"""),"TOTAL") -> TOTAL | AY22: =IFERROR(__xludf.DUMMYFUNCTION("""COMPUTED_VALUE"""),40949.0) -> 40949 | AZ22: =IFERROR(__xludf.DUMMYFUNCTION("""COMPUTED_VALUE"""),4845.0) -> 4845 | BA22: =IFERROR(__xludf.DUMMYFUNCTION("""COMPUTED_VALUE"""),1.163E7) -> 11630000 | BB22: =IFERROR(__xludf.DUMMYFUNCTION("""COMPUTED_VALUE"""),"TOTAL") -> TOTAL | BC22: =IFERROR(__xludf.DUMMYFUNCTION("""COMPUTED_VALUE"""),40949.0) -> 40949 | BD22: =IFERROR(__xludf.DUMMYFUNCTION("""COMPUTED_VALUE"""),4845.0) -> 4845 | BE22: =IFERROR(__xludf.DUMMYFUNCTION("""COMPUTED_VALUE"""),1.163E7) -> 11630000 | BF22: =IFERROR(__xludf.DUMMYFUNCTION("""COMPUTED_VALUE"""),"TOTAL") -> TOTAL
C23: =IFERROR(__xludf.DUMMYFUNCTION("""COMPUTED_VALUE"""),"着電率") -> 着電率 | D23: =IFERROR(__xludf.DUMMYFUNCTION("""COMPUTED_VALUE"""),"LINE登録率") -> LINE登録率 | E23: =IFERROR(__xludf.DUMMYFUNCTION("""COMPUTED_VALUE"""),"アカウント作成率") -> アカウント作成率 | G23: =IFERROR(__xludf.DUMMYFUNCTION("""COMPUTED_VALUE"""),"着電率") -> 着電率 | H23: =IFERROR(__xludf.DUMMYFUNCTION("""COMPUTED_VALUE"""),"LINE登録率") -> LINE登録率 | I23: =IFERROR(__xludf.DUMMYFUNCTION("""COMPUTED_VALUE"""),"アカウント作成率") -> アカウント作成率 | K23: =IFERROR(__xludf.DUMMYFUNCTION("""COMPUTED_VALUE"""),"着電率") -> 着電率 | L23: =IFERROR(__xludf.DUMMYFUNCTION("""COMPUTED_VALUE"""),"LINE登録率") -> LINE登録率 | M23: =IFERROR(__xludf.DUMMYFUNCTION("""COMPUTED_VALUE"""),"アカウント作成率") -> アカウント作成率 | O23: =IFERROR(__xludf.DUMMYFUNCTION("""COMPUTED_VALUE"""),"着電率") -> 着電率 | P23: =IFERROR(__xludf.DUMMYFUNCTION("""COMPUTED_VALUE"""),"LINE登録率") -> LINE登録率 | Q23: =IFERROR(__xludf.DUMMYFUNCTION("""COMPUTED_VALUE"""),"アカウント作成率") -> アカウント作成率 | S23: =IFERROR(__xludf.DUMMYFUNCTION("""COMPUTED_VALUE"""),"着電率") -> 着電率 | T23: =IFERROR(__xludf.DUMMYFUNCTION("""COMPUTED_VALUE"""),"LINE登録率") -> LINE登録率 | U23: =IFERROR(__xludf.DUMMYFUNCTION("""COMPUTED_VALUE"""),"アカウント作成率") -> アカウント作成率 | W23: =IFERROR(__xludf.DUMMYFUNCTION("""COMPUTED_VALUE"""),"着電率") -> 着電率 | X23: =IFERROR(__xludf.DUMMYFUNCTION("""COMPUTED_VALUE"""),"LINE登録率") -> LINE登録率 | Y23: =IFERROR(__xludf.DUMMYFUNCTION("""COMPUTED_VALUE"""),"アカウント作成率") -> アカウント作成率 | AA23: =IFERROR(__xludf.DUMMYFUNCTION("""COMPUTED_VALUE"""),"着電率") -> 着電率 | AB23: =IFERROR(__xludf.DUMMYFUNCTION("""COMPUTED_VALUE"""),"LINE登録率") -> LINE登録率 | AC23: =IFERROR(__xludf.DUMMYFUNCTION("""COMPUTED_VALUE"""),"アカウント作成率") -> アカウント作成率 | AE23: =IFERROR(__xludf.DUMMYFUNCTION("""COMPUTED_VALUE"""),"着電率") -> 着電率 | AF23: =IFERROR(__xludf.DUMMYFUNCTION("""COMPUTED_VALUE"""),"LINE登録率") -> LINE登録率 | AG23: =IFERROR(__xludf.DUMMYFUNCTION("""COMPUTED_VALUE"""),"アカウント作成率") -> アカウント作成率 | AI23: =IFERROR(__xludf.DUMMYFUNCTION("""COMPUTED_VALUE"""),"着電率") -> 着電率 | AJ23: =IFERROR(__xludf.DUMMYFUNCTION("""COMPUTED_VALUE"""),"LINE登録率") -> LINE登録率 | AK23: =IFERROR(__xludf.DUMMYFUNCTION("""COMPUTED_VALUE"""),"アカウント作成率") -> アカウント作成率 | AM23: =IFERROR(__xludf.DUMMYFUNCTION("""COMPUTED_VALUE"""),"着電率") -> 着電率 | AN23: =IFERROR(__xludf.DUMMYFUNCTION("""COMPUTED_VALUE"""),"LINE登録率") -> LINE登録率 | AO23: =IFERROR(__xludf.DUMMYFUNCTION("""COMPUTED_VALUE"""),"アカウント作成率") -> アカウント作成率 | AQ23: =IFERROR(__xludf.DUMMYFUNCTION("""COMPUTED_VALUE"""),"着電率") -> 着電率 | AR23: =IFERROR(__xludf.DUMMYFUNCTION("""COMPUTED_VALUE"""),"LINE登録率") -> LINE登録率 | AS23: =IFERROR(__xludf.DUMMYFUNCTION("""COMPUTED_VALUE"""),"アカウント作成率") -> アカウント作成率 | AU23: =IFERROR(__xludf.DUMMYFUNCTION("""COMPUTED_VALUE"""),"着電率") -> 着電率 | AV23: =IFERROR(__xludf.DUMMYFUNCTION("""COMPUTED_VALUE"""),"LINE登録率") -> LINE登録率 | AW23: =IFERROR(__xludf.DUMMYFUNCTION("""COMPUTED_VALUE"""),"アカウント作成率") -> アカウント作成率 | AY23: =IFERROR(__xludf.DUMMYFUNCTION("""COMPUTED_VALUE"""),"着電率") -> 着電率 | AZ23: =IFERROR(__xludf.DUMMYFUNCTION("""COMPUTED_VALUE"""),"LINE登録率") -> LINE登録率 | BA23: =IFERROR(__xludf.DUMMYFUNCTION("""COMPUTED_VALUE"""),"アカウント作成率") -> アカウント作成率 | BC23: =IFERROR(__xludf.DUMMYFUNCTION("""COMPUTED_VALUE"""),"着電率") -> 着電率 | BD23: =IFERROR(__xludf.DUMMYFUNCTION("""COMPUTED_VALUE"""),"LINE登録率") -> LINE登録率 | BE23: =IFERROR(__xludf.DUMMYFUNCTION("""COMPUTED_VALUE"""),"アカウント作成率") -> アカウント作成率
B24: =IFERROR(__xludf.DUMMYFUNCTION("""COMPUTED_VALUE"""),"リストC") -> リストC | C24: =IFERROR(__xludf.DUMMYFUNCTION("""COMPUTED_VALUE"""),0.12319987581577085) -> 0.12319988 | D24: =IFERROR(__xludf.DUMMYFUNCTION("""COMPUTED_VALUE"""),0.1230581465063459) -> 0.12305815 | E24: =IFERROR(__xludf.DUMMYFUNCTION("""COMPUTED_VALUE"""),0.06634780211217799) -> 0.066347802 | F24: =IFERROR(__xludf.DUMMYFUNCTION("""COMPUTED_VALUE"""),"リストC") -> リストC | G24: =IFERROR(__xludf.DUMMYFUNCTION("""COMPUTED_VALUE"""),0.17914554609339672) -> 0.17914555 | H24: =IFERROR(__xludf.DUMMYFUNCTION("""COMPUTED_VALUE"""),0.0017177159255331335) -> 0.0017177159 | I24: =IFERROR(__xludf.DUMMYFUNCTION("""COMPUTED_VALUE"""),0.0015058040509998995) -> 0.0015058041 | J24: =IFERROR(__xludf.DUMMYFUNCTION("""COMPUTED_VALUE"""),"リストC") -> リストC | K24: =IFERROR(__xludf.DUMMYFUNCTION("""COMPUTED_VALUE"""),0.14220426163679312) -> 0.14220426 | L24: =IFERROR(__xludf.DUMMYFUNCTION("""COMPUTED_VALUE"""),0.0091847167562308) -> 0.0091847168 | M24: =IFERROR(__xludf.DUMMYFUNCTION("""COMPUTED_VALUE"""),0.008887453499291712) -> 0.0088874535 | N24: =IFERROR(__xludf.DUMMYFUNCTION("""COMPUTED_VALUE"""),"リストC") -> リストC | O24: =IFERROR(__xludf.DUMMYFUNCTION("""COMPUTED_VALUE"""),0.0) -> 0 | P24: =IFERROR(__xludf.DUMMYFUNCTION("""COMPUTED_VALUE"""),0.0) -> 0 | Q24: =IFERROR(__xludf.DUMMYFUNCTION("""COMPUTED_VALUE"""),0.0) -> 0 | R24: =IFERROR(__xludf.DUMMYFUNCTION("""COMPUTED_VALUE"""),"リストC") -> リストC | S24: =IFERROR(__xludf.DUMMYFUNCTION("""COMPUTED_VALUE"""),0.07063451078714285) -> 0.070634511 | T24: =IFERROR(__xludf.DUMMYFUNCTION("""COMPUTED_VALUE"""),7.839566169139106E-4) -> 0.00078395662 | U24: =IFERROR(__xludf.DUMMYFUNCTION("""COMPUTED_VALUE"""),6.793601205648369E-4) -> 0.00067936012 | V24: =IFERROR(__xludf.DUMMYFUNCTION("""COMPUTED_VALUE"""),"リストC") -> リストC | W24: =IFERROR(__xludf.DUMMYFUNCTION("""COMPUTED_VALUE"""),0.019646327767030382) -> 0.019646328 | X24: =IFERROR(__xludf.DUMMYFUNCTION("""COMPUTED_VALUE"""),5.846704052254974E-4) -> 0.00058467041 | Y24: =IFERROR(__xludf.DUMMYFUNCTION("""COMPUTED_VALUE"""),4.8626205209146076E-4) -> 0.00048626205 | Z24: =IFERROR(__xludf.DUMMYFUNCTION("""COMPUTED_VALUE"""),"リストC") -> リストC | AA24: =IFERROR(__xludf.DUMMYFUNCTION("""COMPUTED_VALUE"""),0.03530911208050261) -> 0.035309112 | AB24: =IFERROR(__xludf.DUMMYFUNCTION("""COMPUTED_VALUE"""),6.840404110814048E-4) -> 0.00068404041 | AC24: =IFERROR(__xludf.DUMMYFUNCTION("""COMPUTED_VALUE"""),5.307668051278695E-4) -> 0.00053076681 | AD24: =IFERROR(__xludf.DUMMYFUNCTION("""COMPUTED_VALUE"""),"リストC") -> リストC | AE24: =IFERROR(__xludf.DUMMYFUNCTION("""COMPUTED_VALUE"""),0.037447436978039865) -> 0.037447437 | AF24: =IFERROR(__xludf.DUMMYFUNCTION("""COMPUTED_VALUE"""),0.01648548894265388) -> 0.016485489 | AG24: =IFERROR(__xludf.DUMMYFUNCTION("""COMPUTED_VALUE"""),0.018975495508496868) -> 0.018975496 | AH24: =IFERROR(__xludf.DUMMYFUNCTION("""COMPUTED_VALUE"""),"リストC") -> リストC | AI24: =IFERROR(__xludf.DUMMYFUNCTION("""COMPUTED_VALUE"""),0.0) -> 0 | AJ24: =IFERROR(__xludf.DUMMYFUNCTION("""COMPUTED_VALUE"""),0.0) -> 0 | AK24: =IFERROR(__xludf.DUMMYFUNCTION("""COMPUTED_VALUE"""),0.0) -> 0 | AL24: =IFERROR(__xludf.DUMMYFUNCTION("""COMPUTED_VALUE"""),"リストC") -> リストC | AM24: =IFERROR(__xludf.DUMMYFUNCTION("""COMPUTED_VALUE"""),0.0) -> 0 | AN24: =IFERROR(__xludf.DUMMYFUNCTION("""COMPUTED_VALUE"""),0.0) -> 0 | AO24: =IFERROR(__xludf.DUMMYFUNCTION("""COMPUTED_VALUE"""),0.0) -> 0 | AP24: =IFERROR(__xludf.DUMMYFUNCTION("""COMPUTED_VALUE"""),"リストC") -> リストC | AQ24: =IFERROR(__xludf.DUMMYFUNCTION("""COMPUTED_VALUE"""),0.0) -> 0 | AR24: =IFERROR(__xludf.DUMMYFUNCTION("""COMPUTED_VALUE"""),0.0) -> 0 | AS24: =IFERROR(__xludf.DUMMYFUNCTION("""COMPUTED_VALUE"""),0.0) -> 0 | AT24: =IFERROR(__xludf.DUMMYFUNCTION("""COMPUTED_VALUE"""),"リストC") -> リストC | AU24: =IFERROR(__xludf.DUMMYFUNCTION("""COMPUTED_VALUE"""),0.0) -> 0 | AV24: =IFERROR(__xludf.DUMMYFUNCTION("""COMPUTED_VALUE"""),0.0) -> 0 | AW24: =IFERROR(__xludf.DUMMYFUNCTION("""COMPUTED_VALUE"""),0.0) -> 0 | AX24: =IFERROR(__xludf.DUMMYFUNCTION("""COMPUTED_VALUE"""),"リストC") -> リストC | AY24: =IFERROR(__xludf.DUMMYFUNCTION("""COMPUTED_VALUE"""),0.0) -> 0 | AZ24: =IFERROR(__xludf.DUMMYFUNCTION("""COMPUTED_VALUE"""),0.0) -> 0 | BA24: =IFERROR(__xludf.DUMMYFUNCTION("""COMPUTED_VALUE"""),0.0) -> 0 | BB24: =IFERROR(__xludf.DUMMYFUNCTION("""COMPUTED_VALUE"""),"リストC") -> リストC | BC24: =IFERROR(__xludf.DUMMYFUNCTION("""COMPUTED_VALUE"""),0.0) -> 0 | BD24: =IFERROR(__xludf.DUMMYFUNCTION("""COMPUTED_VALUE"""),0.0) -> 0 | BE24: =IFERROR(__xludf.DUMMYFUNCTION("""COMPUTED_VALUE"""),0.0) -> 0 | BF24: =IFERROR(__xludf.DUMMYFUNCTION("""COMPUTED_VALUE"""),"リストC") -> リストC
B25: =IFERROR(__xludf.DUMMYFUNCTION("""COMPUTED_VALUE"""),"リストBE") -> リストBE | C25: =IFERROR(__xludf.DUMMYFUNCTION("""COMPUTED_VALUE"""),0.12360086723245745) -> 0.12360087 | D25: =IFERROR(__xludf.DUMMYFUNCTION("""COMPUTED_VALUE"""),7.974481658692185E-4) -> 0.00079744817 | E25: =IFERROR(__xludf.DUMMYFUNCTION("""COMPUTED_VALUE"""),0.0) -> 0 | F25: =IFERROR(__xludf.DUMMYFUNCTION("""COMPUTED_VALUE"""),"リストBE") -> リストBE | G25: =IFERROR(__xludf.DUMMYFUNCTION("""COMPUTED_VALUE"""),0.0) -> 0 | H25: =IFERROR(__xludf.DUMMYFUNCTION("""COMPUTED_VALUE"""),0.0) -> 0 | I25: =IFERROR(__xludf.DUMMYFUNCTION("""COMPUTED_VALUE"""),0.0) -> 0 | J25: =IFERROR(__xludf.DUMMYFUNCTION("""COMPUTED_VALUE"""),"リストBE") -> リストBE | K25: =IFERROR(__xludf.DUMMYFUNCTION("""COMPUTED_VALUE"""),0.0) -> 0 | L25: =IFERROR(__xludf.DUMMYFUNCTION("""COMPUTED_VALUE"""),0.0) -> 0 | M25: =IFERROR(__xludf.DUMMYFUNCTION("""COMPUTED_VALUE"""),0.0) -> 0 | N25: =IFERROR(__xludf.DUMMYFUNCTION("""COMPUTED_VALUE"""),"リストBE") -> リストBE | O25: =IFERROR(__xludf.DUMMYFUNCTION("""COMPUTED_VALUE"""),0.0) -> 0 | P25: =IFERROR(__xludf.DUMMYFUNCTION("""COMPUTED_VALUE"""),0.0) -> 0 | Q25: =IFERROR(__xludf.DUMMYFUNCTION("""COMPUTED_VALUE"""),0.0) -> 0 | R25: =IFERROR(__xludf.DUMMYFUNCTION("""COMPUTED_VALUE"""),"リストBE") -> リストBE | S25: =IFERROR(__xludf.DUMMYFUNCTION("""COMPUTED_VALUE"""),0.0) -> 0 | T25: =IFERROR(__xludf.DUMMYFUNCTION("""COMPUTED_VALUE"""),0.0) -> 0 | U25: =IFERROR(__xludf.DUMMYFUNCTION("""COMPUTED_VALUE"""),0.0) -> 0 | V25: =IFERROR(__xludf.DUMMYFUNCTION("""COMPUTED_VALUE"""),"リストBE") -> リストBE | W25: =IFERROR(__xludf.DUMMYFUNCTION("""COMPUTED_VALUE"""),0.0) -> 0 | X25: =IFERROR(__xludf.DUMMYFUNCTION("""COMPUTED_VALUE"""),0.0) -> 0 | Y25: =IFERROR(__xludf.DUMMYFUNCTION("""COMPUTED_VALUE"""),0.0) -> 0 | Z25: =IFERROR(__xludf.DUMMYFUNCTION("""COMPUTED_VALUE"""),"リストBE") -> リストBE | AA25: =IFERROR(__xludf.DUMMYFUNCTION("""COMPUTED_VALUE"""),0.0) -> 0 | AB25: =IFERROR(__xludf.DUMMYFUNCTION("""COMPUTED_VALUE"""),0.0) -> 0 | AC25: =IFERROR(__xludf.DUMMYFUNCTION("""COMPUTED_VALUE"""),0.0) -> 0 | AD25: =IFERROR(__xludf.DUMMYFUNCTION("""COMPUTED_VALUE"""),"リストBE") -> リストBE | AE25: =IFERROR(__xludf.DUMMYFUNCTION("""COMPUTED_VALUE"""),0.1014325210086349) -> 0.10143252 | AF25: =IFERROR(__xludf.DUMMYFUNCTION("""COMPUTED_VALUE"""),0.0048627353836681935) -> 0.0048627354 | AG25: =IFERROR(__xludf.DUMMYFUNCTION("""COMPUTED_VALUE"""),0.0034470206741891813) -> 0.0034470207 | AH25: =IFERROR(__xludf.DUMMYFUNCTION("""COMPUTED_VALUE"""),"リストBE") -> リストBE | AI25: =IFERROR(__xludf.DUMMYFUNCTION("""COMPUTED_VALUE"""),0.0) -> 0 | AJ25: =IFERROR(__xludf.DUMMYFUNCTION("""COMPUTED_VALUE"""),0.0) -> 0 | AK25: =IFERROR(__xludf.DUMMYFUNCTION("""COMPUTED_VALUE"""),0.0) -> 0 | AL25: =IFERROR(__xludf.DUMMYFUNCTION("""COMPUTED_VALUE"""),"リストBE") -> リストBE | AM25: =IFERROR(__xludf.DUMMYFUNCTION("""COMPUTED_VALUE"""),0.10955198525780048) -> 0.10955199 | AN25: =IFERROR(__xludf.DUMMYFUNCTION("""COMPUTED_VALUE"""),0.006756206174032764) -> 0.0067562062 | AO25: =IFERROR(__xludf.DUMMYFUNCTION("""COMPUTED_VALUE"""),0.003097511927956114) -> 0.0030975119 | AP25: =IFERROR(__xludf.DUMMYFUNCTION("""COMPUTED_VALUE"""),"リストBE") -> リストBE | AQ25: =IFERROR(__xludf.DUMMYFUNCTION("""COMPUTED_VALUE"""),0.0) -> 0 | AR25: =IFERROR(__xludf.DUMMYFUNCTION("""COMPUTED_VALUE"""),0.0) -> 0 | AS25: =IFERROR(__xludf.DUMMYFUNCTION("""COMPUTED_VALUE"""),0.0) -> 0 | AT25: =IFERROR(__xludf.DUMMYFUNCTION("""COMPUTED_VALUE"""),"リストBE") -> リストBE | AU25: =IFERROR(__xludf.DUMMYFUNCTION("""COMPUTED_VALUE"""),0.0) -> 0 | AV25: =IFERROR(__xludf.DUMMYFUNCTION("""COMPUTED_VALUE"""),0.0) -> 0 | AW25: =IFERROR(__xludf.DUMMYFUNCTION("""COMPUTED_VALUE"""),0.0) -> 0 | AX25: =IFERROR(__xludf.DUMMYFUNCTION("""COMPUTED_VALUE"""),"リストBE") -> リストBE | AY25: =IFERROR(__xludf.DUMMYFUNCTION("""COMPUTED_VALUE"""),0.0) -> 0 | AZ25: =IFERROR(__xludf.DUMMYFUNCTION("""COMPUTED_VALUE"""),0.0) -> 0 | BA25: =IFERROR(__xludf.DUMMYFUNCTION("""COMPUTED_VALUE"""),0.0) -> 0 | BB25: =IFERROR(__xludf.DUMMYFUNCTION("""COMPUTED_VALUE"""),"リストBE") -> リストBE | BC25: =IFERROR(__xludf.DUMMYFUNCTION("""COMPUTED_VALUE"""),0.0) -> 0 | BD25: =IFERROR(__xludf.DUMMYFUNCTION("""COMPUTED_VALUE"""),0.0) -> 0 | BE25: =IFERROR(__xludf.DUMMYFUNCTION("""COMPUTED_VALUE"""),0.0) -> 0 | BF25: =IFERROR(__xludf.DUMMYFUNCTION("""COMPUTED_VALUE"""),"リストBE") -> リストBE
B26: =IFERROR(__xludf.DUMMYFUNCTION("""COMPUTED_VALUE"""),"リストS") -> リストS | C26: =IFERROR(__xludf.DUMMYFUNCTION("""COMPUTED_VALUE"""),0.10954618436209033) -> 0.10954618 | D26: =IFERROR(__xludf.DUMMYFUNCTION("""COMPUTED_VALUE"""),0.0029648634982637136) -> 0.0029648635 | E26: =IFERROR(__xludf.DUMMYFUNCTION("""COMPUTED_VALUE"""),0.00271770581165966) -> 0.0027177058 | F26: =IFERROR(__xludf.DUMMYFUNCTION("""COMPUTED_VALUE"""),"リストS") -> リストS | G26: =IFERROR(__xludf.DUMMYFUNCTION("""COMPUTED_VALUE"""),0.15713293384063254) -> 0.15713293 | H26: =IFERROR(__xludf.DUMMYFUNCTION("""COMPUTED_VALUE"""),0.005950538611789379) -> 0.0059505386 | I26: =IFERROR(__xludf.DUMMYFUNCTION("""COMPUTED_VALUE"""),0.0030130326612875322) -> 0.0030130327 | J26: =IFERROR(__xludf.DUMMYFUNCTION("""COMPUTED_VALUE"""),"リストS") -> リストS | K26: =IFERROR(__xludf.DUMMYFUNCTION("""COMPUTED_VALUE"""),0.17125603542341356) -> 0.17125604 | L26: =IFERROR(__xludf.DUMMYFUNCTION("""COMPUTED_VALUE"""),0.016243384679678792) -> 0.016243385 | M26: =IFERROR(__xludf.DUMMYFUNCTION("""COMPUTED_VALUE"""),0.013834537930222435) -> 0.013834538 | N26: =IFERROR(__xludf.DUMMYFUNCTION("""COMPUTED_VALUE"""),"リストS") -> リストS | O26: =IFERROR(__xludf.DUMMYFUNCTION("""COMPUTED_VALUE"""),0.017469882769695418) -> 0.017469883 | P26: =IFERROR(__xludf.DUMMYFUNCTION("""COMPUTED_VALUE"""),1.5820281601012498E-4) -> 0.00015820282 | Q26: =IFERROR(__xludf.DUMMYFUNCTION("""COMPUTED_VALUE"""),0.0) -> 0 | R26: =IFERROR(__xludf.DUMMYFUNCTION("""COMPUTED_VALUE"""),"リストS") -> リストS | S26: =IFERROR(__xludf.DUMMYFUNCTION("""COMPUTED_VALUE"""),0.020439807046914716) -> 0.020439807 | T26: =IFERROR(__xludf.DUMMYFUNCTION("""COMPUTED_VALUE"""),3.109438092924647E-4) -> 0.00031094381 | U26: =IFERROR(__xludf.DUMMYFUNCTION("""COMPUTED_VALUE"""),2.3430284935509394E-4) -> 0.00023430285 | V26: =IFERROR(__xludf.DUMMYFUNCTION("""COMPUTED_VALUE"""),"リストS") -> リストS | W26: =IFERROR(__xludf.DUMMYFUNCTION("""COMPUTED_VALUE"""),0.03591875340419506) -> 0.035918753 | X26: =IFERROR(__xludf.DUMMYFUNCTION("""COMPUTED_VALUE"""),0.0012034974461566745) -> 0.0012034974 | Y26: =IFERROR(__xludf.DUMMYFUNCTION("""COMPUTED_VALUE"""),0.0010975656492642602) -> 0.0010975656 | Z26: =IFERROR(__xludf.DUMMYFUNCTION("""COMPUTED_VALUE"""),"リストS") -> リストS | AA26: =IFERROR(__xludf.DUMMYFUNCTION("""COMPUTED_VALUE"""),0.04400930426049951) -> 0.044009304 | AB26: =IFERROR(__xludf.DUMMYFUNCTION("""COMPUTED_VALUE"""),0.0013014613494240575) -> 0.0013014613 | AC26: =IFERROR(__xludf.DUMMYFUNCTION("""COMPUTED_VALUE"""),9.808529116195899E-4) -> 0.00098085291 | AD26: =IFERROR(__xludf.DUMMYFUNCTION("""COMPUTED_VALUE"""),"リストS") -> リストS | AE26: =IFERROR(__xludf.DUMMYFUNCTION("""COMPUTED_VALUE"""),0.054582873779094564) -> 0.054582874 | AF26: =IFERROR(__xludf.DUMMYFUNCTION("""COMPUTED_VALUE"""),0.0023907947955060984) -> 0.0023907948 | AG26: =IFERROR(__xludf.DUMMYFUNCTION("""COMPUTED_VALUE"""),0.0018699675893336688) -> 0.0018699676 | AH26: =IFERROR(__xludf.DUMMYFUNCTION("""COMPUTED_VALUE"""),"リストS") -> リストS | AI26: =IFERROR(__xludf.DUMMYFUNCTION("""COMPUTED_VALUE"""),0.05214934659837162) -> 0.052149347 | AJ26: =IFERROR(__xludf.DUMMYFUNCTION("""COMPUTED_VALUE"""),0.0030334074825015232) -> 0.0030334075 | AK26: =IFERROR(__xludf.DUMMYFUNCTION("""COMPUTED_VALUE"""),0.0026666180638937427) -> 0.0026666181 | AL26: =IFERROR(__xludf.DUMMYFUNCTION("""COMPUTED_VALUE"""),"リストS") -> リストS | AM26: =IFERROR(__xludf.DUMMYFUNCTION("""COMPUTED_VALUE"""),0.09827965608554957) -> 0.098279656 | AN26: =IFERROR(__xludf.DUMMYFUNCTION("""COMPUTED_VALUE"""),0.0062810955759963075) -> 0.0062810956 | AO26: =IFERROR(__xludf.DUMMYFUNCTION("""COMPUTED_VALUE"""),0.0029208151060302087) -> 0.0029208151 | AP26: =IFERROR(__xludf.DUMMYFUNCTION("""COMPUTED_VALUE"""),"リストS") -> リストS | AQ26: =IFERROR(__xludf.DUMMYFUNCTION("""COMPUTED_VALUE"""),0.1271596586477591) -> 0.12715966 | AR26: =IFERROR(__xludf.DUMMYFUNCTION("""COMPUTED_VALUE"""),0.018393904644614423) -> 0.018393905 | AS26: =IFERROR(__xludf.DUMMYFUNCTION("""COMPUTED_VALUE"""),0.004336147017767616) -> 0.004336147 | AT26: =IFERROR(__xludf.DUMMYFUNCTION("""COMPUTED_VALUE"""),"リストS") -> リストS | AU26: =IFERROR(__xludf.DUMMYFUNCTION("""COMPUTED_VALUE"""),0.10321372053061353) -> 0.10321372 | AV26: =IFERROR(__xludf.DUMMYFUNCTION("""COMPUTED_VALUE"""),0.004057176164103486) -> 0.0040571762 | AW26: =IFERROR(__xludf.DUMMYFUNCTION("""COMPUTED_VALUE"""),0.0019767930225497877) -> 0.001976793 | AX26: =IFERROR(__xludf.DUMMYFUNCTION("""COMPUTED_VALUE"""),"リストS") -> リストS | AY26: =IFERROR(__xludf.DUMMYFUNCTION("""COMPUTED_VALUE"""),0.09824587854009907) -> 0.098245879 | AZ26: =IFERROR(__xludf.DUMMYFUNCTION("""COMPUTED_VALUE"""),0.004490545760040356) -> 0.0044905458 | BA26: =IFERROR(__xludf.DUMMYFUNCTION("""COMPUTED_VALUE"""),0.0028980908708195587) -> 0.0028980909 | BB26: =IFERROR(__xludf.DUMMYFUNCTION("""COMPUTED_VALUE"""),"リストS") -> リストS | BC26: =IFERROR(__xludf.DUMMYFUNCTION("""COMPUTED_VALUE"""),0.17012049267739537) -> 0.17012049 | BD26: =IFERROR(__xludf.DUMMYFUNCTION("""COMPUTED_VALUE"""),0.013555719143759987) -> 0.013555719 | BE26: =IFERROR(__xludf.DUMMYFUNCTION("""COMPUTED_VALUE"""),0.006550907097509251) -> 0.0065509071 | BF26: =IFERROR(__xludf.DUMMYFUNCTION("""COMPUTED_VALUE"""),"リストS") -> リストS
B27: =IFERROR(__xludf.DUMMYFUNCTION("""COMPUTED_VALUE"""),"リストE") -> リストE | C27: =IFERROR(__xludf.DUMMYFUNCTION("""COMPUTED_VALUE"""),0.11323100485789075) -> 0.113231 | D27: =IFERROR(__xludf.DUMMYFUNCTION("""COMPUTED_VALUE"""),0.0039557364875050065) -> 0.0039557365 | E27: =IFERROR(__xludf.DUMMYFUNCTION("""COMPUTED_VALUE"""),0.0026844876450016018) -> 0.0026844876 | F27: =IFERROR(__xludf.DUMMYFUNCTION("""COMPUTED_VALUE"""),"リストE") -> リストE | G27: =IFERROR(__xludf.DUMMYFUNCTION("""COMPUTED_VALUE"""),0.17608005149451064) -> 0.17608005 | H27: =IFERROR(__xludf.DUMMYFUNCTION("""COMPUTED_VALUE"""),0.007349774821220684) -> 0.0073497748 | I27: =IFERROR(__xludf.DUMMYFUNCTION("""COMPUTED_VALUE"""),0.005874972980236138) -> 0.005874973 | J27: =IFERROR(__xludf.DUMMYFUNCTION("""COMPUTED_VALUE"""),"リストE") -> リストE | K27: =IFERROR(__xludf.DUMMYFUNCTION("""COMPUTED_VALUE"""),0.16557871536851462) -> 0.16557872 | L27: =IFERROR(__xludf.DUMMYFUNCTION("""COMPUTED_VALUE"""),0.019714134383924362) -> 0.019714134 | M27: =IFERROR(__xludf.DUMMYFUNCTION("""COMPUTED_VALUE"""),0.018798049082393818) -> 0.018798049 | N27: =IFERROR(__xludf.DUMMYFUNCTION("""COMPUTED_VALUE"""),"リストE") -> リストE | O27: =IFERROR(__xludf.DUMMYFUNCTION("""COMPUTED_VALUE"""),0.03673134015428544) -> 0.03673134 | P27: =IFERROR(__xludf.DUMMYFUNCTION("""COMPUTED_VALUE"""),9.839176826610297E-4) -> 0.00098391768 | Q27: =IFERROR(__xludf.DUMMYFUNCTION("""COMPUTED_VALUE"""),5.578326178212991E-4) -> 0.00055783262 | R27: =IFERROR(__xludf.DUMMYFUNCTION("""COMPUTED_VALUE"""),"リストE") -> リストE | S27: =IFERROR(__xludf.DUMMYFUNCTION("""COMPUTED_VALUE"""),0.028958613972824458) -> 0.028958614 | T27: =IFERROR(__xludf.DUMMYFUNCTION("""COMPUTED_VALUE"""),6.231502129254387E-4) -> 0.00062315021 | U27: =IFERROR(__xludf.DUMMYFUNCTION("""COMPUTED_VALUE"""),0.0012073140373843323) -> 0.001207314 | V27: =IFERROR(__xludf.DUMMYFUNCTION("""COMPUTED_VALUE"""),"リストE") -> リストE | W27: =IFERROR(__xludf.DUMMYFUNCTION("""COMPUTED_VALUE"""),0.042575474881817864) -> 0.042575475 | X27: =IFERROR(__xludf.DUMMYFUNCTION("""COMPUTED_VALUE"""),0.0011809219799109338) -> 0.001180922 | Y27: =IFERROR(__xludf.DUMMYFUNCTION("""COMPUTED_VALUE"""),9.891600391915788E-4) -> 0.00098916004 | Z27: =IFERROR(__xludf.DUMMYFUNCTION("""COMPUTED_VALUE"""),"リストE") -> リストE | AA27: =IFERROR(__xludf.DUMMYFUNCTION("""COMPUTED_VALUE"""),0.05301607294716358) -> 0.053016073 | AB27: =IFERROR(__xludf.DUMMYFUNCTION("""COMPUTED_VALUE"""),0.0016654042238497411) -> 0.0016654042 | AC27: =IFERROR(__xludf.DUMMYFUNCTION("""COMPUTED_VALUE"""),0.0017711495288040037) -> 0.0017711495 | AD27: =IFERROR(__xludf.DUMMYFUNCTION("""COMPUTED_VALUE"""),"リストE") -> リストE | AE27: =IFERROR(__xludf.DUMMYFUNCTION("""COMPUTED_VALUE"""),0.038578624451474385) -> 0.038578624 | AF27: =IFERROR(__xludf.DUMMYFUNCTION("""COMPUTED_VALUE"""),0.008143914523777605) -> 0.0081439145 | AG27: =IFERROR(__xludf.DUMMYFUNCTION("""COMPUTED_VALUE"""),0.0029243222301858704) -> 0.0029243222 | AH27: =IFERROR(__xludf.DUMMYFUNCTION("""COMPUTED_VALUE"""),"リストE") -> リストE | AI27: =IFERROR(__xludf.DUMMYFUNCTION("""COMPUTED_VALUE"""),0.06255533266081993) -> 0.062555333 | AJ27: =IFERROR(__xludf.DUMMYFUNCTION("""COMPUTED_VALUE"""),0.0032473375825234413) -> 0.0032473376 | AK27: =IFERROR(__xludf.DUMMYFUNCTION("""COMPUTED_VALUE"""),0.0018350860059143147) -> 0.001835086 | AL27: =IFERROR(__xludf.DUMMYFUNCTION("""COMPUTED_VALUE"""),"リストE") -> リストE | AM27: =IFERROR(__xludf.DUMMYFUNCTION("""COMPUTED_VALUE"""),0.1070718987802141) -> 0.1070719 | AN27: =IFERROR(__xludf.DUMMYFUNCTION("""COMPUTED_VALUE"""),0.0031688099012666194) -> 0.0031688099 | AO27: =IFERROR(__xludf.DUMMYFUNCTION("""COMPUTED_VALUE"""),0.001097079289007351) -> 0.0010970793 | AP27: =IFERROR(__xludf.DUMMYFUNCTION("""COMPUTED_VALUE"""),"リストE") -> リストE | AQ27: =IFERROR(__xludf.DUMMYFUNCTION("""COMPUTED_VALUE"""),0.1510356825404112) -> 0.15103568 | AR27: =IFERROR(__xludf.DUMMYFUNCTION("""COMPUTED_VALUE"""),0.01853972136442799) -> 0.018539721 | AS27: =IFERROR(__xludf.DUMMYFUNCTION("""COMPUTED_VALUE"""),0.02565016952617204) -> 0.02565017 | AT27: =IFERROR(__xludf.DUMMYFUNCTION("""COMPUTED_VALUE"""),"リストE") -> リストE | AU27: =IFERROR(__xludf.DUMMYFUNCTION("""COMPUTED_VALUE"""),0.11749327603704401) -> 0.11749328 | AV27: =IFERROR(__xludf.DUMMYFUNCTION("""COMPUTED_VALUE"""),0.007234899077839902) -> 0.0072348991 | AW27: =IFERROR(__xludf.DUMMYFUNCTION("""COMPUTED_VALUE"""),0.00626261700706062) -> 0.006262617 | AX27: =IFERROR(__xludf.DUMMYFUNCTION("""COMPUTED_VALUE"""),"リストE") -> リストE | AY27: =IFERROR(__xludf.DUMMYFUNCTION("""COMPUTED_VALUE"""),0.14896658592739753) -> 0.14896659 | AZ27: =IFERROR(__xludf.DUMMYFUNCTION("""COMPUTED_VALUE"""),0.010108805399976408) -> 0.010108805 | BA27: =IFERROR(__xludf.DUMMYFUNCTION("""COMPUTED_VALUE"""),0.006123646076500831) -> 0.0061236461 | BB27: =IFERROR(__xludf.DUMMYFUNCTION("""COMPUTED_VALUE"""),"リストE") -> リストE | BC27: =IFERROR(__xludf.DUMMYFUNCTION("""COMPUTED_VALUE"""),0.10733750734426688) -> 0.10733751 | BD27: =IFERROR(__xludf.DUMMYFUNCTION("""COMPUTED_VALUE"""),0.007672104789445741) -> 0.0076721048 | BE27: =IFERROR(__xludf.DUMMYFUNCTION("""COMPUTED_VALUE"""),0.004758231830448928) -> 0.0047582318 | BF27: =IFERROR(__xludf.DUMMYFUNCTION("""COMPUTED_VALUE"""),"リストE") -> リストE
B28: =IFERROR(__xludf.DUMMYFUNCTION("""COMPUTED_VALUE"""),"TOTAL") -> TOTAL | C28: =IFERROR(__xludf.DUMMYFUNCTION("""COMPUTED_VALUE"""),0.11739448306705236) -> 0.11739448 | D28: =IFERROR(__xludf.DUMMYFUNCTION("""COMPUTED_VALUE"""),0.032694048664495955) -> 0.032694049 | E28: =IFERROR(__xludf.DUMMYFUNCTION("""COMPUTED_VALUE"""),0.017937498892209813) -> 0.017937499 | F28: =IFERROR(__xludf.DUMMYFUNCTION("""COMPUTED_VALUE"""),"TOTAL") -> TOTAL | G28: =IFERROR(__xludf.DUMMYFUNCTION("""COMPUTED_VALUE"""),0.12808963285713498) -> 0.12808963 | H28: =IFERROR(__xludf.DUMMYFUNCTION("""COMPUTED_VALUE"""),0.0037545073396357993) -> 0.0037545073 | I28: =IFERROR(__xludf.DUMMYFUNCTION("""COMPUTED_VALUE"""),0.0025984524231308925) -> 0.0025984524 | J28: =IFERROR(__xludf.DUMMYFUNCTION("""COMPUTED_VALUE"""),"TOTAL") -> TOTAL | K28: =IFERROR(__xludf.DUMMYFUNCTION("""COMPUTED_VALUE"""),0.11975975310718032) -> 0.11975975 | L28: =IFERROR(__xludf.DUMMYFUNCTION("""COMPUTED_VALUE"""),0.011285558954958488) -> 0.011285559 | M28: =IFERROR(__xludf.DUMMYFUNCTION("""COMPUTED_VALUE"""),0.010380010127976992) -> 0.01038001 | N28: =IFERROR(__xludf.DUMMYFUNCTION("""COMPUTED_VALUE"""),"TOTAL") -> TOTAL | O28: =IFERROR(__xludf.DUMMYFUNCTION("""COMPUTED_VALUE"""),0.013550305730995214) -> 0.013550306 | P28: =IFERROR(__xludf.DUMMYFUNCTION("""COMPUTED_VALUE"""),2.8553012466778866E-4) -> 0.00028553012 | Q28: =IFERROR(__xludf.DUMMYFUNCTION("""COMPUTED_VALUE"""),1.3945815445532477E-4) -> 0.00013945815 | R28: =IFERROR(__xludf.DUMMYFUNCTION("""COMPUTED_VALUE"""),"TOTAL") -> TOTAL | S28: =IFERROR(__xludf.DUMMYFUNCTION("""COMPUTED_VALUE"""),0.030008232951720504) -> 0.030008233 | T28: =IFERROR(__xludf.DUMMYFUNCTION("""COMPUTED_VALUE"""),4.295126597829535E-4) -> 0.00042951266 | U28: =IFERROR(__xludf.DUMMYFUNCTION("""COMPUTED_VALUE"""),5.302442518260658E-4) -> 0.00053024425 | V28: =IFERROR(__xludf.DUMMYFUNCTION("""COMPUTED_VALUE"""),"TOTAL") -> TOTAL | W28: =IFERROR(__xludf.DUMMYFUNCTION("""COMPUTED_VALUE"""),0.03924711414300646) -> 0.039247114 | X28: =IFERROR(__xludf.DUMMYFUNCTION("""COMPUTED_VALUE"""),0.0011922097130338042) -> 0.0011922097 | Y28: =IFERROR(__xludf.DUMMYFUNCTION("""COMPUTED_VALUE"""),0.0010433628442279195) -> 0.0010433628 | Z28: =IFERROR(__xludf.DUMMYFUNCTION("""COMPUTED_VALUE"""),"TOTAL") -> TOTAL | AA28: =IFERROR(__xludf.DUMMYFUNCTION("""COMPUTED_VALUE"""),0.03308362232204143) -> 0.033083622 | AB28: =IFERROR(__xludf.DUMMYFUNCTION("""COMPUTED_VALUE"""),9.127264960888009E-4) -> 0.0009127265 | AC28: =IFERROR(__xludf.DUMMYFUNCTION("""COMPUTED_VALUE"""),8.206923113878658E-4) -> 0.00082069231 | AD28: =IFERROR(__xludf.DUMMYFUNCTION("""COMPUTED_VALUE"""),"TOTAL") -> TOTAL | AE28: =IFERROR(__xludf.DUMMYFUNCTION("""COMPUTED_VALUE"""),0.05801036405431093) -> 0.058010364 | AF28: =IFERROR(__xludf.DUMMYFUNCTION("""COMPUTED_VALUE"""),0.007970733411401445) -> 0.0079707334 | AG28: =IFERROR(__xludf.DUMMYFUNCTION("""COMPUTED_VALUE"""),0.006804201500551397) -> 0.0068042015 | AH28: =IFERROR(__xludf.DUMMYFUNCTION("""COMPUTED_VALUE"""),"TOTAL") -> TOTAL | AI28: =IFERROR(__xludf.DUMMYFUNCTION("""COMPUTED_VALUE"""),0.05735233962959578) -> 0.05735234 | AJ28: =IFERROR(__xludf.DUMMYFUNCTION("""COMPUTED_VALUE"""),0.0031403725325124822) -> 0.0031403725 | AK28: =IFERROR(__xludf.DUMMYFUNCTION("""COMPUTED_VALUE"""),0.0022508520349040287) -> 0.002250852 | AL28: =IFERROR(__xludf.DUMMYFUNCTION("""COMPUTED_VALUE"""),"TOTAL") -> TOTAL | AM28: =IFERROR(__xludf.DUMMYFUNCTION("""COMPUTED_VALUE"""),0.10496784670785471) -> 0.10496785 | AN28: =IFERROR(__xludf.DUMMYFUNCTION("""COMPUTED_VALUE"""),0.005402037217098563) -> 0.0054020372 | AO28: =IFERROR(__xludf.DUMMYFUNCTION("""COMPUTED_VALUE"""),0.002371802107664558) -> 0.0023718021 | AP28: =IFERROR(__xludf.DUMMYFUNCTION("""COMPUTED_VALUE"""),"TOTAL") -> TOTAL | AQ28: =IFERROR(__xludf.DUMMYFUNCTION("""COMPUTED_VALUE"""),0.13909767059408515) -> 0.13909767 | AR28: =IFERROR(__xludf.DUMMYFUNCTION("""COMPUTED_VALUE"""),0.01846681300452121) -> 0.018466813 | AS28: =IFERROR(__xludf.DUMMYFUNCTION("""COMPUTED_VALUE"""),0.014993158271969828) -> 0.014993158 | AT28: =IFERROR(__xludf.DUMMYFUNCTION("""COMPUTED_VALUE"""),"TOTAL") -> TOTAL | AU28: =IFERROR(__xludf.DUMMYFUNCTION("""COMPUTED_VALUE"""),0.11035349828382877) -> 0.1103535 | AV28: =IFERROR(__xludf.DUMMYFUNCTION("""COMPUTED_VALUE"""),0.005646037620971694) -> 0.0056460376 | AW28: =IFERROR(__xludf.DUMMYFUNCTION("""COMPUTED_VALUE"""),0.0041197050148052035) -> 0.004119705 | AX28: =IFERROR(__xludf.DUMMYFUNCTION("""COMPUTED_VALUE"""),"TOTAL") -> TOTAL | AY28: =IFERROR(__xludf.DUMMYFUNCTION("""COMPUTED_VALUE"""),0.12360623223374831) -> 0.12360623 | AZ28: =IFERROR(__xludf.DUMMYFUNCTION("""COMPUTED_VALUE"""),0.007299675580008382) -> 0.0072996756 | BA28: =IFERROR(__xludf.DUMMYFUNCTION("""COMPUTED_VALUE"""),0.004510868473660195) -> 0.0045108685 | BB28: =IFERROR(__xludf.DUMMYFUNCTION("""COMPUTED_VALUE"""),"TOTAL") -> TOTAL | BC28: =IFERROR(__xludf.DUMMYFUNCTION("""COMPUTED_VALUE"""),0.13872900001083113) -> 0.138729 | BD28: =IFERROR(__xludf.DUMMYFUNCTION("""COMPUTED_VALUE"""),0.010613911966602864) -> 0.010613912 | BE28: =IFERROR(__xludf.DUMMYFUNCTION("""COMPUTED_VALUE"""),0.0056545694639790894) -> 0.0056545695 | BF28: =IFERROR(__xludf.DUMMYFUNCTION("""COMPUTED_VALUE"""),"TOTAL") -> TOTAL
B32: =IFERROR(__xludf.DUMMYFUNCTION("IMPORTRANGE(""1vYc4iTJ16E7R6SUnGhwdB4aOJULuweZOJUwnvK3B2Ug"", ""顧客リスト!AR33:BE47"") "),"#REF!") -> #REF!
B52: 営業マン別データ
B54: =IFERROR(__xludf.DUMMYFUNCTION("IMPORTRANGE(""11QmPanSRxykbUTB_EqX7W510tAZnhZpBpW7QiSnxobM"", ""営業マン別データ!B1:I23"") "),"") | C54: =IFERROR(__xludf.DUMMYFUNCTION("""COMPUTED_VALUE"""),"TOTAL") -> TOTAL
C55: =IFERROR(__xludf.DUMMYFUNCTION("""COMPUTED_VALUE"""),"打電件数") -> 打電件数 | D55: =IFERROR(__xludf.DUMMYFUNCTION("""COMPUTED_VALUE"""),"着電件数") -> 着電件数 | E55: =IFERROR(__xludf.DUMMYFUNCTION("""COMPUTED_VALUE"""),"着電率") -> 着電率 | F55: =IFERROR(__xludf.DUMMYFUNCTION("""COMPUTED_VALUE"""),"アポ数") -> アポ数 | G55: =IFERROR(__xludf.DUMMYFUNCTION("""COMPUTED_VALUE"""),"アポ率(着電から)") -> アポ率(着電から) | H55: =IFERROR(__xludf.DUMMYFUNCTION("""COMPUTED_VALUE"""),"LINE誘導数") -> LINE誘導数 | I55: =IFERROR(__xludf.DUMMYFUNCTION("""COMPUTED_VALUE"""),"LINE率(着電から)") -> LINE率(着電から)
B56: =IFERROR(__xludf.DUMMYFUNCTION("""COMPUTED_VALUE"""),"TOTAL") -> TOTAL | C56: =IFERROR(__xludf.DUMMYFUNCTION("""COMPUTED_VALUE"""),894114.0) -> 894114 | D56: =IFERROR(__xludf.DUMMYFUNCTION("""COMPUTED_VALUE"""),61759.0) -> 61759 | E56: =IFERROR(__xludf.DUMMYFUNCTION("""COMPUTED_VALUE"""),0.06907284753398336) -> 0.069072848 | F56: =IFERROR(__xludf.DUMMYFUNCTION("""COMPUTED_VALUE"""),1958.0) -> 1958 | G56: =IFERROR(__xludf.DUMMYFUNCTION("""COMPUTED_VALUE"""),0.03170388121569326) -> 0.031703881 | H56: =IFERROR(__xludf.DUMMYFUNCTION("""COMPUTED_VALUE"""),2557.0) -> 2557 | I56: =IFERROR(__xludf.DUMMYFUNCTION("""COMPUTED_VALUE"""),0.0414028724558364) -> 0.041402872
B57: =IFERROR(__xludf.DUMMYFUNCTION("""COMPUTED_VALUE"""),"木村") -> 木村 | C57: =IFERROR(__xludf.DUMMYFUNCTION("""COMPUTED_VALUE"""),1427.0) -> 1427 | D57: =IFERROR(__xludf.DUMMYFUNCTION("""COMPUTED_VALUE"""),298.0) -> 298 | E57: =IFERROR(__xludf.DUMMYFUNCTION("""COMPUTED_VALUE"""),0.20882971268395234) -> 0.20882971 | F57: =IFERROR(__xludf.DUMMYFUNCTION("""COMPUTED_VALUE"""),17.0) -> 17 | G57: =IFERROR(__xludf.DUMMYFUNCTION("""COMPUTED_VALUE"""),0.05704697986577181) -> 0.05704698 | H57: =IFERROR(__xludf.DUMMYFUNCTION("""COMPUTED_VALUE"""),1.0) -> 1 | I57: =IFERROR(__xludf.DUMMYFUNCTION("""COMPUTED_VALUE"""),0.003355704697986577) -> 0.0033557047
B58: =IFERROR(__xludf.DUMMYFUNCTION("""COMPUTED_VALUE"""),"あり") -> あり | C58: =IFERROR(__xludf.DUMMYFUNCTION("""COMPUTED_VALUE"""),117562.0) -> 117562 | D58: =IFERROR(__xludf.DUMMYFUNCTION("""COMPUTED_VALUE"""),9214.0) -> 9214 | E58: =IFERROR(__xludf.DUMMYFUNCTION("""COMPUTED_VALUE"""),0.07837566560623331) -> 0.078375666 | F58: =IFERROR(__xludf.DUMMYFUNCTION("""COMPUTED_VALUE"""),391.0) -> 391 | G58: =IFERROR(__xludf.DUMMYFUNCTION("""COMPUTED_VALUE"""),0.042435424354243544) -> 0.042435424 | H58: =IFERROR(__xludf.DUMMYFUNCTION("""COMPUTED_VALUE"""),499.0) -> 499 | I58: =IFERROR(__xludf.DUMMYFUNCTION("""COMPUTED_VALUE"""),0.054156718037768614) -> 0.054156718
B59: =IFERROR(__xludf.DUMMYFUNCTION("""COMPUTED_VALUE"""),"太田") -> 太田 | C59: =IFERROR(__xludf.DUMMYFUNCTION("""COMPUTED_VALUE"""),117663.0) -> 117663 | D59: =IFERROR(__xludf.DUMMYFUNCTION("""COMPUTED_VALUE"""),8131.0) -> 8131 | E59: =IFERROR(__xludf.DUMMYFUNCTION("""COMPUTED_VALUE"""),0.06910413638951922) -> 0.069104136 | F59: =IFERROR(__xludf.DUMMYFUNCTION("""COMPUTED_VALUE"""),392.0) -> 392 | G59: =IFERROR(__xludf.DUMMYFUNCTION("""COMPUTED_VALUE"""),0.04821055220760054) -> 0.048210552 | H59: =IFERROR(__xludf.DUMMYFUNCTION("""COMPUTED_VALUE"""),458.0) -> 458 | I59: =IFERROR(__xludf.DUMMYFUNCTION("""COMPUTED_VALUE"""),0.05632763497724757) -> 0.056327635
B60: =IFERROR(__xludf.DUMMYFUNCTION("""COMPUTED_VALUE"""),"高坂") -> 高坂 | C60: =IFERROR(__xludf.DUMMYFUNCTION("""COMPUTED_VALUE"""),36495.0) -> 36495 | D60: =IFERROR(__xludf.DUMMYFUNCTION("""COMPUTED_VALUE"""),2732.0) -> 2732 | E60: =IFERROR(__xludf.DUMMYFUNCTION("""COMPUTED_VALUE"""),0.07485956980408275) -> 0.07485957 | F60: =IFERROR(__xludf.DUMMYFUNCTION("""COMPUTED_VALUE"""),103.0) -> 103 | G60: =IFERROR(__xludf.DUMMYFUNCTION("""COMPUTED_VALUE"""),0.037701317715959005) -> 0.037701318 | H60: =IFERROR(__xludf.DUMMYFUNCTION("""COMPUTED_VALUE"""),114.0) -> 114 | I60: =IFERROR(__xludf.DUMMYFUNCTION("""COMPUTED_VALUE"""),0.04172767203513909) -> 0.041727672
B61: =IFERROR(__xludf.DUMMYFUNCTION("""COMPUTED_VALUE"""),"ジョナ") -> ジョナ | C61: =IFERROR(__xludf.DUMMYFUNCTION("""COMPUTED_VALUE"""),93438.0) -> 93438 | D61: =IFERROR(__xludf.DUMMYFUNCTION("""COMPUTED_VALUE"""),5279.0) -> 5279 | E61: =IFERROR(__xludf.DUMMYFUNCTION("""COMPUTED_VALUE"""),0.05649735653588476) -> 0.056497357 | F61: =IFERROR(__xludf.DUMMYFUNCTION("""COMPUTED_VALUE"""),216.0) -> 216 | G61: =IFERROR(__xludf.DUMMYFUNCTION("""COMPUTED_VALUE"""),0.0409168403106649) -> 0.04091684 | H61: =IFERROR(__xludf.DUMMYFUNCTION("""COMPUTED_VALUE"""),270.0) -> 270 | I61: =IFERROR(__xludf.DUMMYFUNCTION("""COMPUTED_VALUE"""),0.05114605038833112) -> 0.05114605
B62: =IFERROR(__xludf.DUMMYFUNCTION("""COMPUTED_VALUE"""),"武田") -> 武田 | C62: =IFERROR(__xludf.DUMMYFUNCTION("""COMPUTED_VALUE"""),21297.0) -> 21297 | D62: =IFERROR(__xludf.DUMMYFUNCTION("""COMPUTED_VALUE"""),2236.0) -> 2236 | E62: =IFERROR(__xludf.DUMMYFUNCTION("""COMPUTED_VALUE"""),0.10499131333051603) -> 0.10499131 | F62: =IFERROR(__xludf.DUMMYFUNCTION("""COMPUTED_VALUE"""),197.0) -> 197 | G62: =IFERROR(__xludf.DUMMYFUNCTION("""COMPUTED_VALUE"""),0.08810375670840787) -> 0.088103757 | H62: =IFERROR(__xludf.DUMMYFUNCTION("""COMPUTED_VALUE"""),289.0) -> 289 | I62: =IFERROR(__xludf.DUMMYFUNCTION("""COMPUTED_VALUE"""),0.12924865831842575) -> 0.12924866
B63: =IFERROR(__xludf.DUMMYFUNCTION("""COMPUTED_VALUE"""),"山本") -> 山本 | C63: =IFERROR(__xludf.DUMMYFUNCTION("""COMPUTED_VALUE"""),5906.0) -> 5906 | D63: =IFERROR(__xludf.DUMMYFUNCTION("""COMPUTED_VALUE"""),727.0) -> 727 | E63: =IFERROR(__xludf.DUMMYFUNCTION("""COMPUTED_VALUE"""),0.12309515746698273) -> 0.12309516 | F63: =IFERROR(__xludf.DUMMYFUNCTION("""COMPUTED_VALUE"""),15.0) -> 15 | G63: =IFERROR(__xludf.DUMMYFUNCTION("""COMPUTED_VALUE"""),0.02063273727647868) -> 0.020632737 | H63: =IFERROR(__xludf.DUMMYFUNCTION("""COMPUTED_VALUE"""),32.0) -> 32 | I63: =IFERROR(__xludf.DUMMYFUNCTION("""COMPUTED_VALUE"""),0.04401650618982118) -> 0.044016506
B64: =IFERROR(__xludf.DUMMYFUNCTION("""COMPUTED_VALUE"""),"高木") -> 高木 | C64: =IFERROR(__xludf.DUMMYFUNCTION("""COMPUTED_VALUE"""),106843.0) -> 106843 | D64: =IFERROR(__xludf.DUMMYFUNCTION("""COMPUTED_VALUE"""),8495.0) -> 8495 | E64: =IFERROR(__xludf.DUMMYFUNCTION("""COMPUTED_VALUE"""),0.07950918637627173) -> 0.079509186 | F64: =IFERROR(__xludf.DUMMYFUNCTION("""COMPUTED_VALUE"""),113.5) -> 113.5 | G64: =IFERROR(__xludf.DUMMYFUNCTION("""COMPUTED_VALUE"""),0.013360800470865216) -> 0.0133608 | H64: =IFERROR(__xludf.DUMMYFUNCTION("""COMPUTED_VALUE"""),186.0) -> 186 | I64: =IFERROR(__xludf.DUMMYFUNCTION("""COMPUTED_VALUE"""),0.021895232489699823) -> 0.021895232
B65: =IFERROR(__xludf.DUMMYFUNCTION("""COMPUTED_VALUE"""),"中原") -> 中原
B66: =IFERROR(__xludf.DUMMYFUNCTION("""COMPUTED_VALUE"""),"小西") -> 小西 | C66: =IFERROR(__xludf.DUMMYFUNCTION("""COMPUTED_VALUE"""),11451.0) -> 11451 | D66: =IFERROR(__xludf.DUMMYFUNCTION("""COMPUTED_VALUE"""),876.0) -> 876 | E66: =IFERROR(__xludf.DUMMYFUNCTION("""COMPUTED_VALUE"""),0.07649986900707362) -> 0.076499869 | F66: =IFERROR(__xludf.DUMMYFUNCTION("""COMPUTED_VALUE"""),12.0) -> 12 | G66: =IFERROR(__xludf.DUMMYFUNCTION("""COMPUTED_VALUE"""),0.0136986301369863) -> 0.01369863 | H66: =IFERROR(__xludf.DUMMYFUNCTION("""COMPUTED_VALUE"""),29.0) -> 29 | I66: =IFERROR(__xludf.DUMMYFUNCTION("""COMPUTED_VALUE"""),0.033105022831050226) -> 0.033105023
B67: =IFERROR(__xludf.DUMMYFUNCTION("""COMPUTED_VALUE"""),"ソラ") -> ソラ | C67: =IFERROR(__xludf.DUMMYFUNCTION("""COMPUTED_VALUE"""),41828.0) -> 41828 | D67: =IFERROR(__xludf.DUMMYFUNCTION("""COMPUTED_VALUE"""),1676.0) -> 1676 | E67: =IFERROR(__xludf.DUMMYFUNCTION("""COMPUTED_VALUE"""),0.04006885339963661) -> 0.040068853 | F67: =IFERROR(__xludf.DUMMYFUNCTION("""COMPUTED_VALUE"""),54.0) -> 54 | G67: =IFERROR(__xludf.DUMMYFUNCTION("""COMPUTED_VALUE"""),0.032219570405727926) -> 0.03221957 | H67: =IFERROR(__xludf.DUMMYFUNCTION("""COMPUTED_VALUE"""),60.0) -> 60 | I67: =IFERROR(__xludf.DUMMYFUNCTION("""COMPUTED_VALUE"""),0.03579952267303103) -> 0.035799523
B68: =IFERROR(__xludf.DUMMYFUNCTION("""COMPUTED_VALUE"""),"森") -> 森 | C68: =IFERROR(__xludf.DUMMYFUNCTION("""COMPUTED_VALUE"""),5584.0) -> 5584 | D68: =IFERROR(__xludf.DUMMYFUNCTION("""COMPUTED_VALUE"""),844.0) -> 844 | E68: =IFERROR(__xludf.DUMMYFUNCTION("""COMPUTED_VALUE"""),0.1511461318051576) -> 0.15114613 | F68: =IFERROR(__xludf.DUMMYFUNCTION("""COMPUTED_VALUE"""),17.0) -> 17 | G68: =IFERROR(__xludf.DUMMYFUNCTION("""COMPUTED_VALUE"""),0.02014218009478673) -> 0.02014218 | H68: =IFERROR(__xludf.DUMMYFUNCTION("""COMPUTED_VALUE"""),47.0) -> 47 | I68: =IFERROR(__xludf.DUMMYFUNCTION("""COMPUTED_VALUE"""),0.05568720379146919) -> 0.055687204
B69: =IFERROR(__xludf.DUMMYFUNCTION("""COMPUTED_VALUE"""),"大谷") -> 大谷 | C69: =IFERROR(__xludf.DUMMYFUNCTION("""COMPUTED_VALUE"""),89697.0) -> 89697 | D69: =IFERROR(__xludf.DUMMYFUNCTION("""COMPUTED_VALUE"""),3780.0) -> 3780 | E69: =IFERROR(__xludf.DUMMYFUNCTION("""COMPUTED_VALUE"""),0.042141877654771065) -> 0.042141878 | F69: =IFERROR(__xludf.DUMMYFUNCTION("""COMPUTED_VALUE"""),63.5) -> 63.5 | G69: =IFERROR(__xludf.DUMMYFUNCTION("""COMPUTED_VALUE"""),0.0167989417989418) -> 0.016798942 | H69: =IFERROR(__xludf.DUMMYFUNCTION("""COMPUTED_VALUE"""),108.0) -> 108 | I69: =IFERROR(__xludf.DUMMYFUNCTION("""COMPUTED_VALUE"""),0.02857142857142857) -> 0.028571429
B70: =IFERROR(__xludf.DUMMYFUNCTION("""COMPUTED_VALUE"""),"金子") -> 金子 | C70: =IFERROR(__xludf.DUMMYFUNCTION("""COMPUTED_VALUE"""),57363.0) -> 57363 | D70: =IFERROR(__xludf.DUMMYFUNCTION("""COMPUTED_VALUE"""),3607.0) -> 3607 | E70: =IFERROR(__xludf.DUMMYFUNCTION("""COMPUTED_VALUE"""),0.06288025382215016) -> 0.062880254 | F70: =IFERROR(__xludf.DUMMYFUNCTION("""COMPUTED_VALUE"""),66.5) -> 66.5 | G70: =IFERROR(__xludf.DUMMYFUNCTION("""COMPUTED_VALUE"""),0.018436373717771) -> 0.018436374 | H70: =IFERROR(__xludf.DUMMYFUNCTION("""COMPUTED_VALUE"""),98.0) -> 98 | I70: =IFERROR(__xludf.DUMMYFUNCTION("""COMPUTED_VALUE"""),0.027169392847241475) -> 0.027169393
B71: =IFERROR(__xludf.DUMMYFUNCTION("""COMPUTED_VALUE"""),"ハタ") -> ハタ | C71: =IFERROR(__xludf.DUMMYFUNCTION("""COMPUTED_VALUE"""),23118.0) -> 23118 | D71: =IFERROR(__xludf.DUMMYFUNCTION("""COMPUTED_VALUE"""),1945.0) -> 1945 | E71: =IFERROR(__xludf.DUMMYFUNCTION("""COMPUTED_VALUE"""),0.08413357556882083) -> 0.084133576 | F71: =IFERROR(__xludf.DUMMYFUNCTION("""COMPUTED_VALUE"""),43.0) -> 43 | G71: =IFERROR(__xludf.DUMMYFUNCTION("""COMPUTED_VALUE"""),0.02210796915167095) -> 0.022107969 | H71: =IFERROR(__xludf.DUMMYFUNCTION("""COMPUTED_VALUE"""),85.0) -> 85 | I71: =IFERROR(__xludf.DUMMYFUNCTION("""COMPUTED_VALUE"""),0.043701799485861184) -> 0.043701799
B72: =IFERROR(__xludf.DUMMYFUNCTION("""COMPUTED_VALUE"""),"村田") -> 村田 | C72: =IFERROR(__xludf.DUMMYFUNCTION("""COMPUTED_VALUE"""),1198.0) -> 1198 | D72: =IFERROR(__xludf.DUMMYFUNCTION("""COMPUTED_VALUE"""),160.0) -> 160 | E72: =IFERROR(__xludf.DUMMYFUNCTION("""COMPUTED_VALUE"""),0.1335559265442404) -> 0.13355593 | F72: =IFERROR(__xludf.DUMMYFUNCTION("""COMPUTED_VALUE"""),2.0) -> 2 | G72: =IFERROR(__xludf.DUMMYFUNCTION("""COMPUTED_VALUE"""),0.0125) -> 0.0125 | H72: =IFERROR(__xludf.DUMMYFUNCTION("""COMPUTED_VALUE"""),3.0) -> 3 | I72: =IFERROR(__xludf.DUMMYFUNCTION("""COMPUTED_VALUE"""),0.01875) -> 0.01875
B73: =IFERROR(__xludf.DUMMYFUNCTION("""COMPUTED_VALUE"""),"仁子") -> 仁子 | C73: =IFERROR(__xludf.DUMMYFUNCTION("""COMPUTED_VALUE"""),20292.0) -> 20292 | D73: =IFERROR(__xludf.DUMMYFUNCTION("""COMPUTED_VALUE"""),1513.0) -> 1513 | E73: =IFERROR(__xludf.DUMMYFUNCTION("""COMPUTED_VALUE"""),0.07456140350877193) -> 0.074561404 | F73: =IFERROR(__xludf.DUMMYFUNCTION("""COMPUTED_VALUE"""),120.0) -> 120 | G73: =IFERROR(__xludf.DUMMYFUNCTION("""COMPUTED_VALUE"""),0.07931262392597488) -> 0.079312624 | H73: =IFERROR(__xludf.DUMMYFUNCTION("""COMPUTED_VALUE"""),90.0) -> 90 | I73: =IFERROR(__xludf.DUMMYFUNCTION("""COMPUTED_VALUE"""),0.059484467944481166) -> 0.059484468
B74: =IFERROR(__xludf.DUMMYFUNCTION("""COMPUTED_VALUE"""),"小川") -> 小川 | C74: =IFERROR(__xludf.DUMMYFUNCTION("""COMPUTED_VALUE"""),635.0) -> 635 | D74: =IFERROR(__xludf.DUMMYFUNCTION("""COMPUTED_VALUE"""),126.0) -> 126 | E74: =IFERROR(__xludf.DUMMYFUNCTION("""COMPUTED_VALUE"""),0.1984251968503937) -> 0.1984252 | F74: =IFERROR(__xludf.DUMMYFUNCTION("""COMPUTED_VALUE"""),10.0) -> 10 | G74: =IFERROR(__xludf.DUMMYFUNCTION("""COMPUTED_VALUE"""),0.07936507936507936) -> 0.079365079 | H74: =IFERROR(__xludf.DUMMYFUNCTION("""COMPUTED_VALUE"""),10.0) -> 10 | I74: =IFERROR(__xludf.DUMMYFUNCTION("""COMPUTED_VALUE"""),0.07936507936507936) -> 0.079365079
B75: =IFERROR(__xludf.DUMMYFUNCTION("""COMPUTED_VALUE"""),"サラ") -> サラ | C75: =IFERROR(__xludf.DUMMYFUNCTION("""COMPUTED_VALUE"""),12385.0) -> 12385 | D75: =IFERROR(__xludf.DUMMYFUNCTION("""COMPUTED_VALUE"""),1174.0) -> 1174 | E75: =IFERROR(__xludf.DUMMYFUNCTION("""COMPUTED_VALUE"""),0.0947920872022608) -> 0.094792087 | F75: =IFERROR(__xludf.DUMMYFUNCTION("""COMPUTED_VALUE"""),18.0) -> 18 | G75: =IFERROR(__xludf.DUMMYFUNCTION("""COMPUTED_VALUE"""),0.015332197614991482) -> 0.015332198 | H75: =IFERROR(__xludf.DUMMYFUNCTION("""COMPUTED_VALUE"""),30.0) -> 30 | I75: =IFERROR(__xludf.DUMMYFUNCTION("""COMPUTED_VALUE"""),0.02555366269165247) -> 0.025553663
B76: =IFERROR(__xludf.DUMMYFUNCTION("""COMPUTED_VALUE"""),"長瀬") -> 長瀬 | C76: =IFERROR(__xludf.DUMMYFUNCTION("""COMPUTED_VALUE"""),577.0) -> 577 | D76: =IFERROR(__xludf.DUMMYFUNCTION("""COMPUTED_VALUE"""),83.0) -> 83 | E76: =IFERROR(__xludf.DUMMYFUNCTION("""COMPUTED_VALUE"""),0.1438474870017331) -> 0.14384749 | F76: =IFERROR(__xludf.DUMMYFUNCTION("""COMPUTED_VALUE"""),1.0) -> 1 | G76: =IFERROR(__xludf.DUMMYFUNCTION("""COMPUTED_VALUE"""),0.012048192771084338) -> 0.012048193 | H76: =IFERROR(__xludf.DUMMYFUNCTION("""COMPUTED_VALUE"""),1.0) -> 1 | I76: =IFERROR(__xludf.DUMMYFUNCTION("""COMPUTED_VALUE"""),0.012048192771084338) -> 0.012048193
B77: Team-A | C77: =C57+C58+C59+C62+C68 -> 263533 | D77: =D57+D58+D59+D62+D68 -> 20723 | E77: =E57+E58+E59+E62+E68 -> 0.61244696 | F77: =F57+F58+F59+F62+F68 -> 1014 | G77: =G57+G58+G59+G62+G68 -> 0.25593889 | H77: =H57+H58+H59+H62+H68 -> 1294 | I77: =I57+I58+I59+I62+I68 -> 0.29877592
B78: Team-B | C78: =C61+C64+C66+C71 -> 234850 | D78: =D61+D64+D66+D71 -> 16595 | E78: =E61+E64+E66+E71 -> 0.29663999 | F78: =F61+F64+F66+F71 -> 384.5 | G78: =G61+G64+G66+G71 -> 0.09008424 | H78: =H61+H64+H66+H71 -> 570 | I78: =I61+I64+I66+I71 -> 0.14984811
B79: Team-C | C79: =C60+C69+C70+C73 -> 203847 | D79: =D60+D69+D70+D73 -> 11632 | E79: =E60+E69+E70+E73 -> 0.2544431 | F79: =F60+F69+F70+F73 -> 353 | G79: =G60+G69+G70+G73 -> 0.15224926 | H79: =H60+H69+H70+H73 -> 410 | I79: =I60+I69+I70+I73 -> 0.15695296
B81: =IFERROR(__xludf.DUMMYFUNCTION("IMPORTRANGE(""11QmPanSRxykbUTB_EqX7W510tAZnhZpBpW7QiSnxobM"", ""営業マン別データ!B1:Bi25"") "),"") | C81: =IFERROR(__xludf.DUMMYFUNCTION("""COMPUTED_VALUE"""),"TOTAL") -> TOTAL | AL81: =IFERROR(__xludf.DUMMYFUNCTION("""COMPUTED_VALUE"""),"6月 ") -> 6月 | AP81: =IFERROR(__xludf.DUMMYFUNCTION("""COMPUTED_VALUE"""),"5月 ") -> 5月 | AT81: =IFERROR(__xludf.DUMMYFUNCTION("""COMPUTED_VALUE"""),"4月 ") -> 4月 | AX81: =IFERROR(__xludf.DUMMYFUNCTION("""COMPUTED_VALUE"""),"3月") -> 3月 | BB81: =IFERROR(__xludf.DUMMYFUNCTION("""COMPUTED_VALUE"""),"2月") -> 2月 | BF81: =IFERROR(__xludf.DUMMYFUNCTION("""COMPUTED_VALUE"""),"1月") -> 1月
C82: =IFERROR(__xludf.DUMMYFUNCTION("""COMPUTED_VALUE"""),"打電件数") -> 打電件数 | D82: =IFERROR(__xludf.DUMMYFUNCTION("""COMPUTED_VALUE"""),"着電件数") -> 着電件数 | E82: =IFERROR(__xludf.DUMMYFUNCTION("""COMPUTED_VALUE"""),"着電率") -> 着電率 | F82: =IFERROR(__xludf.DUMMYFUNCTION("""COMPUTED_VALUE"""),"アポ数") -> アポ数 | G82: =IFERROR(__xludf.DUMMYFUNCTION("""COMPUTED_VALUE"""),"アポ率(着電から)") -> アポ率(着電から) | H82: =IFERROR(__xludf.DUMMYFUNCTION("""COMPUTED_VALUE"""),"LINE誘導数") -> LINE誘導数 | I82: =IFERROR(__xludf.DUMMYFUNCTION("""COMPUTED_VALUE"""),"LINE率(着電から)") -> LINE率(着電から) | R82: =IFERROR(__xludf.DUMMYFUNCTION("""COMPUTED_VALUE"""),"打電件数") -> 打電件数 | S82: =IFERROR(__xludf.DUMMYFUNCTION("""COMPUTED_VALUE"""),"着電件数") -> 着電件数 | T82: =IFERROR(__xludf.DUMMYFUNCTION("""COMPUTED_VALUE"""),"アポ数") -> アポ数 | U82: =IFERROR(__xludf.DUMMYFUNCTION("""COMPUTED_VALUE"""),"LINE誘導数") -> LINE誘導数 | V82: =IFERROR(__xludf.DUMMYFUNCTION("""COMPUTED_VALUE"""),"打電件数") -> 打電件数 | W82: =IFERROR(__xludf.DUMMYFUNCTION("""COMPUTED_VALUE"""),"着電件数") -> 着電件数 | X82: =IFERROR(__xludf.DUMMYFUNCTION("""COMPUTED_VALUE"""),"アポ数") -> アポ数 | Y82: =IFERROR(__xludf.DUMMYFUNCTION("""COMPUTED_VALUE"""),"LINE誘導数") -> LINE誘導数 | Z82: =IFERROR(__xludf.DUMMYFUNCTION("""COMPUTED_VALUE"""),"打電件数") -> 打電件数 | AA82: =IFERROR(__xludf.DUMMYFUNCTION("""COMPUTED_VALUE"""),"着電件数") -> 着電件数 | AB82: =IFERROR(__xludf.DUMMYFUNCTION("""COMPUTED_VALUE"""),"アポ数") -> アポ数 | AC82: =IFERROR(__xludf.DUMMYFUNCTION("""COMPUTED_VALUE"""),"LINE誘導数") -> LINE誘導数 | AD82: =IFERROR(__xludf.DUMMYFUNCTION("""COMPUTED_VALUE"""),"打電件数") -> 打電件数 | AE82: =IFERROR(__xludf.DUMMYFUNCTION("""COMPUTED_VALUE"""),"着電件数") -> 着電件数 | AF82: =IFERROR(__xludf.DUMMYFUNCTION("""COMPUTED_VALUE"""),"アポ数") -> アポ数 | AG82: =IFERROR(__xludf.DUMMYFUNCTION("""COMPUTED_VALUE"""),"LINE誘導数") -> LINE誘導数 | AH82: =IFERROR(__xludf.DUMMYFUNCTION("""COMPUTED_VALUE"""),"打電件数") -> 打電件数 | AI82: =IFERROR(__xludf.DUMMYFUNCTION("""COMPUTED_VALUE"""),"着電件数") -> 着電件数 | AJ82: =IFERROR(__xludf.DUMMYFUNCTION("""COMPUTED_VALUE"""),"アポ数") -> アポ数 | AK82: =IFERROR(__xludf.DUMMYFUNCTION("""COMPUTED_VALUE"""),"LINE誘導数") -> LINE誘導数 | AL82: =IFERROR(__xludf.DUMMYFUNCTION("""COMPUTED_VALUE"""),"打電件数") -> 打電件数 | AM82: =IFERROR(__xludf.DUMMYFUNCTION("""COMPUTED_VALUE"""),"着電件数") -> 着電件数 | AN82: =IFERROR(__xludf.DUMMYFUNCTION("""COMPUTED_VALUE"""),"アポ数") -> アポ数 | AO82: =IFERROR(__xludf.DUMMYFUNCTION("""COMPUTED_VALUE"""),"LINE誘導数") -> LINE誘導数 | AP82: =IFERROR(__xludf.DUMMYFUNCTION("""COMPUTED_VALUE"""),"打電件数") -> 打電件数 | AQ82: =IFERROR(__xludf.DUMMYFUNCTION("""COMPUTED_VALUE"""),"着電件数") -> 着電件数 | AR82: =IFERROR(__xludf.DUMMYFUNCTION("""COMPUTED_VALUE"""),"アポ数") -> アポ数 | AS82: =IFERROR(__xludf.DUMMYFUNCTION("""COMPUTED_VALUE"""),"LINE誘導数") -> LINE誘導数 | AT82: =IFERROR(__xludf.DUMMYFUNCTION("""COMPUTED_VALUE"""),"打電件数") -> 打電件数 | AU82: =IFERROR(__xludf.DUMMYFUNCTION("""COMPUTED_VALUE"""),"着電件数") -> 着電件数 | AV82: =IFERROR(__xludf.DUMMYFUNCTION("""COMPUTED_VALUE"""),"アポ数") -> アポ数 | AW82: =IFERROR(__xludf.DUMMYFUNCTION("""COMPUTED_VALUE"""),"LINE誘導数") -> LINE誘導数 | AX82: =IFERROR(__xludf.DUMMYFUNCTION("""COMPUTED_VALUE"""),"打電件数") -> 打電件数 | AY82: =IFERROR(__xludf.DUMMYFUNCTION("""COMPUTED_VALUE"""),"着電件数") -> 着電件数 | AZ82: =IFERROR(__xludf.DUMMYFUNCTION("""COMPUTED_VALUE"""),"アポ数") -> アポ数 | BA82: =IFERROR(__xludf.DUMMYFUNCTION("""COMPUTED_VALUE"""),"LINE誘導数") -> LINE誘導数 | BB82: =IFERROR(__xludf.DUMMYFUNCTION("""COMPUTED_VALUE"""),"打電件数") -> 打電件数 | BC82: =IFERROR(__xludf.DUMMYFUNCTION("""COMPUTED_VALUE"""),"着電件数") -> 着電件数 | BD82: =IFERROR(__xludf.DUMMYFUNCTION("""COMPUTED_VALUE"""),"アポ数") -> アポ数 | BE82: =IFERROR(__xludf.DUMMYFUNCTION("""COMPUTED_VALUE"""),"LINE誘導数") -> LINE誘導数 | BF82: =IFERROR(__xludf.DUMMYFUNCTION("""COMPUTED_VALUE"""),"打電件数") -> 打電件数 | BG82: =IFERROR(__xludf.DUMMYFUNCTION("""COMPUTED_VALUE"""),"着電件数") -> 着電件数 | BH82: =IFERROR(__xludf.DUMMYFUNCTION("""COMPUTED_VALUE"""),"アポ数") -> アポ数 | BI82: =IFERROR(__xludf.DUMMYFUNCTION("""COMPUTED_VALUE"""),"LINE誘導数") -> LINE誘導数
B83: =IFERROR(__xludf.DUMMYFUNCTION("""COMPUTED_VALUE"""),"TOTAL") -> TOTAL | C83: =IFERROR(__xludf.DUMMYFUNCTION("""COMPUTED_VALUE"""),894114.0) -> 894114 | D83: =IFERROR(__xludf.DUMMYFUNCTION("""COMPUTED_VALUE"""),61759.0) -> 61759 | E83: =IFERROR(__xludf.DUMMYFUNCTION("""COMPUTED_VALUE"""),0.06907284753398336) -> 0.069072848 | F83: =IFERROR(__xludf.DUMMYFUNCTION("""COMPUTED_VALUE"""),1958.0) -> 1958 | G83: =IFERROR(__xludf.DUMMYFUNCTION("""COMPUTED_VALUE"""),0.03170388121569326) -> 0.031703881 | H83: =IFERROR(__xludf.DUMMYFUNCTION("""COMPUTED_VALUE"""),2557.0) -> 2557 | I83: =IFERROR(__xludf.DUMMYFUNCTION("""COMPUTED_VALUE"""),0.0414028724558364) -> 0.041402872 | R83: =IFERROR(__xludf.DUMMYFUNCTION("""COMPUTED_VALUE"""),10398.0) -> 10398 | S83: =IFERROR(__xludf.DUMMYFUNCTION("""COMPUTED_VALUE"""),1209.0) -> 1209 | T83: =IFERROR(__xludf.DUMMYFUNCTION("""COMPUTED_VALUE"""),47.0) -> 47 | U83: =IFERROR(__xludf.DUMMYFUNCTION("""COMPUTED_VALUE"""),38.0) -> 38 | V83: =IFERROR(__xludf.DUMMYFUNCTION("""COMPUTED_VALUE"""),10579.0) -> 10579 | W83: =IFERROR(__xludf.DUMMYFUNCTION("""COMPUTED_VALUE"""),1716.0) -> 1716 | X83: =IFERROR(__xludf.DUMMYFUNCTION("""COMPUTED_VALUE"""),56.0) -> 56 | Y83: =IFERROR(__xludf.DUMMYFUNCTION("""COMPUTED_VALUE"""),23.0) -> 23 | Z83: =IFERROR(__xludf.DUMMYFUNCTION("""COMPUTED_VALUE"""),12471.0) -> 12471 | AA83: =IFERROR(__xludf.DUMMYFUNCTION("""COMPUTED_VALUE"""),665.0) -> 665 | AB83: =IFERROR(__xludf.DUMMYFUNCTION("""COMPUTED_VALUE"""),11.0) -> 11 | AC83: =IFERROR(__xludf.DUMMYFUNCTION("""COMPUTED_VALUE"""),13.0) -> 13 | AD83: =IFERROR(__xludf.DUMMYFUNCTION("""COMPUTED_VALUE"""),9829.0) -> 9829 | AE83: =IFERROR(__xludf.DUMMYFUNCTION("""COMPUTED_VALUE"""),3754.0) -> 3754 | AF83: =IFERROR(__xludf.DUMMYFUNCTION("""COMPUTED_VALUE"""),12.0) -> 12 | AG83: =IFERROR(__xludf.DUMMYFUNCTION("""COMPUTED_VALUE"""),41.0) -> 41 | AH83: =IFERROR(__xludf.DUMMYFUNCTION("""COMPUTED_VALUE"""),100011.0) -> 100011 | AI83: =IFERROR(__xludf.DUMMYFUNCTION("""COMPUTED_VALUE"""),3839.0) -> 3839 | AJ83: =IFERROR(__xludf.DUMMYFUNCTION("""COMPUTED_VALUE"""),49.0) -> 49 | AK83: =IFERROR(__xludf.DUMMYFUNCTION("""COMPUTED_VALUE"""),50.0) -> 50 | AL83: =IFERROR(__xludf.DUMMYFUNCTION("""COMPUTED_VALUE"""),191066.0) -> 191066 | AM83: =IFERROR(__xludf.DUMMYFUNCTION("""COMPUTED_VALUE"""),7980.0) -> 7980 | AN83: =IFERROR(__xludf.DUMMYFUNCTION("""COMPUTED_VALUE"""),189.0) -> 189 | AO83: =IFERROR(__xludf.DUMMYFUNCTION("""COMPUTED_VALUE"""),200.0) -> 200 | AP83: =IFERROR(__xludf.DUMMYFUNCTION("""COMPUTED_VALUE"""),151838.0) -> 151838 | AQ83: =IFERROR(__xludf.DUMMYFUNCTION("""COMPUTED_VALUE"""),5321.0) -> 5321 | AR83: =IFERROR(__xludf.DUMMYFUNCTION("""COMPUTED_VALUE"""),118.0) -> 118 | AS83: =IFERROR(__xludf.DUMMYFUNCTION("""COMPUTED_VALUE"""),125.0) -> 125 | AT83: =IFERROR(__xludf.DUMMYFUNCTION("""COMPUTED_VALUE"""),95781.0) -> 95781 | AU83: =IFERROR(__xludf.DUMMYFUNCTION("""COMPUTED_VALUE"""),4488.0) -> 4488 | AV83: =IFERROR(__xludf.DUMMYFUNCTION("""COMPUTED_VALUE"""),201.0) -> 201 | AW83: =IFERROR(__xludf.DUMMYFUNCTION("""COMPUTED_VALUE"""),269.0) -> 269 | AX83: =IFERROR(__xludf.DUMMYFUNCTION("""COMPUTED_VALUE"""),63823.0) -> 63823 | AY83: =IFERROR(__xludf.DUMMYFUNCTION("""COMPUTED_VALUE"""),4040.0) -> 4040 | AZ83: =IFERROR(__xludf.DUMMYFUNCTION("""COMPUTED_VALUE"""),149.0) -> 149 | BA83: =IFERROR(__xludf.DUMMYFUNCTION("""COMPUTED_VALUE"""),207.0) -> 207 | BB83: =IFERROR(__xludf.DUMMYFUNCTION("""COMPUTED_VALUE"""),48435.0) -> 48435 | BC83: =IFERROR(__xludf.DUMMYFUNCTION("""COMPUTED_VALUE"""),5039.0) -> 5039 | BD83: =IFERROR(__xludf.DUMMYFUNCTION("""COMPUTED_VALUE"""),111.0) -> 111 | BE83: =IFERROR(__xludf.DUMMYFUNCTION("""COMPUTED_VALUE"""),223.0) -> 223 | BF83: =IFERROR(__xludf.DUMMYFUNCTION("""COMPUTED_VALUE"""),31156.0) -> 31156 | BG83: =IFERROR(__xludf.DUMMYFUNCTION("""COMPUTED_VALUE"""),3724.0) -> 3724 | BH83: =IFERROR(__xludf.DUMMYFUNCTION("""COMPUTED_VALUE"""),141.0) -> 141 | BI83: =IFERROR(__xludf.DUMMYFUNCTION("""COMPUTED_VALUE"""),213.0) -> 213
B84: =IFERROR(__xludf.DUMMYFUNCTION("""COMPUTED_VALUE"""),"木村") -> 木村 | C84: =IFERROR(__xludf.DUMMYFUNCTION("""COMPUTED_VALUE"""),1427.0) -> 1427 | D84: =IFERROR(__xludf.DUMMYFUNCTION("""COMPUTED_VALUE"""),298.0) -> 298 | E84: =IFERROR(__xludf.DUMMYFUNCTION("""COMPUTED_VALUE"""),0.20882971268395234) -> 0.20882971 | F84: =IFERROR(__xludf.DUMMYFUNCTION("""COMPUTED_VALUE"""),17.0) -> 17 | G84: =IFERROR(__xludf.DUMMYFUNCTION("""COMPUTED_VALUE"""),0.05704697986577181) -> 0.05704698 | H84: =IFERROR(__xludf.DUMMYFUNCTION("""COMPUTED_VALUE"""),1.0) -> 1 | I84: =IFERROR(__xludf.DUMMYFUNCTION("""COMPUTED_VALUE"""),0.003355704697986577) -> 0.0033557047
B85: =IFERROR(__xludf.DUMMYFUNCTION("""COMPUTED_VALUE"""),"あり") -> あり | C85: =IFERROR(__xludf.DUMMYFUNCTION("""COMPUTED_VALUE"""),117562.0) -> 117562 | D85: =IFERROR(__xludf.DUMMYFUNCTION("""COMPUTED_VALUE"""),9214.0) -> 9214 | E85: =IFERROR(__xludf.DUMMYFUNCTION("""COMPUTED_VALUE"""),0.07837566560623331) -> 0.078375666 | F85: =IFERROR(__xludf.DUMMYFUNCTION("""COMPUTED_VALUE"""),391.0) -> 391 | G85: =IFERROR(__xludf.DUMMYFUNCTION("""COMPUTED_VALUE"""),0.042435424354243544) -> 0.042435424 | H85: =IFERROR(__xludf.DUMMYFUNCTION("""COMPUTED_VALUE"""),499.0) -> 499 | I85: =IFERROR(__xludf.DUMMYFUNCTION("""COMPUTED_VALUE"""),0.054156718037768614) -> 0.054156718 | R85: =IFERROR(__xludf.DUMMYFUNCTION("""COMPUTED_VALUE"""),1794.0) -> 1794 | S85: =IFERROR(__xludf.DUMMYFUNCTION("""COMPUTED_VALUE"""),204.0) -> 204 | T85: =IFERROR(__xludf.DUMMYFUNCTION("""COMPUTED_VALUE"""),6.0) -> 6 | U85: =IFERROR(__xludf.DUMMYFUNCTION("""COMPUTED_VALUE"""),5.0) -> 5 | V85: =IFERROR(__xludf.DUMMYFUNCTION("""COMPUTED_VALUE"""),1182.0) -> 1182 | W85: =IFERROR(__xludf.DUMMYFUNCTION("""COMPUTED_VALUE"""),210.0) -> 210 | X85: =IFERROR(__xludf.DUMMYFUNCTION("""COMPUTED_VALUE"""),6.0) -> 6 | Y85: =IFERROR(__xludf.DUMMYFUNCTION("""COMPUTED_VALUE"""),8.0) -> 8 | Z85: =IFERROR(__xludf.DUMMYFUNCTION("""COMPUTED_VALUE"""),1094.0) -> 1094 | AA85: =IFERROR(__xludf.DUMMYFUNCTION("""COMPUTED_VALUE"""),149.0) -> 149 | AB85: =IFERROR(__xludf.DUMMYFUNCTION("""COMPUTED_VALUE"""),7.0) -> 7 | AC85: =IFERROR(__xludf.DUMMYFUNCTION("""COMPUTED_VALUE"""),7.0) -> 7 | AD85: =IFERROR(__xludf.DUMMYFUNCTION("""COMPUTED_VALUE"""),3044.0) -> 3044 | AE85: =IFERROR(__xludf.DUMMYFUNCTION("""COMPUTED_VALUE"""),1118.0) -> 1118 | AF85: =IFERROR(__xludf.DUMMYFUNCTION("""COMPUTED_VALUE"""),5.0) -> 5 | AG85: =IFERROR(__xludf.DUMMYFUNCTION("""COMPUTED_VALUE"""),25.0) -> 25 | AH85: =IFERROR(__xludf.DUMMYFUNCTION("""COMPUTED_VALUE"""),11762.0) -> 11762 | AI85: =IFERROR(__xludf.DUMMYFUNCTION("""COMPUTED_VALUE"""),431.0) -> 431 | AJ85: =IFERROR(__xludf.DUMMYFUNCTION("""COMPUTED_VALUE"""),15.0) -> 15 | AK85: =IFERROR(__xludf.DUMMYFUNCTION("""COMPUTED_VALUE"""),14.0) -> 14 | AL85: =IFERROR(__xludf.DUMMYFUNCTION("""COMPUTED_VALUE"""),25723.0) -> 25723 | AM85: =IFERROR(__xludf.DUMMYFUNCTION("""COMPUTED_VALUE"""),956.0) -> 956 | AN85: =IFERROR(__xludf.DUMMYFUNCTION("""COMPUTED_VALUE"""),41.0) -> 41 | AO85: =IFERROR(__xludf.DUMMYFUNCTION("""COMPUTED_VALUE"""),42.0) -> 42 | AP85: =IFERROR(__xludf.DUMMYFUNCTION("""COMPUTED_VALUE"""),21361.0) -> 21361 | AQ85: =IFERROR(__xludf.DUMMYFUNCTION("""COMPUTED_VALUE"""),690.0) -> 690 | AR85: =IFERROR(__xludf.DUMMYFUNCTION("""COMPUTED_VALUE"""),43.0) -> 43 | AS85: =IFERROR(__xludf.DUMMYFUNCTION("""COMPUTED_VALUE"""),43.0) -> 43 | AT85: =IFERROR(__xludf.DUMMYFUNCTION("""COMPUTED_VALUE"""),7611.0) -> 7611 | AU85: =IFERROR(__xludf.DUMMYFUNCTION("""COMPUTED_VALUE"""),554.0) -> 554 | AV85: =IFERROR(__xludf.DUMMYFUNCTION("""COMPUTED_VALUE"""),36.0) -> 36 | AW85: =IFERROR(__xludf.DUMMYFUNCTION("""COMPUTED_VALUE"""),42.0) -> 42 | AX85: =IFERROR(__xludf.DUMMYFUNCTION("""COMPUTED_VALUE"""),8868.0) -> 8868 | AY85: =IFERROR(__xludf.DUMMYFUNCTION("""COMPUTED_VALUE"""),529.0) -> 529 | AZ85: =IFERROR(__xludf.DUMMYFUNCTION("""COMPUTED_VALUE"""),25.0) -> 25 | BA85: =IFERROR(__xludf.DUMMYFUNCTION("""COMPUTED_VALUE"""),30.0) -> 30 | BB85: =IFERROR(__xludf.DUMMYFUNCTION("""COMPUTED_VALUE"""),6021.0) -> 6021 | BC85: =IFERROR(__xludf.DUMMYFUNCTION("""COMPUTED_VALUE"""),646.0) -> 646 | BD85: =IFERROR(__xludf.DUMMYFUNCTION("""COMPUTED_VALUE"""),13.0) -> 13 | BE85: =IFERROR(__xludf.DUMMYFUNCTION("""COMPUTED_VALUE"""),31.0) -> 31 | BF85: =IFERROR(__xludf.DUMMYFUNCTION("""COMPUTED_VALUE"""),3723.0) -> 3723 | BG85: =IFERROR(__xludf.DUMMYFUNCTION("""COMPUTED_VALUE"""),447.0) -> 447 | BH85: =IFERROR(__xludf.DUMMYFUNCTION("""COMPUTED_VALUE"""),23.0) -> 23 | BI85: =IFERROR(__xludf.DUMMYFUNCTION("""COMPUTED_VALUE"""),33.0) -> 33
B86: =IFERROR(__xludf.DUMMYFUNCTION("""COMPUTED_VALUE"""),"太田") -> 太田 | C86: =IFERROR(__xludf.DUMMYFUNCTION("""COMPUTED_VALUE"""),117663.0) -> 117663 | D86: =IFERROR(__xludf.DUMMYFUNCTION("""COMPUTED_VALUE"""),8131.0) -> 8131 | E86: =IFERROR(__xludf.DUMMYFUNCTION("""COMPUTED_VALUE"""),0.06910413638951922) -> 0.069104136 | F86: =IFERROR(__xludf.DUMMYFUNCTION("""COMPUTED_VALUE"""),392.0) -> 392 | G86: =IFERROR(__xludf.DUMMYFUNCTION("""COMPUTED_VALUE"""),0.04821055220760054) -> 0.048210552 | H86: =IFERROR(__xludf.DUMMYFUNCTION("""COMPUTED_VALUE"""),458.0) -> 458 | I86: =IFERROR(__xludf.DUMMYFUNCTION("""COMPUTED_VALUE"""),0.05632763497724757) -> 0.056327635 | R86: =IFERROR(__xludf.DUMMYFUNCTION("""COMPUTED_VALUE"""),3436.0) -> 3436 | S86: =IFERROR(__xludf.DUMMYFUNCTION("""COMPUTED_VALUE"""),390.0) -> 390 | T86: =IFERROR(__xludf.DUMMYFUNCTION("""COMPUTED_VALUE"""),9.0) -> 9 | U86: =IFERROR(__xludf.DUMMYFUNCTION("""COMPUTED_VALUE"""),11.0) -> 11 | V86: =IFERROR(__xludf.DUMMYFUNCTION("""COMPUTED_VALUE"""),3394.0) -> 3394 | W86: =IFERROR(__xludf.DUMMYFUNCTION("""COMPUTED_VALUE"""),397.0) -> 397 | X86: =IFERROR(__xludf.DUMMYFUNCTION("""COMPUTED_VALUE"""),5.0) -> 5 | Y86: =IFERROR(__xludf.DUMMYFUNCTION("""COMPUTED_VALUE"""),8.0) -> 8 | Z86: =IFERROR(__xludf.DUMMYFUNCTION("""COMPUTED_VALUE"""),4103.0) -> 4103 | AA86: =IFERROR(__xludf.DUMMYFUNCTION("""COMPUTED_VALUE"""),61.0) -> 61 | AB86: =IFERROR(__xludf.DUMMYFUNCTION("""COMPUTED_VALUE"""),4.0) -> 4 | AC86: =IFERROR(__xludf.DUMMYFUNCTION("""COMPUTED_VALUE"""),4.0) -> 4 | AD86: =IFERROR(__xludf.DUMMYFUNCTION("""COMPUTED_VALUE"""),0.0) -> 0 | AE86: =IFERROR(__xludf.DUMMYFUNCTION("""COMPUTED_VALUE"""),0.0) -> 0 | AF86: =IFERROR(__xludf.DUMMYFUNCTION("""COMPUTED_VALUE"""),0.0) -> 0 | AG86: =IFERROR(__xludf.DUMMYFUNCTION("""COMPUTED_VALUE"""),0.0) -> 0 | AH86: =IFERROR(__xludf.DUMMYFUNCTION("""COMPUTED_VALUE"""),10213.0) -> 10213 | AI86: =IFERROR(__xludf.DUMMYFUNCTION("""COMPUTED_VALUE"""),457.0) -> 457 | AJ86: =IFERROR(__xludf.DUMMYFUNCTION("""COMPUTED_VALUE"""),16.0) -> 16 | AK86: =IFERROR(__xludf.DUMMYFUNCTION("""COMPUTED_VALUE"""),15.0) -> 15 | AL86: =IFERROR(__xludf.DUMMYFUNCTION("""COMPUTED_VALUE"""),24830.0) -> 24830 | AM86: =IFERROR(__xludf.DUMMYFUNCTION("""COMPUTED_VALUE"""),931.0) -> 931 | AN86: =IFERROR(__xludf.DUMMYFUNCTION("""COMPUTED_VALUE"""),44.0) -> 44 | AO86: =IFERROR(__xludf.DUMMYFUNCTION("""COMPUTED_VALUE"""),45.0) -> 45 | AP86: =IFERROR(__xludf.DUMMYFUNCTION("""COMPUTED_VALUE"""),20096.0) -> 20096 | AQ86: =IFERROR(__xludf.DUMMYFUNCTION("""COMPUTED_VALUE"""),725.0) -> 725 | AR86: =IFERROR(__xludf.DUMMYFUNCTION("""COMPUTED_VALUE"""),26.0) -> 26 | AS86: =IFERROR(__xludf.DUMMYFUNCTION("""COMPUTED_VALUE"""),27.0) -> 27 | AT86: =IFERROR(__xludf.DUMMYFUNCTION("""COMPUTED_VALUE"""),11312.0) -> 11312 | AU86: =IFERROR(__xludf.DUMMYFUNCTION("""COMPUTED_VALUE"""),435.0) -> 435 | AV86: =IFERROR(__xludf.DUMMYFUNCTION("""COMPUTED_VALUE"""),39.0) -> 39 | AW86: =IFERROR(__xludf.DUMMYFUNCTION("""COMPUTED_VALUE"""),49.0) -> 49 | AX86: =IFERROR(__xludf.DUMMYFUNCTION("""COMPUTED_VALUE"""),7554.0) -> 7554 | AY86: =IFERROR(__xludf.DUMMYFUNCTION("""COMPUTED_VALUE"""),276.0) -> 276 | AZ86: =IFERROR(__xludf.DUMMYFUNCTION("""COMPUTED_VALUE"""),28.0) -> 28 | BA86: =IFERROR(__xludf.DUMMYFUNCTION("""COMPUTED_VALUE"""),27.0) -> 27 | BB86: =IFERROR(__xludf.DUMMYFUNCTION("""COMPUTED_VALUE"""),6286.0) -> 6286 | BC86: =IFERROR(__xludf.DUMMYFUNCTION("""COMPUTED_VALUE"""),696.0) -> 696 | BD86: =IFERROR(__xludf.DUMMYFUNCTION("""COMPUTED_VALUE"""),20.0) -> 20 | BE86: =IFERROR(__xludf.DUMMYFUNCTION("""COMPUTED_VALUE"""),33.0) -> 33 | BF86: =IFERROR(__xludf.DUMMYFUNCTION("""COMPUTED_VALUE"""),3430.0) -> 3430 | BG86: =IFERROR(__xludf.DUMMYFUNCTION("""COMPUTED_VALUE"""),391.0) -> 391 | BH86: =IFERROR(__xludf.DUMMYFUNCTION("""COMPUTED_VALUE"""),16.0) -> 16 | BI86: =IFERROR(__xludf.DUMMYFUNCTION("""COMPUTED_VALUE"""),15.0) -> 15
B87: =IFERROR(__xludf.DUMMYFUNCTION("""COMPUTED_VALUE"""),"高坂") -> 高坂 | C87: =IFERROR(__xludf.DUMMYFUNCTION("""COMPUTED_VALUE"""),36495.0) -> 36495 | D87: =IFERROR(__xludf.DUMMYFUNCTION("""COMPUTED_VALUE"""),2732.0) -> 2732 | E87: =IFERROR(__xludf.DUMMYFUNCTION("""COMPUTED_VALUE"""),0.07485956980408275) -> 0.07485957 | F87: =IFERROR(__xludf.DUMMYFUNCTION("""COMPUTED_VALUE"""),103.0) -> 103 | G87: =IFERROR(__xludf.DUMMYFUNCTION("""COMPUTED_VALUE"""),0.037701317715959005) -> 0.037701318 | H87: =IFERROR(__xludf.DUMMYFUNCTION("""COMPUTED_VALUE"""),114.0) -> 114 | I87: =IFERROR(__xludf.DUMMYFUNCTION("""COMPUTED_VALUE"""),0.04172767203513909) -> 0.041727672 | R87: =IFERROR(__xludf.DUMMYFUNCTION("""COMPUTED_VALUE"""),0.0) -> 0 | S87: =IFERROR(__xludf.DUMMYFUNCTION("""COMPUTED_VALUE"""),0.0) -> 0 | T87: =IFERROR(__xludf.DUMMYFUNCTION("""COMPUTED_VALUE"""),0.0) -> 0 | U87: =IFERROR(__xludf.DUMMYFUNCTION("""COMPUTED_VALUE"""),0.0) -> 0 | V87: =IFERROR(__xludf.DUMMYFUNCTION("""COMPUTED_VALUE"""),0.0) -> 0 | W87: =IFERROR(__xludf.DUMMYFUNCTION("""COMPUTED_VALUE"""),0.0) -> 0 | X87: =IFERROR(__xludf.DUMMYFUNCTION("""COMPUTED_VALUE"""),0.0) -> 0 | Y87: =IFERROR(__xludf.DUMMYFUNCTION("""COMPUTED_VALUE"""),0.0) -> 0 | ... AS87: =IFERROR(__xludf.DUMMYFUNCTION("""COMPUTED_VALUE"""),0.0) -> 0 | AT87: =IFERROR(__xludf.DUMMYFUNCTION("""COMPUTED_VALUE"""),7423.0) -> 7423 | AU87: =IFERROR(__xludf.DUMMYFUNCTION("""COMPUTED_VALUE"""),245.0) -> 245 | AV87: =IFERROR(__xludf.DUMMYFUNCTION("""COMPUTED_VALUE"""),5.0) -> 5 | AW87: =IFERROR(__xludf.DUMMYFUNCTION("""COMPUTED_VALUE"""),7.0) -> 7 | AX87: =IFERROR(__xludf.DUMMYFUNCTION("""COMPUTED_VALUE"""),5282.0) -> 5282 | AY87: =IFERROR(__xludf.DUMMYFUNCTION("""COMPUTED_VALUE"""),231.0) -> 231 | AZ87: =IFERROR(__xludf.DUMMYFUNCTION("""COMPUTED_VALUE"""),14.0) -> 14 | BA87: =IFERROR(__xludf.DUMMYFUNCTION("""COMPUTED_VALUE"""),19.0) -> 19 | BB87: =IFERROR(__xludf.DUMMYFUNCTION("""COMPUTED_VALUE"""),5901.0) -> 5901 | BC87: =IFERROR(__xludf.DUMMYFUNCTION("""COMPUTED_VALUE"""),436.0) -> 436 | BD87: =IFERROR(__xludf.DUMMYFUNCTION("""COMPUTED_VALUE"""),6.0) -> 6 | BE87: =IFERROR(__xludf.DUMMYFUNCTION("""COMPUTED_VALUE"""),10.0) -> 10 | BF87: =IFERROR(__xludf.DUMMYFUNCTION("""COMPUTED_VALUE"""),2248.0) -> 2248 | BG87: =IFERROR(__xludf.DUMMYFUNCTION("""COMPUTED_VALUE"""),166.0) -> 166 | BH87: =IFERROR(__xludf.DUMMYFUNCTION("""COMPUTED_VALUE"""),7.0) -> 7 | BI87: =IFERROR(__xludf.DUMMYFUNCTION("""COMPUTED_VALUE"""),13.0) -> 13
B88: =IFERROR(__xludf.DUMMYFUNCTION("""COMPUTED_VALUE"""),"ジョナ") -> ジョナ | C88: =IFERROR(__xludf.DUMMYFUNCTION("""COMPUTED_VALUE"""),93438.0) -> 93438 | D88: =IFERROR(__xludf.DUMMYFUNCTION("""COMPUTED_VALUE"""),5279.0) -> 5279 | E88: =IFERROR(__xludf.DUMMYFUNCTION("""COMPUTED_VALUE"""),0.05649735653588476) -> 0.056497357 | F88: =IFERROR(__xludf.DUMMYFUNCTION("""COMPUTED_VALUE"""),216.0) -> 216 | G88: =IFERROR(__xludf.DUMMYFUNCTION("""COMPUTED_VALUE"""),0.0409168403106649) -> 0.04091684 | H88: =IFERROR(__xludf.DUMMYFUNCTION("""COMPUTED_VALUE"""),270.0) -> 270 | I88: =IFERROR(__xludf.DUMMYFUNCTION("""COMPUTED_VALUE"""),0.05114605038833112) -> 0.05114605 | R88: =IFERROR(__xludf.DUMMYFUNCTION("""COMPUTED_VALUE"""),0.0) -> 0 | S88: =IFERROR(__xludf.DUMMYFUNCTION("""COMPUTED_VALUE"""),0.0) -> 0 | T88: =IFERROR(__xludf.DUMMYFUNCTION("""COMPUTED_VALUE"""),0.0) -> 0 | U88: =IFERROR(__xludf.DUMMYFUNCTION("""COMPUTED_VALUE"""),0.0) -> 0 | V88: =IFERROR(__xludf.DUMMYFUNCTION("""COMPUTED_VALUE"""),0.0) -> 0 | W88: =IFERROR(__xludf.DUMMYFUNCTION("""COMPUTED_VALUE"""),0.0) -> 0 | X88: =IFERROR(__xludf.DUMMYFUNCTION("""COMPUTED_VALUE"""),0.0) -> 0 | Y88: =IFERROR(__xludf.DUMMYFUNCTION("""COMPUTED_VALUE"""),0.0) -> 0 | ... AG88: =IFERROR(__xludf.DUMMYFUNCTION("""COMPUTED_VALUE"""),0.0) -> 0 | AH88: =IFERROR(__xludf.DUMMYFUNCTION("""COMPUTED_VALUE"""),10143.0) -> 10143 | AI88: =IFERROR(__xludf.DUMMYFUNCTION("""COMPUTED_VALUE"""),403.0) -> 403 | AJ88: =IFERROR(__xludf.DUMMYFUNCTION("""COMPUTED_VALUE"""),0.0) -> 0 | AK88: =IFERROR(__xludf.DUMMYFUNCTION("""COMPUTED_VALUE"""),2.0) -> 2 | AL88: =IFERROR(__xludf.DUMMYFUNCTION("""COMPUTED_VALUE"""),13826.0) -> 13826 | AM88: =IFERROR(__xludf.DUMMYFUNCTION("""COMPUTED_VALUE"""),593.0) -> 593 | AN88: =IFERROR(__xludf.DUMMYFUNCTION("""COMPUTED_VALUE"""),7.0) -> 7 | AO88: =IFERROR(__xludf.DUMMYFUNCTION("""COMPUTED_VALUE"""),8.0) -> 8 | AP88: =IFERROR(__xludf.DUMMYFUNCTION("""COMPUTED_VALUE"""),16861.0) -> 16861 | AQ88: =IFERROR(__xludf.DUMMYFUNCTION("""COMPUTED_VALUE"""),619.0) -> 619 | AR88: =IFERROR(__xludf.DUMMYFUNCTION("""COMPUTED_VALUE"""),8.0) -> 8 | AS88: =IFERROR(__xludf.DUMMYFUNCTION("""COMPUTED_VALUE"""),6.0) -> 6 | AT88: =IFERROR(__xludf.DUMMYFUNCTION("""COMPUTED_VALUE"""),9578.0) -> 9578 | AU88: =IFERROR(__xludf.DUMMYFUNCTION("""COMPUTED_VALUE"""),314.0) -> 314 | AV88: =IFERROR(__xludf.DUMMYFUNCTION("""COMPUTED_VALUE"""),12.0) -> 12 | AW88: =IFERROR(__xludf.DUMMYFUNCTION("""COMPUTED_VALUE"""),22.0) -> 22 | AX88: =IFERROR(__xludf.DUMMYFUNCTION("""COMPUTED_VALUE"""),4380.0) -> 4380 | AY88: =IFERROR(__xludf.DUMMYFUNCTION("""COMPUTED_VALUE"""),284.0) -> 284 | AZ88: =IFERROR(__xludf.DUMMYFUNCTION("""COMPUTED_VALUE"""),20.0) -> 20 | BA88: =IFERROR(__xludf.DUMMYFUNCTION("""COMPUTED_VALUE"""),32.0) -> 32 | BB88: =IFERROR(__xludf.DUMMYFUNCTION("""COMPUTED_VALUE"""),5940.0) -> 5940 | BC88: =IFERROR(__xludf.DUMMYFUNCTION("""COMPUTED_VALUE"""),510.0) -> 510 | BD88: =IFERROR(__xludf.DUMMYFUNCTION("""COMPUTED_VALUE"""),7.0) -> 7 | BE88: =IFERROR(__xludf.DUMMYFUNCTION("""COMPUTED_VALUE"""),14.0) -> 14 | BF88: =IFERROR(__xludf.DUMMYFUNCTION("""COMPUTED_VALUE"""),3458.0) -> 3458 | BG88: =IFERROR(__xludf.DUMMYFUNCTION("""COMPUTED_VALUE"""),310.0) -> 310 | BH88: =IFERROR(__xludf.DUMMYFUNCTION("""COMPUTED_VALUE"""),13.0) -> 13 | BI88: =IFERROR(__xludf.DUMMYFUNCTION("""COMPUTED_VALUE"""),20.0) -> 20
B89: =IFERROR(__xludf.DUMMYFUNCTION("""COMPUTED_VALUE"""),"武田") -> 武田 | C89: =IFERROR(__xludf.DUMMYFUNCTION("""COMPUTED_VALUE"""),21297.0) -> 21297 | D89: =IFERROR(__xludf.DUMMYFUNCTION("""COMPUTED_VALUE"""),2236.0) -> 2236 | E89: =IFERROR(__xludf.DUMMYFUNCTION("""COMPUTED_VALUE"""),0.10499131333051603) -> 0.10499131 | F89: =IFERROR(__xludf.DUMMYFUNCTION("""COMPUTED_VALUE"""),197.0) -> 197 | G89: =IFERROR(__xludf.DUMMYFUNCTION("""COMPUTED_VALUE"""),0.08810375670840787) -> 0.088103757 | H89: =IFERROR(__xludf.DUMMYFUNCTION("""COMPUTED_VALUE"""),289.0) -> 289 | I89: =IFERROR(__xludf.DUMMYFUNCTION("""COMPUTED_VALUE"""),0.12924865831842575) -> 0.12924866 | R89: =IFERROR(__xludf.DUMMYFUNCTION("""COMPUTED_VALUE"""),0.0) -> 0 | S89: =IFERROR(__xludf.DUMMYFUNCTION("""COMPUTED_VALUE"""),0.0) -> 0 | T89: =IFERROR(__xludf.DUMMYFUNCTION("""COMPUTED_VALUE"""),0.0) -> 0 | U89: =IFERROR(__xludf.DUMMYFUNCTION("""COMPUTED_VALUE"""),0.0) -> 0 | V89: =IFERROR(__xludf.DUMMYFUNCTION("""COMPUTED_VALUE"""),0.0) -> 0 | W89: =IFERROR(__xludf.DUMMYFUNCTION("""COMPUTED_VALUE"""),0.0) -> 0 | X89: =IFERROR(__xludf.DUMMYFUNCTION("""COMPUTED_VALUE"""),0.0) -> 0 | Y89: =IFERROR(__xludf.DUMMYFUNCTION("""COMPUTED_VALUE"""),0.0) -> 0 | ... AD89: =IFERROR(__xludf.DUMMYFUNCTION("""COMPUTED_VALUE"""),0.0) -> 0 | AE89: =IFERROR(__xludf.DUMMYFUNCTION("""COMPUTED_VALUE"""),32.0) -> 32 | AF89: =IFERROR(__xludf.DUMMYFUNCTION("""COMPUTED_VALUE"""),0.0) -> 0 | AG89: =IFERROR(__xludf.DUMMYFUNCTION("""COMPUTED_VALUE"""),0.0) -> 0 | AH89: =IFERROR(__xludf.DUMMYFUNCTION("""COMPUTED_VALUE"""),0.0) -> 0 | AI89: =IFERROR(__xludf.DUMMYFUNCTION("""COMPUTED_VALUE"""),0.0) -> 0 | AJ89: =IFERROR(__xludf.DUMMYFUNCTION("""COMPUTED_VALUE"""),0.0) -> 0 | AK89: =IFERROR(__xludf.DUMMYFUNCTION("""COMPUTED_VALUE"""),0.0) -> 0 | AL89: =IFERROR(__xludf.DUMMYFUNCTION("""COMPUTED_VALUE"""),0.0) -> 0 | AM89: =IFERROR(__xludf.DUMMYFUNCTION("""COMPUTED_VALUE"""),0.0) -> 0 | ... AS89: =IFERROR(__xludf.DUMMYFUNCTION("""COMPUTED_VALUE"""),0.0) -> 0 | AT89: =IFERROR(__xludf.DUMMYFUNCTION("""COMPUTED_VALUE"""),6660.0) -> 6660 | AU89: =IFERROR(__xludf.DUMMYFUNCTION("""COMPUTED_VALUE"""),0.0) -> 0 | AV89: =IFERROR(__xludf.DUMMYFUNCTION("""COMPUTED_VALUE"""),13.0) -> 13 | AW89: =IFERROR(__xludf.DUMMYFUNCTION("""COMPUTED_VALUE"""),20.0) -> 20 | AX89: =IFERROR(__xludf.DUMMYFUNCTION("""COMPUTED_VALUE"""),25.0) -> 25 | AY89: =IFERROR(__xludf.DUMMYFUNCTION("""COMPUTED_VALUE"""),4.0) -> 4 | AZ89: =IFERROR(__xludf.DUMMYFUNCTION("""COMPUTED_VALUE"""),8.0) -> 8 | BA89: =IFERROR(__xludf.DUMMYFUNCTION("""COMPUTED_VALUE"""),9.0) -> 9 | BB89: =IFERROR(__xludf.DUMMYFUNCTION("""COMPUTED_VALUE"""),1426.0) -> 1426 | BC89: =IFERROR(__xludf.DUMMYFUNCTION("""COMPUTED_VALUE"""),176.0) -> 176 | BD89: =IFERROR(__xludf.DUMMYFUNCTION("""COMPUTED_VALUE"""),11.0) -> 11 | BE89: =IFERROR(__xludf.DUMMYFUNCTION("""COMPUTED_VALUE"""),30.0) -> 30 | BF89: =IFERROR(__xludf.DUMMYFUNCTION("""COMPUTED_VALUE"""),1761.0) -> 1761 | BG89: =IFERROR(__xludf.DUMMYFUNCTION("""COMPUTED_VALUE"""),362.0) -> 362 | BH89: =IFERROR(__xludf.DUMMYFUNCTION("""COMPUTED_VALUE"""),21.0) -> 21 | BI89: =IFERROR(__xludf.DUMMYFUNCTION("""COMPUTED_VALUE"""),28.0) -> 28
B90: =IFERROR(__xludf.DUMMYFUNCTION("""COMPUTED_VALUE"""),"山本") -> 山本 | C90: =IFERROR(__xludf.DUMMYFUNCTION("""COMPUTED_VALUE"""),5906.0) -> 5906 | D90: =IFERROR(__xludf.DUMMYFUNCTION("""COMPUTED_VALUE"""),727.0) -> 727 | E90: =IFERROR(__xludf.DUMMYFUNCTION("""COMPUTED_VALUE"""),0.12309515746698273) -> 0.12309516 | F90: =IFERROR(__xludf.DUMMYFUNCTION("""COMPUTED_VALUE"""),15.0) -> 15 | G90: =IFERROR(__xludf.DUMMYFUNCTION("""COMPUTED_VALUE"""),0.02063273727647868) -> 0.020632737 | H90: =IFERROR(__xludf.DUMMYFUNCTION("""COMPUTED_VALUE"""),32.0) -> 32 | I90: =IFERROR(__xludf.DUMMYFUNCTION("""COMPUTED_VALUE"""),0.04401650618982118) -> 0.044016506 | R90: =IFERROR(__xludf.DUMMYFUNCTION("""COMPUTED_VALUE"""),0.0) -> 0 | S90: =IFERROR(__xludf.DUMMYFUNCTION("""COMPUTED_VALUE"""),0.0) -> 0 | T90: =IFERROR(__xludf.DUMMYFUNCTION("""COMPUTED_VALUE"""),0.0) -> 0 | U90: =IFERROR(__xludf.DUMMYFUNCTION("""COMPUTED_VALUE"""),0.0) -> 0 | V90: =IFERROR(__xludf.DUMMYFUNCTION("""COMPUTED_VALUE"""),0.0) -> 0 | W90: =IFERROR(__xludf.DUMMYFUNCTION("""COMPUTED_VALUE"""),0.0) -> 0 | X90: =IFERROR(__xludf.DUMMYFUNCTION("""COMPUTED_VALUE"""),0.0) -> 0 | Y90: =IFERROR(__xludf.DUMMYFUNCTION("""COMPUTED_VALUE"""),0.0) -> 0 | ... AO90: =IFERROR(__xludf.DUMMYFUNCTION("""COMPUTED_VALUE"""),0.0) -> 0 | AT90: =IFERROR(__xludf.DUMMYFUNCTION("""COMPUTED_VALUE"""),0.0) -> 0 | AU90: =IFERROR(__xludf.DUMMYFUNCTION("""COMPUTED_VALUE"""),0.0) -> 0 | AV90: =IFERROR(__xludf.DUMMYFUNCTION("""COMPUTED_VALUE"""),0.0) -> 0 | AW90: =IFERROR(__xludf.DUMMYFUNCTION("""COMPUTED_VALUE"""),0.0) -> 0 | AX90: =IFERROR(__xludf.DUMMYFUNCTION("""COMPUTED_VALUE"""),0.0) -> 0 | AY90: =IFERROR(__xludf.DUMMYFUNCTION("""COMPUTED_VALUE"""),0.0) -> 0 | AZ90: =IFERROR(__xludf.DUMMYFUNCTION("""COMPUTED_VALUE"""),0.0) -> 0 | BA90: =IFERROR(__xludf.DUMMYFUNCTION("""COMPUTED_VALUE"""),0.0) -> 0 | ... BI90: =IFERROR(__xludf.DUMMYFUNCTION("""COMPUTED_VALUE"""),0.0) -> 0
B91: =IFERROR(__xludf.DUMMYFUNCTION("""COMPUTED_VALUE"""),"高木") -> 高木 | C91: =IFERROR(__xludf.DUMMYFUNCTION("""COMPUTED_VALUE"""),106843.0) -> 106843 | D91: =IFERROR(__xludf.DUMMYFUNCTION("""COMPUTED_VALUE"""),8495.0) -> 8495 | E91: =IFERROR(__xludf.DUMMYFUNCTION("""COMPUTED_VALUE"""),0.07950918637627173) -> 0.079509186 | F91: =IFERROR(__xludf.DUMMYFUNCTION("""COMPUTED_VALUE"""),113.5) -> 113.5 | G91: =IFERROR(__xludf.DUMMYFUNCTION("""COMPUTED_VALUE"""),0.013360800470865216) -> 0.0133608 | H91: =IFERROR(__xludf.DUMMYFUNCTION("""COMPUTED_VALUE"""),186.0) -> 186 | I91: =IFERROR(__xludf.DUMMYFUNCTION("""COMPUTED_VALUE"""),0.021895232489699823) -> 0.021895232 | R91: =IFERROR(__xludf.DUMMYFUNCTION("""COMPUTED_VALUE"""),1754.0) -> 1754 | S91: =IFERROR(__xludf.DUMMYFUNCTION("""COMPUTED_VALUE"""),227.0) -> 227 | T91: =IFERROR(__xludf.DUMMYFUNCTION("""COMPUTED_VALUE"""),1.0) -> 1 | U91: =IFERROR(__xludf.DUMMYFUNCTION("""COMPUTED_VALUE"""),5.0) -> 5 | V91: =IFERROR(__xludf.DUMMYFUNCTION("""COMPUTED_VALUE"""),2255.0) -> 2255 | W91: =IFERROR(__xludf.DUMMYFUNCTION("""COMPUTED_VALUE"""),420.0) -> 420 | X91: =IFERROR(__xludf.DUMMYFUNCTION("""COMPUTED_VALUE"""),4.0) -> 4 | Y91: =IFERROR(__xludf.DUMMYFUNCTION("""COMPUTED_VALUE"""),4.0) -> 4 | Z91: =IFERROR(__xludf.DUMMYFUNCTION("""COMPUTED_VALUE"""),3224.0) -> 3224 | AA91: =IFERROR(__xludf.DUMMYFUNCTION("""COMPUTED_VALUE"""),317.0) -> 317 | AB91: =IFERROR(__xludf.DUMMYFUNCTION("""COMPUTED_VALUE"""),0.0) -> 0 | AC91: =IFERROR(__xludf.DUMMYFUNCTION("""COMPUTED_VALUE"""),1.0) -> 1 | AD91: =IFERROR(__xludf.DUMMYFUNCTION("""COMPUTED_VALUE"""),2967.0) -> 2967 | AE91: =IFERROR(__xludf.DUMMYFUNCTION("""COMPUTED_VALUE"""),1225.0) -> 1225 | AF91: =IFERROR(__xludf.DUMMYFUNCTION("""COMPUTED_VALUE"""),5.0) -> 5 | AG91: =IFERROR(__xludf.DUMMYFUNCTION("""COMPUTED_VALUE"""),10.0) -> 10 | AH91: =IFERROR(__xludf.DUMMYFUNCTION("""COMPUTED_VALUE"""),12793.0) -> 12793 | AI91: =IFERROR(__xludf.DUMMYFUNCTION("""COMPUTED_VALUE"""),429.0) -> 429 | AJ91: =IFERROR(__xludf.DUMMYFUNCTION("""COMPUTED_VALUE"""),2.0) -> 2 | AK91: =IFERROR(__xludf.DUMMYFUNCTION("""COMPUTED_VALUE"""),5.0) -> 5 | AL91: =IFERROR(__xludf.DUMMYFUNCTION("""COMPUTED_VALUE"""),21242.0) -> 21242 | AM91: =IFERROR(__xludf.DUMMYFUNCTION("""COMPUTED_VALUE"""),776.0) -> 776 | AN91: =IFERROR(__xludf.DUMMYFUNCTION("""COMPUTED_VALUE"""),9.0) -> 9 | AO91: =IFERROR(__xludf.DUMMYFUNCTION("""COMPUTED_VALUE"""),8.0) -> 8 | AP91: =IFERROR(__xludf.DUMMYFUNCTION("""COMPUTED_VALUE"""),21564.0) -> 21564 | AQ91: =IFERROR(__xludf.DUMMYFUNCTION("""COMPUTED_VALUE"""),1016.0) -> 1016 | AR91: =IFERROR(__xludf.DUMMYFUNCTION("""COMPUTED_VALUE"""),7.5) -> 7.5 | AS91: =IFERROR(__xludf.DUMMYFUNCTION("""COMPUTED_VALUE"""),11.0) -> 11 | AT91: =IFERROR(__xludf.DUMMYFUNCTION("""COMPUTED_VALUE"""),8015.0) -> 8015 | AU91: =IFERROR(__xludf.DUMMYFUNCTION("""COMPUTED_VALUE"""),492.0) -> 492 | AV91: =IFERROR(__xludf.DUMMYFUNCTION("""COMPUTED_VALUE"""),6.0) -> 6 | AW91: =IFERROR(__xludf.DUMMYFUNCTION("""COMPUTED_VALUE"""),10.0) -> 10 | AX91: =IFERROR(__xludf.DUMMYFUNCTION("""COMPUTED_VALUE"""),8536.0) -> 8536 | AY91: =IFERROR(__xludf.DUMMYFUNCTION("""COMPUTED_VALUE"""),398.0) -> 398 | AZ91: =IFERROR(__xludf.DUMMYFUNCTION("""COMPUTED_VALUE"""),5.0) -> 5 | BA91: =IFERROR(__xludf.DUMMYFUNCTION("""COMPUTED_VALUE"""),8.0) -> 8 | BB91: =IFERROR(__xludf.DUMMYFUNCTION("""COMPUTED_VALUE"""),5280.0) -> 5280 | BC91: =IFERROR(__xludf.DUMMYFUNCTION("""COMPUTED_VALUE"""),488.0) -> 488 | BD91: =IFERROR(__xludf.DUMMYFUNCTION("""COMPUTED_VALUE"""),7.0) -> 7 | BE91: =IFERROR(__xludf.DUMMYFUNCTION("""COMPUTED_VALUE"""),13.0) -> 13 | BF91: =IFERROR(__xludf.DUMMYFUNCTION("""COMPUTED_VALUE"""),4053.0) -> 4053 | BG91: =IFERROR(__xludf.DUMMYFUNCTION("""COMPUTED_VALUE"""),539.0) -> 539 | BH91: =IFERROR(__xludf.DUMMYFUNCTION("""COMPUTED_VALUE"""),19.0) -> 19 | BI91: =IFERROR(__xludf.DUMMYFUNCTION("""COMPUTED_VALUE"""),29.0) -> 29
B92: =IFERROR(__xludf.DUMMYFUNCTION("""COMPUTED_VALUE"""),"中原") -> 中原 | R92: =IFERROR(__xludf.DUMMYFUNCTION("""COMPUTED_VALUE"""),0.0) -> 0 | S92: =IFERROR(__xludf.DUMMYFUNCTION("""COMPUTED_VALUE"""),0.0) -> 0 | T92: =IFERROR(__xludf.DUMMYFUNCTION("""COMPUTED_VALUE"""),0.0) -> 0 | U92: =IFERROR(__xludf.DUMMYFUNCTION("""COMPUTED_VALUE"""),0.0) -> 0 | V92: =IFERROR(__xludf.DUMMYFUNCTION("""COMPUTED_VALUE"""),0.0) -> 0 | W92: =IFERROR(__xludf.DUMMYFUNCTION("""COMPUTED_VALUE"""),0.0) -> 0 | X92: =IFERROR(__xludf.DUMMYFUNCTION("""COMPUTED_VALUE"""),0.0) -> 0 | Y92: =IFERROR(__xludf.DUMMYFUNCTION("""COMPUTED_VALUE"""),0.0) -> 0 | ... AO92: =IFERROR(__xludf.DUMMYFUNCTION("""COMPUTED_VALUE"""),0.0) -> 0
B93: =IFERROR(__xludf.DUMMYFUNCTION("""COMPUTED_VALUE"""),"小西") -> 小西 | C93: =IFERROR(__xludf.DUMMYFUNCTION("""COMPUTED_VALUE"""),11451.0) -> 11451 | D93: =IFERROR(__xludf.DUMMYFUNCTION("""COMPUTED_VALUE"""),876.0) -> 876 | E93: =IFERROR(__xludf.DUMMYFUNCTION("""COMPUTED_VALUE"""),0.07649986900707362) -> 0.076499869 | F93: =IFERROR(__xludf.DUMMYFUNCTION("""COMPUTED_VALUE"""),12.0) -> 12 | G93: =IFERROR(__xludf.DUMMYFUNCTION("""COMPUTED_VALUE"""),0.0136986301369863) -> 0.01369863 | H93: =IFERROR(__xludf.DUMMYFUNCTION("""COMPUTED_VALUE"""),29.0) -> 29 | I93: =IFERROR(__xludf.DUMMYFUNCTION("""COMPUTED_VALUE"""),0.033105022831050226) -> 0.033105023 | R93: =IFERROR(__xludf.DUMMYFUNCTION("""COMPUTED_VALUE"""),0.0) -> 0 | S93: =IFERROR(__xludf.DUMMYFUNCTION("""COMPUTED_VALUE"""),0.0) -> 0 | T93: =IFERROR(__xludf.DUMMYFUNCTION("""COMPUTED_VALUE"""),0.0) -> 0 | U93: =IFERROR(__xludf.DUMMYFUNCTION("""COMPUTED_VALUE"""),0.0) -> 0 | V93: =IFERROR(__xludf.DUMMYFUNCTION("""COMPUTED_VALUE"""),0.0) -> 0 | W93: =IFERROR(__xludf.DUMMYFUNCTION("""COMPUTED_VALUE"""),0.0) -> 0 | X93: =IFERROR(__xludf.DUMMYFUNCTION("""COMPUTED_VALUE"""),0.0) -> 0 | Y93: =IFERROR(__xludf.DUMMYFUNCTION("""COMPUTED_VALUE"""),0.0) -> 0 | ... BE93: =IFERROR(__xludf.DUMMYFUNCTION("""COMPUTED_VALUE"""),0.0) -> 0 | BF93: =IFERROR(__xludf.DUMMYFUNCTION("""COMPUTED_VALUE"""),829.0) -> 829 | BG93: =IFERROR(__xludf.DUMMYFUNCTION("""COMPUTED_VALUE"""),43.0) -> 43 | BH93: =IFERROR(__xludf.DUMMYFUNCTION("""COMPUTED_VALUE"""),1.0) -> 1 | BI93: =IFERROR(__xludf.DUMMYFUNCTION("""COMPUTED_VALUE"""),2.0) -> 2
B94: =IFERROR(__xludf.DUMMYFUNCTION("""COMPUTED_VALUE"""),"ソラ") -> ソラ | C94: =IFERROR(__xludf.DUMMYFUNCTION("""COMPUTED_VALUE"""),41828.0) -> 41828 | D94: =IFERROR(__xludf.DUMMYFUNCTION("""COMPUTED_VALUE"""),1676.0) -> 1676 | E94: =IFERROR(__xludf.DUMMYFUNCTION("""COMPUTED_VALUE"""),0.04006885339963661) -> 0.040068853 | F94: =IFERROR(__xludf.DUMMYFUNCTION("""COMPUTED_VALUE"""),54.0) -> 54 | G94: =IFERROR(__xludf.DUMMYFUNCTION("""COMPUTED_VALUE"""),0.032219570405727926) -> 0.03221957 | H94: =IFERROR(__xludf.DUMMYFUNCTION("""COMPUTED_VALUE"""),60.0) -> 60 | I94: =IFERROR(__xludf.DUMMYFUNCTION("""COMPUTED_VALUE"""),0.03579952267303103) -> 0.035799523 | R94: =IFERROR(__xludf.DUMMYFUNCTION("""COMPUTED_VALUE"""),0.0) -> 0 | S94: =IFERROR(__xludf.DUMMYFUNCTION("""COMPUTED_VALUE"""),0.0) -> 0 | T94: =IFERROR(__xludf.DUMMYFUNCTION("""COMPUTED_VALUE"""),0.0) -> 0 | U94: =IFERROR(__xludf.DUMMYFUNCTION("""COMPUTED_VALUE"""),0.0) -> 0 | V94: =IFERROR(__xludf.DUMMYFUNCTION("""COMPUTED_VALUE"""),0.0) -> 0 | W94: =IFERROR(__xludf.DUMMYFUNCTION("""COMPUTED_VALUE"""),0.0) -> 0 | X94: =IFERROR(__xludf.DUMMYFUNCTION("""COMPUTED_VALUE"""),0.0) -> 0 | Y94: =IFERROR(__xludf.DUMMYFUNCTION("""COMPUTED_VALUE"""),0.0) -> 0 | ... AC94: =IFERROR(__xludf.DUMMYFUNCTION("""COMPUTED_VALUE"""),0.0) -> 0 | AD94: =IFERROR(__xludf.DUMMYFUNCTION("""COMPUTED_VALUE"""),850.0) -> 850 | AE94: =IFERROR(__xludf.DUMMYFUNCTION("""COMPUTED_VALUE"""),0.0) -> 0 | AF94: =IFERROR(__xludf.DUMMYFUNCTION("""COMPUTED_VALUE"""),0.0) -> 0 | AG94: =IFERROR(__xludf.DUMMYFUNCTION("""COMPUTED_VALUE"""),0.0) -> 0 | AH94: =IFERROR(__xludf.DUMMYFUNCTION("""COMPUTED_VALUE"""),14973.0) -> 14973 | AI94: =IFERROR(__xludf.DUMMYFUNCTION("""COMPUTED_VALUE"""),516.0) -> 516 | AJ94: =IFERROR(__xludf.DUMMYFUNCTION("""COMPUTED_VALUE"""),5.0) -> 5 | AK94: =IFERROR(__xludf.DUMMYFUNCTION("""COMPUTED_VALUE"""),3.0) -> 3 | AL94: =IFERROR(__xludf.DUMMYFUNCTION("""COMPUTED_VALUE"""),25923.0) -> 25923 | AM94: =IFERROR(__xludf.DUMMYFUNCTION("""COMPUTED_VALUE"""),1152.0) -> 1152 | AN94: =IFERROR(__xludf.DUMMYFUNCTION("""COMPUTED_VALUE"""),47.0) -> 47 | AO94: =IFERROR(__xludf.DUMMYFUNCTION("""COMPUTED_VALUE"""),54.0) -> 54
B95: =IFERROR(__xludf.DUMMYFUNCTION("""COMPUTED_VALUE"""),"森") -> 森 | C95: =IFERROR(__xludf.DUMMYFUNCTION("""COMPUTED_VALUE"""),5584.0) -> 5584 | D95: =IFERROR(__xludf.DUMMYFUNCTION("""COMPUTED_VALUE"""),844.0) -> 844 | E95: =IFERROR(__xludf.DUMMYFUNCTION("""COMPUTED_VALUE"""),0.1511461318051576) -> 0.15114613 | F95: =IFERROR(__xludf.DUMMYFUNCTION("""COMPUTED_VALUE"""),17.0) -> 17 | G95: =IFERROR(__xludf.DUMMYFUNCTION("""COMPUTED_VALUE"""),0.02014218009478673) -> 0.02014218 | H95: =IFERROR(__xludf.DUMMYFUNCTION("""COMPUTED_VALUE"""),47.0) -> 47 | I95: =IFERROR(__xludf.DUMMYFUNCTION("""COMPUTED_VALUE"""),0.05568720379146919) -> 0.055687204 | R95: =IFERROR(__xludf.DUMMYFUNCTION("""COMPUTED_VALUE"""),0.0) -> 0 | S95: =IFERROR(__xludf.DUMMYFUNCTION("""COMPUTED_VALUE"""),0.0) -> 0 | T95: =IFERROR(__xludf.DUMMYFUNCTION("""COMPUTED_VALUE"""),0.0) -> 0 | V95: =IFERROR(__xludf.DUMMYFUNCTION("""COMPUTED_VALUE"""),0.0) -> 0 | W95: =IFERROR(__xludf.DUMMYFUNCTION("""COMPUTED_VALUE"""),0.0) -> 0 | X95: =IFERROR(__xludf.DUMMYFUNCTION("""COMPUTED_VALUE"""),0.0) -> 0 | Z95: =IFERROR(__xludf.DUMMYFUNCTION("""COMPUTED_VALUE"""),0.0) -> 0 | AA95: =IFERROR(__xludf.DUMMYFUNCTION("""COMPUTED_VALUE"""),0.0) -> 0 | AB95: =IFERROR(__xludf.DUMMYFUNCTION("""COMPUTED_VALUE"""),0.0) -> 0 | AD95: =IFERROR(__xludf.DUMMYFUNCTION("""COMPUTED_VALUE"""),0.0) -> 0 | AE95: =IFERROR(__xludf.DUMMYFUNCTION("""COMPUTED_VALUE"""),0.0) -> 0 | AF95: =IFERROR(__xludf.DUMMYFUNCTION("""COMPUTED_VALUE"""),0.0) -> 0 | AH95: =IFERROR(__xludf.DUMMYFUNCTION("""COMPUTED_VALUE"""),0.0) -> 0 | AI95: =IFERROR(__xludf.DUMMYFUNCTION("""COMPUTED_VALUE"""),0.0) -> 0 | AJ95: =IFERROR(__xludf.DUMMYFUNCTION("""COMPUTED_VALUE"""),0.0) -> 0 | AL95: =IFERROR(__xludf.DUMMYFUNCTION("""COMPUTED_VALUE"""),0.0) -> 0 | AM95: =IFERROR(__xludf.DUMMYFUNCTION("""COMPUTED_VALUE"""),0.0) -> 0 | AN95: =IFERROR(__xludf.DUMMYFUNCTION("""COMPUTED_VALUE"""),0.0) -> 0 | BF95: =IFERROR(__xludf.DUMMYFUNCTION("""COMPUTED_VALUE"""),0.0) -> 0 | BG95: =IFERROR(__xludf.DUMMYFUNCTION("""COMPUTED_VALUE"""),0.0) -> 0 | BH95: =IFERROR(__xludf.DUMMYFUNCTION("""COMPUTED_VALUE"""),0.0) -> 0 | BI95: =IFERROR(__xludf.DUMMYFUNCTION("""COMPUTED_VALUE"""),0.0) -> 0
B96: =IFERROR(__xludf.DUMMYFUNCTION("""COMPUTED_VALUE"""),"大谷") -> 大谷 | C96: =IFERROR(__xludf.DUMMYFUNCTION("""COMPUTED_VALUE"""),89697.0) -> 89697 | D96: =IFERROR(__xludf.DUMMYFUNCTION("""COMPUTED_VALUE"""),3780.0) -> 3780 | E96: =IFERROR(__xludf.DUMMYFUNCTION("""COMPUTED_VALUE"""),0.042141877654771065) -> 0.042141878 | F96: =IFERROR(__xludf.DUMMYFUNCTION("""COMPUTED_VALUE"""),63.5) -> 63.5 | G96: =IFERROR(__xludf.DUMMYFUNCTION("""COMPUTED_VALUE"""),0.0167989417989418) -> 0.016798942 | H96: =IFERROR(__xludf.DUMMYFUNCTION("""COMPUTED_VALUE"""),108.0) -> 108 | I96: =IFERROR(__xludf.DUMMYFUNCTION("""COMPUTED_VALUE"""),0.02857142857142857) -> 0.028571429 | R96: =IFERROR(__xludf.DUMMYFUNCTION("""COMPUTED_VALUE"""),0.0) -> 0 | S96: =IFERROR(__xludf.DUMMYFUNCTION("""COMPUTED_VALUE"""),0.0) -> 0 | T96: =IFERROR(__xludf.DUMMYFUNCTION("""COMPUTED_VALUE"""),0.0) -> 0 | U96: =IFERROR(__xludf.DUMMYFUNCTION("""COMPUTED_VALUE"""),0.0) -> 0 | V96: =IFERROR(__xludf.DUMMYFUNCTION("""COMPUTED_VALUE"""),0.0) -> 0 | W96: =IFERROR(__xludf.DUMMYFUNCTION("""COMPUTED_VALUE"""),0.0) -> 0 | X96: =IFERROR(__xludf.DUMMYFUNCTION("""COMPUTED_VALUE"""),0.0) -> 0 | Y96: =IFERROR(__xludf.DUMMYFUNCTION("""COMPUTED_VALUE"""),0.0) -> 0 | ... AG96: =IFERROR(__xludf.DUMMYFUNCTION("""COMPUTED_VALUE"""),0.0) -> 0 | AH96: =IFERROR(__xludf.DUMMYFUNCTION("""COMPUTED_VALUE"""),11147.0) -> 11147 | AI96: =IFERROR(__xludf.DUMMYFUNCTION("""COMPUTED_VALUE"""),411.0) -> 411 | AJ96: =IFERROR(__xludf.DUMMYFUNCTION("""COMPUTED_VALUE"""),0.0) -> 0 | AK96: =IFERROR(__xludf.DUMMYFUNCTION("""COMPUTED_VALUE"""),1.0) -> 1 | AL96: =IFERROR(__xludf.DUMMYFUNCTION("""COMPUTED_VALUE"""),19336.0) -> 19336 | AM96: =IFERROR(__xludf.DUMMYFUNCTION("""COMPUTED_VALUE"""),661.0) -> 661 | AN96: =IFERROR(__xludf.DUMMYFUNCTION("""COMPUTED_VALUE"""),5.0) -> 5 | AO96: =IFERROR(__xludf.DUMMYFUNCTION("""COMPUTED_VALUE"""),10.0) -> 10 | AP96: =IFERROR(__xludf.DUMMYFUNCTION("""COMPUTED_VALUE"""),29746.0) -> 29746 | AQ96: =IFERROR(__xludf.DUMMYFUNCTION("""COMPUTED_VALUE"""),457.0) -> 457 | AR96: =IFERROR(__xludf.DUMMYFUNCTION("""COMPUTED_VALUE"""),1.5) -> 1.5 | AS96: =IFERROR(__xludf.DUMMYFUNCTION("""COMPUTED_VALUE"""),1.0) -> 1 | AT96: =IFERROR(__xludf.DUMMYFUNCTION("""COMPUTED_VALUE"""),8743.0) -> 8743 | AU96: =IFERROR(__xludf.DUMMYFUNCTION("""COMPUTED_VALUE"""),276.0) -> 276 | AV96: =IFERROR(__xludf.DUMMYFUNCTION("""COMPUTED_VALUE"""),15.0) -> 15 | AW96: =IFERROR(__xludf.DUMMYFUNCTION("""COMPUTED_VALUE"""),22.0) -> 22 | AX96: =IFERROR(__xludf.DUMMYFUNCTION("""COMPUTED_VALUE"""),6587.0) -> 6587 | AY96: =IFERROR(__xludf.DUMMYFUNCTION("""COMPUTED_VALUE"""),253.0) -> 253 | AZ96: =IFERROR(__xludf.DUMMYFUNCTION("""COMPUTED_VALUE"""),3.0) -> 3 | BA96: =IFERROR(__xludf.DUMMYFUNCTION("""COMPUTED_VALUE"""),4.0) -> 4 | BB96: =IFERROR(__xludf.DUMMYFUNCTION("""COMPUTED_VALUE"""),3033.0) -> 3033 | BC96: =IFERROR(__xludf.DUMMYFUNCTION("""COMPUTED_VALUE"""),281.0) -> 281 | BD96: =IFERROR(__xludf.DUMMYFUNCTION("""COMPUTED_VALUE"""),11.0) -> 11 | BE96: =IFERROR(__xludf.DUMMYFUNCTION("""COMPUTED_VALUE"""),19.0) -> 19 | BF96: =IFERROR(__xludf.DUMMYFUNCTION("""COMPUTED_VALUE"""),2946.0) -> 2946 | BG96: =IFERROR(__xludf.DUMMYFUNCTION("""COMPUTED_VALUE"""),348.0) -> 348 | BH96: =IFERROR(__xludf.DUMMYFUNCTION("""COMPUTED_VALUE"""),10.0) -> 10 | BI96: =IFERROR(__xludf.DUMMYFUNCTION("""COMPUTED_VALUE"""),15.0) -> 15
B97: =IFERROR(__xludf.DUMMYFUNCTION("""COMPUTED_VALUE"""),"金子") -> 金子 | C97: =IFERROR(__xludf.DUMMYFUNCTION("""COMPUTED_VALUE"""),57363.0) -> 57363 | D97: =IFERROR(__xludf.DUMMYFUNCTION("""COMPUTED_VALUE"""),3607.0) -> 3607 | E97: =IFERROR(__xludf.DUMMYFUNCTION("""COMPUTED_VALUE"""),0.06288025382215016) -> 0.062880254 | F97: =IFERROR(__xludf.DUMMYFUNCTION("""COMPUTED_VALUE"""),66.5) -> 66.5 | G97: =IFERROR(__xludf.DUMMYFUNCTION("""COMPUTED_VALUE"""),0.018436373717771) -> 0.018436374 | H97: =IFERROR(__xludf.DUMMYFUNCTION("""COMPUTED_VALUE"""),98.0) -> 98 | I97: =IFERROR(__xludf.DUMMYFUNCTION("""COMPUTED_VALUE"""),0.027169392847241475) -> 0.027169393 | R97: =IFERROR(__xludf.DUMMYFUNCTION("""COMPUTED_VALUE"""),0.0) -> 0 | S97: =IFERROR(__xludf.DUMMYFUNCTION("""COMPUTED_VALUE"""),0.0) -> 0 | T97: =IFERROR(__xludf.DUMMYFUNCTION("""COMPUTED_VALUE"""),0.0) -> 0 | V97: =IFERROR(__xludf.DUMMYFUNCTION("""COMPUTED_VALUE"""),0.0) -> 0 | W97: =IFERROR(__xludf.DUMMYFUNCTION("""COMPUTED_VALUE"""),0.0) -> 0 | X97: =IFERROR(__xludf.DUMMYFUNCTION("""COMPUTED_VALUE"""),0.0) -> 0 | Z97: =IFERROR(__xludf.DUMMYFUNCTION("""COMPUTED_VALUE"""),0.0) -> 0 | AA97: =IFERROR(__xludf.DUMMYFUNCTION("""COMPUTED_VALUE"""),0.0) -> 0 | AB97: =IFERROR(__xludf.DUMMYFUNCTION("""COMPUTED_VALUE"""),0.0) -> 0 | AD97: =IFERROR(__xludf.DUMMYFUNCTION("""COMPUTED_VALUE"""),0.0) -> 0 | AE97: =IFERROR(__xludf.DUMMYFUNCTION("""COMPUTED_VALUE"""),0.0) -> 0 | AF97: =IFERROR(__xludf.DUMMYFUNCTION("""COMPUTED_VALUE"""),0.0) -> 0 | AH97: =IFERROR(__xludf.DUMMYFUNCTION("""COMPUTED_VALUE"""),1261.0) -> 1261 | AI97: =IFERROR(__xludf.DUMMYFUNCTION("""COMPUTED_VALUE"""),36.0) -> 36 | AJ97: =IFERROR(__xludf.DUMMYFUNCTION("""COMPUTED_VALUE"""),1.0) -> 1 | AL97: =IFERROR(__xludf.DUMMYFUNCTION("""COMPUTED_VALUE"""),16976.0) -> 16976 | AM97: =IFERROR(__xludf.DUMMYFUNCTION("""COMPUTED_VALUE"""),533.0) -> 533 | AN97: =IFERROR(__xludf.DUMMYFUNCTION("""COMPUTED_VALUE"""),10.0) -> 10 | AP97: =IFERROR(__xludf.DUMMYFUNCTION("""COMPUTED_VALUE"""),14439.0) -> 14439 | AQ97: =IFERROR(__xludf.DUMMYFUNCTION("""COMPUTED_VALUE"""),806.0) -> 806 | AR97: =IFERROR(__xludf.DUMMYFUNCTION("""COMPUTED_VALUE"""),9.5) -> 9.5 | AS97: =IFERROR(__xludf.DUMMYFUNCTION("""COMPUTED_VALUE"""),11.0) -> 11 | AT97: =IFERROR(__xludf.DUMMYFUNCTION("""COMPUTED_VALUE"""),7431.0) -> 7431 | AU97: =IFERROR(__xludf.DUMMYFUNCTION("""COMPUTED_VALUE"""),656.0) -> 656 | AV97: =IFERROR(__xludf.DUMMYFUNCTION("""COMPUTED_VALUE"""),14.0) -> 14 | AW97: =IFERROR(__xludf.DUMMYFUNCTION("""COMPUTED_VALUE"""),24.0) -> 24 | AX97: =IFERROR(__xludf.DUMMYFUNCTION("""COMPUTED_VALUE"""),6975.0) -> 6975 | AY97: =IFERROR(__xludf.DUMMYFUNCTION("""COMPUTED_VALUE"""),485.0) -> 485 | AZ97: =IFERROR(__xludf.DUMMYFUNCTION("""COMPUTED_VALUE"""),7.0) -> 7 | BA97: =IFERROR(__xludf.DUMMYFUNCTION("""COMPUTED_VALUE"""),15.0) -> 15 | BB97: =IFERROR(__xludf.DUMMYFUNCTION("""COMPUTED_VALUE"""),4460.0) -> 4460 | BC97: =IFERROR(__xludf.DUMMYFUNCTION("""COMPUTED_VALUE"""),514.0) -> 514 | BD97: =IFERROR(__xludf.DUMMYFUNCTION("""COMPUTED_VALUE"""),14.0) -> 14 | BE97: =IFERROR(__xludf.DUMMYFUNCTION("""COMPUTED_VALUE"""),26.0) -> 26 | BF97: =IFERROR(__xludf.DUMMYFUNCTION("""COMPUTED_VALUE"""),3291.0) -> 3291 | BG97: =IFERROR(__xludf.DUMMYFUNCTION("""COMPUTED_VALUE"""),327.0) -> 327 | BH97: =IFERROR(__xludf.DUMMYFUNCTION("""COMPUTED_VALUE"""),9.0) -> 9 | BI97: =IFERROR(__xludf.DUMMYFUNCTION("""COMPUTED_VALUE"""),15.0) -> 15
B98: =IFERROR(__xludf.DUMMYFUNCTION("""COMPUTED_VALUE"""),"ハタ") -> ハタ | C98: =IFERROR(__xludf.DUMMYFUNCTION("""COMPUTED_VALUE"""),23118.0) -> 23118 | D98: =IFERROR(__xludf.DUMMYFUNCTION("""COMPUTED_VALUE"""),1945.0) -> 1945 | E98: =IFERROR(__xludf.DUMMYFUNCTION("""COMPUTED_VALUE"""),0.08413357556882083) -> 0.084133576 | F98: =IFERROR(__xludf.DUMMYFUNCTION("""COMPUTED_VALUE"""),43.0) -> 43 | G98: =IFERROR(__xludf.DUMMYFUNCTION("""COMPUTED_VALUE"""),0.02210796915167095) -> 0.022107969 | H98: =IFERROR(__xludf.DUMMYFUNCTION("""COMPUTED_VALUE"""),85.0) -> 85 | I98: =IFERROR(__xludf.DUMMYFUNCTION("""COMPUTED_VALUE"""),0.043701799485861184) -> 0.043701799 | R98: =IFERROR(__xludf.DUMMYFUNCTION("""COMPUTED_VALUE"""),0.0) -> 0 | S98: =IFERROR(__xludf.DUMMYFUNCTION("""COMPUTED_VALUE"""),0.0) -> 0 | T98: =IFERROR(__xludf.DUMMYFUNCTION("""COMPUTED_VALUE"""),0.0) -> 0 | U98: =IFERROR(__xludf.DUMMYFUNCTION("""COMPUTED_VALUE"""),0.0) -> 0 | V98: =IFERROR(__xludf.DUMMYFUNCTION("""COMPUTED_VALUE"""),0.0) -> 0 | W98: =IFERROR(__xludf.DUMMYFUNCTION("""COMPUTED_VALUE"""),0.0) -> 0 | X98: =IFERROR(__xludf.DUMMYFUNCTION("""COMPUTED_VALUE"""),0.0) -> 0 | Y98: =IFERROR(__xludf.DUMMYFUNCTION("""COMPUTED_VALUE"""),0.0) -> 0 | ... AS98: =IFERROR(__xludf.DUMMYFUNCTION("""COMPUTED_VALUE"""),0.0) -> 0 | AT98: =IFERROR(__xludf.DUMMYFUNCTION("""COMPUTED_VALUE"""),7922.0) -> 7922 | AU98: =IFERROR(__xludf.DUMMYFUNCTION("""COMPUTED_VALUE"""),56.0) -> 56 | AV98: =IFERROR(__xludf.DUMMYFUNCTION("""COMPUTED_VALUE"""),9.0) -> 9 | AW98: =IFERROR(__xludf.DUMMYFUNCTION("""COMPUTED_VALUE"""),8.0) -> 8 | AX98: =IFERROR(__xludf.DUMMYFUNCTION("""COMPUTED_VALUE"""),3468.0) -> 3468 | AY98: =IFERROR(__xludf.DUMMYFUNCTION("""COMPUTED_VALUE"""),219.0) -> 219 | AZ98: =IFERROR(__xludf.DUMMYFUNCTION("""COMPUTED_VALUE"""),3.0) -> 3 | BA98: =IFERROR(__xludf.DUMMYFUNCTION("""COMPUTED_VALUE"""),4.0) -> 4 | BB98: =IFERROR(__xludf.DUMMYFUNCTION("""COMPUTED_VALUE"""),5296.0) -> 5296 | BC98: =IFERROR(__xludf.DUMMYFUNCTION("""COMPUTED_VALUE"""),678.0) -> 678 | BD98: =IFERROR(__xludf.DUMMYFUNCTION("""COMPUTED_VALUE"""),6.0) -> 6 | BE98: =IFERROR(__xludf.DUMMYFUNCTION("""COMPUTED_VALUE"""),20.0) -> 20 | BF98: =IFERROR(__xludf.DUMMYFUNCTION("""COMPUTED_VALUE"""),3980.0) -> 3980 | BG98: =IFERROR(__xludf.DUMMYFUNCTION("""COMPUTED_VALUE"""),615.0) -> 615 | BH98: =IFERROR(__xludf.DUMMYFUNCTION("""COMPUTED_VALUE"""),19.0) -> 19 | BI98: =IFERROR(__xludf.DUMMYFUNCTION("""COMPUTED_VALUE"""),38.0) -> 38
B99: =IFERROR(__xludf.DUMMYFUNCTION("""COMPUTED_VALUE"""),"村田") -> 村田 | C99: =IFERROR(__xludf.DUMMYFUNCTION("""COMPUTED_VALUE"""),1198.0) -> 1198 | D99: =IFERROR(__xludf.DUMMYFUNCTION("""COMPUTED_VALUE"""),160.0) -> 160 | E99: =IFERROR(__xludf.DUMMYFUNCTION("""COMPUTED_VALUE"""),0.1335559265442404) -> 0.13355593 | F99: =IFERROR(__xludf.DUMMYFUNCTION("""COMPUTED_VALUE"""),2.0) -> 2 | G99: =IFERROR(__xludf.DUMMYFUNCTION("""COMPUTED_VALUE"""),0.0125) -> 0.0125 | H99: =IFERROR(__xludf.DUMMYFUNCTION("""COMPUTED_VALUE"""),3.0) -> 3 | I99: =IFERROR(__xludf.DUMMYFUNCTION("""COMPUTED_VALUE"""),0.01875) -> 0.01875 | R99: =IFERROR(__xludf.DUMMYFUNCTION("""COMPUTED_VALUE"""),0.0) -> 0 | S99: =IFERROR(__xludf.DUMMYFUNCTION("""COMPUTED_VALUE"""),0.0) -> 0 | T99: =IFERROR(__xludf.DUMMYFUNCTION("""COMPUTED_VALUE"""),0.0) -> 0 | U99: =IFERROR(__xludf.DUMMYFUNCTION("""COMPUTED_VALUE"""),0.0) -> 0 | V99: =IFERROR(__xludf.DUMMYFUNCTION("""COMPUTED_VALUE"""),0.0) -> 0 | W99: =IFERROR(__xludf.DUMMYFUNCTION("""COMPUTED_VALUE"""),0.0) -> 0 | X99: =IFERROR(__xludf.DUMMYFUNCTION("""COMPUTED_VALUE"""),0.0) -> 0 | Y99: =IFERROR(__xludf.DUMMYFUNCTION("""COMPUTED_VALUE"""),0.0) -> 0 | ... AN99: =IFERROR(__xludf.DUMMYFUNCTION("""COMPUTED_VALUE"""),0.0) -> 0 | AP99: =IFERROR(__xludf.DUMMYFUNCTION("""COMPUTED_VALUE"""),0.0) -> 0 | AQ99: =IFERROR(__xludf.DUMMYFUNCTION("""COMPUTED_VALUE"""),0.0) -> 0 | AR99: =IFERROR(__xludf.DUMMYFUNCTION("""COMPUTED_VALUE"""),0.0) -> 0 | AS99: =IFERROR(__xludf.DUMMYFUNCTION("""COMPUTED_VALUE"""),0.0) -> 0 | AT99: =IFERROR(__xludf.DUMMYFUNCTION("""COMPUTED_VALUE"""),0.0) -> 0 | AU99: =IFERROR(__xludf.DUMMYFUNCTION("""COMPUTED_VALUE"""),0.0) -> 0 | AV99: =IFERROR(__xludf.DUMMYFUNCTION("""COMPUTED_VALUE"""),0.0) -> 0 | AW99: =IFERROR(__xludf.DUMMYFUNCTION("""COMPUTED_VALUE"""),0.0) -> 0 | ... BI99: =IFERROR(__xludf.DUMMYFUNCTION("""COMPUTED_VALUE"""),0.0) -> 0
B100: =IFERROR(__xludf.DUMMYFUNCTION("""COMPUTED_VALUE"""),"仁子") -> 仁子 | C100: =IFERROR(__xludf.DUMMYFUNCTION("""COMPUTED_VALUE"""),20292.0) -> 20292 | D100: =IFERROR(__xludf.DUMMYFUNCTION("""COMPUTED_VALUE"""),1513.0) -> 1513 | E100: =IFERROR(__xludf.DUMMYFUNCTION("""COMPUTED_VALUE"""),0.07456140350877193) -> 0.074561404 | F100: =IFERROR(__xludf.DUMMYFUNCTION("""COMPUTED_VALUE"""),120.0) -> 120 | G100: =IFERROR(__xludf.DUMMYFUNCTION("""COMPUTED_VALUE"""),0.07931262392597488) -> 0.079312624 | H100: =IFERROR(__xludf.DUMMYFUNCTION("""COMPUTED_VALUE"""),90.0) -> 90 | I100: =IFERROR(__xludf.DUMMYFUNCTION("""COMPUTED_VALUE"""),0.059484467944481166) -> 0.059484468 | R100: =IFERROR(__xludf.DUMMYFUNCTION("""COMPUTED_VALUE"""),0.0) -> 0 | S100: =IFERROR(__xludf.DUMMYFUNCTION("""COMPUTED_VALUE"""),0.0) -> 0 | T100: =IFERROR(__xludf.DUMMYFUNCTION("""COMPUTED_VALUE"""),19.0) -> 19 | U100: =IFERROR(__xludf.DUMMYFUNCTION("""COMPUTED_VALUE"""),0.0) -> 0 | V100: =IFERROR(__xludf.DUMMYFUNCTION("""COMPUTED_VALUE"""),0.0) -> 0 | W100: =IFERROR(__xludf.DUMMYFUNCTION("""COMPUTED_VALUE"""),0.0) -> 0 | X100: =IFERROR(__xludf.DUMMYFUNCTION("""COMPUTED_VALUE"""),40.0) -> 40 | Y100: =IFERROR(__xludf.DUMMYFUNCTION("""COMPUTED_VALUE"""),0.0) -> 0 | Z100: =IFERROR(__xludf.DUMMYFUNCTION("""COMPUTED_VALUE"""),0.0) -> 0 | AA100: =IFERROR(__xludf.DUMMYFUNCTION("""COMPUTED_VALUE"""),0.0) -> 0 | AB100: =IFERROR(__xludf.DUMMYFUNCTION("""COMPUTED_VALUE"""),0.0) -> 0 | AC100: =IFERROR(__xludf.DUMMYFUNCTION("""COMPUTED_VALUE"""),0.0) -> 0 | AD100: =IFERROR(__xludf.DUMMYFUNCTION("""COMPUTED_VALUE"""),0.0) -> 0 | AE100: =IFERROR(__xludf.DUMMYFUNCTION("""COMPUTED_VALUE"""),0.0) -> 0 | AF100: =IFERROR(__xludf.DUMMYFUNCTION("""COMPUTED_VALUE"""),0.0) -> 0 | ... AO100: =IFERROR(__xludf.DUMMYFUNCTION("""COMPUTED_VALUE"""),0.0) -> 0 | AP100: =IFERROR(__xludf.DUMMYFUNCTION("""COMPUTED_VALUE"""),1096.0) -> 1096 | AQ100: =IFERROR(__xludf.DUMMYFUNCTION("""COMPUTED_VALUE"""),85.0) -> 85 | AR100: =IFERROR(__xludf.DUMMYFUNCTION("""COMPUTED_VALUE"""),1.0) -> 1 | AS100: =IFERROR(__xludf.DUMMYFUNCTION("""COMPUTED_VALUE"""),0.0) -> 0 | AT100: =IFERROR(__xludf.DUMMYFUNCTION("""COMPUTED_VALUE"""),7864.0) -> 7864 | AU100: =IFERROR(__xludf.DUMMYFUNCTION("""COMPUTED_VALUE"""),385.0) -> 385 | AV100: =IFERROR(__xludf.DUMMYFUNCTION("""COMPUTED_VALUE"""),27.0) -> 27 | AW100: =IFERROR(__xludf.DUMMYFUNCTION("""COMPUTED_VALUE"""),33.0) -> 33 | AX100: =IFERROR(__xludf.DUMMYFUNCTION("""COMPUTED_VALUE"""),7799.0) -> 7799 | AY100: =IFERROR(__xludf.DUMMYFUNCTION("""COMPUTED_VALUE"""),624.0) -> 624 | AZ100: =IFERROR(__xludf.DUMMYFUNCTION("""COMPUTED_VALUE"""),27.0) -> 27 | BA100: =IFERROR(__xludf.DUMMYFUNCTION("""COMPUTED_VALUE"""),40.0) -> 40 | BB100: =IFERROR(__xludf.DUMMYFUNCTION("""COMPUTED_VALUE"""),3533.0) -> 3533 | BC100: =IFERROR(__xludf.DUMMYFUNCTION("""COMPUTED_VALUE"""),419.0) -> 419 | BD100: =IFERROR(__xludf.DUMMYFUNCTION("""COMPUTED_VALUE"""),6.0) -> 6 | BE100: =IFERROR(__xludf.DUMMYFUNCTION("""COMPUTED_VALUE"""),17.0) -> 17
B101: =IFERROR(__xludf.DUMMYFUNCTION("""COMPUTED_VALUE"""),"小川") -> 小川 | C101: =IFERROR(__xludf.DUMMYFUNCTION("""COMPUTED_VALUE"""),635.0) -> 635 | D101: =IFERROR(__xludf.DUMMYFUNCTION("""COMPUTED_VALUE"""),126.0) -> 126 | E101: =IFERROR(__xludf.DUMMYFUNCTION("""COMPUTED_VALUE"""),0.1984251968503937) -> 0.1984252 | F101: =IFERROR(__xludf.DUMMYFUNCTION("""COMPUTED_VALUE"""),10.0) -> 10 | G101: =IFERROR(__xludf.DUMMYFUNCTION("""COMPUTED_VALUE"""),0.07936507936507936) -> 0.079365079 | H101: =IFERROR(__xludf.DUMMYFUNCTION("""COMPUTED_VALUE"""),10.0) -> 10 | I101: =IFERROR(__xludf.DUMMYFUNCTION("""COMPUTED_VALUE"""),0.07936507936507936) -> 0.079365079 | BB101: =IFERROR(__xludf.DUMMYFUNCTION("""COMPUTED_VALUE"""),635.0) -> 635 | BC101: =IFERROR(__xludf.DUMMYFUNCTION("""COMPUTED_VALUE"""),126.0) -> 126 | BD101: =IFERROR(__xludf.DUMMYFUNCTION("""COMPUTED_VALUE"""),10.0) -> 10 | BE101: =IFERROR(__xludf.DUMMYFUNCTION("""COMPUTED_VALUE"""),10.0) -> 10
B102: =IFERROR(__xludf.DUMMYFUNCTION("""COMPUTED_VALUE"""),"サラ") -> サラ | C102: =IFERROR(__xludf.DUMMYFUNCTION("""COMPUTED_VALUE"""),12385.0) -> 12385 | D102: =IFERROR(__xludf.DUMMYFUNCTION("""COMPUTED_VALUE"""),1174.0) -> 1174 | E102: =IFERROR(__xludf.DUMMYFUNCTION("""COMPUTED_VALUE"""),0.0947920872022608) -> 0.094792087 | F102: =IFERROR(__xludf.DUMMYFUNCTION("""COMPUTED_VALUE"""),18.0) -> 18 | G102: =IFERROR(__xludf.DUMMYFUNCTION("""COMPUTED_VALUE"""),0.015332197614991482) -> 0.015332198 | H102: =IFERROR(__xludf.DUMMYFUNCTION("""COMPUTED_VALUE"""),30.0) -> 30 | I102: =IFERROR(__xludf.DUMMYFUNCTION("""COMPUTED_VALUE"""),0.02555366269165247) -> 0.025553663 | BB102: =IFERROR(__xludf.DUMMYFUNCTION("""COMPUTED_VALUE"""),624.0) -> 624 | BC102: =IFERROR(__xludf.DUMMYFUNCTION("""COMPUTED_VALUE"""),69.0) -> 69 | BD102: =IFERROR(__xludf.DUMMYFUNCTION("""COMPUTED_VALUE"""),0.0) -> 0 | BE102: =IFERROR(__xludf.DUMMYFUNCTION("""COMPUTED_VALUE"""),0.0) -> 0 | BF102: =IFERROR(__xludf.DUMMYFUNCTION("""COMPUTED_VALUE"""),860.0) -> 860 | BG102: =IFERROR(__xludf.DUMMYFUNCTION("""COMPUTED_VALUE"""),93.0) -> 93 | BH102: =IFERROR(__xludf.DUMMYFUNCTION("""COMPUTED_VALUE"""),2.0) -> 2 | BI102: =IFERROR(__xludf.DUMMYFUNCTION("""COMPUTED_VALUE"""),4.0) -> 4
B103: =IFERROR(__xludf.DUMMYFUNCTION("""COMPUTED_VALUE"""),"長瀬") -> 長瀬 | C103: =IFERROR(__xludf.DUMMYFUNCTION("""COMPUTED_VALUE"""),577.0) -> 577 | D103: =IFERROR(__xludf.DUMMYFUNCTION("""COMPUTED_VALUE"""),83.0) -> 83 | E103: =IFERROR(__xludf.DUMMYFUNCTION("""COMPUTED_VALUE"""),0.1438474870017331) -> 0.14384749 | F103: =IFERROR(__xludf.DUMMYFUNCTION("""COMPUTED_VALUE"""),1.0) -> 1 | G103: =IFERROR(__xludf.DUMMYFUNCTION("""COMPUTED_VALUE"""),0.012048192771084338) -> 0.012048193 | H103: =IFERROR(__xludf.DUMMYFUNCTION("""COMPUTED_VALUE"""),1.0) -> 1 | I103: =IFERROR(__xludf.DUMMYFUNCTION("""COMPUTED_VALUE"""),0.012048192771084338) -> 0.012048193 | U103: =IFERROR(__xludf.DUMMYFUNCTION("""COMPUTED_VALUE"""),0.0) -> 0 | Y103: =IFERROR(__xludf.DUMMYFUNCTION("""COMPUTED_VALUE"""),0.0) -> 0 | AC103: =IFERROR(__xludf.DUMMYFUNCTION("""COMPUTED_VALUE"""),0.0) -> 0 | BF103: =IFERROR(__xludf.DUMMYFUNCTION("""COMPUTED_VALUE"""),577.0) -> 577 | BG103: =IFERROR(__xludf.DUMMYFUNCTION("""COMPUTED_VALUE"""),83.0) -> 83 | BH103: =IFERROR(__xludf.DUMMYFUNCTION("""COMPUTED_VALUE"""),1.0) -> 1 | BI103: =IFERROR(__xludf.DUMMYFUNCTION("""COMPUTED_VALUE"""),1.0) -> 1
B104: =IFERROR(__xludf.DUMMYFUNCTION("""COMPUTED_VALUE"""),"鈴木") -> 鈴木 | C104: =IFERROR(__xludf.DUMMYFUNCTION("""COMPUTED_VALUE"""),84574.0) -> 84574 | D104: =IFERROR(__xludf.DUMMYFUNCTION("""COMPUTED_VALUE"""),4837.0) -> 4837 | E104: =IFERROR(__xludf.DUMMYFUNCTION("""COMPUTED_VALUE"""),0.057192517795067045) -> 0.057192518 | F104: =IFERROR(__xludf.DUMMYFUNCTION("""COMPUTED_VALUE"""),85.5) -> 85.5 | G104: =IFERROR(__xludf.DUMMYFUNCTION("""COMPUTED_VALUE"""),0.017676245606781063) -> 0.017676246 | H104: =IFERROR(__xludf.DUMMYFUNCTION("""COMPUTED_VALUE"""),116.0) -> 116 | I104: =IFERROR(__xludf.DUMMYFUNCTION("""COMPUTED_VALUE"""),0.02398180690510647) -> 0.023981807 | R104: =IFERROR(__xludf.DUMMYFUNCTION("""COMPUTED_VALUE"""),273.0) -> 273 | S104: =IFERROR(__xludf.DUMMYFUNCTION("""COMPUTED_VALUE"""),61.0) -> 61 | T104: =IFERROR(__xludf.DUMMYFUNCTION("""COMPUTED_VALUE"""),9.0) -> 9 | U104: =IFERROR(__xludf.DUMMYFUNCTION("""COMPUTED_VALUE"""),12.0) -> 12 | V104: =IFERROR(__xludf.DUMMYFUNCTION("""COMPUTED_VALUE"""),1844.0) -> 1844 | W104: =IFERROR(__xludf.DUMMYFUNCTION("""COMPUTED_VALUE"""),390.0) -> 390 | X104: =IFERROR(__xludf.DUMMYFUNCTION("""COMPUTED_VALUE"""),1.0) -> 1 | Y104: =IFERROR(__xludf.DUMMYFUNCTION("""COMPUTED_VALUE"""),2.0) -> 2 | Z104: =IFERROR(__xludf.DUMMYFUNCTION("""COMPUTED_VALUE"""),1533.0) -> 1533 | AA104: =IFERROR(__xludf.DUMMYFUNCTION("""COMPUTED_VALUE"""),0.0) -> 0 | AB104: =IFERROR(__xludf.DUMMYFUNCTION("""COMPUTED_VALUE"""),0.0) -> 0 | AC104: =IFERROR(__xludf.DUMMYFUNCTION("""COMPUTED_VALUE"""),0.0) -> 0 | AD104: =IFERROR(__xludf.DUMMYFUNCTION("""COMPUTED_VALUE"""),0.0) -> 0 | AE104: =IFERROR(__xludf.DUMMYFUNCTION("""COMPUTED_VALUE"""),0.0) -> 0 | AF104: =IFERROR(__xludf.DUMMYFUNCTION("""COMPUTED_VALUE"""),0.0) -> 0 | AG104: =IFERROR(__xludf.DUMMYFUNCTION("""COMPUTED_VALUE"""),0.0) -> 0 | AH104: =IFERROR(__xludf.DUMMYFUNCTION("""COMPUTED_VALUE"""),13761.0) -> 13761 | AI104: =IFERROR(__xludf.DUMMYFUNCTION("""COMPUTED_VALUE"""),581.0) -> 581 | AJ104: =IFERROR(__xludf.DUMMYFUNCTION("""COMPUTED_VALUE"""),4.0) -> 4 | AK104: =IFERROR(__xludf.DUMMYFUNCTION("""COMPUTED_VALUE"""),4.0) -> 4 | AL104: =IFERROR(__xludf.DUMMYFUNCTION("""COMPUTED_VALUE"""),22917.0) -> 22917 | AM104: =IFERROR(__xludf.DUMMYFUNCTION("""COMPUTED_VALUE"""),1070.0) -> 1070 | AN104: =IFERROR(__xludf.DUMMYFUNCTION("""COMPUTED_VALUE"""),16.0) -> 16 | AO104: =IFERROR(__xludf.DUMMYFUNCTION("""COMPUTED_VALUE"""),21.0) -> 21 | AP104: =IFERROR(__xludf.DUMMYFUNCTION("""COMPUTED_VALUE"""),26675.0) -> 26675 | AQ104: =IFERROR(__xludf.DUMMYFUNCTION("""COMPUTED_VALUE"""),923.0) -> 923 | AR104: =IFERROR(__xludf.DUMMYFUNCTION("""COMPUTED_VALUE"""),21.5) -> 21.5 | AS104: =IFERROR(__xludf.DUMMYFUNCTION("""COMPUTED_VALUE"""),26.0) -> 26 | AT104: =IFERROR(__xludf.DUMMYFUNCTION("""COMPUTED_VALUE"""),13222.0) -> 13222 | AU104: =IFERROR(__xludf.DUMMYFUNCTION("""COMPUTED_VALUE"""),1075.0) -> 1075 | AV104: =IFERROR(__xludf.DUMMYFUNCTION("""COMPUTED_VALUE"""),25.0) -> 25 | AW104: =IFERROR(__xludf.DUMMYFUNCTION("""COMPUTED_VALUE"""),32.0) -> 32 | AX104: =IFERROR(__xludf.DUMMYFUNCTION("""COMPUTED_VALUE"""),4349.0) -> 4349 | AY104: =IFERROR(__xludf.DUMMYFUNCTION("""COMPUTED_VALUE"""),737.0) -> 737 | AZ104: =IFERROR(__xludf.DUMMYFUNCTION("""COMPUTED_VALUE"""),9.0) -> 9 | BA104: =IFERROR(__xludf.DUMMYFUNCTION("""COMPUTED_VALUE"""),19.0) -> 19
B105: =IFERROR(__xludf.DUMMYFUNCTION("""COMPUTED_VALUE"""),"仲間") -> 仲間 | C105: =IFERROR(__xludf.DUMMYFUNCTION("""COMPUTED_VALUE"""),44781.0) -> 44781 | D105: =IFERROR(__xludf.DUMMYFUNCTION("""COMPUTED_VALUE"""),4026.0) -> 4026 | E105: =IFERROR(__xludf.DUMMYFUNCTION("""COMPUTED_VALUE"""),0.0899042004421518) -> 0.0899042 | F105: =IFERROR(__xludf.DUMMYFUNCTION("""COMPUTED_VALUE"""),21.0) -> 21 | G105: =IFERROR(__xludf.DUMMYFUNCTION("""COMPUTED_VALUE"""),0.005216095380029807) -> 0.0052160954 | H105: =IFERROR(__xludf.DUMMYFUNCTION("""COMPUTED_VALUE"""),31.0) -> 31 | I105: =IFERROR(__xludf.DUMMYFUNCTION("""COMPUTED_VALUE"""),0.007699950322901143) -> 0.0076999503 | R105: =IFERROR(__xludf.DUMMYFUNCTION("""COMPUTED_VALUE"""),3141.0) -> 3141 | S105: =IFERROR(__xludf.DUMMYFUNCTION("""COMPUTED_VALUE"""),327.0) -> 327 | T105: =IFERROR(__xludf.DUMMYFUNCTION("""COMPUTED_VALUE"""),3.0) -> 3 | U105: =IFERROR(__xludf.DUMMYFUNCTION("""COMPUTED_VALUE"""),5.0) -> 5 | V105: =IFERROR(__xludf.DUMMYFUNCTION("""COMPUTED_VALUE"""),1904.0) -> 1904 | W105: =IFERROR(__xludf.DUMMYFUNCTION("""COMPUTED_VALUE"""),299.0) -> 299 | X105: =IFERROR(__xludf.DUMMYFUNCTION("""COMPUTED_VALUE"""),0.0) -> 0 | Y105: =IFERROR(__xludf.DUMMYFUNCTION("""COMPUTED_VALUE"""),1.0) -> 1 | Z105: =IFERROR(__xludf.DUMMYFUNCTION("""COMPUTED_VALUE"""),2517.0) -> 2517 | AA105: =IFERROR(__xludf.DUMMYFUNCTION("""COMPUTED_VALUE"""),138.0) -> 138 | AB105: =IFERROR(__xludf.DUMMYFUNCTION("""COMPUTED_VALUE"""),0.0) -> 0 | AC105: =IFERROR(__xludf.DUMMYFUNCTION("""COMPUTED_VALUE"""),1.0) -> 1 | AD105: =IFERROR(__xludf.DUMMYFUNCTION("""COMPUTED_VALUE"""),2968.0) -> 2968 | AE105: =IFERROR(__xludf.DUMMYFUNCTION("""COMPUTED_VALUE"""),1379.0) -> 1379 | AF105: =IFERROR(__xludf.DUMMYFUNCTION("""COMPUTED_VALUE"""),2.0) -> 2 | AG105: =IFERROR(__xludf.DUMMYFUNCTION("""COMPUTED_VALUE"""),6.0) -> 6 | AH105: =IFERROR(__xludf.DUMMYFUNCTION("""COMPUTED_VALUE"""),13958.0) -> 13958 | AI105: =IFERROR(__xludf.DUMMYFUNCTION("""COMPUTED_VALUE"""),575.0) -> 575 | AJ105: =IFERROR(__xludf.DUMMYFUNCTION("""COMPUTED_VALUE"""),6.0) -> 6 | AK105: =IFERROR(__xludf.DUMMYFUNCTION("""COMPUTED_VALUE"""),6.0) -> 6 | AL105: =IFERROR(__xludf.DUMMYFUNCTION("""COMPUTED_VALUE"""),20293.0) -> 20293 | AM105: =IFERROR(__xludf.DUMMYFUNCTION("""COMPUTED_VALUE"""),1308.0) -> 1308 | AN105: =IFERROR(__xludf.DUMMYFUNCTION("""COMPUTED_VALUE"""),10.0) -> 10 | AO105: =IFERROR(__xludf.DUMMYFUNCTION("""COMPUTED_VALUE"""),12.0) -> 12
B108: =IFERROR(__xludf.DUMMYFUNCTION("IMPORTRANGE(""1vYc4iTJ16E7R6SUnGhwdB4aOJULuweZOJUwnvK3B2Ug"", ""顧客リスト!AR6:BE30"") "),"#REF!") -> #REF!

Sheet シートまとめ
A1: --
C2: URL | D2: 修正点 | E2: 修正点
A3: O | B3: 経費 | C3: https://docs.google.com/spreadsheets/d/1T1trhXRLFLmvsw6NF2ctVVuwIVOBYo9gekGltVhcgf4/edit?gid=2089831337#gid=2089831337
B4: Paymentfee | C4: https://docs.google.com/spreadsheets/d/14XIjmVcs8qf6tS7n0A5FnYSYOV-msbbCaARCRnN4wc0/edit?gid=0#gid=0
A5: O | B5: 通信費 | C5: https://docs.google.com/spreadsheets/d/19eD15JPI2SoHKLgnXs8hXbY1ZpP5huYLpI6fo8Mr8bk/edit?gid=441054899#gid=441054899
A6: O | B6: インセンティブ | C6: https://docs.google.com/spreadsheets/d/1t2YDL0W_FSrPAtUBku2Z8HGiTZPLv8M1UVfIaROZ8Vc/edit?usp=sharing
A7: O | B7: 求人 | C7: https://docs.google.com/spreadsheets/d/1DTUC32YJHSyBa8CTkg1se2r2AQ3xxkB4dVQorqRF3gM/edit?gid=0#gid=0
A8: O | B8: Tarat 求人 | C8: https://docs.google.com/spreadsheets/d/1IQ05Dc9TE4AMwJzFRQDEJSGFNYHLKOkxgx7Fz5DM9ck/edit?gid=0#gid=0
A9: O | B9: 人件費 | C9: https://docs.google.com/spreadsheets/d/1-7D4xn7jPVWxK4Hv_jQ4ruRle9vkJvezFGDqi1GFnd4/edit?gid=0#gid=0
A10: O | B10: プロモーション | C10: https://docs.google.com/spreadsheets/d/14TMKG3wMlr7bVuDirYrw4abQ53_H-KZVarVgfXdR5pc/edit?gid=1563093964#gid=1563093964
B11: 管理費(オフィス等)
A12: O | B12: シフト | C12: https://docs.google.com/spreadsheets/d/1NzugtBxvrjbwprdJ3UJh-QfTIm61HxnySjCs2DhWXO0/edit?gid=1485379724#gid=1485379724
A13: O | B13: エージェント | C13: https://docs.google.com/spreadsheets/d/18x6IWuQJn1ECOgQSNubEgXz8Xj1z6J9FHAFuT_pHK4I/edit?gid=619570511#gid=619570511
B14: データ | C14: https://docs.google.com/spreadsheets/d/1hs7lDEWl3aqZCNELOHJ3W4x_fICLInX1n9Up--SMMKw/edit?gid=992341450#gid=992341450
A15: O | B15: 経費 | C15: https://docs.google.com/spreadsheets/d/1T1trhXRLFLmvsw6NF2ctVVuwIVOBYo9gekGltVhcgf4/edit?gid=1483108432#gid=1483108432
A16: O | B16: 停止銀行 | C16: https://docs.google.com/spreadsheets/d/1MBNCLrFtp3uGvnqofQQR8vTd0o9xmYlSUaowMIKWNR8/edit?gid=0#gid=0
A17: O | B17: ボーナス | C17: ボーナス付与可能金額 | D17: 顧客シートにまとめる
A18: O | B18: 必達 | C18: 必達管理＆営業資料-SAM
A19: O | B19: 必達管理＆営業資料 | C19: https://docs.google.com/spreadsheets/d/12d14wcOMXJQGiE1SgOrroORQ6MNdgPTZ1Qx2EneljKA/edit?gid=1564874204#gid=1564874204
A20: O | B20: CSマニュアル | C20: https://docs.google.com/document/d/18wThd2o5n6_G_G2thy-dTQUKm_0mT8hxHEpKluOo-m0/edit?tab=t.0#heading=h.ux0m98l75fsd
A21: O | B21: SAM顧客管理シート | C21: https://docs.google.com/spreadsheets/d/1vYc4iTJ16E7R6SUnGhwdB4aOJULuweZOJUwnvK3B2Ug/edit?pli=1&gid=69945731#gid=69945731
A22: O | B22: 電話用 | C22: https://docs.google.com/spreadsheets/d/1EYW0axbvIM3_qW8F6fKNkPg29oWP2Ac4a0IadqE3zzI/edit?gid=0#gid=0
A23: O | B23: リストBE | C23: https://docs.google.com/spreadsheets/d/1RU8MWWQqUe2qMkZwxm-pnHjLc1877wd4e299FV-zMfo/edit?usp=sharing
A24: O | B24: リストＥ | C24: https://docs.google.com/spreadsheets/d/1xQfQPXYrNd8-wxyQ1Mk4c3xS5qARAPgI9yiS0K4mVLA/edit?usp=sharing
A25: O | B25: リストＳ | C25: https://docs.google.com/spreadsheets/d/1JSq5IYiP3uXDsXhbDw28lYGEaJA3kFpB-8FUPJNc0WQ/edit?usp=sharing
B26: Japan call | C26: https://docs.google.com/spreadsheets/d/18s0zwW8MkvgGIWswb_5sDcp8eF_jfpRoV17r3xX6NO0/edit?gid=0#gid=0
B27: KYC待ちテスト | C27: https://docs.google.com/spreadsheets/d/1DlPYyHqALEXjVrIS8-NLSJqVyq7TkU4qIvYkU9GiNGY/edit?gid=0#gid=0
B28: そのほかリスト | C28: https://docs.google.com/spreadsheets/d/1p9ccg4xcnBW255bsb0SRlPfvuckiWZc3ag0YBAUdXrE/edit?gid=1680971485#gid=1680971485
B29: 入出金履歴 | C29: https://docs.google.com/spreadsheets/d/1wQNVMmuj-a4xpp5BuA75uVJ7tQLnllAFiullap81ALE/edit?usp=sharing
B30: VOISO | C30: https://docs.google.com/spreadsheets/d/1ESPRy1HoY4ufwKaRQLpUCpjQmdqYgquR/edit?gid=2055936698#gid=2055936698
B31: 銀行・取引所 | C31: https://docs.google.com/spreadsheets/d/18Y7q33TB_4CauTQemGNnS2A-1KkpAZKblBsyaJA7LR8/edit?gid=0#gid=0
B32: ＥＣプラットフォーム | C32: https://docs.google.com/spreadsheets/d/1NNJBI9h3MmZTIL92g0kjdX9FDu1aiobcH1jc4o4OlFE/edit?gid=0#gid=0
B33: ECサイト | C33: https://docs.google.com/spreadsheets/d/1G5jFwlM3dch0PGoau7_0JE7mCKeDG1EAV91dPdnwIs4/edit?gid=965343278#gid=965343278
B34: インボイス雛形 | C34: https://docs.google.com/spreadsheets/d/1lOaRl54pl4wRVOvIhf1LCTPNHda5wroCvWyn69LNvvc/edit?gid=0#gid=0
B35: インボイス作成 | C35: https://docs.google.com/spreadsheets/d/1lOaRl54pl4wRVOvIhf1LCTPNHda5wroCvWyn69LNvvc/edit?gid=1145697343#gid=1145697343
B36: インボイス送信 | C36: https://docs.google.com/spreadsheets/d/1WpJvatgKuVTKS5YIEhTU9Vgi7BA7iMWx5g9niYmy39Y/edit?gid=0#gid=0
B37: EC着金確認 | C37: https://docs.google.com/spreadsheets/d/1ZuAC4KXT1-OKMIGsWUWp2SWGqzrLpReJHH5K674-_gI/edit?gid=0#gid=0
... B65: 別部署経費計算シート | C65: https://docs.google.com/spreadsheets/d/1fZMBNk5-kulRwASx2B9DPX82HYxD9_xsplXmQigsxSg/edit?usp=sharing

Sheet TOTAL
B2: TOTAL | AA2: $1 | AD2: $1 | AG2: $1 | AJ2: $1 | AM2: $1 | AP2: $1 | AS2: $1 | AV2: $1 | AY2: $1 | BB2: $1 | BD2: $1
AA3: 144.07 | AD3: 149.91 | AG3: 155 | AJ3: 155 | AM3: 155.2 | AP3: 157.16 | AS3: 149.75 | AV3: 151.96 | AY3: 143.71 | BB3: 146.2 | BD3: 149.2
C4: TOTAL | D4: 12月-December | G4: 11月-Nobember | J4: 10月-October | M4: 9月-September | P4: 8月-August | S4: 7月-July | V4: 6月-June | Y4: 5月-May | AB4: 4月-April | AE4: 3月-March | AH4: 2月-February | AK4: 1月-January | AN4: 12月-December | AQ4: 11月-Nobember | AT4: 10月-October | AW4: 9月-September | AZ4: 8月-August | BC4: 7月-July
D5: 実数字 | E5: KPI | F5: 達成度 | G5: 実数字 | H5: KPI | I5: 達成度 | J5: 実数字 | K5: KPI | L5: 達成度 | M5: 実数字 | N5: KPI | O5: 達成度 | P5: 実数字 | Q5: KPI | R5: 達成度 | S5: 実数字 | T5: KPI | U5: 達成度 | V5: 実数字 | W5: KPI | X5: 達成度 | Y5: 実数字 | Z5: KPI | AA5: 達成度 | AB5: 実数字 | AC5: KPI | AD5: 達成度 | AE5: 実数字 | AF5: KPI | AG5: 達成度 | AH5: 実数字 | AI5: KPI | AJ5: 達成度 | AK5: 実数字 | AL5: KPI | AM5: 達成度 | AN5: 実数字 | AO5: KPI | AP5: 達成度 | AQ5: 実数字 | AR5: KPI | AS5: 達成度 | AT5: 実数字 | AU5: KPI | AV5: 達成度 | AW5: 実数字 | AX5: KPI | AY5: 達成度 | AZ5: 実数字 | BA5: KPI | BB5: 達成度 | BC5: 実数字 | BD5: KPI | BE5: 達成度
B6: リスト件数 | C6: =AH6+AK6+AN6+AT6+AW6+AZ6+BC6+AE6+AB6+Y6+V6+S6+P6+M6+J6+G6+D6 -> 166547 | D6: ='2025年12月収益'!C2 | E6: 15000 | F6: =IFERROR(D6/E6, " ") -> 0 | G6: ='2025年11月収益'!C2 -> 14867 | H6: 15000 | I6: =IFERROR(G6/H6, " ") -> 0.99113333 | J6: ='2025年10月収益'!C2 -> 14542 | K6: 15000 | L6: =IFERROR(J6/K6, " ") -> 0.96946667 | M6: ='2025年9月収益D'!C2 -> 14807 | N6: 15000 | O6: =IFERROR(M6/N6, " ") -> 0.98713333 | P6: ='2025年8月収益'!C2 -> 9997 | Q6: 10000 | R6: =IFERROR(P6/T6, " ") -> 0.9997 | S6: ='2025年7月収益'!C2 -> 9957 | T6: 10000 | U6: =IFERROR(S6/W6, " ") -> 0.9957 | V6: ='2025年6月収益'!C2 -> 9884 | W6: 10000 | X6: =IFERROR(V6/Z6, " ") -> 0.9884 | Y6: ='2025年5月収益'!C2 -> 9967 | Z6: 10000 | AA6: =IFERROR(Y6/AC6, " ") -> 0.9967 | AB6: ='2025年4月収益'!C2 -> 9601 | AC6: 10000 | AD6: =IFERROR(AB6/AF6, " ") -> 0.9601 | AE6: ='2025年3月収益'!C2 -> 6976 | AF6: 10000 | AG6: =IFERROR(AE6/AF6, " ") -> 0.6976 | AH6: ='2025年2月収益'!C2 -> 5948 | AI6: 10000 | AJ6: =IFERROR(AH6/AI6, " ") -> 0.5948 | AK6: ='2025年1月収益'!C2 -> 4231 | AL6: 10000 | AM6: =IFERROR(AK6/AL6, " ") -> 0.4231 | AN6: ='2024年12月収益'!C2 -> 5492 | AO6: 10000 | AP6: =IFERROR(AN6/AO6, " ") -> 0.5492 | AQ6: ='2024年11月収益'!C2 -> 34638 | AR6: 10000 | AS6: =IFERROR(AQ6/AR6, " ") -> 3.4638 | AT6: ='2024年10月収益'!C2 -> 10278 | AU6: 10000 | AV6: =IFERROR(AT6/AU6, " ") -> 1.0278 | AW6: ='2024年9月収益'!C2 -> 14000 | AX6: 10000 | AY6: =IFERROR(AW6/AX6, " ") -> 1.4 | AZ6: ='2024年8月収益'!C2 -> 16000 | BA6: 10000 | BB6: =IFERROR(BA6/AZ6, " ") -> 0.625 | BC6: ='2024年7月収益'!C2 -> 10000
B7: 打電数 | C7: =AH7+AK7+AN7+AT7+AW7+AZ7+BC7+AE7+AB7+Y7+V7+S7+P7+M7+J7+G7+D7 -> 867255 | D7: ='2025年12月収益'!C3 | G7: ='2025年11月収益'!C3 -> 10398 | J7: ='2025年10月収益'!C3 -> 10579 | M7: ='2025年9月収益D'!C3 -> 12471 | P7: ='2025年8月収益'!C3 -> 9829 | S7: ='2025年7月収益'!C3 -> 100011 | V7: ='2025年6月収益'!C3 -> 191066 | Y7: ='2025年5月収益'!C3 -> 171257 | AB7: ='2025年4月収益'!C3 -> 95781 | AE7: ='2025年3月収益'!C3 -> 63823 | AH7: ='2025年2月収益'!C3 -> 47811 | AK7: ='2025年1月収益'!C3 -> 31156 | AN7: ='2024年12月収益'!C3 -> 37455 | AQ7: ='2024年11月収益'!C3 -> 41317 | AT7: ='2024年10月収益'!C3 -> 35815 | AW7: ='2024年9月収益'!C3 -> 12626 | AZ7: ='2024年8月収益'!C3 -> 18177 | BC7: ='2024年7月収益'!C3 -> 19000
B8: 着電数 | C8: =AH8+AK8+AN8+AT8+AW8+AZ8+BC8+AE8+AB8+Y8+V8+S8+P8+M8+J8+G8+D8 -> 58832 | D8: ='2025年12月収益'!C4 | E8: 3600 | F8: =IFERROR(D8/E8, " ") -> 0 | G8: ='2025年11月収益'!C4 -> 1209 | H8: 3600 | I8: =IFERROR(G8/H8, " ") -> 0.33583333 | J8: ='2025年10月収益'!C4 -> 1716 | K8: 3600 | L8: =IFERROR(J8/K8, " ") -> 0.47666667 | M8: ='2025年9月収益D'!C4 -> 2418 | N8: 3600 | O8: =IFERROR(M8/N8, " ") -> 0.67166667 | P8: ='2025年8月収益'!C4 -> 3810 | Q8: 3600 | R8: =IFERROR(P8/T8, " ") -> 1.0583333 | S8: ='2025年7月収益'!C4 -> 3839 | T8: 3600 | U8: =IFERROR(S8/W8, " ") -> 1.0663889 | V8: ='2025年6月収益'!C4 -> 7980 | W8: 3600 | X8: =IFERROR(V8/Z8, " ") -> 2.2166667 | Y8: ='2025年5月収益'!C4 -> 6193 | Z8: 3600 | AA8: =IFERROR(Y8/AC8, " ") -> 1.7202778 | AB8: ='2025年4月収益'!C4 -> 4488 | AC8: 3600 | AD8: =IFERROR(AB8/AF8, " ") -> 1.2466667 | AE8: ='2025年3月収益'!C4 -> 4040 | AF8: 3600 | AG8: =IFERROR(AE8/AF8, " ") -> 1.1222222 | AH8: ='2025年2月収益'!C4 -> 4970 | AI8: 3600 | AJ8: =IFERROR(AH8/AI8, " ") -> 1.3805556 | AK8: ='2025年1月収益'!C4 -> 3724 | AL8: 3200 | AM8: =IFERROR(AK8/AL8, " ") -> 1.16375 | AN8: ='2024年12月収益'!C4 -> 4104 | AO8: 3200 | AP8: =IFERROR(AN8/AO8, " ") -> 1.2825 | AQ8: ='2024年11月収益'!C4 -> 4881 | AR8: 2800 | AS8: =IFERROR(AQ8/AR8, " ") -> 1.7432143 | AT8: ='2024年10月収益'!C4 -> 4262 | AU8: 2800 | AV8: =IFERROR(AT8/AU8, " ") -> 1.5221429 | AW8: ='2024年9月収益'!C4 -> 1610 | AX8: 2400 | AY8: =IFERROR(AW8/AX8, " ") -> 0.67083333 | AZ8: ='2024年8月収益'!C4 -> 1927 | BA8: 2400 | BB8: =IFERROR(BA8/AZ8, " ") -> 1.2454593 | BC8: ='2024年7月収益'!C4 -> 2542
B9: LINE登録数 | C9: =AH9+AK9+AN9+AT9+AW9+AZ9+BC9+AE9+AB9+Y9+V9+S9+P9+M9+J9+G9+D9 -> 3068 | D9: ='2025年12月収益'!C5 | G9: ='2025年11月収益'!C5 -> 38 | J9: ='2025年10月収益'!C5 -> 23 | M9: ='2025年9月収益D'!C5 -> 161 | P9: ='2025年8月収益'!C5 -> 48 | S9: ='2025年7月収益'!C5 -> 51 | V9: ='2025年6月収益'!C5 -> 367 | Y9: ='2025年5月収益'!C5 -> 497 | AB9: ='2025年4月収益'!C5 -> 269 | AE9: ='2025年3月収益'!C5 -> 207 | AH9: ='2025年2月収益'!C5 -> 223 | AK9: ='2025年1月収益'!C5 -> 213 | AN9: ='2024年12月収益'!C5 -> 177 | AQ9: ='2024年11月収益'!C5 -> 238 | AT9: ='2024年10月収益'!C5 -> 266 | AW9: ='2024年9月収益'!C5 -> 198 | AZ9: ='2024年8月収益'!C5 -> 200 | BC9: ='2024年7月収益'!C5 -> 130
B10: アカウント作成数 | C10: =AH10+AK10+AN10+AT10+AW10+AZ10+BC10+AE10+AB10+Y10+V10+S10+P10+M10+J10+G10+D10 -> #REF! | D10: ='2025年12月収益'!C6 -> 27 | E10: 640 | F10: =IFERROR(D10/E10, " ") -> 0.0421875 | G10: ='2025年11月収益'!C6 -> 77 | H10: 640 | I10: =IFERROR(G10/H10, " ") -> 0.1203125 | J10: ='2025年10月収益'!C6 -> 141 | K10: 640 | L10: =IFERROR(J10/K10, " ") -> 0.2203125 | M10: ='2025年9月収益D'!C6 -> 233 | N10: 640 | O10: =IFERROR(M10/N10, " ") -> 0.3640625 | P10: ='2025年8月収益'!C6 -> 78 | Q10: 640 | R10: =IFERROR(P10/T10, " ") -> 0.121875 | S10: ='2025年7月収益'!C6 -> 67 | T10: 640 | U10: =IFERROR(S10/W10, " ") -> 0.1046875 | V10: ='2025年6月収益'!C6 -> #REF! | W10: 640 | X10: =IFERROR(V10/Z10, " ") | Y10: ='2025年5月収益'!C6 -> 316 | Z10: 640 | AA10: =IFERROR(Y10/AC10, " ") -> 0.49375 | AB10: ='2025年4月収益'!C6 -> 208 | AC10: 640 | AD10: =IFERROR(AB10/AF10, " ") -> 0.325 | AE10: ='2025年3月収益'!C6 -> 159 | AF10: 640 | AG10: =IFERROR(AE10/AF10, " ") -> 0.2484375 | AH10: ='2025年2月収益'!C6 -> 113 | AI10: 640 | AJ10: =IFERROR(AH10/AI10, " ") -> 0.1765625 | AK10: ='2025年1月収益'!C6 -> 149 | AL10: 640 | AM10: =IFERROR(AK10/AL10, " ") -> 0.2328125 | AN10: ='2024年12月収益'!C6 -> 111 | AO10: 640 | AP10: =IFERROR(AN10/AO10, " ") -> 0.1734375 | AQ10: ='2024年11月収益'!C6 -> 151 | AR10: 640 | AS10: =IFERROR(AQ10/AR10, " ") -> 0.2359375 | AT10: ='2024年10月収益'!C6 -> 161 | AU10: 640 | AV10: =IFERROR(AT10/AU10, " ") -> 0.2515625 | AW10: ='2024年9月収益'!C6 -> 149 | AX10: 640 | AY10: =IFERROR(AW10/AX10, " ") -> 0.2328125 | AZ10: ='2024年8月収益'!C6 -> 134 | BA10: 640 | BB10: =IFERROR(BA10/AZ10, " ") -> 4.7761194 | BC10: ='2024年7月収益'!C6 -> 68
B11: FTD数 | C11: =AH11+AK11+AN11+AT11+AW11+AZ11+BC11+AE11+AB11+Y11+V11+S11+P11+M11+J11+G11+D11 -> #REF! | D11: ='2025年12月収益'!C7 -> 8 | E11: 320 | F11: =IFERROR(D11/E11, " ") -> 0.025 | G11: ='2025年11月収益'!C7 -> 61 | H11: 320 | I11: =IFERROR(G11/H11, " ") -> 0.190625 | J11: ='2025年10月収益'!C7 -> 82 | K11: 320 | L11: =IFERROR(J11/K11, " ") -> 0.25625 | M11: ='2025年9月収益D'!C7 -> 154 | N11: 320 | O11: =IFERROR(M11/N11, " ") -> 0.48125 | P11: ='2025年8月収益'!C7 -> 60 | Q11: 320 | R11: =IFERROR(P11/T11, " ") -> 0.1875 | S11: ='2025年7月収益'!C7 -> 39 | T11: 320 | U11: =IFERROR(S11/W11, " ") -> 0.121875 | V11: ='2025年6月収益'!C7 -> #REF! | W11: 320 | X11: =IFERROR(V11/Z11, " ") | Y11: ='2025年5月収益'!C7 -> 0 | Z11: 320 | AA11: =IFERROR(Y11/AC11, " ") -> 0 | AB11: ='2025年4月収益'!C7 -> 0 | AC11: 320 | AD11: =IFERROR(AB11/AF11, " ") -> 0 | AE11: ='2025年3月収益'!C7 -> 0 | AF11: 320 | AG11: =IFERROR(AE11/AF11, " ") -> 0 | AH11: ='2025年2月収益'!C7 -> 0 | AI11: 320 | AJ11: =IFERROR(AH11/AI11, " ") -> 0 | AK11: ='2025年1月収益'!C7 -> 0 | AL11: 240 | AM11: =IFERROR(AK11/AL11, " ") -> 0 | AN11: ='2024年12月収益'!C7 -> 0 | AO11: 240 | AP11: =IFERROR(AN11/AO11, " ") -> 0 | AQ11: ='2024年11月収益'!C7 -> 0 | AR11: 240 | AS11: =IFERROR(AQ11/AR11, " ") -> 0 | AT11: ='2024年10月収益'!C7 -> 0 | AU11: 160 | AV11: =IFERROR(AT11/AU11, " ") -> 0 | AW11: ='2024年9月収益'!C7 -> 0 | AX11: 160 | AY11: =IFERROR(AW11/AX11, " ") -> 0 | AZ11: ='2024年8月収益'!C7 -> 0 | BA11: 160 | BB11: =IFERROR(BA11/AZ11, " ") | BC11: ='2024年7月収益'!C7 -> 0
B12: 前月リテンション数 | C12: =AH12+AK12+AN12+AT12+AW12+AZ12+BC12+AE12+AB12+Y12+V12+S12+P12+M12+J12+G12+D12 -> 1102 | D12: ='2025年12月収益'!C15 -> 0 | E12: 297 | F12: =IFERROR(D12/E12, " ") -> 0 | G12: ='2025年11月収益'!C15 -> 82 | H12: 297 | I12: =IFERROR(G12/H12, " ") -> 0.27609428 | J12: ='2025年10月収益'!C15 -> 75 | K12: 297 | L12: =IFERROR(J12/K12, " ") -> 0.25252525 | M12: ='2025年9月収益D'!C15 -> 21 | N12: 297 | O12: =IFERROR(M12/N12, " ") -> 0.070707071 | P12: ='2025年8月収益'!C15 -> 88 | Q12: 297 | R12: =IFERROR(P12/T12, " ") -> 0.2962963 | S12: ='2025年7月収益'!C15 -> 17 | T12: 297 | U12: =IFERROR(S12/W12, " ") -> 0.057239057 | V12: ='2025年6月収益'!C15 -> 235 | W12: 297 | X12: =IFERROR(V12/Z12, " ") -> 0.79124579 | Y12: ='2025年5月収益'!C15 -> 119 | Z12: 297 | AA12: =IFERROR(Y12/AC12, " ") -> 0.4006734 | AB12: ='2025年4月収益'!C15 -> 74 | AC12: 297 | AD12: =IFERROR(AB12/AF12, " ") -> 0.24915825 | AE12: ='2025年3月収益'!C15 -> 56 | AF12: 297 | AG12: =IFERROR(AE12/AF12, " ") -> 0.18855219 | AH12: ='2025年2月収益'!C15 -> 75 | AI12: 220 | AJ12: =IFERROR(AH12/AI12, " ") -> 0.34090909 | AK12: ='2025年1月収益'!C15 -> 60 | AL12: 199 | AM12: =IFERROR(AK12/AL12, " ") -> 0.30150754 | AN12: ='2024年12月収益'!C15 -> 60 | AO12: 159 | AP12: =IFERROR(AN12/AO12, " ") -> 0.37735849 | AQ12: ='2024年11月収益'!C15 -> 75 | AR12: 112 | AS12: =IFERROR(AQ12/AR12, " ") -> 0.66964286 | AT12: ='2024年10月収益'!C15 -> 67 | AU12: 90 | AV12: =IFERROR(AT12/AU12, " ") -> 0.74444444 | AW12: ='2024年9月収益'!C15 -> 62 | AX12: 64 | AY12: =IFERROR(AW12/AX12, " ") -> 0.96875 | AZ12: ='2024年8月収益'!C15 -> 11 | BA12: 0 | BC12: ='2024年7月収益'!C15 -> 0
B13: 引継ぎプレイヤー数 | C13: =AH13+AK13+AN13+AT13+AW13+AZ13+BC13+AE13+AB13+Y13+V13+S13+P13+M13+J13+G13+D13 -> #REF! | D13: ='2025年12月収益'!C16 | G13: ='2025年11月収益'!C16 -> 150 | J13: ='2025年10月収益'!C16 -> 153 | M13: ='2025年9月収益D'!C16 -> 65 | P13: ='2025年8月収益'!C16 -> 206 | S13: ='2025年7月収益'!C16 -> 314 | V13: ='2025年6月収益'!C16 -> #REF! | Y13: ='2025年5月収益'!C16 -> 438 | AB13: ='2025年4月収益'!C16 -> 343 | AE13: ='2025年3月収益'!C16 -> 296 | AH13: ='2025年2月収益'!C16 -> 256 | AK13: ='2025年1月収益'!C16 -> 208 | AN13: ='2024年12月収益'!C16 -> 246 | AQ13: ='2024年11月収益'!C16 -> 155 | AT13: ='2024年10月収益'!C16 -> 104 | AW13: ='2024年9月収益'!C16 -> 57 | AZ13: ='2024年8月収益'!C16 -> -10 | BC13: ='2024年7月収益'!C16 -> 0
B14: アクティブユーザー数 | C14: =AH14+AK14+AN14+AT14+AW14+AZ14+BC14+AE14+AB14+Y14+V14+S14+P14+M14+J14+G14+D14 -> 5970 | D14: ='2025年12月収益'!C17 -> 292 | E14: 617 | F14: =IFERROR(D14/E14, " ") -> 0.4732577 | G14: ='2025年11月収益'!C17 -> 227 | H14: 617 | I14: =IFERROR(G14/H14, " ") -> 0.36790924 | J14: ='2025年10月収益'!C17 -> 294 | K14: 617 | L14: =IFERROR(J14/K14, " ") -> 0.47649919 | M14: ='2025年9月収益D'!C17 -> 298 | N14: 617 | O14: =IFERROR(M14/N14, " ") -> 0.48298217 | P14: ='2025年8月収益'!C17 -> 284 | Q14: 617 | R14: =IFERROR(P14/T14, " ") -> 0.46029173 | S14: ='2025年7月収益'!C17 -> 381 | T14: 617 | U14: =IFERROR(S14/W14, " ") -> 0.61750405 | V14: ='2025年6月収益'!C17 -> 698 | W14: 617 | X14: =IFERROR(V14/Z14, " ") -> 1.1312804 | Y14: ='2025年5月収益'!C17 -> 754 | Z14: 617 | AA14: =IFERROR(Y14/AC14, " ") -> 1.2220421 | AB14: ='2025年4月収益'!C17 -> 551 | AC14: 617 | AD14: =IFERROR(AB14/AF14, " ") -> 0.89303079 | AE14: ='2025年3月収益'!C17 -> 455 | AF14: 617 | AG14: =IFERROR(AE14/AF14, " ") -> 0.73743922 | AH14: ='2025年2月収益'!C17 -> 369 | AI14: 540 | AJ14: =IFERROR(AH14/AI14, " ") -> 0.68333333 | AK14: ='2025年1月収益'!C17 -> 357 | AL14: 439 | AM14: =IFERROR(AK14/AL14, " ") -> 0.81321185 | AN14: ='2024年12月収益'!C17 -> 357 | AO14: 399 | AP14: =IFERROR(AN14/AO14, " ") -> 0.89473684 | AQ14: ='2024年11月収益'!C17 -> 306 | AR14: 352 | AS14: =IFERROR(AQ14/AR14, " ") -> 0.86931818 | AT14: ='2024年10月収益'!C17 -> 265 | AU14: 250 | AV14: =IFERROR(AT14/AU14, " ") -> 1.06 | AW14: ='2024年9月収益'!C17 -> 206 | AX14: 224 | AY14: =IFERROR(AW14/AX14, " ") -> 0.91964286 | AZ14: ='2024年8月収益'!C17 -> 124 | BA14: 160 | BB14: =IFERROR(BA14/AZ14, " ") -> 1.2903226 | BC14: ='2024年7月収益'!C17 -> 58
B15: T/O | C15: =AH15+AK15+AN15+AT15+AW15+AZ15+BC15+AE15+AB15+Y15+V15+S15+P15+M15+J15+G15+D15 -> 47580629414 | D15: ='2025年12月収益'!C18 -> 1514244472 | G15: ='2025年11月収益'!C18 -> 1568206350 | J15: ='2025年10月収益'!C18 -> 1577495818 | M15: ='2025年9月収益D'!C18 -> 2578173994 | P15: ='2025年8月収益'!C18 -> 1910465086 | S15: ='2025年7月収益'!C18 -> 3753649644 | V15: ='2025年6月収益'!C18 -> 3764837699 | Y15: ='2025年5月収益'!C18 -> 5416323483 | AB15: ='2025年4月収益'!C18 -> 3401315523 | AE15: ='2025年3月収益'!C18 -> 2574622274 | AH15: ='2025年2月収益'!C18 -> 2663696845 | AK15: ='2025年1月収益'!C18 -> 3640093327 | AN15: ='2024年12月収益'!C18 -> 7252322684 | AQ15: ='2024年11月収益'!C18 -> 2401777358 | AT15: ='2024年10月収益'!C18 -> 2159690163 | AW15: ='2024年9月収益'!C18 -> 1392132574 | AZ15: ='2024年8月収益'!C18 -> 2283745296 | BC15: ='2024年7月収益'!C18 -> 129614183
B16: 勝利金 | C16: =AH16+AK16+AN16+AT16+AW16+AZ16+BC16+AE16+AB16+Y16+V16+S16+P16+M16+J16+G16+D16 -> 46483843913 | D16: ='2025年12月収益'!C19 -> 1460665967 | F16: =IFERROR(D16/H16, " ") | G16: ='2025年11月収益'!C19 -> 1503305351 | I16: =IFERROR(G16/K16, " ") | J16: ='2025年10月収益'!C19 -> 1507184478 | L16: =IFERROR(J16/N16, " ") | M16: ='2025年9月収益D'!C19 -> 2503998997 | O16: =IFERROR(M16/Q16, " ") | P16: ='2025年8月収益'!C19 -> 1853512419 | R16: =IFERROR(P16/T16, " ") | S16: ='2025年7月収益'!C19 -> 3664240730 | U16: =IFERROR(S16/W16, " ") | V16: ='2025年6月収益'!C19 -> 3658015706 | X16: =IFERROR(V16/Z16, " ") | Y16: ='2025年5月収益'!C19 -> 5413798942 | AA16: =IFERROR(Y16/AC16, " ") | AB16: ='2025年4月収益'!C19 -> 3320603296 | AD16: =IFERROR(AB16/AF16, " ") | AE16: ='2025年3月収益'!C19 -> 2506838109 | AG16: =IFERROR(AE16/AF16, " ") | AH16: ='2025年2月収益'!C19 -> 2583305717 | AJ16: =IFERROR(AH16/AI16, " ") | AK16: ='2025年1月収益'!C19 -> 3541831671 | AM16: =IFERROR(AK16/AL16, " ") | AN16: ='2024年12月収益'!C19 -> 7125128234 | AP16: =IFERROR(AN16/AO16, " ") | AQ16: ='2024年11月収益'!C19 -> 2337436763 | AS16: =IFERROR(AQ16/AR16, " ") | AT16: ='2024年10月収益'!C19 -> 2103768160 | AV16: =IFERROR(AT16/AU16, " ") | AW16: ='2024年9月収益'!C19 -> 1389785960 | AY16: =IFERROR(AW16/AX16, " ") | AZ16: ='2024年8月収益'!C19 -> 2225182287 | BC16: ='2024年7月収益'!C19 -> 122677890
B17: RTP | C17: =C16/C15 -> 0.97694891 | D17: ='2025年12月収益'!C20 -> 0.964617 | G17: ='2025年11月収益'!C20 -> 0.9586145 | J17: ='2025年10月収益'!C20 -> 0.95542851 | M17: ='2025年9月収益D'!C20 -> 0.97122964 | P17: ='2025年8月収益'!C20 -> 0.9735 | S17: ='2025年7月収益'!C20 -> 0.9761808 | V17: ='2025年6月収益'!C20 -> 0.9716264 | Y17: ='2025年5月収益'!C20 -> 0.9995339 | AB17: ='2025年4月収益'!C20 -> 0.97627029 | AE17: ='2025年3月収益'!C20 -> 0.97367219 | AH17: ='2025年2月収益'!C20 -> 0.96981972 | AK17: ='2025年1月収益'!C20 -> 0.97300573 | AN17: ='2024年12月収益'!C20 -> 0.98246156 | AQ17: ='2024年11月収益'!C20 -> 0.97321126 | AT17: ='2024年10月収益'!C20 -> 0.97410647 | AW17: ='2024年9月収益'!C20 -> 0.99831437 | AZ17: ='2024年8月収益'!C20 -> 0.97435659 | BC17: ='2024年7月収益'!C20 -> 0.94648508
B18: WIN/LOSE | C18: =AH18+AK18+AN18+AT18+AW18+AZ18+BC18+AE18+AB18+Y18+V18+S18+P18+M18+J18+G18+D18 -> 1096785502 | D18: ='2025年12月収益'!C21 -> 53578506 | F18: =IFERROR(D18/H18, " ") | G18: ='2025年11月収益'!C21 -> 64900999 | I18: =IFERROR(G18/K18, " ") | J18: ='2025年10月収益'!C21 -> 70311340 | L18: =IFERROR(J18/N18, " ") | M18: ='2025年9月収益D'!C21 -> 74174997 | O18: =IFERROR(M18/Q18, " ") | P18: ='2025年8月収益'!C21 -> 56952667 | R18: =IFERROR(P18/T18, " ") | S18: ='2025年7月収益'!C21 -> 89408914 | U18: =IFERROR(S18/W18, " ") | V18: ='2025年6月収益'!C21 -> 1.0682199e+08 | X18: =IFERROR(V18/Z18, " ") | Y18: ='2025年5月収益'!C21 -> 2524541 | AA18: =IFERROR(Y18/AC18, " ") | AB18: ='2025年4月収益'!C21 -> 80712227 | AD18: =IFERROR(AB18/AF18, " ") | AE18: ='2025年3月収益'!C21 -> 67784165 | AG18: =IFERROR(AE18/AF18, " ") | AH18: ='2025年2月収益'!C21 -> 80391127 | AJ18: =IFERROR(AH18/AI18, " ") | AK18: ='2025年1月収益'!C21 -> 98261656 | AM18: =IFERROR(AK18/AL18, " ") | AN18: ='2024年12月収益'!C21 -> 127194450 | AP18: =IFERROR(AN18/AO18, " ") | AQ18: ='2024年11月収益'!C21 -> 64340595 | AS18: =IFERROR(AQ18/AR18, " ") | AT18: ='2024年10月収益'!C21 -> 55922003 | AV18: =IFERROR(AT18/AU18, " ") | AW18: ='2024年9月収益'!C21 -> 2346613.9 | AY18: =IFERROR(AW18/AX18, " ") | AZ18: ='2024年8月収益'!C21 -> 58563009 | BC18: ='2024年7月収益'!C21 -> 6936293
B19: LTV(WIN/LOSE) | C19: =AH19+AK19+AN19+AT19+AW19+AZ19+BC19+AE19+AB19+Y19+V19+S19+P19+M19+J19+G19+D19 -> 3698472.5 | D19: ='2025年12月収益'!C22 -> 184753.47 | G19: ='2025年11月収益'!C22 -> 285907.48 | J19: ='2025年10月収益'!C22 -> 239154.22 | M19: ='2025年9月収益D'!C22 -> 248909.39 | P19: ='2025年8月収益'!C22 -> 389548 | S19: ='2025年7月収益'!C22 -> 234669.07 | V19: ='2025年6月収益'!C22 -> 153040.1 | Y19: ='2025年5月収益'!C22 -> 3348.1976 | AB19: ='2025年4月収益'!C22 -> 146483.17 | AE19: ='2025年3月収益'!C22 -> 148976.19 | AH19: ='2025年2月収益'!C22 -> 217862.13 | AK19: ='2025年1月収益'!C22 -> 275242.73 | AN19: ='2024年12月収益'!C22 -> 356286.97 | AQ19: ='2024年11月収益'!C22 -> 210263.38 | AT19: ='2024年10月収益'!C22 -> 211026.43 | AW19: ='2024年9月収益'!C22 -> 11391.329 | AZ19: ='2024年8月収益'!C22 -> 472282.33 | BC19: ='2024年7月収益'!C22 -> 119591.26
B20: 回収予定金額 | C20: =AH20+AK20+AN20+AT20+AW20+AZ20+BC20+AE20+AB20+Y20+V20+S20+P20+M20+J20+G20+D20 -> #REF! | D20: ='2025年12月収益'!C23 -> 73458827 | G20: ='2025年11月収益'!C23 -> 77447062 | J20: ='2025年10月収益'!C23 -> 71840329 | M20: ='2025年9月収益D'!C23 -> 76698567 | P20: ='2025年8月収益'!C23 -> 56467301 | S20: ='2025年7月収益'!C23 -> 1.067379e+08 | V20: ='2025年6月収益'!C23 -> #REF! | Y20: ='2025年5月収益'!C23 -> 1.2720747e+08 | AB20: ='2025年4月収益'!C23 -> 1.2247777e+08 | AE20: ='2025年3月収益'!C23 -> 1.4499839e+08 | AG20: =IFERROR(AE20/AF20, " ") | AH20: ='2025年2月収益'!C23 -> 105750924 | AJ20: =IFERROR(AH20/AI20, " ") | AK20: ='2025年1月収益'!C23 -> 1.4649082e+08 | AM20: =IFERROR(AK20/AL20, " ") | AN20: ='2024年12月収益'!C23 -> 200248158 | AP20: =IFERROR(AN20/AO20, " ") | AQ20: ='2024年11月収益'!C23 -> 91106410 | AS20: =IFERROR(AQ20/AR20, " ") | AT20: ='2024年10月収益'!C23 -> 70318275 | AV20: =IFERROR(AT20/AU20, " ") | AW20: ='2024年9月収益'!C23 -> 66130411 | AY20: =IFERROR(AW20/AX20, " ") | AZ20: ='2024年8月収益'!C23 -> 67593086 | BC20: ='2024年7月収益'!C23 -> 5432157.6
B21: 回収金額 | C21: =AH21+AK21+AN21+AT21+AW21+AZ21+BC21+AE21+AB21+Y21+V21+S21+P21+M21+J21+G21+D21 -> #REF! | D21: ='2025年12月収益'!C24 -> 61567404 | G21: ='2025年11月収益'!C24 -> 64213601 | J21: ='2025年10月収益'!C24 -> 55956778 | M21: ='2025年9月収益D'!C24 -> 62846588 | P21: ='2025年8月収益'!C24 -> 41786755 | S21: ='2025年7月収益'!C24 -> 74754328 | V21: ='2025年6月収益'!C24 -> #REF! | Y21: ='2025年5月収益'!C24 -> 1.080073e+08 | AB21: ='2025年4月収益'!C24 -> 114885739 | AE21: ='2025年3月収益'!C24 -> 1.3886023e+08 | AH21: ='2025年2月収益'!C24 -> 1.0511108e+08 | AK21: ='2025年1月収益'!C24 -> 129120304 | AN21: ='2024年12月収益'!C24 -> 190324998 | AQ21: ='2024年11月収益'!C24 -> 82763467 | AT21: ='2024年10月収益'!C24 -> 57837291 | AW21: ='2024年9月収益'!C24 -> 55774912 | AZ21: ='2024年8月収益'!C24 -> 45528650 | BC21: ='2024年7月収益'!C24 -> 4115281
B22: 回収率 | C22: =C21/C20 -> #REF! | D22: ='2025年12月収益'!C25 -> 0.83812125 | E22: 0.4 | F22: =F21/F20 -> #DIV/0! | G22: =G21/G20 -> 0.82912895 | H22: 0.4 | I22: =I21/I20 -> #DIV/0! | J22: =J21/J20 -> 0.77890481 | K22: 0.4 | L22: =IFERROR(J22/K22, " ") -> 1.947262 | M22: =M21/M20 -> 0.81939716 | N22: 0.4 | O22: =IFERROR(M22/N22, " ") -> 2.0484929 | P22: =P21/P20 -> 0.74001686 | Q22: 0.4 | R22: =IFERROR(P22/T22, " ") -> 1.8500422 | S22: =S21/S20 -> 0.70035409 | T22: 0.4 | U22: =IFERROR(S22/W22, " ") -> 1.7508852 | V22: =V21/V20 -> #REF! | W22: 0.4 | X22: =IFERROR(V22/Z22, " ") | Y22: =Y21/Y20 -> 0.8490641 | Z22: 0.4 | AA22: =IFERROR(Y22/AC22, " ") -> 2.1226602 | AB22: ='2025年4月収益'!C25 -> 0.93801298 | AC22: 0.4 | AD22: =IFERROR(AB22/AF22, " ") -> 1.0422366 | AE22: ='2025年3月収益'!C25 -> 0.95766736 | AF22: 0.9 | AG22: =IFERROR(AE22/AF22, " ") -> 1.0640748 | AH22: ='2025年2月収益'!C25 -> 0.99394956 | AI22: 0.9 | AJ22: =IFERROR(AH22/AI22, " ") -> 1.1043884 | AK22: ='2025年1月収益'!C25 -> 0.88142248 | AL22: 0.9 | AM22: =IFERROR(AK22/AL22, " ") -> 0.97935831 | AN22: ='2024年12月収益'!C25 -> 0.95044569 | AO22: 0.9 | AP22: =IFERROR(AN22/AO22, " ") -> 1.0560508 | AQ22: ='2024年11月収益'!C25 -> 0.90842638 | AR22: 0.9 | AS22: =IFERROR(AQ22/AR22, " ") -> 1.0093626 | AT22: ='2024年10月収益'!C25 -> 0.82250725 | AU22: 0.9 | AV22: =IFERROR(AT22/AU22, " ") -> 0.91389695 | AW22: ='2024年9月収益'!C25 -> 0.84340791 | AX22: 0.9 | AY22: =IFERROR(AW22/AX22, " ") -> 0.9371199 | AZ22: ='2024年8月収益'!C25 -> 0.67356963 | BA22: 0.9 | BB22: =IFERROR(BA22/AZ22, " ") -> 1.3361648 | BC22: ='2024年7月収益'!C25 -> 0.75757762
B23: 出金金額 | C23: =AH23+AK23+AN23+AT23+AW23+AZ23+BC23 -> 2.5314562e+08 | D23: ='2025年12月収益'!C26 -> 20555338 | G23: ='2025年11月収益'!C26 -> 19725328 | J23: ='2025年10月収益'!C26 -> 17719827 | M23: ='2025年9月収益D'!C26 -> 21551493 | P23: ='2025年8月収益'!C26 -> 13154437 | S23: ='2025年7月収益'!C26 -> 37542660 | V23: ='2025年6月収益'!C26 -> #REF! | Y23: ='2025年5月収益'!C26 -> 74028096 | AB23: ='2025年4月収益'!C26 -> 39921751 | AE23: ='2025年3月収益'!C26 -> 45743713 | AH23: ='2025年2月収益'!C26 -> 25727451 | AK23: ='2025年1月収益'!C26 -> 57374896 | AN23: ='2024年12月収益'!C26 -> 64423375 | AQ23: ='2024年11月収益'!C26 -> 33439172 | AT23: ='2024年10月収益'!C26 -> 21652355 | AW23: ='2024年9月収益'!C26 -> 64758806 | AZ23: ='2024年8月収益'!C26 -> 17978411 | BC23: ='2024年7月収益'!C26 -> 1230324
B24: GGR | C24: =AB24+AE24+AH24+AK24+AN24+AT24+AW24+AZ24+BC24+Y24+V24+S24+P24+M24+J24+G24+D24 -> 798175006 | D24: ='2025年12月収益'!C27 -> 38616975 | E24: =1233600*AA3 -> 177724752 | F24: =IFERROR(D24/E24, " ") -> 0.21728529 | G24: ='2025年11月収益'!C27 -> 43448785 | H24: =1233600*AD3 -> 184928976 | I24: =IFERROR(G24/H24, " ") -> 0.2349485 | J24: ='2025年10月収益'!C27 -> 38174451 | K24: =1233600*AG3 -> 191208000 | L24: =IFERROR(J24/K24, " ") -> 0.19964882 | M24: ='2025年9月収益D'!C27 -> 40783402 | N24: =1233600*AJ3 -> 191208000 | O24: =IFERROR(M24/N24, " ") -> 0.21329339 | P24: =26206490-1612843 -> 24593647 | Q24: =1233600*AM3 -> 191454720 | R24: =IFERROR(P24/T24, " ") -> 0.1268547 | S24: ='2025年7月収益'!C27 -> 11754882 | T24: =1233600*AP3 -> 193872576 | U24: =IFERROR(S24/W24, " ") -> 0.06363222 | V24: ='2025年6月収益'!C27 -> 79117068 | W24: =1233600*AS3 -> 184731600 | X24: =IFERROR(V24/Z24, " ") -> 0.42205256 | Y24: ='2025年5月収益'!C27 -> 30822400 | Z24: =1233600*AV3 -> 187457856 | AA24: =IFERROR(Y24/AC24, " ") -> 0.17386217 | AB24: ='2025年4月収益'!C27 -> 69357611 | AC24: =1233600*AY3 -> 177280656 | AD24: =IFERROR(AB24/AF24, " ") -> 0.38456733 | AE24: ='2025年3月収益'!C27 -> 88303648 | AF24: =1233600*BB3 -> 180352320 | AG24: =IFERROR(AE24/AF24, " ") -> 0.48961748 | AH24: ='2025年2月収益'!C27 -> 76779202 | AI24: =1079272*BB3 -> 1.5778957e+08 | AJ24: =IFERROR(AH24/AI24, " ") -> 0.48659239 | AK24: ='2025年1月収益'!C27 -> 72496605 | AL24: =878544*BB3 -> 1.2844313e+08 | AM24: =IFERROR(AK24/AL24, " ") -> 0.5644257 | AN24: ='2024年12月収益'!C27 -> 124135759 | AO24: =797088*BB3 -> 1.1653427e+08 | AP24: =IFERROR(AN24/AO24, " ") -> 1.0652297 | AQ24: ='2024年11月収益'!C27 -> 49324295 | AR24: =704640*BB3 -> 103018368 | AS24: =IFERROR(AQ24/AR24, " ") -> 0.47879126 | AT24: ='2024年10月収益'!C27 -> 35789786 | AU24: =499200*BB3 -> 72983040 | AV24: =IFERROR(AT24/AU24, " ") -> 0.49038497 | AW24: ='2024年9月収益'!C27 -> -8983894 | AX24: =448000*BB3 -> 65497600 | AY24: =IFERROR(AW24/AX24, " ") -> -0.13716371 | AZ24: ='2024年8月収益'!C27 -> 30099722 | BA24: =320000*BB3 -> 46784000 | BB24: =IFERROR(BA24/AZ24, " ") -> 1.5543001 | BC24: ='2024年7月収益'!C27 -> 2884957
B25: LTV(GGR) | C25: =C24/C14 -> 133697.66 | D25: ='2025年12月収益'!C28 -> 133161.98 | E25: =2000*F3 -> 0 | F25: =IFERROR(D25/H25, " ") | G25: ='2025年11月収益'!C28 -> 191404.34 | H25: =2000*I3 -> 0 | I25: =IFERROR(G25/K25, " ") | J25: ='2025年10月収益'!C28 -> 129845.07 | K25: =2000*L3 -> 0 | L25: =IFERROR(J25/N25, " ") | M25: ='2025年9月収益D'!C28 -> 137774.17 | N25: =2000*O3 -> 0 | O25: =IFERROR(M25/Q25, " ") | P25: ='2025年8月収益'!C28 -> 92276.373 | Q25: =2000*R3 -> 0 | R25: =IFERROR(P25/T25, " ") | S25: ='2025年7月収益'!C28 -> 34271.252 | T25: =2000*U3 -> 0 | U25: =IFERROR(S25/W25, " ") | V25: ='2025年6月収益'!C28 -> 113348.24 | W25: =2000*X3 -> 0 | X25: =IFERROR(V25/Z25, " ") -> 0.39337903 | Y25: ='2025年5月収益'!C28 -> 40878.515 | Z25: =2000*AA3 -> 288140 | AA25: =IFERROR(Y25/AC25, " ") -> 0.13634352 | AB25: ='2025年4月収益'!C28 -> 125875.88 | AC25: =2000*AD3 -> 299820 | AD25: =IFERROR(AB25/AF25, " ") -> 0.40605123 | AE25: ='2025年3月収益'!C28 -> 194073.95 | AF25: =2000*AG3 -> 310000 | AG25: =IFERROR(AE25/AF25, " ") -> 0.62604501 | AH25: ='2025年2月収益'!C28 -> 208073.72 | AI25: =2000*AG3 -> 310000 | AJ25: =IFERROR(AH25/AI25, " ") -> 0.67120554 | AK25: ='2025年1月収益'!C28 -> 203071.72 | AL25: =2000*AG3 -> 310000 | AM25: =IFERROR(AK25/AL25, " ") -> 0.65507007 | AN25: ='2024年12月収益'!C28 -> 347719.21 | AO25: =2000*AG3 -> 310000 | AP25: =IFERROR(AN25/AO25, " ") -> 1.1216749 | AQ25: ='2024年11月収益'!C28 -> 161190.51 | AR25: =2000*AG3 -> 310000 | AS25: =IFERROR(AQ25/AR25, " ") -> 0.51996937 | AT25: ='2024年10月収益'!C28 -> 135055.8 | AU25: =2000*AG3 -> 310000 | AV25: =IFERROR(AT25/AU25, " ") -> 0.43566386 | AW25: ='2024年9月収益'!C28 -> -43611.136 | AX25: =2000*AG3 -> 310000 | AY25: =IFERROR(AW25/AX25, " ") -> -0.14068108 | AZ25: ='2024年8月収益'!C28 -> 242739.69 | BA25: =2000*AG3 -> 310000 | BB25: =IFERROR(BA25/AZ25, " ") -> 1.2770882 | BC25: ='2024年7月収益'!C28 -> 49740.638
B26: プロバイダーフィー | C26: =AH26+AK26+AN26+AT26+AW26+AZ26+BC26+AE26+AB26+Y26+V26+S26+P26+M26+J26+G26+D26 -> 1.2173114e+08 | D26: ='2025年12月収益'!C29 -> 7374448 | F26: =IFERROR(D26/H26, " ") | G26: ='2025年11月収益'!C29 -> 9838142.7 | I26: =IFERROR(G26/K26, " ") | J26: ='2025年10月収益'!C29 -> 7263554.6 | L26: =IFERROR(J26/N26, " ") | M26: ='2025年9月収益D'!C29 -> 9010618 | O26: =IFERROR(M26/Q26, " ") | P26: ='2025年8月収益'!C29 -> 3559976 | R26: =IFERROR(P26/T26, " ") | S26: ='2025年7月収益'!C29 -> 7963281 | U26: =IFERROR(S26/W26, " ") | V26: ='2025年6月収益'!C29 -> 9996206.4 | X26: =IFERROR(V26/Z26, " ") | Y26: ='2025年5月収益'!C29 -> 9327506.3 | AA26: =IFERROR(Y26/AC26, " ") | AB26: ='2025年4月収益'!C29 -> 6733329 | AD26: =IFERROR(AB26/AF26, " ") | AE26: ='2025年3月収益'!C29 -> 14728276 | AG26: =IFERROR(AE26/AI26, " ") | AH26: ='2025年2月収益'!C29 -> 7017654.5 | AK26: ='2025年1月収益'!C29 -> 7973518 | AN26: ='2024年12月収益'!C29 -> 10434557 | AQ26: ='2024年11月収益'!C29 -> 5577475 | AT26: ='2024年10月収益'!C29 -> 4908551 | AV26: =IFERROR(AT26/AU26, " ") | AW26: ='2024年9月収益'!C29 -> 339726 | AY26: =IFERROR(AW26/AX26, " ") | AZ26: ='2024年8月収益'!C29 -> 4679490 | BC26: ='2024年7月収益'!C29 -> 582310.2
B27: NGR | C27: =SUM(D27:BM27) -> 722616509 | D27: ='2025年12月収益'!C30 -> 31242527 | G27: ='2025年11月収益'!C30 -> 33610642 | J27: ='2025年10月収益'!C30 -> 30910896 | M27: ='2025年9月収益D'!C30 -> 31772784 | P27: ='2025年8月収益'!C30 -> 23459499 | R27: =IFERROR(P27/T27, " ") | S27: ='2025年7月収益'!C30 -> 3791600.9 | U27: =IFERROR(S27/W27, " ") | V27: ='2025年6月収益'!C30 -> 69120862 | X27: =IFERROR(V27/Z27, " ") | Y27: ='2025年5月収益'!C30 -> 21494894 | AA27: =IFERROR(Y27/AC27, " ") | AB27: ='2025年4月収益'!C30 -> 62624282 | AD27: =IFERROR(AB27/AF27, " ") | AE27: ='2025年3月収益'!C30 -> 73575372 | AG27: =IFERROR(AE27/AI27, " ") | AH27: ='2025年2月収益'!C30 -> 69761547 | AJ27: =IFERROR(AH27/AI27, " ") | AK27: ='2025年1月収益'!C30 -> 64523087 | AN27: ='2024年12月収益'!C30 -> 113701202 | AQ27: ='2024年11月収益'!C30 -> 43746820 | AT27: ='2024年10月収益'!C30 -> 30881235 | AW27: ='2024年9月収益'!C30 -> -9323620 | AZ27: ='2024年8月収益'!C30 -> 25420232 | BC27: ='2024年7月収益'!C30 -> 2302646.8
B28: date | C28: =SUM(G28:BM28) -> 1.4009432e+08 | D28: ='2025年12月収益'!C31 -> 6248505 | G28: ='2025年11月収益'!C31 -> 6722128.4 | J28: ='2025年10月収益'!C31 -> 6337611.4 | M28: ='2025年9月収益D'!C31 -> 6306878.4 | P28: ='2025年8月収益'!C31 -> 5174440 | R28: =IFERROR(P28/T28, " ") | S28: ='2025年7月収益'!C31 -> 760833.92 | U28: =IFERROR(S28/W28, " ") | V28: 13824172 | X28: =IFERROR(V28/Z28, " ") | Y28: 5025483.2 | AA28: =IFERROR(Y28/AC28, " ") | AB28: 12524856 | AD28: =IFERROR(AB28/AF28, " ") | AE28: 14714017 | AG28: =IFERROR(AE28/AI28, " ") | AH28: ='2025年2月収益'!C31 -> 13952309 | AJ28: =IFERROR(AH28/AI28, " ") | AK28: ='2025年1月収益'!C31 -> 12717637 | AN28: ='2024年12月収益'!C31 -> 22740240 | AQ28: ='2024年11月収益'!C31 -> 9702782.8 | AT28: ='2024年10月収益'!C31 -> 6186256.2 | AW28: ='2024年9月収益'!C31 -> -1679368.4 | AY28: =IFERROR(AW28/AX28, " ") | AZ28: ='2024年8月収益'!C31 -> 5084046.3 | BC28: ='2024年7月収益'!C31 -> 0
B29: MS | C29: =SUM(G29:BM29) -> 1.5760612e+08 | D29: ='2025年12月収益'!C32 -> 7029569 | G29: ='2025年11月収益'!C32 -> 7562394.5 | J29: ='2025年10月収益'!C32 -> 7129812.8 | M29: ='2025年9月収益D'!C32 -> 7095238.2 | P29: ='2025年8月収益'!C32 -> 5821245 | R29: =IFERROR(P29/T29, " ") | S29: ='2025年7月収益'!C32 -> 855938.16 | U29: =IFERROR(S29/W29, " ") | V29: 15552194 | X29: =IFERROR(V29/Z29, " ") | Y29: 5653668.6 | AA29: =IFERROR(Y29/AC29, " ") | AB29: 14090463 | AD29: =IFERROR(AB29/AF29, " ") | AE29: 16553269 | AG29: =IFERROR(AE29/AI29, " ") | AH29: ='2025年2月収益'!C32 -> 15696348 | AJ29: =IFERROR(AH29/AI29, " ") | AK29: ='2025年1月収益'!C32 -> 14307342 | AM29: =IFERROR(AL29/AK29, " ") -> 0 | AN29: ='2024年12月収益'!C32 -> 25582771 | AQ29: ='2024年11月収益'!C32 -> 10915631 | AT29: ='2024年10月収益'!C32 -> 6959538.3 | AW29: ='2024年9月収益'!C32 -> -1889289.5 | AZ29: ='2024年8月収益'!C32 -> 5719552.1 | BC29: ='2024年7月収益'!C32 -> 0
B30: JP | C30: =SUM(D30:BM30) -> 193303303 | D30: ='2025年12月収益'!C41 | G30: ='2025年11月収益'!C41 -> 9242926.6 | J30: ='2025年10月収益'!C41 -> 8714215.7 | M30: ='2025年9月収益D'!C41 -> 8671957.8 | P30: ='2025年8月収益'!C41 -> 7114855 | R30: =IFERROR(P30/T30, " ") | S30: ='2025年7月収益'!C41 -> 1046146.6 | U30: =IFERROR(S30/W30, " ") | V30: 19008237 | X30: =IFERROR(V30/Z30, " ") | Y30: ='2025年5月収益'!C41 -> 6910039.4 | AA30: =IFERROR(Y30/AC30, " ") | AB30: ='2025年4月収益'!C41 -> 17221678 | AD30: =IFERROR(AB30/AF30, " ") | AE30: ='2025年3月収益'!C41 -> 20231773 | AG30: =IFERROR(AE30/AI30, " ") | AH30: ='2025年2月収益'!C41 -> 19184425 | AJ30: =IFERROR(AH30/AI30, " ") | AK30: ='2025年1月収益'!C41 -> 17486751 | AM30: =IFERROR(AL30/AK30, " ") -> 0 | AN30: ='2024年12月収益'!C41 -> 31267831 | AP30: =IFERROR(AO30/AN30, " ") -> 0 | AQ30: ='2024年11月収益'!C41 -> 13341326 | AT30: ='2024年10月収益'!C41 -> 8506102.3 | AW30: ='2024年9月収益'!C41 -> -2309131.6 | AY30: =IFERROR(AW30/AX30, " ") | AZ30: ='2024年8月収益'!C41 -> 6990563.7 | BC30: ='2024年7月収益'!C41 -> 673606
B31: 合計経費 | C31: =SUM(G31:BM31) -> 2.5923738e+08 | D31: ='2025年12月収益'!C40 -> 62559986 | G31: ='2025年11月収益'!C40 -> 15297170 | J31: ='2025年10月収益'!C40 -> 14157282 | M31: ='2025年9月収益D'!C40 -> 16197194 | P31: ='2025年8月収益'!C40 -> 7321812.7 | R31: =IFERROR(P31/T31, " ") | S31: ='2025年7月収益'!C40 -> 25992405 | U31: =IFERROR(S31/W31, " ") | V31: ='2025年6月収益'!C40 -> 15775814 | X31: =IFERROR(V31/Z31, " ") | Y31: ='2025年5月収益'!C40 -> 22380221 | AA31: =IFERROR(Y31/AC31, " ") | AB31: ='2025年4月収益'!C40 -> 19903104 | AD31: =IFERROR(AB31/AF31, " ") | AE31: ='2025年3月収益'!C40 -> 19965511 | AG31: =IFERROR(AE31/AI31, " ") | AH31: ='2025年2月収益'!C40 -> 17858544 | AJ31: =IFERROR(AH31/AI31, " ") | AK31: ='2025年1月収益'!C40 -> 15706129 | AN31: ='2024年12月収益'!C40 -> 34095525 | AQ31: ='2024年11月収益'!C40 -> 11403532 | AT31: ='2024年10月収益'!C40 -> 8440091.1 | AW31: ='2024年9月収益'!C40 -> 5288634.7 | AZ31: ='2024年8月収益'!C40 -> 7375620.7 | BC31: ='2024年7月収益'!C40 -> 2078794.4
